Workbook

Sheet Open Jobs
A1: W.M. Lyles Co.
A2: JOB SUMMARIES BY AREA
A3: FISCAL YEAR ENDING 12/31/25
A4: For the 12 Months Period Ended 12/31/25
M6: Month: | N6: 46022
M8: Anticipated | N8: Contractual | O8: Change in | P8: Previous
A9: Job | B9: Description and | C9: Project | D9: Project | E9: Contract | F9: % | G9: Revenue | H9: Cost | I9: Profit | J9: Prior Year | K9: Current | L9: Revenue | M9: Total | N9: Completion | O9: Anticipated | P9: Anticipated
A10: No. | B10: Customer | C10: Sup | D10: Est | E10: Amount | F10: Comp | G10: to Date | H10: to Date | I10: to Date | J10: Profit | K10: Profit | L10: Remaining | M10: Profit | N10: Date | O10: Profit | P10: Profits | Q10: Notes
A12: Area: | B12: Rocklin
A14: 51.1108 | B14: JV w/AECOM - Stockton - RWCF Phase 2A/2B | C14: DC | D14: Joe, VG, RB, PVT | E14: 94196098 | F14: =H14/(E14-M14) -> 0.99925302 | G14: =H14+I14 -> 94126377 | H14: 93268108 | I14: =IF(F14>0.2,IF(M14>0,IF(J14>M14,M14,IF((F14*M14)>J14,F14*M14,J14)),M14),0) -> 858269 | J14: 858269 | K14: =I14-J14 -> 0 | L14: =E14-G14 -> 69721.29 | M14: 858269 | N14: 46109 | O14: =M14-P14 -> 0 | P14: 858269 | Q14: Through Amendment 23. Includes anticipated profits from the 3% OH generated from the issued JV's SC's & PA's less credit back for management 50hr vs 40hr. Completion date listed for building completion - minus 10% management OH credit back to JV. Adjusted contract value to match anticipated reported on JV financials
A15: 51.1109 | B15: JV w/AECOM - Stockton - RWCF Phase 2A/2B Overhead (JV) | C15: DC | D15: N/A | F15: =H15/(E15-M15) -> 0.98087533 | G15: 0 | H15: -3462489.9 | I15: =G15-H15 -> 3462489.9 | J15: 3470130.8 | K15: =I15-J15 -> -7640.84 | L15: =E15-G15 -> 0 | M15: 3530000 | N15: 46109 | O15: =M15-P15 -> 0 | P15: 3530000 | Q15: Revenue generated by billing to 51.1108.
A16: 51.1129 | B16: Union Sanitary Dist - Enhanced Trtmnt & Site Upgrd Ph. 1A Aeration Basin Modifications | C16: RB/AH | D16: RB/MV | E16: 1.2648358e+08 | F16: =H16/(E16-M16) -> 0.75772321 | G16: =H16+(F16*M16)+534407 -> 96373952 | H16: 87315159 | I16: =G16-H16 -> 9058793.2 | J16: 7950623.4 | K16: =I16-J16 -> 1108169.8 | L16: =E16-G16 -> 30109628 | M16: 11250000 | N16: 46563 | O16: =M16-P16 -> 0 | P16: 11250000 | Q16: Through change order 111 minus 2, 29, 58, 78, 84 & 99. Increase in profits to date are realized buyout items and VE ideas gains. Problem with material delivery delayed the project. Profit projection includes the project realized gains (buyout/VE/profits) and projected losses due to delay.
A17: 51.1137 | B17: CA Water Service Co. - Bear Gulch Pump Station 18 | C17: AH | D17: KS | E17: 1312151.5 | F17: =H17/(E17-M17) -> 0.86960311 | G17: =H17+I17 -> 1141051 | H17: 1042229.3 | I17: =IF(F17>0.2,IF(M17>0,IF(J17>M17,M17,IF((F17*M17)>J17,F17*M17,J17)),M17),0) -> 98821.697 | J17: 27243.589 | K17: =I17-J17 -> 71578.108 | L17: =E17-G17 -> 171100.47 | M17: 113640 | N17: 46053 | O17: =M17-P17 -> 0 | P17: 113640
A18: 51.1144 | B18: Silicon Valley Clean Water - FEP Improvements Project | C18: EL | D18: VG | E18: 14969566 | F18: =H18/(E18-M18) -> 0.60744172 | G18: =H18+I18 -> 9093139 | H18: 8406760.8 | I18: =IF(F18>0.2,IF(M18>0,IF(J18>M18,M18,IF((F18*M18)>J18,F18*M18,J18)),M18),0) -> 686378.17 | J18: 90331.451 | K18: =I18-J18 -> 596046.72 | L18: =E18-G18 -> 5876427 | M18: 1129949 | N18: 46376 | O18: =M18-P18 -> 0 | P18: 1129949 | Q18: Stage 1 Design is to be completed by 9/30/24 by PDB Agreement but is behind -20 days due to Owner Delay. Stage 2 construction anticipated to begin 3/25 and complete by 12/20/26 and is seasonal
A19: 51.1146 | B19: National Carbon Technologies, LLC - Aymium Williams Production Facility | C19: MS | D19: MV | E19: 60980234 | F19: =H19/(E19-M19) -> 0.9294008 | G19: =H19+I19 -> 56675079 | H19: 42734066 | I19: =IF(F19>0.2,IF(M19>0,IF(J19>M19,M19,IF((F19*M19)>J19,F19*M19,J19)),M19),0) -> 13941012 | J19: 510849.94 | K19: =I19-J19 -> 13430162 | L19: =E19-G19 -> 4305155.5 | M19: 15000000 | N19: 46081 | O19: =M19-P19 -> 1400000 | P19: 13600000 | Q19: We demobilized in early November. All in, the Project has the potential to be $20m ($18.2 51.1146 + $1.8 51.1155). This does not include potential greivence settletmens or setttling up with Amyium. Based on all this, the December projection is $15.0m. We are holding back -$1m for Union grievances and another -$2m for other open issues w/ Amyium regarding their refusal to release retention.
A20: 51.1151 | B20: Sonoma Valley County Sanitation Dist. - Sonoma Valley Influent Effluent Upgrade | C20: MV | D20: SS | E20: 10658200 | F20: =H20/(E20-M20) -> 0.48846743 | G20: =H20+I20 -> 5206183.6 | H20: 4923435.2 | I20: =IF(F20>0.2,IF(M20>0,IF(J20>M20,M20,IF((F20*M20)>J20,F20*M20,J20)),M20),0) -> 282748.4 | J20: 0 | K20: =I20-J20 -> 282748.4 | L20: =E20-G20 -> 5452016.4 | M20: 578848 | N20: 46351 | O20: =M20-P20 -> 0 | P20: 578848
A21: 51.1152 | B21: Mozingo Construction Inc - ElD Sly Park Intertie Project | C21: MV | D21: EG | E21: 19974489 | F21: =H21/(E21-M21) -> 0.72332631 | G21: =H21+I21 -> 14448074 | H21: 13474809 | I21: =IF(F21>0.2,IF(M21>0,IF(J21>M21,M21,IF((F21*M21)>J21,F21*M21,J21)),M21),0) -> 973265.21 | J21: 0 | K21: =I21-J21 -> 973265.21 | L21: =E21-G21 -> 5526415.6 | M21: 1345541 | N21: 46203 | O21: =M21-P21 -> 0 | P21: 1345541
A22: 51.1153 | B22: Linda County Water Dist. - Aeration Blower Replacement | C22: JL | D22: JL | E22: 562824.68 | F22: =H22/(E22-M22) -> 0.7360519 | G22: =H22+I22 -> 414268.17 | H22: 334550.81 | I22: =IF(F22>0.2,IF(M22>0,IF(J22>M22,M22,IF((F22*M22)>J22,F22*M22,J22)),M22),0) -> 79717.365 | J22: 12859.389 | K22: =I22-J22 -> 66857.976 | L22: =E22-G22 -> 148556.51 | M22: 108304 | N22: 46053 | O22: =M22-P22 -> 0 | P22: 108304 | Q22: Checking for final invoices, Should move to closed jobs next month
A23: 51.1154 | B23: Keyes Community Services Dist. - TCP Treatment Impvmts Wells 7,8,9,10 | C23: LP | D23: KS | E23: 13363835 | F23: =H23/(E23-M23) -> 0.95063652 | G23: =H23+I23 -> 12704150 | H23: 11872343 | I23: =IF(F23>0.2,IF(M23>0,IF(J23>M23,M23,IF((F23*M23)>J23,F23*M23,J23)),M23),0) -> 831806.95 | J23: 0 | K23: =I23-J23 -> 831806.95 | L23: =E23-G23 -> 659685.45 | M23: 875000 | N23: 46068 | O23: =M23-P23 -> 0 | P23: 875000
A24: 51.1155 | B24: National Carbon Technologies, LLC - Aymium Williams Production Facility - Mgmt Chg Out | F24: =+H24/(E24-M24) -> 1 | G24: =H24+I24 -> 0 | H24: -1783380 | I24: =IF(F24>0,IF(M24>0,IF(J24>M24,M24,IF((F24*M24)>J24,F24*M24,J24)),M24),0) -> 1783380 | J24: 571197.48 | K24: =I24-J24 -> 1212182.5 | L24: =E24-G24 -> 0 | M24: 1783380 | N24: 46081 | O24: =M24-P24 -> -16620.03 | P24: 1800000
A25: 51.1158 | B25: Schneider Electric - City of Ceres WWTP Phase 1- Schneider Electric | E25: 104446 | F25: =+H25/(E25-M25) -> 0.54536019 | G25: =H25+I25 -> 56960.69 | H25: 56960.69 | I25: =IF(F25>0.2,IF(M25>0,IF(J25>M25,M25,IF((F25*M25)>J25,F25*M25,J25)),M25),0) -> 0 | J25: 0 | K25: =I25-J25 -> 0 | L25: =E25-G25 -> 47485.31 | M25: 0 | N25: 46173 | O25: =M25-P25 -> 0 | P25: 0 | Q25: Hold at $0 profit, need to verify final numbers once project path is determined (go/no-go). Do not close WIP.
A26: 51.1159 | B26: El Dorado Irrigation Dist. - EID Reservoir A WTP Backwash-to-waste Valve Repalcement | C26: EG | D26: MV | E26: 1199000 | F26: =+H26/(E26-M26) -> 0.73204396 | G26: =H26+I26 -> 877720.7 | H26: 790051.12 | I26: =IF(F26>0.2,IF(M26>0,IF(J26>M26,M26,IF((F26*M26)>J26,F26*M26,J26)),M26),0) -> 87669.584 | J26: 0 | K26: =I26-J26 -> 87669.584 | L26: =E26-G26 -> 321279.3 | M26: 119760 | N26: 46096 | O26: =M26-P26 -> 0 | P26: 119760
A27: 51.116 | B27: City of Galt Public Works - Industrial WWTP Expansion | C27: JL | D27: MV | E27: 1757000 | F27: =+H27/(E27-M27) -> 0.14823553 | G27: =H27+I27 -> 250518.05 | H27: 250518.05 | I27: =IF(F27>0.2,IF(M27>0,IF(J27>M27,M27,IF((F27*M27)>J27,F27*M27,J27)),M27),0) -> 0 | J27: 0 | K27: =I27-J27 -> 0 | L27: =E27-G27 -> 1506481.9 | M27: 67000 | N27: 46285 | O27: =M27-P27 -> 0 | P27: 67000
A28: 51.1161 | B28: Sacramento Area Sewer Dist. - SASD Influent Pump Nos. 2 and 5 Installation Project | C28: JA | D28: MV | E28: 10848599 | F28: =+H28/(E28-M28) -> 0.058652896 | G28: =H28+I28 -> 601852.17 | H28: 601852.17 | I28: =IF(F28>0.2,IF(M28>0,IF(J28>M28,M28,IF((F28*M28)>J28,F28*M28,J28)),M28),0) -> 0 | J28: 0 | K28: =I28-J28 -> 0 | L28: =E28-G28 -> 10246747 | M28: 587347 | N28: 46366 | O28: =M28-P28 -> 0 | P28: 587347
A29: 51.1162 | B29: City of Chico - Chico Primary Clarifiers No. 1-3 Rehabilitation Project | C29: CT | D29: MV | E29: 6029750 | F29: =+H29/(E29-M29) -> 0.01470274 | G29: =H29+I29 -> 85941.38 | H29: 85941.38 | I29: =IF(F29>0.2,IF(M29>0,IF(J29>M29,M29,IF((F29*M29)>J29,F29*M29,J29)),M29),0) -> 0 | J29: 0 | K29: =I29-J29 -> 0 | L29: =E29-G29 -> 5943808.6 | M29: 184487 | N29: 46681 | O29: =M29-P29 -> 0 | P29: 184487
A30: 51.1164 | B30: CA Water Service Co. - Stockton Roofing | C30: JL | D30: JS | E30: 387260 | F30: =+H30/(E30-M30) -> 0.011380798 | G30: =H30+I30 -> 4363.25 | H30: 4363.25 | I30: =IF(F30>0.2,IF(M30>0,IF(J30>M30,M30,IF((F30*M30)>J30,F30*M30,J30)),M30),0) -> 0 | K30: =I30-J30 -> 0 | L30: =E30-G30 -> 382896.75 | M30: 3873 | N30: 46112 | O30: =M30-P30 -> 3873
A31: 51.1165 | B31: City of Yuba City - WTP Aquifer Storage and Recovery Well No. 3 | C31: EG | D31: MV | E31: 5304500 | F31: =+H31/(E31-M31) -> 0.0047745016 | G31: =H31+I31 -> 23330.33 | H31: 23330.33 | I31: =IF(F31>0.2,IF(M31>0,IF(J31>M31,M31,IF((F31*M31)>J31,F31*M31,J31)),M31),0) -> 0 | K31: =I31-J31 -> 0 | L31: =E31-G31 -> 5281169.7 | M31: 418057 | N31: 46660 | O31: =M31-P31 -> 418057
B33: Rocklin Totals this Month | E33: =SUM(E14:E32) -> 3.6813153e+08 | G33: =SUM(G14:G32) -> 2.9208296e+08 | H33: =SUM(H14:H32) -> 2.5993861e+08 | I33: =SUM(I14:I32) -> 32144351 | J33: =SUM(J14:J32) -> 13491505 | K33: =SUM(K14:K32) -> 18652847 | L33: =SUM(L14:L32) -> 76048576 | M33: =SUM(M14:M32) -> 37953455 | O33: =SUM(O14:O32) -> 1805310 | P33: =SUM(P14:P32) -> 36148145
B34: Rocklin Closed Job Total | E34: ='Closed Jobs'!E23 -> 18225885 | G34: =+'Closed Jobs'!G23 -> 18225885 | H34: =+'Closed Jobs'!H23 -> 18509364 | I34: =+'Closed Jobs'!I23 -> -283479.41 | J34: =+'Closed Jobs'!J23 -> 1459158.3 | K34: =+'Closed Jobs'!K23 -> -1742637.7 | L34: =+'Closed Jobs'!L23 -> 0 | M34: =+'Closed Jobs'!M23 -> -283479.41 | O34: =+'Closed Jobs'!O23 -> -525178.96 | P34: =+'Closed Jobs'!P23 -> 241699.55
B35: Rocklin Total | E35: =E34+E33 -> 3.8635742e+08 | G35: =+G33+G34 -> 3.1030884e+08 | H35: =+H33+H34 -> 2.7844797e+08 | I35: =+I33+I34 -> 31860872 | J35: =+J33+J34 -> 14950663 | K35: =+K33+K34 -> 16910209 | L35: =+L33+L34 -> 76048576 | M35: =+M33+M34 -> 37669976 | O35: =+O33+O34 -> 1280131 | P35: =+P33+P34 -> 36389845
A37: JV | B37: Stockton - RWCF Phase 2A/2B | C37: DC | D37: Joe, VG, RB, PVT | E37: =(225085557/2) -> 1.1254278e+08 | F37: =H37/(E37-M37) -> 0.9990221 | G37: =H37+I37 -> 1.12439e+08 | H37: =((212041638)/2) -> 106020819 | I37: =IF(F37>0.3,IF(M37>0,IF(J37>M37,M37,IF((F37*M37)>J37,F37*M37,J37)),M37),0) -> 6418180.5 | J37: 7118423.5 | K37: =I37-J37 -> -700243 | L37: =E37-G37 -> 103779 | M37: =12836361/2 -> 6418180.5 | N37: 46109 | O37: =M37-P37 -> -31801 | P37: 6449981.5 | Q37: Includes December JV Financials | R37: Profit fade is a result of exceleration of the buildings to complete by Jan '25. Paying for subcontractors to work extended hours and weekends -$250k plus an additional -200k in reimbursable change order work in negotiations with Owner (tracking $400k allowing for 50% recovery). Added another -$100k for future sub accel to complete buildings on time. Overall project impacts on buildings alone due to design/misc. issues - $1.6m. See project narrative for more details.
B39: Rocklin Totals this Month w/ JVs & Closed Jobs | K39: =K37+K35 -> 16209966 | S39: Curr Month | T39: =H35 -> 2.7844797e+08
B40: Rocklin Prior Month Totals w/ JV's & Closed Jobs | K40: 14439549 | S40: Company Activity | T40: -7220844.2
B41: Rocklin Current Month Changes w/ JV's & Closed Jobs | K41: =K39-K40 -> 1770416.5 | T41: =SUM(T39:T40) -> 2.7122713e+08
S43: Prior Month | T43: 2.7122713e+08
A44: Area: | B44: Fresno | S44: Variance | T44: =T41-T43 -> 0
A46: 52.8563 | B46: City of Santa Cruz - Graham Hill WTP Facility Improvements - Phase 1 | C46: RM | D46: JL | E46: 1174182.7 | F46: =+H46/(E46-M46) -> 0.98150165 | G46: =H46+I46 -> 1152462.3 | H46: 1152462.3 | I46: =IF(F46>0.2,IF(M46>0,IF(J46>M46,M46,IF((F46*M46)>J46,F46*M46,J46)),M46),0) -> 0 | J46: 0 | K46: =I46-J46 -> 0 | L46: =E46-G46 -> 21720.44 | M46: 0 | N46: 46059 | O46: =M46-P46 -> 0 | P46: 0
A47: 52.8564 | B47: City of Santa Cruz - Graham Hill WTP Facility Improvements -Mgmt Chg Out | C47: RM | D47: JL | F47: =+H47/(E47-M47) -> 0.99997481 | G47: 0 | H47: -293385.24 | I47: =IF(F47>0.2,IF(M47>0,IF(J47>M47,M47,IF((F47*M47)>J47,F47*M47,J47)),M47),0) -> 293385.24 | J47: 264189.76 | K47: =I47-J47 -> 29195.48 | L47: =E47-G47 -> 0 | M47: 293392.63 | N47: 46059 | O47: =M47-P47 -> 0 | P47: 293392.63 | Q47: Through JV Amendment 4
A48: 52.8566 | B48: City of Visalia - Water Reclamation Facility RPGS SCR System | C48: RM | D48: RM | E48: 1259398 | F48: =+H48/(E48-M48) -> 0.99458232 | G48: =H48+I48 -> 1252575 | H48: 1023821.1 | I48: =IF(F48>0.2,IF(M48>0,IF(J48>M48,M48,IF((F48*M48)>J48,F48*M48,J48)),M48),0) -> 228753.93 | J48: 223974.51 | K48: =I48-J48 -> 4779.4271 | L48: =E48-G48 -> 6823.0166 | M48: 230000 | N48: 46081 | O48: =M48-P48 -> 0 | P48: 230000 | Q48: Waiting on Cummins (owner furnished equipment), to complete their commissioning.
A49: 52.8586 | B49: Tesoro Viejo MMWC- WTP/WWTP/RWSP Phase B Expansion - Phase 1 | C49: RM | D49: RM | E49: 12611349 | F49: =+H49/(E49-M49) -> 0.99100599 | G49: =H49+I49 -> 12497922 | H49: 10565461 | I49: =IF(F49>0.2,IF(M49>0,IF(J49>M49,M49,IF((F49*M49)>J49,F49*M49,J49)),M49),0) -> 1932461.7 | J49: 1757780 | K49: =I49-J49 -> 174681.68 | L49: =E49-G49 -> 113426.58 | M49: 1950000 | N49: 46053 | O49: =M49-P49 -> 0 | P49: 1950000
A50: 52.8634 | B50: City of Huron - Water Treatment Plant Imp. Phase 2 | C50: DG | D50: KSH | E50: 13892723 | F50: =+H50/(E50-M50) -> 0.88752212 | G50: =H50+I50 -> 12330099 | H50: 11707058 | I50: =IF(F50>0.2,IF(M50>0,IF(J50>M50,M50,IF((F50*M50)>J50,F50*M50,J50)),M50),0) -> 623040.53 | J50: 277972.01 | K50: =I50-J50 -> 345068.52 | L50: =E50-G50 -> 1562624 | M50: 702000 | N50: 46148 | O50: =M50-P50 -> 0 | P50: 702000
A51: 52.8636 | B51: Anaergia Technologies, LLC - Anaergia M1W Digester Mixing Project | C51: PR | D51: KSH | E51: 3642197 | F51: =+H51/(E51-M51) -> 0.99995556 | G51: =H51+I51 -> 3642035.1 | H51: 3367047.4 | I51: =IF(F51>0.2,IF(M51>0,IF(J51>M51,M51,IF((F51*M51)>J51,F51*M51,J51)),M51),0) -> 274987.78 | J51: 204319.71 | K51: =I51-J51 -> 70668.068 | L51: =E51-G51 -> 161.86114 | M51: 275000 | N51: 46081 | O51: =M51-P51 -> -35000 | P51: 310000 | Q51: Reduced profits. Performing additional work on Odor Control System. Anaergia will be issuing an RFP which will increase the contract and put back the profits at a later date.
A52: 52.8637 | B52: Root Creek Water Dist. - Groundwater Blending & Arsenic | C52: LP | D52: KSH | E52: 26264578 | F52: =+H52/(E52-M52) -> 0.99023836 | G52: =H52+I52 -> 26008192 | H52: 24374299 | I52: =IF(F52>0.2,IF(M52>0,IF(J52>M52,M52,IF((F52*M52)>J52,F52*M52,J52)),M52),0) -> 1633893.3 | J52: 1208391.8 | K52: =I52-J52 -> 425501.54 | L52: =E52-G52 -> 256385.32 | M52: 1650000 | N52: 46081 | O52: =M52-P52 -> 0 | P52: 1650000
A53: 52.864 | B53: City of Dos Palos - WTP Replacement Project | C53: TC | D53: KSH | E53: 38646363 | F53: =+H53/(E53-M53) -> 0.87452061 | G53: =H53+I53 -> 33797041 | H53: 32158781 | I53: =IF(F53>0.2,IF(M53>0,IF(J53>M53,M53,IF((F53*M53)>J53,F53*M53,J53)),M53),0) -> 1638259.6 | J53: 703966.84 | K53: =I53-J53 -> 934292.73 | L53: =E53-G53 -> 4849322.1 | M53: 1873323 | N53: 46129 | O53: =M53-P53 -> 0 | P53: 1873323
A54: 52.8668 | B54: California Water Service Co. - Cal Water - Salinas Station 57 | C54: EB | D54: SF | E54: 411851 | F54: =+H54/(E54-M54) -> 0.94884474 | G54: =H54+I54 -> 390782.65 | H54: 357710.67 | I54: =IF(F54>0.3,IF(M54>0,IF(J54>M54,M54,IF((F54*M54)>J54,F54*M54,J54)),M54),0) -> 33071.983 | J54: 0 | K54: =I54-J54 -> 33071.983 | L54: =E54-G54 -> 21068.347 | M54: 34855 | N54: 46022 | O54: =M54-P54 -> -1145 | P54: 36000 | Q54: All work has been completed. Waiting on final change order to be processed.
A55: 52.8678 | B55: City of Chowchilla - Well 15 & Generator Improvement Projects | C55: EB | D55: RH | E55: 1240321 | F55: =+H55/(E55-M55) -> 0.7966881 | G55: =H55+I55 -> 988148.98 | H55: 926007.31 | I55: =IF(F55>0.2,IF(M55>0,IF(J55>M55,M55,IF((F55*M55)>J55,F55*M55,J55)),M55),0) -> 62141.672 | J55: 0 | K55: =I55-J55 -> 62141.672 | L55: =E55-G55 -> 252172.02 | M55: 78000 | N55: 46053 | O55: =M55-P55 -> 0 | P55: 78000
A56: 52.8687 | B56: California Water Service Co. - Salinas Station 205 | C56: EB | D56: JS | E56: 877954 | F56: =+H56/(E56-M56) -> 0.93659097 | G56: =H56+I56 -> 822283.79 | H56: 740629.43 | I56: =IF(F56>0.2,IF(M56>0,IF(J56>M56,M56,IF((F56*M56)>J56,F56*M56,J56)),M56),0) -> 81654.361 | J56: 0 | K56: =I56-J56 -> 81654.361 | L56: =E56-G56 -> 55670.209 | M56: 87182.52 | N56: 46022 | O56: =M56-P56 -> 5760.52 | P56: 81422 | Q56: All work has been completed. Waiting on final change order to be processed.
A57: 52.8692 | B57: New England Sheet Metal and Mechanical Co. - Clovis South T&M | C57: DG | D57: DG | E57: 55135.37 | F57: =+H57/(E57-M57) -> 1 | G57: =H57+I57 -> 55135.37 | H57: 49682.49 | I57: =IF(F57>0.2,IF(M57>0,IF(J57>M57,M57,IF((F57*M57)>J57,F57*M57,J57)),M57),0) -> 5452.88 | J57: 0 | K57: =I57-J57 -> 5452.88 | L57: =E57-G57 -> 0 | M57: =E57-H57 -> 5452.88 | N57: 46053 | O57: =M57-P57 -> 0 | P57: 5452.88 | Q57: January costs, will be billed in January
A58: 52.8697 | B58: City of Tulare - Industrial WWTP Dewatering Improvements | C58: JL | D58: RM | E58: 1388000 | F58: =+H58/(E58-M58) -> 0.58257127 | G58: =H58+I58 -> 808608.92 | H58: 772187.73 | I58: =IF(F58>0.2,IF(M58>0,IF(J58>M58,M58,IF((F58*M58)>J58,F58*M58,J58)),M58),0) -> 36421.191 | J58: 0 | K58: =I58-J58 -> 36421.191 | L58: =E58-G58 -> 579391.08 | M58: 62518 | N58: 46225 | O58: =M58-P58 -> 0 | P58: 62518
A59: 52.8698 | B59: California Water Service Co. - Tesoro Viejo RWSP Liner Repair | E59: 22713 | F59: =+H59/(E59-M59) -> 0.94642857 | G59: =H59+I59 -> 21496.232 | H59: 15264 | I59: =IF(F59>0.2,IF(M59>0,IF(J59>M59,M59,IF((F59*M59)>J59,F59*M59,J59)),M59),0) -> 6232.2321 | K59: =I59-J59 -> 6232.2321 | L59: =E59-G59 -> 1216.7679 | M59: 6585 | N59: 46053 | O59: =M59-P59 -> 6585
A60: 52.8704 | B60: City of Visalia - Solids Handling Improvements Project | C60: LP | D60: SF | E60: 13744000 | F60: =+H60/(E60-M60) -> 0.060853945 | G60: =H60+I60 -> 820988.3 | H60: 820988.3 | I60: =IF(F60>0.2,IF(M60>0,IF(J60>M60,M60,IF((F60*M60)>J60,F60*M60,J60)),M60),0) -> 0 | J60: 0 | K60: =I60-J60 -> 0 | L60: =E60-G60 -> 12923012 | M60: 252873 | N60: 46418 | O60: =M60-P60 -> 0 | P60: 252873
A61: 52.8705 | B61: California Water Service Co. - Visalia Station 200 - New Storage Tank & Booster | C61: MDA | D61: JS | E61: 775000 | F61: =+H61/(E61-M61) -> 0.39683247 | G61: =H61+I61 -> 307545.16 | H61: 285425.72 | I61: =IF(F61>0.2,IF(M61>0,IF(J61>M61,M61,IF((F61*M61)>J61,F61*M61,J61)),M61),0) -> 22119.442 | J61: 0 | K61: =I61-J61 -> 22119.442 | L61: =E61-G61 -> 467454.84 | M61: 55740 | N61: 46081 | O61: =M61-P61 -> 0 | P61: 55740
A62: 52.8707 | B62: County of Fresno - Westside Water Tank and Pump Station | C62: AC | D62: RM | E62: 3693200 | F62: =+H62/(E62-M62) -> 0.29236881 | G62: =H62+I62 -> 1079776.5 | H62: 1012057.1 | I62: =IF(F62>0.2,IF(M62>0,IF(J62>M62,M62,IF((F62*M62)>J62,F62*M62,J62)),M62),0) -> 67719.34 | J62: 0 | K62: =I62-J62 -> 67719.34 | L62: =E62-G62 -> 2613423.5 | M62: 231623 | N62: 46215 | O62: =M62-P62 -> 0 | P62: 231623
A63: 52.8708 | B63: County of Fresno - CSA 44A Wastewater Improvements | C63: AKC | D63: JS | E63: 363833 | F63: =+H63/(E63-M63) -> 0.023017315 | G63: =H63+I63 -> 7682.19 | H63: 7682.19 | I63: =IF(F63>0.2,IF(M63>0,IF(J63>M63,M63,IF((F63*M63)>J63,F63*M63,J63)),M63),0) -> 0 | K63: =I63-J63 -> 0 | L63: =E63-G63 -> 356150.81 | M63: 30076 | N63: 46081 | O63: =M63-P63 -> 0 | P63: 30076
A64: 52.8711 | B64: California Water Service Co. - Tesoro Viejo ARV Replacement | C64: AKC | D64: AKC | E64: 6860 | F64: =+H64/(E64-M64) -> 0.72348535 | G64: =H64+I64 -> 4963.1095 | H64: 4568.81 | I64: =IF(F64>0.2,IF(M64>0,IF(J64>M64,M64,IF((F64*M64)>J64,F64*M64,J64)),M64),0) -> 394.29952 | K64: =I64-J64 -> 394.29952 | L64: =E64-G64 -> 1896.8905 | M64: 545 | N64: 46053 | O64: =M64-P64 -> 545
A65: 52.8713 | B65: City of Visalia - Remove & Replace Chain and Flight Mechanic | C65: EB | D65: EB | E65: 218842 | F65: =+H65/(E65-M65) -> 0.0048703259 | G65: =H65+I65 -> 927.5 | H65: 927.5 | I65: =IF(F65>0.2,IF(M65>0,IF(J65>M65,M65,IF((F65*M65)>J65,F65*M65,J65)),M65),0) -> 0 | K65: =I65-J65 -> 0 | L65: =E65-G65 -> 217914.5 | M65: 28403 | N65: 46112 | O65: =M65-P65 -> 28403
A66: 52.8714 | B66: New England Sheet Metal and Mechanical Co. - VCH Digging Water Line T&M | C66: DG | D66: DG | E66: 5084.94 | F66: =+H66/(E66-M66) -> 1 | G66: =H66+I66 -> 5084.94 | H66: 4465.61 | I66: =IF(F66>0.2,IF(M66>0,IF(J66>M66,M66,IF((F66*M66)>J66,F66*M66,J66)),M66),0) -> 619.33 | K66: =I66-J66 -> 619.33 | L66: =E66-G66 -> 0 | M66: =E66-H66 -> 619.33 | N66: 46053 | O66: =M66-P66 -> 619.33
B68: Fresno Totals this Month | E68: =SUM(E46:E67) -> 1.2029358e+08 | G68: =SUM(G46:G67) -> 95993751 | H68: =SUM(H46:H67) -> 89053142 | I68: =SUM(I46:I67) -> 6940608.8 | J68: =SUM(J46:J67) -> 4640594.6 | K68: =SUM(K46:K67) -> 2300014.2 | L68: =SUM(L46:L67) -> 24299834 | M68: =SUM(M46:M67) -> 7848188.4 | O68: =SUM(O46:O67) -> 5767.85 | P68: =SUM(P46:P67) -> 7842420.5
B69: Fresno Closed Job Total | E69: ='Closed Jobs'!E62 -> 24381266 | G69: ='Closed Jobs'!G62 -> 24381266 | H69: ='Closed Jobs'!H62 -> 23380699 | I69: ='Closed Jobs'!I62 -> 1000567.2 | J69: ='Closed Jobs'!J62 -> 947524.52 | K69: ='Closed Jobs'!K62 -> 53042.704 | L69: ='Closed Jobs'!L62 -> 0 | M69: ='Closed Jobs'!M62 -> 1000567.2 | N69: ='Closed Jobs'!N62 -> 0 | ... P69: ='Closed Jobs'!P62 -> 1099491.4
B70: Fresno Total | E70: =E68+E69 -> 1.4467485e+08 | G70: =+G68+G69 -> 1.2037502e+08 | H70: =+H68+H69 -> 1.1243384e+08 | I70: =+I68+I69 -> 7941176 | J70: =+J68+J69 -> 5588119.1 | K70: =+K68+K69 -> 2353056.9 | L70: =+L68+L69 -> 24299834 | M70: =+M68+M69 -> 8848755.6 | O70: =+O68+O69 -> -93156.28 | P70: =+P68+P69 -> 8941911.9
A72: JV | B72: City of Santa Cruz - Graham Hill WTP Facility Improvements | C72: RM | D72: JL | E72: =11042467/2 -> 5521233.5 | F72: =H72/(E72-M72) -> 0.99441086 | G72: =(10980750/2) -> 5490375 | H72: =10946425/2 -> 5473212.5 | I72: =G72-H72 -> 17162.5 | J72: 171855.18 | K72: =I72-J72 -> -154692.68 | L72: =E72-G72 -> 30858.5 | M72: =(34517/2) -> 17258.5 | N72: 46059 | O72: =M72-P72 -> 0 | P72: 17258.5 | Q72: Includes December JV Financials | R72: Used March 2024 JV - WML Adjusted Finanicals, Note Schedule showing project now -79 float behind as a result of push on 90% Design Review and resulting 100% Design efforts, likely City will reduce some of their review or negotiation period to reduce this
B74: Fresno Totals this Month w/ JVs & Closed Jobs | K74: =K70+K72 -> 2198364.2 | S74: Curr Month | T74: =H70 -> 1.1243384e+08
B75: Fresno Prior Month Totals w/ JV's & Closed Jobs | K75: 1916999.7 | S75: Company Activity | T75: -7110923.4
B76: Fresno Current Month Changes w/ JV's & Closed Jobs | K76: =K74-K75 -> 281364.5 | T76: =SUM(T74:T75) -> 1.0532292e+08
S78: Prior Month | T78: 1.0532292e+08
A79: Area: | B79: East Bay | S79: Variance | T79: =T76-T78 -> 0
A81: 53.2007 | B81: Union Sanitary Dist. - Phase 1B Secondary Clarifiers | E81: 324530134 | F81: =+H81/(E81-M81) -> 0.0013887146 | G81: =H81+I81 -> 404852.16 | H81: 404852.16 | I81: =IF(F81>0.2,IF(M81>0,IF(J81>M81,M81,IF((F81*M81)>J81,F81*M81,J81)),M81),0) -> 0 | J81: 0 | K81: =I81-J81 -> 0 | L81: =E81-G81 -> 3.2412528e+08 | M81: 33000000 | N81: 11352 | O81: =M81-P81 -> 0 | P81: 33000000
B83: East Bay Totals this Month | E83: =SUM(E81:E82) -> 324530134 | G83: =SUM(G81:G82) -> 404852.16 | H83: =SUM(H81:H82) -> 404852.16 | I83: =SUM(I81:I82) -> 0 | J83: =SUM(J81:J82) -> 0 | K83: =SUM(K81:K82) -> 0 | L83: =SUM(L81:L82) -> 3.2412528e+08 | M83: =SUM(M81:M82) -> 33000000 | O83: =SUM(O81:O82) -> 0 | P83: =SUM(P81:P82) -> 33000000 | S83: Curr Month | T83: =H85 -> 1969911.5
B84: East Bay Closed Job Total | E84: ='Closed Jobs'!E70 -> 1173753.5 | F84: ='Closed Jobs'!F70 -> 0 | G84: ='Closed Jobs'!G70 -> 1173753.5 | H84: ='Closed Jobs'!H70 -> 1565059.3 | I84: ='Closed Jobs'!I70 -> -391305.86 | J84: ='Closed Jobs'!J70 -> 0 | K84: ='Closed Jobs'!K70 -> -391305.86 | L84: ='Closed Jobs'!L70 -> 0 | ... P84: ='Closed Jobs'!P70 -> -363445.93 | S84: Company Activity | T84: -245768.3
B85: East Bay Total | E85: =E83+E84 -> 3.2570389e+08 | G85: =+G83+G84 -> 1578605.6 | H85: =+H83+H84 -> 1969911.5 | I85: =+I83+I84 -> -391305.86 | J85: =+J83+J84 -> 0 | K85: =+K83+K84 -> -391305.86 | L85: =+L83+L84 -> 3.2412528e+08 | M85: =+M83+M84 -> 32608694 | O85: =+O83+O84 -> -27859.93 | P85: =+P83+P84 -> 32636554 | T85: =SUM(T83:T84) -> 1724143.2
B87: East Bay Totals this Month w/ JVs & Closed Jobs | K87: =K85 -> -391305.86 | S87: Prior Month | T87: 1724143.2
B88: East Bay Prior Month Totals w/ JV's & Closed Jobs | K88: -369273.78 | S88: Variance | T88: =T85-T87 -> 0
B89: East Bay Current Month Changes w/ JV's & Closed Jobs | K89: =K87-K88 -> -22032.083
A92: Area: | B92: Bakersfield
A94: 54.9033 | B94: Semitropic WSD - Stored Water Recovery Unit Phase 2A, Amendment 8 | C94: REA | D94: REA | E94: 118278.58 | F94: =+H94/(E94-M94) -> 1 | G94: =H94+I94 -> 118278.58 | H94: 104550.27 | I94: =IF(F94>0.2,IF(M94>0,IF(J94>M94,M94,IF((F94*M94)>J94,F94*M94,J94)),M94),0) -> 13728.31 | J94: 10966.87 | K94: =I94-J94 -> 2761.44 | L94: =E94-G94 -> 0 | M94: 13728.31 | N94: 46357 | O94: =M94-P94 -> 2761.31 | P94: 10967 | Q94: Please do not close at year-end REA applying consulting time
A95: 54.9135 | B95: Calif. Rail Bldrs LLC - North Kern WSD Canal 9-22 Relocation Project | C95: AH | D95: REA | E95: 9470658.6 | F95: =+H95/(E95-M95) -> 1 | G95: =H95+I95 -> 9470658.6 | H95: 9050951.9 | I95: =IF(F95>0.2,IF(M95>0,IF(J95>M95,M95,IF((F95*M95)>J95,F95*M95,J95)),M95),0) -> 419706.76 | J95: 551994.37 | K95: =I95-J95 -> -132287.61 | L95: =E95-G95 -> 0 | M95: 419706.76 | N95: 46023 | O95: =M95-P95 -> -214351.24 | P95: 634058 | Q95: Antcipating dispute on unpaid T&M Change Order work.
A96: 54.9257 | B96: City of Guadalupe - Highway 1 Lift Station | C96: PR | D96: PR | E96: 1471328 | F96: =+H96/(E96-M96) -> 0.53438694 | G96: =H96+I96 -> 786258.46 | H96: 762211.05 | I96: =IF(F96>0.2,IF(M96>0,IF(J96>M96,M96,IF((F96*M96)>J96,F96*M96,J96)),M96),0) -> 24047.412 | J96: 0 | K96: =I96-J96 -> 24047.412 | L96: =E96-G96 -> 685069.54 | M96: 45000 | N96: 46096 | O96: =M96-P96 -> 0 | P96: 45000
A97: 54.9268 | B97: Semitropic Water Storage Dist. - Amendment No. 23 Raw Water Processing Plant Pipeline Replacement | C97: DS | D97: RA | E97: 949567.99 | F97: =+H97/(E97-M97) -> 0.95487095 | G97: =H97+I97 -> 909648.28 | H97: 844648.28 | I97: =IF(F97>0.2,IF(M97>0,IF(J97>M97,M97,IF((F97*M97)>J97,F97*M97,J97)),M97),0) -> 65000 | J97: 71013.067 | K97: =I97-J97 -> -6013.0668 | L97: =E97-G97 -> 39919.71 | M97: 65000 | N97: 46054 | O97: =M97-P97 -> 0 | P97: 65000 | Q97: Pump accepted will close when invoice clears ---- Per Dave S., no December billing
A98: 54.9269 | B98: Semitropic Water Storage Dist. - Design & Construction of the Central TCP Facility-Phase 1 | C98: KSH | D98: REA | E98: 625819.17 | F98: =+H98/(E98-M98) -> 0.92942108 | G98: =H98+I98 -> 584066.79 | H98: 549817.74 | I98: =IF(F98>0.1,IF(M98>0,IF(J98>M98,M98,IF((F98*M98)>J98,F98*M98,J98)),M98),0) -> 34249.05 | J98: 34249.05 | K98: =I98-J98 -> 0 | L98: =E98-G98 -> 41752.38 | M98: 34249.05 | N98: 46204 | O98: =M98-P98 -> 0.05 | P98: 34249 | Q98: Profit accounts for Phase 1 work. Phase 2 may be subject to a loss
A99: 54.9285 | B99: Semitropic Water Storage Dist. - Emergency Radial Arm Gate Removal and Replacement | C99: DS | D99: DS | E99: 462022 | F99: =+H99/(E99-M99) -> 0.80858393 | G99: =H99+I99 -> 373583.56 | H99: 312939.77 | I99: =IF(F99>0.2,IF(M99>0,IF(J99>M99,M99,IF((F99*M99)>J99,F99*M99,J99)),M99),0) -> 60643.795 | J99: 35686.238 | K99: =I99-J99 -> 24957.557 | L99: =E99-G99 -> 88438.435 | M99: 75000 | N99: 46054 | O99: =M99-P99 -> 0 | P99: 75000 | Q99: CCO coming for control changes
A100: 54.9313 | B100: Granite Construction Co. - Granite Chumash Camp 4 Infrastructure Project | C100: PR | D100: KSH | E100: 7886885 | F100: =+H100/(E100-M100) -> 0.93780908 | G100: =H100+I100 -> 7396392.4 | H100: 6449205.2 | I100: =IF(F100>0.2,IF(M100>0,IF(J100>M100,M100,IF((F100*M100)>J100,F100*M100,J100)),M100),0) -> 947187.17 | J100: 197714.51 | K100: =I100-J100 -> 749472.66 | L100: =E100-G100 -> 490492.65 | M100: 1010000 | N100: 46054 | O100: =M100-P100 -> 130000 | P100: 880000 | Q100: Owner reduction in scope, increased profit projection.
A101: 54.933 | B101: City of Bakersfield Public Works - Wastewater Treatment Plant No. 3 Septage Processing Unit Rep | C101: DS | D101: JS | E101: 324900 | F101: =+H101/(E101-M101) -> 0.99538556 | G101: =H101+I101 -> 323400.77 | H101: 306221.41 | I101: =IF(F101>0.2,IF(M101>0,IF(J101>M101,M101,IF((F101*M101)>J101,F101*M101,J101)),M101),0) -> 17179.359 | J101: 10642.127 | K101: =I101-J101 -> 6537.2322 | L101: =E101-G101 -> 1499.2306 | M101: 17259 | N101: 46022 | O101: =M101-P101 -> 1259 | P101: 16000 | Q101: Waiting on final Change Order to be executed to finalize contract value
A102: 54.9336 | B102: Palmdale Water Dist. - Pure Water AV - Demonstration Facility | C102: CB | D102: MC | E102: 25191177 | F102: =+H102/(E102-M102) -> 0.53030685 | G102: =H102+I102 -> 13359053 | H102: 12340864 | I102: =IF(F102>0.2,IF(M102>0,IF(J102>M102,M102,IF((F102*M102)>J102,F102*M102,J102)),M102),0) -> 1018189.1 | J102: 0 | K102: =I102-J102 -> 1018189.1 | L102: =E102-G102 -> 11832123 | M102: 1920000 | N102: 46274 | O102: =M102-P102 -> 20000 | P102: 1900000
A103: 54.9337 | B103: City of Bakersfield Public Works - WWTP 3 Digester Gas Booster Blower Replacement Project | C103: DS | D103: JS | E103: 4104848 | F103: =+H103/(E103-M103) -> 0.38254116 | G103: =H103+I103 -> 1570273.3 | H103: 1509066.7 | I103: =IF(F103>0.2,IF(M103>0,IF(J103>M103,M103,IF((F103*M103)>J103,F103*M103,J103)),M103),0) -> 61206.586 | J103: 0 | K103: =I103-J103 -> 61206.586 | L103: =E103-G103 -> 2534574.7 | M103: 160000 | N103: 46321 | O103: =M103-P103 -> 0 | P103: 160000 | Q103: 5 CCOs expected with +-10 Mo Time extension
A104: 54.9343 | B104: Tehachapi-Cummings County Water District - DB – Replace Diesel Engines PP2 and PP3 | C104: RH | D104: RH | E104: 6881300 | F104: =+H104/(E104-M104) -> 0.57100364 | G104: =H104+I104 -> 3929247.4 | H104: 3415344.1 | I104: =IF(F104>0.2,IF(M104>0,IF(J104>M104,M104,IF((F104*M104)>J104,F104*M104,J104)),M104),0) -> 513903.28 | J104: 0 | K104: =I104-J104 -> 513903.28 | L104: =E104-G104 -> 2952052.6 | M104: 900000 | N104: 46168 | O104: =M104-P104 -> 50000 | P104: 850000
A105: 54.9356 | B105: North of River Sanitary Dist. No. 1 - WWTP Digester Gas Scrubber Vessel and Effluent Storage Pond | C105: TM | D105: JS | E105: 1298330 | F105: =+H105/(E105-M105) -> 0.84939808 | G105: =H105+I105 -> 1102799 | H105: 775780.75 | I105: =IF(F105>0.2,IF(M105>0,IF(J105>M105,M105,IF((F105*M105)>J105,F105*M105,J105)),M105),0) -> 327018.26 | J105: 0 | K105: =I105-J105 -> 327018.26 | L105: =E105-G105 -> 195530.99 | M105: 385000 | N105: 46142 | O105: =M105-P105 -> 0 | P105: 385000 | Q105: Completetion date pushed back due to vessel design discrepancy
A106: 54.9366 | B106: City of Pismo Beach Community Development Dept. - WWTP Clarifier Equipment Replacement | C106: PR | D106: PR | E106: 1230131 | F106: =+H106/(E106-M106) -> 0.85473012 | G106: =H106+I106 -> 1051430 | H106: 923220.5 | I106: =IF(F106>0.2,IF(M106>0,IF(J106>M106,M106,IF((F106*M106)>J106,F106*M106,J106)),M106),0) -> 128209.52 | J106: 0 | K106: =I106-J106 -> 128209.52 | L106: =E106-G106 -> 178700.98 | M106: 150000 | N106: 46143 | O106: =M106-P106 -> 60000 | P106: 90000
A107: 54.9369 | B107: California Water Service Co. - PFAS Treatment Program Project | C107: PR | D107: JS | E107: 28550625 | F107: =+H107/(E107-M107) -> 0.10647402 | G107: =H107+I107 -> 2787466.7 | H107: 2787466.7 | I107: =IF(F107>0.2,IF(M107>0,IF(J107>M107,M107,IF((F107*M107)>J107,F107*M107,J107)),M107),0) -> 0 | J107: 0 | K107: =I107-J107 -> 0 | L107: =E107-G107 -> 25763158 | M107: 2370843 | N107: 46478 | O107: =M107-P107 -> 0 | P107: 2370843
A108: 54.9373 | B108: City of Guadalupe - Guadalupe Pioneer Lift Station Replacement | C108: PR | D108: PR | E108: 1524766 | F108: =+H108/(E108-M108) -> 0.036103518 | G108: =H108+I108 -> 50303.97 | H108: 50303.97 | I108: =IF(F108>0.2,IF(M108>0,IF(J108>M108,M108,IF((F108*M108)>J108,F108*M108,J108)),M108),0) -> 0 | J108: 0 | K108: =I108-J108 -> 0 | L108: =E108-G108 -> 1474462 | M108: 131440 | N108: 46172 | O108: =M108-P108 -> 0 | P108: 131440
A109: 54.9389 | B109: City of Atascadero - Atascadero Lift Stations 4 & 11 Rehab Project | C109: PR | D109: RH | E109: 299780 | F109: =+H109/(E109-M109) -> 0.99082486 | G109: =H109+I109 -> 296891.85 | H109: 311891.85 | I109: =IF(F109>0.2,IF(M109>0,IF(J109>M109,M109,IF((F109*M109)>J109,F109*M109,J109)),M109),0) -> -15000 | J109: 0 | K109: =I109-J109 -> -15000 | L109: =E109-G109 -> 2888.15 | M109: -15000 | N109: 46081 | O109: =M109-P109 -> 0 | P109: -15000
A110: 54.9391 | B110: Arvin Edison Water Storage Dist. - HQ Concrete R&R | C110: RF | D110: RF | E110: 532604.57 | F110: =+H110/(E110-M110) -> 1 | G110: =H110+I110 -> 532604.57 | H110: 512057.34 | I110: =IF(F110>0.2,IF(M110>0,IF(J110>M110,M110,IF((F110*M110)>J110,F110*M110,J110)),M110),0) -> 20547.23 | J110: 0 | K110: =I110-J110 -> 20547.23 | L110: =E110-G110 -> 0 | M110: 20547.23 | N110: 46053 | O110: =M110-P110 -> 547.23 | P110: 20000 | Q110: Project being performed for AEWSD at reduced mark-up to keep crews busy
A111: 54.9395 | B111: Semitropic Water Storage Dist. - Pond Poso Pumping Plant Siphon Pipe Replacement Project | C111: DS | D111: DS | E111: 1795652.7 | F111: =+H111/(E111-M111) -> 0.79685874 | G111: =H111+I111 -> 1430881.5 | H111: 1349601.9 | I111: =IF(F111>0.2,IF(M111>0,IF(J111>M111,M111,IF((F111*M111)>J111,F111*M111,J111)),M111),0) -> 81279.591 | J111: 0 | K111: =I111-J111 -> 81279.591 | L111: =E111-G111 -> 364771.15 | M111: 102000 | N111: 46079 | O111: =M111-P111 -> 72000 | P111: 30000
A112: 54.9396 | B112: Mojave Groundwater Storage LLC - Mojave Water Bank Northern Pipeline Facilities Construction | C112: JM | D112: MC | E112: 157746.09 | F112: =+H112/(E112-M112) -> 1 | G112: =H112+I112 -> 157746.09 | H112: 157746.09 | I112: =IF(F112>0.2,IF(M112>0,IF(J112>M112,M112,IF((F112*M112)>J112,F112*M112,J112)),M112),0) -> 0 | J112: 0 | K112: =I112-J112 -> 0 | L112: =E112-G112 -> 0 | M112: 0 | N112: 46138 | O112: =M112-P112 -> -9546 | P112: 9546
A113: 54.9397 | B113: Cawelo Water Dist. - Friant-Kern Canal Pump Station | C113: RF | D113: JS | E113: 3690645 | F113: =+H113/(E113-M113) -> 0.30527095 | G113: =H113+I113 -> 1126646.7 | H113: 1035065.4 | I113: =IF(F113>0.2,IF(M113>0,IF(J113>M113,M113,IF((F113*M113)>J113,F113*M113,J113)),M113),0) -> 91581.284 | J113: 0 | K113: =I113-J113 -> 91581.284 | L113: =E113-G113 -> 2563998.3 | M113: 300000 | N113: 46113 | O113: =M113-P113 -> 0 | P113: 300000
A114: 54.9403 | B114: Lost Hills Utility Dist. - WTP Improvements | C114: TM | D114: RH | E114: 381600 | F114: =+H114/(E114-M114) -> 0.38155726 | G114: =H114+I114 -> 145602.25 | H114: 129004.89 | I114: =IF(F114>0.2,IF(M114>0,IF(J114>M114,M114,IF((F114*M114)>J114,F114*M114,J114)),M114),0) -> 16597.359 | J114: 0 | K114: =I114-J114 -> 16597.359 | L114: =E114-G114 -> 235997.75 | M114: 43499 | N114: 46079 | O114: =M114-P114 -> 0 | P114: 43499
A115: 54.9404 | B115: Cawelo Water Dist. - Reuse of Produced Water | C115: RF | D115: SF | E115: 3720000 | F115: =+H115/(E115-M115) -> 0.54081245 | G115: =H115+I115 -> 2011822.3 | H115: 1939024.6 | I115: =IF(F115>0.2,IF(M115>0,IF(J115>M115,M115,IF((F115*M115)>J115,F115*M115,J115)),M115),0) -> 72797.682 | J115: 0 | K115: =I115-J115 -> 72797.682 | L115: =E115-G115 -> 1708177.7 | M115: 134608 | N115: 46080 | O115: =M115-P115 -> 0 | P115: 134608
A116: 54.9405 | B116: Semitropic Water Storage Dist. - Pump Platform Replacement Project | C116: DS | D116: DS | E116: 942000 | F116: =+H116/(E116-M116) -> 0.71157163 | G116: =H116+I116 -> 670300.47 | H116: 577796.16 | I116: =IF(F116>0.2,IF(M116>0,IF(J116>M116,M116,IF((F116*M116)>J116,F116*M116,J116)),M116),0) -> 92504.311 | J116: 0 | K116: =I116-J116 -> 92504.311 | L116: =E116-G116 -> 271699.53 | M116: 130000 | N116: 46107 | O116: =M116-P116 -> 10000 | P116: 120000
A117: 54.9406 | B117: California Water Service Co. - Emergency PACL leak repair | C117: DS | D117: DS | E117: 1120.65 | F117: =+H117/(E117-M117) -> 1 | G117: =H117+I117 -> 1120.65 | H117: 1120.65 | I117: =IF(F117>0.2,IF(M117>0,IF(J117>M117,M117,IF((F117*M117)>J117,F117*M117,J117)),M117),0) -> 0 | J117: 0 | K117: =I117-J117 -> 0 | L117: =E117-G117 -> 0 | M117: 0 | N117: 46023 | O117: =M117-P117 -> 0
A118: 54.9408 | B118: Nipomo Community Service Dist. - Frontage Road Sewer Trunk Line | C118: PR | D118: SF | E118: 3777777 | F118: =+H118/(E118-M118) -> 0.011775587 | G118: =H118+I118 -> 41652.43 | H118: 41652.43 | I118: =IF(F118>0.2,IF(M118>0,IF(J118>M118,M118,IF((F118*M118)>J118,F118*M118,J118)),M118),0) -> 0 | J118: 0 | K118: =I118-J118 -> 0 | L118: =E118-G118 -> 3736124.6 | M118: 240592 | N118: 46234 | O118: =M118-P118 -> 0 | P118: 240592
A119: 54.9411 | B119: Moorefield Construction Inc. - Hard Rock Tejon AEWSD Line Relocation | C119: AH | D119: AH | E119: 103300 | F119: =+H119/(E119-M119) -> 0.91150511 | G119: =H119+I119 -> 94158.478 | H119: 71370.85 | I119: =IF(F119>0.2,IF(M119>0,IF(J119>M119,M119,IF((F119*M119)>J119,F119*M119,J119)),M119),0) -> 22787.628 | J119: 0 | K119: =I119-J119 -> 22787.628 | L119: =E119-G119 -> 9141.5223 | M119: 25000 | N119: 46023 | O119: =M119-P119 -> 0 | P119: 25000 | Q119: WML will need to relocate ARV due to survey error. Pursuing CO for remob.
...

Sheet Closed Jobs
M2: Month: | N2: ='Open Jobs'!N6 -> 46022
M4: Anticipated | O4: Change in | P4: Previous
A5: Job | B5: Customer and | C5: Project | E5: Contract | F5: % | G5: Revenue | H5: Cost | I5: Profit | J5: Prior Year | K5: Current | L5: Revenue | M5: Total | N5: Completion | O5: Anticipated | P5: Anticipated
A6: No. | B6: Description | C6: Sup | D6: Est | E6: Amount | F6: Comp | G6: to Date | H6: to Date | I6: to Date | J6: Profit | K6: Profit | L6: Remaining | M6: Profit | N6: Date | O6: Profit | P6: Profits
A8: Northern Closed Jobs
A10: Area: | B10: Rocklin
A12: 51.1133 | B12: CA Water Service Co. - S. San Francisco St 1-A Pump Replacement | C12: AH | D12: KS | E12: 372738 | F12: =H12/(E12-M12) -> 1 | G12: =H12+I12 -> 372738 | H12: 331855.28 | I12: =IF(F12>0.2,IF(M12>0,IF(J12>M12,M12,IF((F12*M12)>J12,F12*M12,J12)),M12),0) -> 40882.72 | J12: 17359.581 | K12: =I12-J12 -> 23523.139 | L12: =E12-G12 -> 0 | M12: =E12-H12 -> 40882.72 | N12: 45747 | O12: =M12-P12 -> 0 | P12: 40882.72
A13: 51.1136 | B13: Union Sanitary Dist - USD Plant Misc. Improvements | C13: SS | D13: MV | E13: 5483550 | F13: =H13/(E13-M13) -> 1 | G13: =H13+I13 -> 5483550 | H13: 4531817.9 | I13: =IF(F13>0.2,IF(M13>0,IF(J13>M13,M13,IF((F13*M13)>J13,F13*M13,J13)),M13),0) -> 951732.14 | J13: 758905.79 | K13: =I13-J13 -> 192826.35 | L13: =E13-G13 -> 0 | M13: =E13-H13 -> 951732.14 | N13: 46053 | O13: =M13-P13 -> -281873.86 | P13: 1233606
A14: 51.1138 | B14: CA Water Service Co. - Bear Gulch Pump Station 21 | C14: AH | D14: KS | E14: 1120182.1 | F14: =H14/(E14-M14) -> 1 | G14: =H14+I14 -> 1120182.1 | H14: 1167704.1 | I14: =IF(F14>0.2,IF(M14>0,IF(J14>M14,M14,IF((F14*M14)>J14,F14*M14,J14)),M14),0) -> -47522.08 | J14: 77778.099 | K14: =I14-J14 -> -125300.18 | L14: =E14-G14 -> 0 | M14: =E14-H14 -> -47522.08 | N14: 45802 | O14: =M14-P14 -> 0 | P14: -47522.08
A15: 51.1139 | B15: CA Water Service Co. - Bear Gulch Pump Station 14/29 | C15: AH | D15: KS | E15: 61902 | F15: =H15/(E15-M15) -> 1 | G15: =H15+I15 -> 61902 | H15: 56994.44 | I15: =IF(F15>0.2,IF(M15>0,IF(J15>M15,M15,IF((F15*M15)>J15,F15*M15,J15)),M15),0) -> 4907.56 | J15: 4426.359 | K15: =I15-J15 -> 481.20101 | L15: =E15-G15 -> 0 | M15: =E15-H15 -> 4907.56 | N15: 46053 | O15: =M15-P15 -> -5300.17 | P15: 10207.73
A16: 51.1141 | B16: City of Colfax - WWTP Algae Reduction Project | C16: EG | D16: MV | E16: 3967189.8 | F16: =H16/(E16-M16) -> 1 | G16: =H16+I16 -> 3967189.8 | H16: =3846103.91-11009.18 -> 3835094.7 | I16: =IF(F16>0.2,IF(M16>0,IF(J16>M16,M16,IF((F16*M16)>J16,F16*M16,J16)),M16),0) -> 132095.06 | J16: 79920.299 | K16: =I16-J16 -> 52174.761 | L16: =E16-G16 -> 0 | M16: =E16-H16 -> 132095.06 | N16: 45777 | O16: =M16-P16 -> 0 | P16: 132095.06
A17: 51.1143 | B17: Olivehurst Plumas Lake Manganese Filter Expansion | C17: JL | D17: MV | E17: 1991231.4 | F17: =H17/(E17-M17) -> 1 | G17: =H17+I17 -> 1991231.4 | H17: 1758132.6 | I17: =IF(F17>0.2,IF(M17>0,IF(J17>M17,M17,IF((F17*M17)>J17,F17*M17,J17)),M17),0) -> 233098.8 | J17: 226011.76 | K17: =I17-J17 -> 7087.0371 | L17: =E17-G17 -> 0 | M17: =E17-H17 -> 233098.8 | N17: 45833 | O17: =M17-P17 -> 0 | P17: 233098.8
A18: 51.1147 | B18: City of Lodi-Public Works Dept. - Aeration Diffusers Replacement Project | C18: JL | D18: MV | E18: 2742860.1 | F18: =H18/(E18-M18) -> 1 | G18: =H18+I18 -> 2742860.1 | H18: =2547017.95+1595.47+111.5 -> 2548724.9 | I18: =IF(F18>0.2,IF(M18>0,IF(J18>M18,M18,IF((F18*M18)>J18,F18*M18,J18)),M18),0) -> 194135.16 | J18: 128284.54 | K18: =I18-J18 -> 65850.625 | L18: =E18-G18 -> 0 | M18: =E18-H18 -> 194135.16 | N18: 46053 | O18: =M18-P18 -> -111.5 | P18: 194246.66
A19: 51.115 | B19: Sacramento Co. Dept. of Water Resources - D49 Metro Air Park Storm Drain Pump Station Phase 2 | C19: MV | D19: TBD | E19: 2486231.6 | F19: =H19/(E19-M19) -> 1 | G19: =H19+I19 -> 2486231.6 | H19: 2239435.1 | I19: =IF(F19>0.2,IF(M19>0,IF(J19>M19,M19,IF((F19*M19)>J19,F19*M19,J19)),M19),0) -> 246796.44 | J19: 166471.83 | K19: =I19-J19 -> 80324.611 | L19: =E19-G19 -> 0 | M19: =E19-H19 -> 246796.44 | N19: 45747 | O19: =M19-P19 -> 0 | P19: 246796.44
A20: 51.1156 | B20: Rocklin Overhead 2025 | C20: DC | D20: DC | F20: =H20/(E20-M20) -> 1 | G20: =H20+I20 -> 0 | H20: 1426058.7 | I20: =IF(F20>0.2,IF(M20>0,IF(J20>M20,M20,IF((F20*M20)>J20,F20*M20,J20)),M20),0) -> -1426058.7 | J20: 0 | K20: =I20-J20 -> -1426058.7 | L20: =E20-G20 -> 0 | M20: =-H20 -> -1426058.7 | N20: 46022 | O20: =M20-P20 -> -176737.46 | P20: -1249321.2
A21: 51.1157 | B21: Rocklin Estimating 2025 | C21: DC | D21: DC | F21: =H21/(E21-M21) -> 1 | G21: =H21+I21 -> 0 | H21: 613546.52 | I21: =IF(F21>0.2,IF(M21>0,IF(J21>M21,M21,IF((F21*M21)>J21,F21*M21,J21)),M21),0) -> -613546.52 | J21: 0 | K21: =I21-J21 -> -613546.52 | L21: =E21-G21 -> 0 | M21: =-H21 -> -613546.52 | N21: 46022 | O21: =M21-P21 -> -61155.97 | P21: -552390.55
B23: Rocklin Totals this Month | E23: =SUM(E12:E22) -> 18225885 | G23: =SUM(G12:G22) -> 18225885 | H23: =SUM(H12:H22) -> 18509364 | I23: =SUM(I12:I22) -> -283479.41 | J23: =SUM(J12:J22) -> 1459158.3 | K23: =SUM(K12:K22) -> -1742637.7 | L23: =SUM(L12:L22) -> 0 | M23: =SUM(M12:M22) -> -283479.41 | O23: =SUM(O12:O22) -> -525178.96 | P23: =SUM(P12:P22) -> 241699.55
A25: Area: | B25: Fresno
A27: 52.8567 | B27: City of Modesto - Grayson Well 69 | C27: DG | D27: KA | E27: 3059859 | F27: =+H27/(E27-M27) -> 1 | G27: =H27+I27 -> 3059859 | H27: 3128023.9 | I27: =IF(F27>0.2,IF(M27>0,IF(J27>M27,M27,IF((F27*M27)>J27,F27*M27,J27)),M27),0) -> -68164.94 | J27: -83000 | K27: =I27-J27 -> 14835.06 | L27: =E27-G27 -> 0 | M27: =E27-H27 -> -68164.94 | N27: 45807 | O27: =M27-P27 -> 0 | P27: -68164.94
A28: 52.8604 | B28: City of Atwater - Project No. 20-2, Well 20-A TCP Mitigation | C28: TC | D28: GK | E28: 5095691 | F28: =+H28/(E28-M28) -> 1 | G28: =H28+I28 -> 5095691 | H28: =4573089.88-586.65 -> 4572503.2 | I28: =IF(F28>0.2,IF(M28>0,IF(J28>M28,M28,IF((F28*M28)>J28,F28*M28,J28)),M28),0) -> 523187.74 | J28: 329989.13 | K28: =I28-J28 -> 193198.61 | L28: =E28-G28 -> 0 | M28: =E28-H28 -> 523187.74 | N28: 45838 | O28: =M28-P28 -> 0 | P28: 523187.74
A29: 52.8628 | B29: City of Tulare - Well 4-3 Equipping & I Drive Pipeline Proj. | C29: AKC | D29: SF | E29: 5213345.5 | F29: =+H29/(E29-M29) -> 1 | G29: =H29+I29 -> 5213345.5 | H29: 4745798.5 | I29: =IF(F29>0.2,IF(M29>0,IF(J29>M29,M29,IF((F29*M29)>J29,F29*M29,J29)),M29),0) -> 467546.97 | J29: 197224.75 | K29: =I29-J29 -> 270322.22 | L29: =E29-G29 -> 0 | M29: =E29-H29 -> 467546.97 | N29: 46022 | O29: =M29-P29 -> 42546.97 | P29: 425000
A30: 52.8631 | B30: Gunner Ranch, Inc. - Well 1 Equipping and Site Improvements | C30: DG | D30: KA | E30: 2560650.1 | F30: =+H30/(E30-M30) -> 1 | G30: =H30+I30 -> 2560650.1 | H30: 2448658.3 | I30: =IF(F30>0.2,IF(M30>0,IF(J30>M30,M30,IF((F30*M30)>J30,F30*M30,J30)),M30),0) -> 111991.88 | J30: 73003.701 | K30: =I30-J30 -> 38988.179 | L30: =E30-G30 -> 0 | M30: =E30-H30 -> 111991.88 | N30: 46022 | O30: =M30-P30 -> -5008.12 | P30: 117000
A31: 52.8652 | B31: California Water Service Co. - Salinas 77 Booster Station | C31: PR | D31: KA | E31: 1290184 | F31: =+H31/(E31-M31) -> 1 | G31: =H31+I31 -> 1290184 | H31: =1039279.07+97.01 -> 1039376.1 | I31: =IF(F31>0.2,IF(M31>0,IF(J31>M31,M31,IF((F31*M31)>J31,F31*M31,J31)),M31),0) -> 250807.92 | J31: 170698.84 | K31: =I31-J31 -> 80109.083 | L31: =E31-G31 -> 0 | M31: =E31-H31 -> 250807.92 | N31: 45911 | O31: =M31-P31 -> 0 | P31: 250807.92
A32: 52.8658 | B32: California Water Service Co. - Visalia Station 98 Water Storage Tank & Booster Site | C32: MDA | D32: SF | E32: 1870915 | F32: =+H32/(E32-M32) -> 1 | G32: =H32+I32 -> 1870915 | H32: 1633530.2 | I32: =IF(F32>0.2,IF(M32>0,IF(J32>M32,M32,IF((F32*M32)>J32,F32*M32,J32)),M32),0) -> 237384.78 | J32: 148751 | K32: =I32-J32 -> 88633.78 | L32: =E32-G32 -> 0 | M32: =E32-H32 -> 237384.78 | N32: 45868 | O32: =M32-P32 -> 0 | P32: 237384.78
A33: 52.8663 | B33: Root Creek Water Dist. - Ag Well 277 Conversion Project | C33: LP | D33: RM | E33: 1641800 | F33: =+H33/(E33-M33) -> 1 | G33: =H33+I33 -> 1641800 | H33: 1379688.3 | I33: =IF(F33>0.2,IF(M33>0,IF(J33>M33,M33,IF((F33*M33)>J33,F33*M33,J33)),M33),0) -> 262111.72 | J33: 42676.951 | K33: =I33-J33 -> 219434.77 | L33: =E33-G33 -> 0 | M33: =E33-H33 -> 262111.72 | N33: 46081 | O33: =M33-P33 -> 2111.72 | P33: 260000
A34: 52.8667 | B34: California Water Service Co. - Cal Water Salinas Station 33 | C34: EB | D34: KA | E34: 314085.77 | F34: =+H34/(E34-M34) -> 1 | G34: =H34+I34 -> 314085.77 | H34: 290726.11 | I34: =IF(F34>0.3,IF(M34>0,IF(J34>M34,M34,IF((F34*M34)>J34,F34*M34,J34)),M34),0) -> 23359.66 | J34: 26868.865 | K34: =I34-J34 -> -3509.2053 | L34: =E34-G34 -> 0 | M34: =E34-H34 -> 23359.66 | N34: 45808 | O34: =M34-P34 -> 0 | P34: 23359.66
A35: 52.867 | B35: California Water Service Co. - Cal Water - King City Station 10 | C35: EB | D35: SF | E35: 274166.01 | F35: =+H35/(E35-M35) -> 1 | G35: =H35+I35 -> 274166.01 | H35: 267282.05 | I35: =IF(F35>0.3,IF(M35>0,IF(J35>M35,M35,IF((F35*M35)>J35,F35*M35,J35)),M35),0) -> 6883.96 | J35: 10404.436 | K35: =I35-J35 -> -3520.4756 | L35: =E35-G35 -> 0 | M35: =E35-H35 -> 6883.96 | N35: 45838 | O35: =M35-P35 -> 0 | P35: 6883.96
A36: 52.8674 | B36: City of Hanford - WWTP Standby Influent Pump Install | C36: DG | D36: SF | E36: 279244 | F36: =+H36/(E36-M36) -> 1 | G36: =H36+I36 -> 279244 | H36: 251088.2 | I36: =IF(F36>0.2,IF(M36>0,IF(J36>M36,M36,IF((F36*M36)>J36,F36*M36,J36)),M36),0) -> 28155.8 | J36: 15534.584 | K36: =I36-J36 -> 12621.216 | L36: =E36-G36 -> 0 | M36: =E36-H36 -> 28155.8 | N36: 45688 | O36: =M36-P36 -> 0 | P36: 28155.8
A37: 52.8677 | B37: Gunner Ranch, Inc. - CSA 22C Tank and PW2 Site Improvements | C37: DG | D37: SF | E37: 796055.3 | F37: =+H37/(E37-M37) -> 1 | G37: =H37+I37 -> 796055.3 | H37: 689831.96 | I37: =IF(F37>0.2,IF(M37>0,IF(J37>M37,M37,IF((F37*M37)>J37,F37*M37,J37)),M37),0) -> 106223.34 | J37: 0 | K37: =I37-J37 -> 106223.34 | L37: =E37-G37 -> 0 | M37: =E37-H37 -> 106223.34 | N37: 46022 | O37: =M37-P37 -> 18223.34 | P37: 88000
A38: 52.868 | B38: City of Orange Cove - Orange Cove West Clarifier T&M | C38: DG | D38: DG | E38: 29838.25 | F38: =+H38/(E38-M38) -> 1 | G38: =H38+I38 -> 29838.25 | H38: 26088.33 | I38: =IF(F38>0.2,IF(M38>0,IF(J38>M38,M38,IF((F38*M38)>J38,F38*M38,J38)),M38),0) -> 3749.92 | J38: 0 | K38: =I38-J38 -> 3749.92 | L38: =E38-G38 -> 0 | M38: =E38-H38 -> 3749.92 | N38: 45838 | O38: =M38-P38 -> 0 | P38: 3749.92
A39: 52.8682 | B39: Fresno Overhead 2025 | C39: RM | D39: RM | F39: =+H39/(E39-M39) -> 1 | G39: =H39+I39 -> 0 | H39: 1121157.1 | I39: =IF(F39>0.2,IF(M39>0,IF(J39>M39,M39,IF((F39*M39)>J39,F39*M39,J39)),M39),0) -> -1121157.1 | J39: 0 | K39: =I39-J39 -> -1121157.1 | L39: =E39-G39 -> 0 | M39: =-H39 -> -1121157.1 | N39: 46022 | O39: =M39-P39 -> -156002.73 | P39: -965154.37
A40: 52.8683 | B40: Fresno Estimating 2025 | C40: RM | D40: RM | F40: =+H40/(E40-M40) -> 1 | G40: =H40+I40 -> 0 | H40: 415452.52 | I40: =IF(F40>0.2,IF(M40>0,IF(J40>M40,M40,IF((F40*M40)>J40,F40*M40,J40)),M40),0) -> -415452.52 | J40: 0 | K40: =I40-J40 -> -415452.52 | L40: =E40-G40 -> 0 | M40: =-H40 -> -415452.52 | N40: 46022 | O40: =M40-P40 -> -64541.14 | P40: -350911.38
A41: 52.8684 | B41: Lakeside Ditch Co. - Lakeland Radial Gate Repair (T&M) | C41: JL | D41: JL | E41: 50568.05 | F41: =+H41/(E41-M41) -> 1 | G41: =H41+I41 -> 50568.05 | H41: =45194.09+97.3 -> 45291.39 | I41: =IF(F41>0.2,IF(M41>0,IF(J41>M41,M41,IF((F41*M41)>J41,F41*M41,J41)),M41),0) -> 5276.66 | J41: 0 | K41: =I41-J41 -> 5276.66 | L41: =E41-G41 -> 0 | M41: =E41-H41 -> 5276.66 | N41: 45939 | O41: =M41-P41 -> 830.03 | P41: 4446.63
A42: 52.8685 | B42: Malaga County Water Dist. - Malaga County Water District | C42: DG | D42: JS | E42: 451254 | F42: =+H42/(E42-M42) -> 1 | G42: =H42+I42 -> 451254 | H42: 382067.32 | I42: =IF(F42>0.2,IF(M42>0,IF(J42>M42,M42,IF((F42*M42)>J42,F42*M42,J42)),M42),0) -> 69186.68 | J42: 0 | K42: =I42-J42 -> 69186.68 | L42: =E42-G42 -> 0 | M42: =E42-H42 -> 69186.68 | N42: 46022 | O42: =M42-P42 -> 34186.68 | P42: 35000
A43: 52.8686 | B43: Root Creek Water Dist. - Groundwater - 48-Inch RCP Repair | C43: LP | D43: LP | E43: 23957 | F43: =+H43/(E43-M43) -> 1 | G43: =H43+I43 -> 23957 | H43: =7389.72+115.54 -> 7505.26 | I43: =IF(F43>0.2,IF(M43>0,IF(J43>M43,M43,IF((F43*M43)>J43,F43*M43,J43)),M43),0) -> 16451.74 | J43: 15372.257 | K43: =I43-J43 -> 1079.4833 | L43: =E43-G43 -> 0 | M43: =E43-H43 -> 16451.74 | N43: 46022 | O43: =M43-P43 -> 0 | P43: 16451.74
A44: 52.8688 | B44: New England Sheet Metal and Mechanical Co. - Valley Children's Hospital NESM Trench Limits | C44: DG | D44: DG | E44: 132492.2 | F44: =+H44/(E44-M44) -> 1 | G44: =H44+I44 -> 132492.2 | H44: 116972.75 | I44: =IF(F44>0.2,IF(M44>0,IF(J44>M44,M44,IF((F44*M44)>J44,F44*M44,J44)),M44),0) -> 15519.45 | J44: 0 | K44: =I44-J44 -> 15519.45 | L44: =E44-G44 -> 0 | M44: =E44-H44 -> 15519.45 | N44: 45900 | O44: =M44-P44 -> 0 | P44: 15519.45
A45: 52.8689 | B45: City of Sanger - Public Works Dept. - City of Sanger WWTP- Remove and Install Valves T&M | C45: DG | D45: DG | E45: 16665.83 | F45: =+H45/(E45-M45) -> 1 | G45: =H45+I45 -> 16665.83 | H45: 16095.58 | I45: =IF(F45>0.2,IF(M45>0,IF(J45>M45,M45,IF((F45*M45)>J45,F45*M45,J45)),M45),0) -> 570.25 | K45: =I45-J45 -> 570.25 | L45: =E45-G45 -> 0 | M45: =E45-H45 -> 570.25 | N45: 45808 | O45: =M45-P45 -> 0 | P45: 570.25
A46: 52.869 | B46: City of Dinuba - WWTP Rake Replacement | C46: DG | D46: DG | E46: 14151.97 | F46: =+H46/(E46-M46) -> 1 | G46: =H46+I46 -> 14151.97 | H46: 13155.83 | I46: =IF(F46>0.2,IF(M46>0,IF(J46>M46,M46,IF((F46*M46)>J46,F46*M46,J46)),M46),0) -> 996.14 | K46: =I46-J46 -> 996.14 | L46: =E46-G46 -> 0 | M46: =E46-H46 -> 996.14 | N46: 45779 | O46: =M46-P46 -> 0 | P46: 996.14
A47: 52.8691 | B47: County of Fresno - Quail Lakes Repair at Bodega Bay Rd | C47: TC | D47: TC | E47: 11302.84 | F47: =+H47/(E47-M47) -> 1 | G47: =H47+I47 -> 11302.84 | H47: 8287.82 | I47: =IF(F47>0.2,IF(M47>0,IF(J47>M47,M47,IF((F47*M47)>J47,F47*M47,J47)),M47),0) -> 3015.02 | J47: 0 | K47: =I47-J47 -> 3015.02 | L47: =E47-G47 -> 0 | M47: =E47-H47 -> 3015.02 | N47: 45838 | O47: =M47-P47 -> 0 | P47: 3015.02
A48: 52.8693 | B48: New England Sheet Metal and Mechanical Co. - VCH Service Meter Connections | C48: AC | D48: RH | E48: 1120704.2 | F48: =+H48/(E48-M48) -> 1 | G48: =H48+I48 -> 1120704.2 | H48: 663140.99 | I48: =IF(F48>0.2,IF(M48>0,IF(J48>M48,M48,IF((F48*M48)>J48,F48*M48,J48)),M48),0) -> 457563.21 | J48: 0 | K48: =I48-J48 -> 457563.21 | L48: =E48-G48 -> 0 | M48: =E48-H48 -> 457563.21 | N48: 46022 | O48: =M48-P48 -> 27563.21 | P48: 430000
A49: 52.8694 | B49: Pixley Public Utility District - Pixley WWTF - STM-Aerotor Repair | C49: JL | D49: JL | E49: 43047.45 | F49: =+H49/(E49-M49) -> 1 | G49: =H49+I49 -> 43047.45 | H49: 38541.99 | I49: =IF(F49>0.2,IF(M49>0,IF(J49>M49,M49,IF((F49*M49)>J49,F49*M49,J49)),M49),0) -> 4505.46 | J49: 0 | K49: =I49-J49 -> 4505.46 | L49: =E49-G49 -> 0 | M49: =E49-H49 -> 4505.46 | N49: 45777 | O49: =M49-P49 -> 0 | P49: 4505.46
A50: 52.8695 | B50: Lyles Services Co. - LSC GO Trash Enclosure | C50: LP | D50: LP | E50: 13769 | F50: =+H50/(E50-M50) -> 1 | G50: =H50+I50 -> 13769 | H50: 13024.37 | I50: =IF(F50>0.2,IF(M50>0,IF(J50>M50,M50,IF((F50*M50)>J50,F50*M50,J50)),M50),0) -> 744.63 | J50: 0 | K50: =I50-J50 -> 744.63 | L50: =E50-G50 -> 0 | M50: =E50-H50 -> 744.63 | N50: 45838 | O50: =M50-P50 -> 0 | P50: 744.63
A51: 52.8696 | B51: American Paving Co. - Hot Tap for APC- Tule River Parkway | C51: DG | D51: DG | E51: 1059.22 | F51: =+H51/(E51-M51) -> 1 | G51: =H51+I51 -> 1059.22 | H51: 887.65 | I51: =IF(F51>0.2,IF(M51>0,IF(J51>M51,M51,IF((F51*M51)>J51,F51*M51,J51)),M51),0) -> 171.57 | K51: =I51-J51 -> 171.57 | L51: =E51-G51 -> 0 | M51: =E51-H51 -> 171.57 | N51: 45808 | O51: =M51-P51 -> 0 | P51: 171.57
A52: 52.8699 | B52: City of Hanford - WWTP Repair T&M | C52: DG | D52: DG | E52: 3001.12 | F52: =+H52/(E52-M52) -> 1 | G52: =H52+I52 -> 3001.12 | H52: 2948.91 | I52: =IF(F52>0.2,IF(M52>0,IF(J52>M52,M52,IF((F52*M52)>J52,F52*M52,J52)),M52),0) -> 52.21 | J52: 0 | K52: =I52-J52 -> 52.21 | L52: =E52-G52 -> 0 | M52: =E52-H52 -> 52.21 | N52: 45838 | O52: =M52-P52 -> 0 | P52: 52.21
A53: 52.87 | B53: Lyles Services Co. - LSC GO Misc. Work | C53: LP | D53: LP | E53: 5297 | F53: =+H53/(E53-M53) -> 1 | G53: =H53+I53 -> 5297 | H53: 4446.13 | I53: =IF(F53>0.2,IF(M53>0,IF(J53>M53,M53,IF((F53*M53)>J53,F53*M53,J53)),M53),0) -> 850.87 | J53: 0 | K53: =I53-J53 -> 850.87 | L53: =E53-G53 -> 0 | M53: =E53-H53 -> 850.87 | N53: 46022 | O53: =M53-P53 -> 500.87 | P53: 350
A54: 52.8701 | B54: County of Fresno - 47 Water | C54: AC | D54: AC | E54: 13433.85 | F54: =+H54/(E54-M54) -> 1 | G54: =H54+I54 -> 13433.85 | H54: =10712.24+1473.95+234.89 -> 12421.08 | I54: =IF(F54>0.2,IF(M54>0,IF(J54>M54,M54,IF((F54*M54)>J54,F54*M54,J54)),M54),0) -> 1012.77 | J54: 0 | K54: =I54-J54 -> 1012.77 | L54: =E54-G54 -> 0 | M54: =E54-H54 -> 1012.77 | N54: 45900 | O54: =M54-P54 -> -234.89 | P54: 1247.66
A55: 52.8702 | B55: New England Sheet Metal and Mechanical Co. - FUSD Wilson Elementary T&M | C55: DG | D55: DG | E55: 5626.78 | F55: =+H55/(E55-M55) -> 1 | G55: =H55+I55 -> 5626.78 | H55: 4725.28 | I55: =IF(F55>0.2,IF(M55>0,IF(J55>M55,M55,IF((F55*M55)>J55,F55*M55,J55)),M55),0) -> 901.5 | J55: 0 | K55: =I55-J55 -> 901.5 | L55: =E55-G55 -> 0 | M55: =E55-H55 -> 901.5 | N55: 45869 | O55: =M55-P55 -> 0 | P55: 901.5
A56: 52.8703 | B56: County of Fresno - CSA 47 Egret Point Water Line Repair | C56: AC | D56: AC | E56: 14402.18 | F56: =+H56/(E56-M56) -> 1 | G56: =H56+I56 -> 14402.18 | H56: =11468.02+762.24+341.28 -> 12571.54 | I56: =IF(F56>0.2,IF(M56>0,IF(J56>M56,M56,IF((F56*M56)>J56,F56*M56,J56)),M56),0) -> 1830.64 | J56: 0 | K56: =I56-J56 -> 1830.64 | L56: =E56-G56 -> 0 | M56: =E56-H56 -> 1830.64 | N56: 45880 | O56: =M56-P56 -> -341.28 | P56: 2171.92
A57: 52.8706 | B57: City of Hanford - WWTP Weld Repair T&M 2 | C57: DG | D57: DG | E57: 2868.6 | F57: =+H57/(E57-M57) -> 1 | G57: =H57+I57 -> 2868.6 | H57: 2435.78 | I57: =IF(F57>0.2,IF(M57>0,IF(J57>M57,M57,IF((F57*M57)>J57,F57*M57,J57)),M57),0) -> 432.82 | J57: 0 | K57: =I57-J57 -> 432.82 | L57: =E57-G57 -> 0 | M57: =E57-H57 -> 432.82 | N57: 45930 | O57: =M57-P57 -> 0 | P57: 432.82
A58: 52.8709 | B58: County of Fresno - 47.1 Water | C58: AC | D58: AC | E58: 17765.14 | F58: =+H58/(E58-M58) -> 1 | G58: =H58+I58 -> 17765.14 | H58: =14699.58+174.78 -> 14874.36 | I58: =IF(F58>0.2,IF(M58>0,IF(J58>M58,M58,IF((F58*M58)>J58,F58*M58,J58)),M58),0) -> 2890.78 | K58: =I58-J58 -> 2890.78 | L58: =E58-G58 -> 0 | M58: =E58-H58 -> 2890.78 | N58: 45991 | O58: =M58-P58 -> -174.78 | P58: 3065.56
A59: 52.871 | B59: City of Dinuba - WWTP Bar Screen Motor Bracket Repair | C59: DG | D59: DG | E59: 4064.54 | F59: =+H59/(E59-M59) -> 1 | G59: =H59+I59 -> 4064.54 | H59: 3514.84 | I59: =IF(F59>0.2,IF(M59>0,IF(J59>M59,M59,IF((F59*M59)>J59,F59*M59,J59)),M59),0) -> 549.7 | K59: =I59-J59 -> 549.7 | L59: =E59-G59 -> 0 | M59: =E59-H59 -> 549.7 | N59: 45991 | O59: =M59-P59 -> 0 | P59: 549.7
A60: 52.8715 | B60: New England Sheet Metal and Mechanical Co. - Vitro Glass Plant Concrete Pad T&M | C60: DG | D60: DG | E60: 10001.43 | F60: =+H60/(E60-M60) -> 1 | G60: =H60+I60 -> 10001.43 | H60: 8585.44 | I60: =IF(F60>0.2,IF(M60>0,IF(J60>M60,M60,IF((F60*M60)>J60,F60*M60,J60)),M60),0) -> 1415.99 | K60: =I60-J60 -> 1415.99 | L60: =E60-G60 -> 0 | M60: =E60-H60 -> 1415.99 | N60: 46053 | O60: =M60-P60 -> 1415.99
B62: Fresno Totals this Month | E62: =SUM(E27:E61) -> 24381266 | G62: =SUM(G27:G61) -> 24381266 | H62: =SUM(H27:H61) -> 23380699 | I62: =SUM(I27:I61) -> 1000567.2 | J62: =SUM(J27:J61) -> 947524.52 | K62: =SUM(K27:K61) -> 53042.704 | L62: =SUM(L27:L61) -> 0 | M62: =SUM(M27:M61) -> 1000567.2 | O62: =SUM(O27:O61) -> -98924.13 | P62: =SUM(P27:P61) -> 1099491.4
A64: Area: | B64: East Bay
A66: 53.2004 | B66: City of Millbrae - Millbrae Sludge Thickener & Digester No. 2 Rehab Project | C66: RB | D66: MV | E66: 1173753.5 | F66: =+H66/(E66-M66) -> 1 | G66: =H66+I66 -> 1173753.5 | H66: 980791.05 | I66: =IF(F66>0.2,IF(M66>0,IF(J66>M66,M66,IF((F66*M66)>J66,F66*M66,J66)),M66),0) -> 192962.42 | J66: 0 | K66: =I66-J66 -> 192962.42 | L66: =E66-G66 -> 0 | M66: =E66-H66 -> 192962.42 | N66: 46053 | O66: =M66-P66 -> 9072.42 | P66: 183890
A67: 53.2005 | B67: East Bay Overhead 2025 | C67: RB | D67: RB | F67: =+H67/(E67-M67) -> 1 | G67: =H67+I67 -> 0 | H67: 279281.96 | I67: =IF(F67>0.2,IF(M67>0,IF(J67>M67,M67,IF((F67*M67)>J67,F67*M67,J67)),M67),0) -> -279281.96 | J67: 0 | K67: =I67-J67 -> -279281.96 | L67: =E67-G67 -> 0 | M67: =-H67 -> -279281.96 | N67: 46022 | O67: =M67-P67 -> -36895.25 | P67: -242386.71
A68: 53.2006 | B68: East Bay Estimating 2026 | C68: RB | D68: RB | F68: =+H68/(E68-M68) -> 1 | G68: =H68+I68 -> 0 | H68: 304986.32 | I68: =IF(F68>0.2,IF(M68>0,IF(J68>M68,M68,IF((F68*M68)>J68,F68*M68,J68)),M68),0) -> -304986.32 | J68: 0 | K68: =I68-J68 -> -304986.32 | L68: =E68-G68 -> 0 | M68: =-H68 -> -304986.32 | N68: 46022 | O68: =M68-P68 -> -37.1 | P68: -304949.22
B70: East Bay Totals this Month | E70: =SUM(E64:E69) -> 1173753.5 | G70: =SUM(G64:G69) -> 1173753.5 | H70: =SUM(H64:H69) -> 1565059.3 | I70: =SUM(I64:I69) -> -391305.86 | J70: =SUM(J64:J69) -> 0 | K70: =SUM(K64:K69) -> -391305.86 | L70: =SUM(L64:L69) -> 0 | M70: =SUM(M64:M69) -> -391305.86 | O70: =SUM(O64:O69) -> -27859.93 | P70: =SUM(P64:P69) -> -363445.93
A72: Area: | B72: Bakersfield
A74: 54.9099 | B74: Laguna County Sanitation Dist. - Phase 1 Plant Upgrade | C74: PR | D74: KSH | E74: 55712110 | F74: =+H74/(E74-M74) -> 1 | G74: =H74+I74 -> 55712110 | H74: 45328893 | I74: =IF(F74>0.2,IF(M74>0,IF(J74>M74,M74,IF((F74*M74)>J74,F74*M74,J74)),M74),0) -> 10383217 | J74: 10372752 | K74: =I74-J74 -> 10465.739 | L74: =E74-G74 -> 0 | M74: =E74-H74 -> 10383217 | N74: 46022 | O74: =M74-P74 -> 8217.32 | P74: 10375000
A75: 54.9172 | B75: Calif. Rail Bldrs LLC - SWSD Distribution System Conflict | C75: AH | D75: RA | E75: 24160002 | F75: =+H75/(E75-M75) -> 1 | G75: =H75+I75 -> 24160002 | H75: =21054098.14+74.71+836.87-36577.5 -> 21018432 | I75: =IF(F75>0.2,IF(M75>0,IF(J75>M75,M75,IF((F75*M75)>J75,F75*M75,J75)),M75),0) -> 3141570.2 | J75: 3076351.4 | K75: =I75-J75 -> 65218.771 | L75: =E75-G75 -> 0 | M75: =E75-H75 -> 3141570.2 | N75: 45717 | O75: =M75-P75 -> 0 | P75: 3141570.2
A76: 54.9216 | B76: CA Dept. of Corr. - Water Treatment Improvements | C76: DS | D76: DS | E76: 2472164 | F76: =+H76/(E76-M76) -> 1 | G76: =H76+I76 -> 2472164 | H76: =2286067.7+196.73 -> 2286264.4 | I76: =IF(F76>0.2,IF(M76>0,IF(J76>M76,M76,IF((F76*M76)>J76,F76*M76,J76)),M76),0) -> 185899.62 | J76: 140849.75 | K76: =I76-J76 -> 45049.866 | L76: =E76-G76 -> 0 | M76: =E76-H76 -> 185899.62 | N76: 45925 | O76: =M76-P76 -> -196.73 | P76: 186096.35
A77: 54.9246 | B77: Kern County Water Agency - Well 38 & 39 Well Equipping Project | C77: DS | D77: SF | E77: 1777852 | F77: =+H77/(E77-M77) -> 1 | G77: =H77+I77 -> 1777852 | H77: 1708475.3 | I77: =IF(F77>0.2,IF(M77>0,IF(J77>M77,M77,IF((F77*M77)>J77,F77*M77,J77)),M77),0) -> 69376.68 | J77: 69196.454 | K77: =I77-J77 -> 180.22572 | L77: =E77-G77 -> 0 | M77: =E77-H77 -> 69376.68 | N77: 46022 | O77: =M77-P77 -> 9376.68 | P77: 60000
A78: 54.9265 | B78: Semitropic Water Storage Dist. - Amendment No. 22 JPP Valve Control Modification | C78: DS | D78: DS | E78: 223896.47 | F78: =+H78/(E78-M78) -> 1 | G78: =H78+I78 -> 223896.47 | H78: 220754.51 | I78: =IF(F78>0.2,IF(M78>0,IF(J78>M78,M78,IF((F78*M78)>J78,F78*M78,J78)),M78),0) -> 3141.96 | J78: 0 | K78: =I78-J78 -> 3141.96 | L78: =E78-G78 -> 0 | M78: =E78-H78 -> 3141.96 | N78: 45807 | O78: =M78-P78 -> 0 | P78: 3141.96
A79: 54.9279 | B79: City of Bakersfield Public Works - Sewer Lift Station Rehabilitation | C79: RF | D79: KA | E79: 3216240 | F79: =+H79/(E79-M79) -> 1 | G79: =H79+I79 -> 3216240 | H79: =3153374.79-137.39 -> 3153237.4 | I79: =IF(F79>0.2,IF(M79>0,IF(J79>M79,M79,IF((F79*M79)>J79,F79*M79,J79)),M79),0) -> 63002.61 | J79: -15000 | K79: =I79-J79 -> 78002.61 | L79: =E79-G79 -> 0 | M79: =E79-H79 -> 63002.61 | N79: 45870 | O79: =M79-P79 -> 0 | P79: 63002.61
A80: 54.9289 | B80: Michael K. Nunley & Assoc., Inc. - AMWC Sycamore & NWT Budgeting | C80: KSH | D80: KSH | E80: 44560 | F80: =+H80/(E80-M80) -> 1 | G80: =H80+I80 -> 44560 | H80: 25097.25 | I80: =IF(F80>0.2,IF(M80>0,IF(J80>M80,M80,IF((F80*M80)>J80,F80*M80,J80)),M80),0) -> 19462.75 | J80: 669.81 | K80: =I80-J80 -> 18792.94 | L80: =E80-G80 -> 0 | M80: =E80-H80 -> 19462.75 | N80: 46357 | O80: =M80-P80 -> 0 | P80: 19462.75
A81: 54.9292 | B81: Michael K. Nunley & Assoc., Inc. - Waterton WTP Budgeting | C81: KSH | D81: KSH | E81: 4300 | F81: =+H81/(E81-M81) -> 1 | G81: =H81+I81 -> 4300 | H81: 1313.45 | I81: =IF(F81>0.2,IF(M81>0,IF(J81>M81,M81,IF((F81*M81)>J81,F81*M81,J81)),M81),0) -> 2986.55 | J81: 2986.55 | K81: =I81-J81 -> 0 | L81: =E81-G81 -> 0 | M81: =E81-H81 -> 2986.55 | N81: 46022 | O81: =M81-P81 -> 0 | P81: 2986.55
A82: 54.9309 | B82: Teviston Community Services Dist. - Teviston Drought Resilience Water System Impr | C82: AH | D82: SF | E82: 3968668.9 | F82: =+H82/(E82-M82) -> 1 | G82: =H82+I82 -> 3968668.9 | H82: 3790858.3 | I82: =IF(F82>0.2,IF(M82>0,IF(J82>M82,M82,IF((F82*M82)>J82,F82*M82,J82)),M82),0) -> 177810.56 | J82: 62853.416 | K82: =I82-J82 -> 114957.14 | L82: =E82-G82 -> 0 | M82: =E82-H82 -> 177810.56 | N82: 46016 | O82: =M82-P82 -> 12810.56 | P82: 165000
A83: 54.9323 | B83: Semitropic Water Storage Dist. - Buena Vista Water Storage District Turnout Valve Repair | C83: DS | D83: DS | E83: 110661.47 | F83: =+H83/(E83-M83) -> 1 | G83: =H83+I83 -> 110661.47 | H83: =86308.26+2536.57+5638.38 -> 94483.21 | I83: =IF(F83>0.2,IF(M83>0,IF(J83>M83,M83,IF((F83*M83)>J83,F83*M83,J83)),M83),0) -> 16178.26 | J83: 0 | K83: =I83-J83 -> 16178.26 | L83: =E83-G83 -> 0 | M83: =E83-H83 -> 16178.26 | N83: 45747 | O83: =M83-P83 -> 0 | P83: 16178.26
A84: 54.9329 | B84: Kern Water Bank Authority - Valve Replacement Parts | C84: DS | D84: DS | E84: 18201.12 | F84: =+H84/(E84-M84) -> 1 | G84: =H84+I84 -> 18201.12 | H84: 16466.72 | I84: =IF(F84>0.2,IF(M84>0,IF(J84>M84,M84,IF((F84*M84)>J84,F84*M84,J84)),M84),0) -> 1734.4 | K84: =I84-J84 -> 1734.4 | L84: =E84-G84 -> 0 | M84: =E84-H84 -> 1734.4 | N84: 45931 | O84: =M84-P84 -> 0 | P84: 1734.4
A85: 54.9333 | B85: Semitropic Water Storage Dist. - SWSD 2 Hydro Turbine Repair Project | C85: DS | D85: DS | E85: 427464.77 | F85: =+H85/(E85-M85) -> 1 | G85: =H85+I85 -> 427464.77 | H85: =368815.29+3099.97 -> 371915.26 | I85: =IF(F85>0.2,IF(M85>0,IF(J85>M85,M85,IF((F85*M85)>J85,F85*M85,J85)),M85),0) -> 55549.51 | J85: 14888.68 | K85: =I85-J85 -> 40660.83 | L85: =E85-G85 -> 0 | M85: =E85-H85 -> 55549.51 | N85: 45717 | O85: =M85-P85 -> -3099.97 | P85: 58649.48
A86: 54.9338 | B86: Laguna County Sanitation Dist. - WWTP Storage Pond Slide Gates Replacement | C86: PR | D86: PR | E86: 175884.64 | F86: =+H86/(E86-M86) -> 1 | G86: =H86+I86 -> 175884.64 | H86: 119186.11 | I86: =IF(F86>0.2,IF(M86>0,IF(J86>M86,M86,IF((F86*M86)>J86,F86*M86,J86)),M86),0) -> 56698.53 | J86: 54179.798 | K86: =I86-J86 -> 2518.7323 | L86: =E86-G86 -> 0 | M86: =E86-H86 -> 56698.53 | N86: 45688 | O86: =M86-P86 -> 0 | P86: 56698.53
A87: 54.9341 | B87: Nipomo Community Service Dist. - Water Project Interconnection Improvements | C87: PR | D87: PR | E87: 1251279 | F87: =+H87/(E87-M87) -> 1 | G87: =H87+I87 -> 1251279 | H87: 1063532.4 | I87: =IF(F87>0.2,IF(M87>0,IF(J87>M87,M87,IF((F87*M87)>J87,F87*M87,J87)),M87),0) -> 187746.6 | J87: 0 | K87: =I87-J87 -> 187746.6 | L87: =E87-G87 -> 0 | M87: =E87-H87 -> 187746.6 | N87: 46022 | O87: =M87-P87 -> 415.6 | P87: 187331
A88: 54.9342 | B88: North of River Sanitary Dist. No. 1 - Sanitary Sewer Rehab Package 21 Remove and Replace | C88: DS | D88: DS | E88: 199161.5 | F88: =+H88/(E88-M88) -> 1 | G88: =H88+I88 -> 199161.5 | H88: 124146.3 | I88: =IF(F88>0.2,IF(M88>0,IF(J88>M88,M88,IF((F88*M88)>J88,F88*M88,J88)),M88),0) -> 75015.2 | J88: 41394.113 | K88: =I88-J88 -> 33621.087 | L88: =E88-G88 -> 0 | M88: =E88-H88 -> 75015.2 | N88: 45688 | O88: =M88-P88 -> 0 | P88: 75015.2
A89: 54.9347 | B89: City of Guadalupe - Effluent Pump Station Flow Meter Installation | C89: JG | D89: PR | E89: 7100 | F89: =+H89/(E89-M89) -> 1 | G89: =H89+I89 -> 7100 | H89: 3227.7 | I89: =IF(F89>0.2,IF(M89>0,IF(J89>M89,M89,IF((F89*M89)>J89,F89*M89,J89)),M89),0) -> 3872.3 | K89: =I89-J89 -> 3872.3 | L89: =E89-G89 -> 0 | M89: =E89-H89 -> 3872.3 | N89: 45716 | O89: =M89-P89 -> 0 | P89: 3872.3
A90: 54.9349 | B90: North of River Sanitary Dist. No. 1 - Sanitary Sewer Rehabilitation Package A | C90: DS | D90: DS | E90: 290129 | F90: =+H90/(E90-M90) -> 1 | G90: =H90+I90 -> 290129 | H90: 197889.31 | I90: =IF(F90>0.2,IF(M90>0,IF(J90>M90,M90,IF((F90*M90)>J90,F90*M90,J90)),M90),0) -> 92239.69 | J90: 4519.6837 | K90: =I90-J90 -> 87720.006 | L90: =E90-G90 -> 0 | M90: =E90-H90 -> 92239.69 | N90: 45716 | O90: =M90-P90 -> 0 | P90: 92239.69
A91: 54.935 | B91: Kern Water Bank Authority - Construct New Well 18P01 | C91: DS | D91: DS | E91: 129965.06 | F91: =+H91/(E91-M91) -> 1 | G91: =H91+I91 -> 129965.06 | H91: =104443.06+2267.9+914.22+718.5-718.5+12693.5 -> 120318.68 | I91: =IF(F91>0.2,IF(M91>0,IF(J91>M91,M91,IF((F91*M91)>J91,F91*M91,J91)),M91),0) -> 9646.38 | J91: 0 | K91: =I91-J91 -> 9646.38 | L91: =E91-G91 -> 0 | M91: =E91-H91 -> 9646.38 | N91: 45747 | O91: =M91-P91 -> 0 | P91: 9646.38
A92: 54.9351 | B92: Arvin Edison Water Storage Dist. - Forrest Frick Valve Replacement | C92: RF | D92: RF | E92: 153298.79 | F92: =+H92/(E92-M92) -> 1 | G92: =H92+I92 -> 153298.79 | H92: 136808.3 | I92: =IF(F92>0.2,IF(M92>0,IF(J92>M92,M92,IF((F92*M92)>J92,F92*M92,J92)),M92),0) -> 16490.49 | J92: 11095.267 | K92: =I92-J92 -> 5395.2229 | L92: =E92-G92 -> 0 | M92: =E92-H92 -> 16490.49 | N92: 45688 | O92: =M92-P92 -> 0 | P92: 16490.49
A93: 54.9353 | B93: Kern Water Bank Authority - Cut In Valve at Well 18R01 | C93: DS | D93: DS | E93: 2008.42 | F93: =+H93/(E93-M93) -> 1 | G93: =H93+I93 -> 2008.42 | H93: 1117.5 | I93: =IF(F93>0.2,IF(M93>0,IF(J93>M93,M93,IF((F93*M93)>J93,F93*M93,J93)),M93),0) -> 890.92 | J93: 0 | K93: =I93-J93 -> 890.92 | L93: =E93-G93 -> 0 | M93: =E93-H93 -> 890.92 | N93: 45747 | O93: =M93-P93 -> 0 | P93: 890.92
A94: 54.9354 | B94: California Water Service Co. - Northeast Plant Lift Station Pipe Repair | C94: DS | D94: DS | E94: 9571.2 | F94: =+H94/(E94-M94) -> 1 | G94: =H94+I94 -> 9571.2 | H94: =12351.11-3887.06-233.22 -> 8230.83 | I94: =IF(F94>0.2,IF(M94>0,IF(J94>M94,M94,IF((F94*M94)>J94,F94*M94,J94)),M94),0) -> 1340.37 | J94: 1923.43 | K94: =I94-J94 -> -583.06 | L94: =E94-G94 -> 0 | M94: =E94-H94 -> 1340.37 | N94: 45688 | O94: =M94-P94 -> 0 | P94: 1340.37
A95: 54.9355 | B95: Kern Water Bank Authority - Install Canal Valve at Well 17P01 | C95: DS | D95: DS | E95: 2806.42 | F95: =+H95/(E95-M95) -> 1 | G95: =H95+I95 -> 2806.42 | H95: 1815.23 | I95: =IF(F95>0.2,IF(M95>0,IF(J95>M95,M95,IF((F95*M95)>J95,F95*M95,J95)),M95),0) -> 991.19 | J95: 0 | K95: =I95-J95 -> 991.19 | L95: =E95-G95 -> 0 | M95: =E95-H95 -> 991.19 | N95: 45747 | O95: =M95-P95 -> 0 | P95: 991.19
A96: 54.9357 | B96: Kern Water Bank Authority - Install Canal Valve at Well 20A01 | C96: DS | D96: DS | E96: 1760.42 | F96: =+H96/(E96-M96) -> 1 | G96: =H96+I96 -> 1760.42 | H96: 889.66 | I96: =IF(F96>0.2,IF(M96>0,IF(J96>M96,M96,IF((F96*M96)>J96,F96*M96,J96)),M96),0) -> 870.76 | J96: 0 | K96: =I96-J96 -> 870.76 | L96: =E96-G96 -> 0 | M96: =E96-H96 -> 870.76 | N96: 45747 | O96: =M96-P96 -> 0 | P96: 870.76
A97: 54.9358 | B97: Arvin Edison Water Storage Dist. - Frick Unit - Phase I Turnout | C97: AH | D97: SF | E97: 1147640 | F97: =+H97/(E97-M97) -> 1 | G97: =H97+I97 -> 1147640 | H97: 1125399.8 | I97: =IF(F97>0.2,IF(M97>0,IF(J97>M97,M97,IF((F97*M97)>J97,F97*M97,J97)),M97),0) -> 22240.17 | J97: 15917.551 | K97: =I97-J97 -> 6322.6193 | L97: =E97-G97 -> 0 | M97: =E97-H97 -> 22240.17 | N97: 45925 | O97: =M97-P97 -> 0 | P97: 22240.17
A98: 54.936 | B98: Kern Water Bank Authority - Install Canal Valve at Well 20C01 | C98: DS | D98: DS | E98: 1855.92 | F98: =+H98/(E98-M98) -> 1 | G98: =H98+I98 -> 1855.92 | H98: 1144.88 | I98: =IF(F98>0.2,IF(M98>0,IF(J98>M98,M98,IF((F98*M98)>J98,F98*M98,J98)),M98),0) -> 711.04 | J98: 0 | K98: =I98-J98 -> 711.04 | L98: =E98-G98 -> 0 | M98: =E98-H98 -> 711.04 | N98: 45747 | O98: =M98-P98 -> 0 | P98: 711.04
A99: 54.9361 | B99: Semitropic Water Storage Dist. - Pond Poso Pumping Plant Pipe Repair | C99: DS | D99: DS | E99: 108668.35 | F99: =+H99/(E99-M99) -> 1 | G99: =H99+I99 -> 108668.35 | H99: =100591.91+6482.96 -> 107074.87 | I99: =IF(F99>0.2,IF(M99>0,IF(J99>M99,M99,IF((F99*M99)>J99,F99*M99,J99)),M99),0) -> 1593.48 | K99: =I99-J99 -> 1593.48 | L99: =E99-G99 -> 0 | M99: =E99-H99 -> 1593.48 | N99: 45746 | O99: =M99-P99 -> 0 | P99: 1593.48
A100: 54.9362 | B100: Cawelo Water Dist. - Remove and Replace 24” and 18” Well Line | C100: AH | D100: AH | E100: 425035.04 | F100: =+H100/(E100-M100) -> 1 | G100: =H100+I100 -> 425035.04 | H100: 375601.24 | I100: =IF(F100>0.2,IF(M100>0,IF(J100>M100,M100,IF((F100*M100)>J100,F100*M100,J100)),M100),0) -> 49433.8 | J100: 18050.992 | K100: =I100-J100 -> 31382.808 | L100: =E100-G100 -> 0 | M100: =E100-H100 -> 49433.8 | N100: 45682 | O100: =M100-P100 -> 0 | P100: 49433.8
A101: 54.9363 | B101: Kern Water Bank Authority - Install Canal Valve at Well 21A02 | C101: DS | D101: DS | E101: 1855.92 | F101: =+H101/(E101-M101) -> 1 | G101: =H101+I101 -> 1855.92 | H101: 777.55 | I101: =IF(F101>0.2,IF(M101>0,IF(J101>M101,M101,IF((F101*M101)>J101,F101*M101,J101)),M101),0) -> 1078.37 | J101: 0 | K101: =I101-J101 -> 1078.37 | L101: =E101-G101 -> 0 | M101: =E101-H101 -> 1078.37 | N101: 45747 | O101: =M101-P101 -> 0 | P101: 1078.37
A102: 54.9365 | B102: Kern Water Bank Authority - Install Canal Valve at Well 16J01 | C102: DS | D102: DS | E102: 2216.42 | F102: =+H102/(E102-M102) -> 1 | G102: =H102+I102 -> 2216.42 | H102: 1263.33 | I102: =IF(F102>0.2,IF(M102>0,IF(J102>M102,M102,IF((F102*M102)>J102,F102*M102,J102)),M102),0) -> 953.09 | J102: 0 | K102: =I102-J102 -> 953.09 | L102: =E102-G102 -> 0 | M102: =E102-H102 -> 953.09 | N102: 45747 | O102: =M102-P102 -> 0 | P102: 953.09
A103: 54.9367 | B103: Kern Water Bank Authority - Install Canal Valve at Well 15N01 | C103: DS | D103: DS | E103: 2540.42 | F103: =+H103/(E103-M103) -> 1 | G103: =H103+I103 -> 2540.42 | H103: 1602.33 | I103: =IF(F103>0.2,IF(M103>0,IF(J103>M103,M103,IF((F103*M103)>J103,F103*M103,J103)),M103),0) -> 938.09 | J103: 0 | K103: =I103-J103 -> 938.09 | L103: =E103-G103 -> 0 | M103: =E103-H103 -> 938.09 | N103: 45747 | O103: =M103-P103 -> 0 | P103: 938.09
A104: 54.9368 | B104: North of River Sanitary Dist. No. 1 - Wilson Ave Sewer Repair | C104: DS | D104: DS | E104: 15697.91 | F104: =+H104/(E104-M104) -> 1 | G104: =H104+I104 -> 15697.91 | H104: 13653.62 | I104: =IF(F104>0.2,IF(M104>0,IF(J104>M104,M104,IF((F104*M104)>J104,F104*M104,J104)),M104),0) -> 2044.29 | J104: 2044.29 | K104: =I104-J104 -> 0 | L104: =E104-G104 -> 0 | M104: =E104-H104 -> 2044.29 | N104: 45688 | O104: =M104-P104 -> 0 | P104: 2044.29
A105: 54.937 | B105: Kern Water Bank Authority - Install Canal Valve at Well 20L01 | C105: DS | D105: DS | E105: 1760.42 | F105: =+H105/(E105-M105) -> 1 | G105: =H105+I105 -> 1760.42 | H105: 889.64 | I105: =IF(F105>0.2,IF(M105>0,IF(J105>M105,M105,IF((F105*M105)>J105,F105*M105,J105)),M105),0) -> 870.78 | J105: 0 | K105: =I105-J105 -> 870.78 | L105: =E105-G105 -> 0 | M105: =E105-H105 -> 870.78 | N105: 45747 | O105: =M105-P105 -> 0 | P105: 870.78
A106: 54.9371 | B106: Bakersfield Overhead 2025 | C106: JJM | D106: JJM | F106: =+H106/(E106-M106) -> 1 | G106: =H106+I106 -> 0 | H106: 1267652.8 | I106: =IF(F106>0.2,IF(M106>0,IF(J106>M106,M106,IF((F106*M106)>J106,F106*M106,J106)),M106),0) -> -1267652.8 | J106: 0 | K106: =I106-J106 -> -1267652.8 | L106: =E106-G106 -> 0 | M106: -1267652.8 | N106: 46022 | O106: =M106-P106 -> -70266.13 | P106: -1197386.6
A107: 54.9372 | B107: Bakersfield Estimating 2025 | C107: JJM | D107: JJM | F107: =+H107/(E107-M107) -> 1 | G107: =H107+I107 -> 0 | H107: 588792.6 | I107: =IF(F107>0.2,IF(M107>0,IF(J107>M107,M107,IF((F107*M107)>J107,F107*M107,J107)),M107),0) -> -588792.6 | J107: 0 | K107: =I107-J107 -> -588792.6 | L107: =E107-G107 -> 0 | M107: -588792.6 | N107: 46022 | O107: =M107-P107 -> -39388.72 | P107: -549403.88
A108: 54.9374 | B108: City of Santa Maria - WWTP Trickling Filter Repairs | C108: PR | D108: PR | E108: 32962 | F108: =+H108/(E108-M108) -> 1 | G108: =H108+I108 -> 32962 | H108: 19986.45 | I108: =IF(F108>0.2,IF(M108>0,IF(J108>M108,M108,IF((F108*M108)>J108,F108*M108,J108)),M108),0) -> 12975.55 | K108: =I108-J108 -> 12975.55 | L108: =E108-G108 -> 0 | M108: =E108-H108 -> 12975.55 | N108: 45747 | O108: =M108-P108 -> 0 | P108: 12975.55
A109: 54.9375 | B109: City of Santa Maria - WWTP Clarifier Repairs | C109: PR | D109: PR | E109: 8232.73 | F109: =+H109/(E109-M109) -> 1 | G109: =H109+I109 -> 8232.73 | H109: 4545.48 | I109: =IF(F109>0.2,IF(M109>0,IF(J109>M109,M109,IF((F109*M109)>J109,F109*M109,J109)),M109),0) -> 3687.25 | K109: =I109-J109 -> 3687.25 | L109: =E109-G109 -> 0 | M109: =E109-H109 -> 3687.25 | N109: 45729 | O109: =M109-P109 -> 0 | P109: 3687.25
A110: 54.9379 | B110: Semitropic Water Storage Dist. - Delta System Pipe Repair | C110: DS | D110: DS | E110: 41679.77 | F110: =+H110/(E110-M110) -> 1 | G110: =H110+I110 -> 41679.77 | H110: 36111.95 | I110: =IF(F110>0.2,IF(M110>0,IF(J110>M110,M110,IF((F110*M110)>J110,F110*M110,J110)),M110),0) -> 5567.82 | K110: =I110-J110 -> 5567.82 | L110: =E110-G110 -> 0 | M110: =E110-H110 -> 5567.82 | N110: 45716 | O110: =M110-P110 -> 0 | P110: 5567.82
A111: 54.938 | B111: Cawelo Water Dist. - CWD Pump Station Pipe Repair | C111: RF | D111: AH | E111: 22446.19 | F111: =+H111/(E111-M111) -> 1 | G111: =H111+I111 -> 22446.19 | H111: 18064.72 | I111: =IF(F111>0.2,IF(M111>0,IF(J111>M111,M111,IF((F111*M111)>J111,F111*M111,J111)),M111),0) -> 4381.47 | K111: =I111-J111 -> 4381.47 | L111: =E111-G111 -> 0 | M111: =E111-H111 -> 4381.47 | N111: 45741 | O111: =M111-P111 -> 0 | P111: 4381.47
A112: 54.9381 | B112: Kern Sanitation Authority - KSA Trickling Filter Bracket Replacement | C112: DS | D112: DS | E112: 58900 | F112: =+H112/(E112-M112) -> 1 | G112: =H112+I112 -> 58900 | H112: 28875.38 | I112: =IF(F112>0.2,IF(M112>0,IF(J112>M112,M112,IF((F112*M112)>J112,F112*M112,J112)),M112),0) -> 30024.62 | K112: =I112-J112 -> 30024.62 | L112: =E112-G112 -> 0 | M112: =E112-H112 -> 30024.62 | N112: 45746 | O112: =M112-P112 -> 0 | P112: 30024.62
A113: 54.9382 | B113: Laguna County Sanitation Dist. - Laguna WWTP Flow Meter FIT-7000 Replacement | C113: PR | D113: PR | E113: 143799 | F113: =+H113/(E113-M113) -> 1 | G113: =H113+I113 -> 143799 | H113: 108690.45 | I113: =IF(F113>0.2,IF(M113>0,IF(J113>M113,M113,IF((F113*M113)>J113,F113*M113,J113)),M113),0) -> 35108.55 | J113: 0 | K113: =I113-J113 -> 35108.55 | L113: =E113-G113 -> 0 | M113: =E113-H113 -> 35108.55 | N113: 46053 | O113: =M113-P113 -> 2108.55 | P113: 33000
A114: 54.9383 | B114: Semitropic Water Storage Dist. - Amendment No. 19 Operate 300 CFS RWPP 2025 | C114: DS | D114: DS | E114: 17542.44 | F114: =+H114/(E114-M114) -> 1 | G114: =H114+I114 -> 17542.44 | H114: 15759.76 | I114: =IF(F114>0.2,IF(M114>0,IF(J114>M114,M114,IF((F114*M114)>J114,F114*M114,J114)),M114),0) -> 1782.68 | K114: =I114-J114 -> 1782.68 | L114: =E114-G114 -> 0 | M114: =E114-H114 -> 1782.68 | N114: 46021 | O114: =M114-P114 -> 0 | P114: 1782.68
...
