Workbook

Sheet JV GAAP WIP
A1: W.M. Lyles Co.
A2: JV WORK IN PROCESS-GAAP BASIS
A3: ='JV GAAP'!A4 -> For the 12 Months Period Ended 12/31/25
C5: AMOUNT | D5: REMAINING | E5: TOTAL | F5: COSTS | G5: ESTIMATED | H5: TOTAL | I5: TOTAL | J5: % OF | L5: OVER
C6: BILLED | D6: TO BE | E6: ESTIMATED | F6: INCURED | G6: COSTS TO | H6: ESTIMATED | I6: ESTIMATED | J6: COMPLETION | K6: PROFIT / | L6: (UNDER)
A7: AREA | B7: DESCRIPTION | C7: TO DATE | D7: BILLED | E7: CONTRACT | F7: TO DATE | G7: COMPLETE | H7: COSTS | I7: PROFIT | J7: COST/COST | K7: LOSS | L7: BILLIING
A9: ='JV GAAP'!A11 -> Northern | B9: ='JV GAAP'!B11 -> Stockton Phase 1 | C9: ='JV GAAP'!K11 -> 5508112 | D9: ='JV GAAP'!N11 -> 0 | E9: ='JV GAAP'!D11 -> 5508112 | F9: ='JV GAAP'!G11 -> 4939022 | G9: ='JV GAAP'!M11 -> 0 | H9: ='JV GAAP'!E11 -> 4939022 | I9: ='JV GAAP'!F11 -> 569090 | J9: ='JV GAAP'!H11 -> 1 | K9: ='JV GAAP'!I11 -> 569090 | L9: ='JV GAAP'!L11 -> 0
A10: ='JV GAAP'!A12 -> Northern | B10: ='JV GAAP'!B12 -> Stockton Phase 2 | C10: ='JV GAAP'!K12 -> 225085557 | D10: ='JV GAAP'!N12 -> 644014.63 | E10: ='JV GAAP'!D12 -> 2.2572957e+08 | F10: ='JV GAAP'!G12 -> 2.12615e+08 | G10: ='JV GAAP'!M12 -> 0 | H10: ='JV GAAP'!E12 -> 2.12615e+08 | I10: ='JV GAAP'!F12 -> 13114570 | J10: ='JV GAAP'!H12 -> 1 | K10: ='JV GAAP'!I12 -> 13114570 | L10: ='JV GAAP'!L12 -> -644014.63
A11: ='JV GAAP'!A13 -> Northern | B11: ='JV GAAP'!B13 -> City of Santa Cruz - Graham Hill WTP | C11: ='JV GAAP'!K13 -> 11042468 | D11: ='JV GAAP'!N13 -> 55906.69 | E11: ='JV GAAP'!D13 -> 11098374 | F11: ='JV GAAP'!G13 -> 10929118 | G11: ='JV GAAP'!M13 -> 0 | H11: ='JV GAAP'!E13 -> 10929118 | I11: ='JV GAAP'!F13 -> 169256.76 | J11: ='JV GAAP'!H13 -> 1 | K11: ='JV GAAP'!I13 -> 169256.76 | L11: ='JV GAAP'!L13 -> -55906.69
A12: ='JV GAAP'!A14 -> Southern | B12: ='JV GAAP'!B14 -> Silverlake | C12: ='JV GAAP'!K14 -> 364279554 | D12: ='JV GAAP'!N14 -> 2066292 | E12: ='JV GAAP'!D14 -> 366345846 | F12: ='JV GAAP'!G14 -> 3.3529479e+08 | G12: ='JV GAAP'!M14 -> 5666024.4 | H12: ='JV GAAP'!E14 -> 340960819 | I12: ='JV GAAP'!F14 -> 25385027 | J12: ='JV GAAP'!H14 -> 0.98338218 | K12: ='JV GAAP'!I14 -> 25406592 | L12: ='JV GAAP'!L14 -> 3578167
A13: ='JV GAAP'!A15 -> Southern | B13: ='JV GAAP'!B15 -> East County Advanced Package 1 | C13: ='JV GAAP'!K15 -> 4.1684452e+08 | D13: ='JV GAAP'!N15 -> 63585781 | E13: ='JV GAAP'!D15 -> 4.804303e+08 | F13: ='JV GAAP'!G15 -> 4.0411575e+08 | G13: ='JV GAAP'!M15 -> 48017632 | H13: ='JV GAAP'!E15 -> 4.5213338e+08 | I13: ='JV GAAP'!F15 -> 28296915 | J13: ='JV GAAP'!H15 -> 0.89379764 | K13: ='JV GAAP'!I15 -> 30680783 | L13: ='JV GAAP'!L15 -> -17952016
A14: ='JV GAAP'!A16 -> Southern | B14: ='JV GAAP'!B16 -> East County Advanced Package 3 | C14: ='JV GAAP'!K16 -> 73088486 | D14: ='JV GAAP'!N16 -> 21497344 | E14: ='JV GAAP'!D16 -> 94585830 | F14: ='JV GAAP'!G16 -> 92385154 | G14: ='JV GAAP'!M16 -> 0 | H14: ='JV GAAP'!E16 -> 92385154 | I14: ='JV GAAP'!F16 -> 2200676.8 | J14: ='JV GAAP'!H16 -> 1 | K14: ='JV GAAP'!I16 -> 2200676.8 | L14: ='JV GAAP'!L16 -> -21497344
A15: ='JV GAAP'!A17 -> Southern | B15: ='JV GAAP'!B17 -> City of Banning | C15: ='JV GAAP'!K17 -> 1255755.8 | D15: ='JV GAAP'!N17 -> 2742872.2 | E15: ='JV GAAP'!D17 -> 3998628 | F15: ='JV GAAP'!G17 -> 1142481.3 | G15: ='JV GAAP'!M17 -> 2492634.7 | H15: ='JV GAAP'!E17 -> 3635116 | I15: ='JV GAAP'!F17 -> 363512 | J15: ='JV GAAP'!H17 -> 0.31429019 | K15: ='JV GAAP'!I17 -> 113274.33 | L15: ='JV GAAP'!L17 -> 0.13
C17: =SUM(C9:C16) -> 1.0971044e+09 | D17: =SUM(D9:D16) -> 90592211 | E17: =SUM(E9:E16) -> 1.1876967e+09 | F17: =SUM(F9:F16) -> 1.0614213e+09 | G17: =SUM(G9:G16) -> 56176292 | H17: =SUM(H9:H16) -> 1.1175976e+09 | I17: =SUM(I9:I16) -> 70099047 | K17: =SUM(K9:K16) -> 72254243 | L17: =SUM(L9:L16) -> -36571115

Sheet JV GAAP
A1: W.M. Lyles Co.
A2: JV WORK IN PROCESS
A3: FISCAL YEAR ENDING 12/31/25
A4: For the 12 Months Period Ended 12/31/25
A7: Full JV
D8: CONTRACT | E8: EST. TOTAL | F8: EXPECTED | G8: JOB TO DATE | H8: COST / | I8: JOB TO DATE | J8: JOB TO DATE | M8: EST. COST TO | N8: CONTRACT | O8: PRIOR YR | P8: CURRENT
A9: AREA | B9: DESCRIPTION | D9: AMOUNT | E9: COSTS | F9: PROFIT | G9: JOB COSTS | H9: COST | I9: PROFIT/LOSS | J9: EARNED REV. | K9: JTD BILLED | L9: CURRENT WIP | M9: COMPLETE | N9: BALANCE | O9: JTD PROFIT | P9: YTD PROFIT
A10: JV Projects
A11: Northern | B11: Stockton Phase 1 | D11: 5508112 | E11: =D11-F11 -> 4939022 | F11: 569090 | G11: 4939022 | H11: =IF(E11<>0,+G11/E11,0) -> 1 | I11: 569090 | J11: =+G11+I11 -> 5508112 | K11: 5508112 | L11: =K11-J11 -> 0 | M11: =+E11-G11 -> 0 | N11: =+D11-K11 -> 0 | O11: =O26*2 -> 569090 | P11: =I11-O11 -> 0
A12: Northern | B12: Stockton Phase 2 | D12: 2.2572957e+08 | E12: 2.12615e+08 | F12: =D12-E12 -> 13114570 | G12: 2.12615e+08 | H12: =IF(E12<>0,+G12/E12,0) -> 1 | I12: =J12-G12 -> 13114570 | J12: 2.2572957e+08 | K12: 225085557 | L12: =K12-J12 -> -644014.63 | M12: =+E12-G12 -> 0 | N12: =+D12-K12 -> 644014.63 | O12: =O27*2 -> 19477451 | P12: =I12-O12 -> -6362880.5
A13: Northern | B13: City of Santa Cruz - Graham Hill WTP | D13: 11098374 | E13: 10929118 | F13: =D13-E13 -> 169256.76 | G13: 10929118 | H13: =IF(E13<>0,+G13/E13,0) -> 1 | I13: =J13-G13 -> 169256.76 | J13: 11098374 | K13: 11042468 | L13: =K13-J13 -> -55906.69 | M13: =+E13-G13 -> 0 | N13: =+D13-K13 -> 55906.69 | O13: =O28*2 -> -62367.34 | P13: =I13-O13 -> 231624.1
A14: Southern | B14: Silverlake | D14: 366345846 | E14: =D14-F14 -> 340960819 | F14: 25385027 | G14: =G29*4 -> 3.3529479e+08 | H14: =IF(E14<>0,+G14/E14,0) -> 0.98338218 | I14: =I29*4 -> 25406592 | J14: =+G14+I14 -> 360701387 | K14: 364279554 | L14: =K14-J14 -> 3578167 | M14: =+E14-G14 -> 5666024.4 | N14: =+D14-K14 -> 2066292 | O14: =O29/0.25 -> 24716046 | P14: =I14-O14 -> 690546
A15: Southern | B15: East County Advanced Package 1 | D15: 4.804303e+08 | E15: =D15-F15 -> 4.5213338e+08 | F15: 28296915 | G15: 4.0411575e+08 | H15: =IF(E15<>0,+G15/E15,0) -> 0.89379764 | I15: 30680783 | J15: =+G15+I15 -> 4.3479653e+08 | K15: 4.1684452e+08 | L15: =K15-J15 -> -17952016 | M15: =+E15-G15 -> 48017632 | N15: =+D15-K15 -> 63585781 | O15: =O30*2 -> 26187673 | P15: =I15-O15 -> 4493110
A16: Southern | B16: East County Advanced Package 3 | D16: 94585830 | E16: 92385154 | F16: =D16-E16 -> 2200676.8 | G16: 92385154 | H16: =IF(E16<>0,+G16/E16,0) -> 1 | I16: =J16-G16 -> 2200676.8 | J16: 94585830 | K16: 73088486 | L16: =K16-J16 -> -21497344 | M16: =+E16-G16 -> 0 | N16: =+D16-K16 -> 21497344 | O16: =O31*2 -> 3468742.3 | P16: =I16-O16 -> -1268065.5
A17: Southern | B17: City of Banning | D17: 3998628 | E17: =D17-F17 -> 3635116 | F17: 363512 | G17: 1142481.3 | H17: =IF(E17<>0,+G17/E17,0) -> 0.31429019 | I17: 113274.33 | J17: =+G17+I17 -> 1255755.6 | K17: 1255755.8 | L17: =K17-J17 -> 0.13 | M17: =+E17-G17 -> 2492634.7 | N17: =+D17-K17 -> 2742872.2 | O17: =O32*2 -> 0 | P17: =I17-O17 -> 113274.33
A19: Grand Totals | D19: =SUM(D11:D18) -> 1.1876967e+09 | E19: =SUM(E11:E18) -> 1.1175976e+09 | F19: =SUM(F11:F18) -> 70099047 | G19: =SUM(G11:G18) -> 1.0614213e+09 | I19: =SUM(I11:I18) -> 72254243 | J19: =SUM(J11:J18) -> 1.1336756e+09 | K19: =SUM(K11:K18) -> 1.0971044e+09 | L19: =SUM(L11:L18) -> -36571115 | M19: =SUM(M11:M18) -> 56176292 | N19: =SUM(N11:N18) -> 90592211 | O19: =SUM(O11:O18) -> 74356635 | P19: =SUM(P11:P18) -> -2102391.6
A22: WML Portion
A24: AREA | B24: DESCRIPTION | C24: % of JV | D24: CONTRACT AMOUNT | E24: EST. TOTALS COSTS | F24: EXPECTED PROFIT | G24: JOB TO DATE JOB COSTS | H24: COST/COST | I24: JOB TO DATE PROFIT/LOSS | J24: JOB TO DATE EARNED REV. | K24: JTD BILLED | L24: CURRENT WIP | M24: EST. COST TO COMPLETE | N24: CONTRACT BALANCE | O24: PRIOR YR JTD PROFIT | P24: CURRENT YTD PROFIT
A25: JV Projects
A26: Northern | B26: Stockton Phase 1 | C26: 0.5 | D26: =D11/2 -> 2754056 | E26: =D26-F26 -> 2469511 | F26: =F11/2 -> 284545 | G26: =G11/2 -> 2469511 | H26: =IF(E26<>0,+G26/E26,0) -> 1 | I26: =I11/2 -> 284545 | J26: =+G26+I26 -> 2754056 | K26: =K11/2 -> 2754056 | L26: =K26-J26 -> 0 | M26: =+E26-G26 -> 0 | N26: =+D26-K26 -> 0 | O26: 284545 | P26: =I26-O26 -> 0
A27: Northern | B27: Stockton Phase 2 | C27: 0.5 | D27: =D12/2 -> 1.1286479e+08 | E27: =D27-F27 -> 1.063075e+08 | F27: =F12/2 -> 6557285 | G27: =G12/2 -> 1.063075e+08 | H27: =IF(E27<>0,+G27/E27,0) -> 1 | I27: =I12/2 -> 6557285 | J27: =+G27+I27 -> 1.1286479e+08 | K27: =K12/2 -> 1.1254278e+08 | L27: =K27-J27 -> -322007.31 | M27: =+E27-G27 -> 0 | N27: =+D27-K27 -> 322007.31 | O27: 9738725.3 | P27: =I27-O27 -> -3181440.3
A28: Northern | B28: City of Santa Cruz - Graham Hill WTP | C28: 0.5 | D28: =D13/2 -> 5549187.2 | E28: =D28-F28 -> 5464558.9 | F28: =F13/2 -> 84628.38 | G28: =G13/2 -> 5464558.9 | H28: =IF(E28<>0,+G28/E28,0) -> 1 | I28: =I13/2 -> 84628.38 | J28: =+G28+I28 -> 5549187.2 | K28: =K13/2 -> 5521233.9 | L28: =K28-J28 -> -27953.345 | M28: =+E28-G28 -> 0 | N28: =+D28-K28 -> 27953.345 | O28: -31183.67 | P28: =I28-O28 -> 115812.05
A29: Southern | B29: Silverlake | C29: 0.25 | D29: =D14*0.25 -> 91586462 | E29: =D29-F29 -> 85240205 | F29: =F14*0.25 -> 6346256.8 | G29: 83823699 | H29: =IF(E29<>0,+G29/E29,0) -> 0.98338218 | I29: 6351648.1 | J29: =+G29+I29 -> 90175347 | K29: =K14*0.25 -> 91069888 | L29: =K29-J29 -> 894541.75 | M29: =+E29-G29 -> 1416506.1 | N29: =+D29-K29 -> 516573 | O29: 6179011.6 | P29: =I29-O29 -> 172636.5
A30: Southern | B30: East County Advanced Package 1 | C30: 0.5 | D30: =D15/2 -> 2.4021515e+08 | E30: =D30-F30 -> 2.2606669e+08 | F30: =F15/2 -> 14148457 | G30: =G15/2 -> 2.0205787e+08 | H30: =IF(E30<>0,+G30/E30,0) -> 0.89379764 | I30: =I15/2 -> 15340391 | J30: =+G30+I30 -> 2.1739827e+08 | K30: =K15/2 -> 2.0842226e+08 | L30: =K30-J30 -> -8976008.1 | M30: =+E30-G30 -> 24008816 | N30: =+D30-K30 -> 31792890 | O30: 13093836 | P30: =I30-O30 -> 2246555
A31: Southern | B31: East County Advanced Package 3 | C31: 0.5 | D31: =D16/2 -> 47292915 | E31: =D31-F31 -> 46192577 | F31: =F16/2 -> 1100338.4 | G31: =G16/2 -> 46192577 | H31: =IF(E31<>0,+G31/E31,0) -> 1 | I31: =I16/2 -> 1100338.4 | J31: =+G31+I31 -> 47292915 | K31: =K16/2 -> 36544243 | L31: =K31-J31 -> -10748672 | M31: =+E31-G31 -> 0 | N31: =+D31-K31 -> 10748672 | O31: 1734371.1 | P31: =I31-O31 -> -634032.74
A32: Southern | B32: City of Banning | C32: 0.5 | D32: =D17/2 -> 1999314 | E32: =D32-F32 -> 1817558 | F32: =F17/2 -> 181756 | G32: =G17/2 -> 571240.65 | H32: =IF(E32<>0,+G32/E32,0) -> 0.31429019 | I32: =I17/2 -> 56637.165 | J32: =+G32+I32 -> 627877.82 | K32: =K17/2 -> 627877.88 | L32: =K32-J32 -> 0.065 | M32: =+E32-G32 -> 1246317.4 | N32: =+D32-K32 -> 1371436.1 | O32: 0 | P32: =I32-O32 -> 56637.165
A34: Totals | D34: =SUM(D26:D33) -> 5.0226187e+08 | E34: =SUM(E26:E33) -> 4.735586e+08 | F34: =SUM(F26:F33) -> 28703267 | G34: =SUM(G26:G33) -> 4.4688696e+08 | I34: =SUM(I26:I33) -> 29775474 | J34: =SUM(J26:J33) -> 4.7666243e+08 | K34: =SUM(K26:K33) -> 4.5748234e+08 | L34: =SUM(L26:L33) -> -19180099 | M34: =SUM(M26:M33) -> 26671640 | N34: =SUM(N26:N33) -> 44779532 | O34: =SUM(O26:O33) -> 30999306 | P34: =SUM(P26:P33) -> -1223832.3
A37: JTD Profit Comparison
D38: GAAP | E38: BONUS
A39: AREA | B39: Description | D39: PROFIT | E39: PROFIT | F39: Variance
A40: JV Projects
A41: Northern | B41: Stockton Phase 1 | D41: =I26 -> 284545 | E41: 284545 | F41: =D41-E41 -> 0
A42: Northern | B42: Stockton Phase 2 | D42: =I27 -> 6557285 | E42: 6418180.5 | F42: =D42-E42 -> 139104.5
A43: Northern | B43: City of Santa Cruz - Graham Hill WTP | D43: =I28 -> 84628.38 | E43: 17162.5 | F43: =D43-E43 -> 67465.88
A44: Southern | B44: Silverlake | D44: =I29 -> 6351648.1 | E44: 6242676.8 | F44: =D44-E44 -> 108971.36
A45: Southern | B45: East County Advanced Package 1 | D45: =I30 -> 15340391 | E45: 8546652 | F45: =D45-E45 -> 6793739.4
A46: Southern | B46: East County Advanced Package 3 | D46: =I31 -> 1100338.4 | E46: -10262956 | F46: =D46-E46 -> 11363294
A47: Southern | B47: City of Banning | D47: =I32 -> 56637.165 | E47: 0 | F47: =D47-E47 -> 56637.165
A49: WML % JV Job Totals | D49: =SUM(D41:D48) -> 29775474 | E49: =SUM(E41:E48) -> 11246261 | F49: =SUM(F41:F48) -> 18529213

Sheet Bonus vs GAAP
A1: W. M. Lyles Co.
A2: Bonus vs. GAAP Comparison
A3: =GAAP!A4 -> For the Month Period Ended 12/31/2025
E5: Job to Date | Q5: Year to Date | AC5: 2024 Job to Date
C6: Bonus | D6: GAAP | E6: Bonus | I6: GAAP | M6: Bonus vs GAAP | Q6: Bonus | U6: GAAP | Y6: Bonus vs GAAP
A7: Job | B7: Description | C7: % Complete | D7: % Complete | E7: Revenue | F7: Cost | G7: Profit | I7: Revenue | J7: Cost | K7: Profit | M7: Revenue | N7: Cost | O7: Profit | Q7: Revenue | R7: Cost | S7: Profit | U7: Revenue | V7: Cost | W7: Profit | Y7: Revenue | Z7: Cost | AA7: Profit | AC7: Bonus vs GAAP
A8: Rocklin Open Jobs | AC8: =O8-AA8 -> 0
A9: =Bonus!A9 -> 51.1108 | B9: =Bonus!B9 -> City of Stockton - RWCF Phase 2A/2B | C9: =Bonus!G9 -> 0.99997538 | D9: =GAAP!G9 -> 1 | E9: =Bonus!I9 -> 94126377 | F9: =Bonus!F9 -> 89805618 | G9: =E9-F9 -> 4320758.9 | I9: =GAAP!I9 -> 94045648 | J9: =GAAP!F9 -> 89805618 | K9: =I9-J9 -> 4240030.1 | M9: =E9-I9 -> 80728.85 | N9: =F9-J9 -> 0 | O9: =G9-K9 -> 80728.85 | Q9: =R9+S9 -> 1278782 | R9: =Bonus!Q9 -> 1286422.8 | S9: =Bonus!S9 -> -7640.84 | U9: =V9+W9 -> 1490690.3 | V9: =GAAP!Q9 -> 1286422.8 | W9: =GAAP!S9 -> 204267.49 | Y9: =Q9-U9 -> -211908.33 | Z9: =R9-V9 -> 0 | AA9: =S9-W9 -> -211908.33 | AC9: =O9-AA9 -> 292637.18
A10: =Bonus!A10 -> 51.1129 | B10: =Bonus!B10 -> Union Sanit. Dist - Enhanced Trtmnt & Site Upgrd Ph. 1A Aeration Basin | C10: =Bonus!G10 -> 0.75772321 | D10: =GAAP!G10 -> 0.75772321 | E10: =Bonus!I10 -> 96373952 | F10: =Bonus!F10 -> 87315159 | G10: =E10-F10 -> 9058793.2 | I10: =GAAP!I10 -> 95839545 | J10: =GAAP!F10 -> 87315159 | K10: =I10-J10 -> 8524386.2 | M10: =E10-I10 -> 534407 | N10: =F10-J10 -> 0 | O10: =G10-K10 -> 534407 | Q10: =R10+S10 -> 24666258 | R10: =Bonus!Q10 -> 23558089 | S10: =Bonus!S10 -> 1108169.8 | U10: =V10+W10 -> 25124997 | V10: =GAAP!Q10 -> 23558089 | W10: =GAAP!S10 -> 1566908.8 | Y10: =Q10-U10 -> -458739 | Z10: =R10-V10 -> 0 | AA10: =S10-W10 -> -458739 | AC10: =O10-AA10 -> 993146
A11: =Bonus!A11 -> 51.1137 | B11: =Bonus!B11 -> CA Water Service Co. - Bear Gulch Pump Station 18 | C11: =Bonus!G11 -> 0.86960311 | D11: =GAAP!G11 -> 0.86960311 | E11: =Bonus!I11 -> 1141051 | F11: =Bonus!F11 -> 1042229.3 | G11: =E11-F11 -> 98821.697 | I11: =GAAP!I11 -> 1141051 | J11: =GAAP!F11 -> 1042229.3 | K11: =I11-J11 -> 98821.697 | M11: =E11-I11 -> 0 | N11: =F11-J11 -> 0 | O11: =G11-K11 -> 0 | Q11: =R11+S11 -> 842122.98 | R11: =Bonus!Q11 -> 770544.87 | S11: =Bonus!S11 -> 71578.108 | U11: =V11+W11 -> 842122.98 | V11: =GAAP!Q11 -> 770544.87 | W11: =GAAP!S11 -> 71578.108 | Y11: =Q11-U11 -> 0 | Z11: =R11-V11 -> 0 | AA11: =S11-W11 -> 0 | AC11: =O11-AA11 -> 0
A12: =Bonus!A12 -> 51.1144 | B12: =Bonus!B12 -> Silicon Valley Clean Water - FEP Improvements Project | C12: =Bonus!G12 -> 0.60744172 | D12: =GAAP!G12 -> 0.60744172 | E12: =Bonus!I12 -> 9093139 | F12: =Bonus!F12 -> 8406760.8 | G12: =E12-F12 -> 686378.17 | I12: =GAAP!I12 -> 9093139 | J12: =GAAP!F12 -> 8406760.8 | K12: =I12-J12 -> 686378.17 | M12: =E12-I12 -> 0 | N12: =F12-J12 -> 0 | O12: =G12-K12 -> 0 | Q12: =R12+S12 -> 7649428.1 | R12: =Bonus!Q12 -> 7053381.4 | S12: =Bonus!S12 -> 596046.72 | U12: =V12+W12 -> 7649428.1 | V12: =GAAP!Q12 -> 7053381.4 | W12: =GAAP!S12 -> 596046.72 | Y12: =Q12-U12 -> 0 | Z12: =R12-V12 -> 0 | AA12: =S12-W12 -> 0 | AC12: =O12-AA12 -> 0
A13: =Bonus!A13 -> 51.1146 | B13: =Bonus!B13 -> National Carbon Technologies, LLC - Aymium Williams Production Facility | C13: =Bonus!G13 -> 0.92655207 | D13: =GAAP!G13 -> 0.92655207 | E13: =Bonus!I13 -> 56675079 | F13: =Bonus!F13 -> 40950686 | G13: =E13-F13 -> 15724392 | I13: =GAAP!I13 -> 56501362 | J13: =GAAP!F13 -> 40950686 | K13: =I13-J13 -> 15550675 | M13: =E13-I13 -> 173716.62 | N13: =F13-J13 -> 0 | O13: =G13-K13 -> 173716.62 | Q13: =R13+S13 -> 51031950 | R13: =Bonus!Q13 -> 36389605 | S13: =Bonus!S13 -> 14642345 | U13: =V13+W13 -> 51940281 | V13: =GAAP!Q13 -> 36389605 | W13: =GAAP!S13 -> 15550675 | Y13: =Q13-U13 -> -908330.8 | Z13: =R13-V13 -> 0 | AA13: =S13-W13 -> -908330.8 | AC13: =O13-AA13 -> 1082047.4
A14: =Bonus!A14 -> 51.1151 | B14: =Bonus!B14 -> Sonoma Valley County Sanitation Dist. - Sonoma Valley Influent Effluent Upgrade | C14: =Bonus!G14 -> 0.48846743 | D14: =GAAP!G14 -> 0.48846743 | E14: =Bonus!I14 -> 5206183.6 | F14: =Bonus!F14 -> 4923435.2 | G14: =E14-F14 -> 282748.4 | I14: =GAAP!I14 -> 5206183.6 | J14: =GAAP!F14 -> 4923435.2 | K14: =I14-J14 -> 282748.4 | M14: =E14-I14 -> 0 | N14: =F14-J14 -> 0 | O14: =G14-K14 -> 0 | Q14: =R14+S14 -> 5019039.5 | R14: =Bonus!Q14 -> 4736291.1 | S14: =Bonus!S14 -> 282748.4 | U14: =V14+W14 -> 5019039.5 | V14: =GAAP!Q14 -> 4736291.1 | W14: =GAAP!S14 -> 282748.4 | Y14: =Q14-U14 -> 0 | Z14: =R14-V14 -> 0 | AA14: =S14-W14 -> 0 | AC14: =O14-AA14 -> 0
A15: =Bonus!A15 -> 51.1152 | B15: =Bonus!B15 -> Mozingo Construction Inc - ElD Sly Park Intertie Project | C15: =Bonus!G15 -> 0.72332631 | D15: =GAAP!G15 -> 0.72332631 | E15: =Bonus!I15 -> 14448074 | F15: =Bonus!F15 -> 13474809 | G15: =E15-F15 -> 973265.21 | I15: =GAAP!I15 -> 14448074 | J15: =GAAP!F15 -> 13474809 | K15: =I15-J15 -> 973265.21 | M15: =E15-I15 -> 0 | N15: =F15-J15 -> 0 | O15: =G15-K15 -> 0 | Q15: =R15+S15 -> 13001303 | R15: =Bonus!Q15 -> 12028038 | S15: =Bonus!S15 -> 973265.21 | U15: =V15+W15 -> 13001303 | V15: =GAAP!Q15 -> 12028038 | W15: =GAAP!S15 -> 973265.21 | Y15: =Q15-U15 -> 0 | Z15: =R15-V15 -> 0 | AA15: =S15-W15 -> 0 | AC15: =O15-AA15 -> 0
A16: =Bonus!A16 -> 51.1153 | B16: =Bonus!B16 -> Linda County Water Dist. - Aeration Blower Replacement | C16: =Bonus!G16 -> 0.7360519 | D16: =GAAP!G16 -> 0.7360519 | E16: =Bonus!I16 -> 414268.17 | F16: =Bonus!F16 -> 334550.81 | G16: =E16-F16 -> 79717.365 | I16: =GAAP!I16 -> 414268.17 | J16: =GAAP!F16 -> 334550.81 | K16: =I16-J16 -> 79717.365 | M16: =E16-I16 -> 0 | N16: =F16-J16 -> 0 | O16: =G16-K16 -> 0 | Q16: =R16+S16 -> 302445.43 | R16: =Bonus!Q16 -> 235587.45 | S16: =Bonus!S16 -> 66857.976 | U16: =V16+W16 -> 302445.43 | V16: =GAAP!Q16 -> 235587.45 | W16: =GAAP!S16 -> 66857.976 | Y16: =Q16-U16 -> 0 | Z16: =R16-V16 -> 0 | AA16: =S16-W16 -> 0 | AC16: =O16-AA16 -> 0
A17: =Bonus!A17 -> 51.1154 | B17: =Bonus!B17 -> Keyes Community Services Dist. - TCP Treatment Impvmts Wells 7,8,9,10 | C17: =Bonus!G17 -> 0.95063652 | D17: =GAAP!G17 -> 0.95063652 | E17: =Bonus!I17 -> 12704150 | F17: =Bonus!F17 -> 11872343 | G17: =E17-F17 -> 831806.95 | I17: =GAAP!I17 -> 12704150 | J17: =GAAP!F17 -> 11872343 | K17: =I17-J17 -> 831806.95 | M17: =E17-I17 -> 0 | N17: =F17-J17 -> 0 | O17: =G17-K17 -> 0 | Q17: =R17+S17 -> 10325590 | R17: =Bonus!Q17 -> 9493783.4 | S17: =Bonus!S17 -> 831806.95 | U17: =V17+W17 -> 10231270 | V17: =GAAP!Q17 -> 9493783.4 | W17: =GAAP!S17 -> 737486.53 | Y17: =Q17-U17 -> 94320.423 | Z17: =R17-V17 -> 0 | AA17: =S17-W17 -> 94320.423 | AC17: =O17-AA17 -> -94320.423
A18: =Bonus!A18 -> 51.1158 | B18: =Bonus!B18 -> Schneider Electric - City of Ceres WWTP Phase 1- Schneider Electric | C18: =Bonus!G18 -> 0.54536019 | D18: =GAAP!G18 -> 0.54536019 | E18: =Bonus!I18 -> 56960.69 | F18: =Bonus!F18 -> 56960.69 | G18: =E18-F18 -> 0 | I18: =GAAP!I18 -> 56960.69 | J18: =GAAP!F18 -> 56960.69 | K18: =I18-J18 -> 0 | M18: =E18-I18 -> 0 | N18: =F18-J18 -> 0 | O18: =G18-K18 -> 0 | Q18: =R18+S18 -> 56960.69 | R18: =Bonus!Q18 -> 56960.69 | S18: =Bonus!S18 -> 0 | U18: =V18+W18 -> 56960.69 | V18: =GAAP!Q18 -> 56960.69 | W18: =GAAP!S18 -> 0 | Y18: =Q18-U18 -> 0 | Z18: =R18-V18 -> 0 | AA18: =S18-W18 -> 0 | AC18: =O18-AA18 -> 0
A19: =Bonus!A19 -> 51.1159 | B19: =Bonus!B19 -> El Dorado Irrigation Dist. - EID Reservoir A WTP Backwash-to-waste Valve Repalcement | C19: =Bonus!G19 -> 0.73204396 | D19: =GAAP!G19 -> 0.73204396 | E19: =Bonus!I19 -> 877720.7 | F19: =Bonus!F19 -> 790051.12 | G19: =E19-F19 -> 87669.584 | I19: =GAAP!I19 -> 877720.7 | J19: =GAAP!F19 -> 790051.12 | K19: =I19-J19 -> 87669.584 | M19: =E19-I19 -> 0 | N19: =F19-J19 -> 0 | O19: =G19-K19 -> 0 | Q19: =R19+S19 -> 877720.7 | R19: =Bonus!Q19 -> 790051.12 | S19: =Bonus!S19 -> 87669.584 | U19: =V19+W19 -> 877720.7 | V19: =GAAP!Q19 -> 790051.12 | W19: =GAAP!S19 -> 87669.584 | Y19: =Q19-U19 -> 0 | Z19: =R19-V19 -> 0 | AA19: =S19-W19 -> 0 | AC19: =O19-AA19 -> 0
A20: =Bonus!A20 -> 51.116 | B20: =Bonus!B20 -> City of Galt Public Works - Industrial WWTP Expansion | C20: =Bonus!G20 -> 0.14823553 | D20: =GAAP!G20 -> 0.14823553 | E20: =Bonus!I20 -> 250518.05 | F20: =Bonus!F20 -> 250518.05 | G20: =E20-F20 -> 0 | I20: =GAAP!I20 -> 260449.83 | J20: =GAAP!F20 -> 250518.05 | K20: =I20-J20 -> 9931.7807 | M20: =E20-I20 -> -9931.7807 | N20: =F20-J20 -> 0 | O20: =G20-K20 -> -9931.7807 | Q20: =R20+S20 -> 250518.05 | R20: =Bonus!Q20 -> 250518.05 | S20: =Bonus!S20 -> 0 | U20: =V20+W20 -> 260449.83 | V20: =GAAP!Q20 -> 250518.05 | W20: =GAAP!S20 -> 9931.7807 | Y20: =Q20-U20 -> -9931.7807 | Z20: =R20-V20 -> 0 | AA20: =S20-W20 -> -9931.7807 | AC20: =O20-AA20 -> 0
... A24: =Bonus!A24 -> 51.1165 | B24: =Bonus!B24 -> City of Yuba City - WTP Aquifer Storage and Recovery Well No. 3 | C24: =Bonus!G24 -> 0.0047745016 | D24: =GAAP!G24 -> 0.0047745016 | E24: =Bonus!I24 -> 23330.33 | F24: =Bonus!F24 -> 23330.33 | G24: =E24-F24 -> 0 | I24: =GAAP!I24 -> 23330.33 | J24: =GAAP!F24 -> 23330.33 | K24: =I24-J24 -> 0 | M24: =E24-I24 -> 0 | N24: =F24-J24 -> 0 | O24: =G24-K24 -> 0 | Q24: =R24+S24 -> 23330.33 | R24: =Bonus!Q24 -> 23330.33 | S24: =Bonus!S24 -> 0 | U24: =V24+W24 -> 23330.33 | V24: =GAAP!Q24 -> 23330.33 | W24: =GAAP!S24 -> 0 | Y24: =Q24-U24 -> 0 | Z24: =R24-V24 -> 0 | AA24: =S24-W24 -> 0 | AC24: =O24-AA24 -> 0
Q25: 0 | S25: =Q25-R25 -> 0 | AC25: =O25-AA25 -> 0
A26: Rocklin Open Jobs Total | E26: =SUM(E9:E25) -> 2.9208296e+08 | F26: =SUM(F9:F25) -> 2.5993861e+08 | G26: =SUM(G9:G25) -> 32144351 | I26: =SUM(I9:I25) -> 2.9130404e+08 | J26: =SUM(J9:J25) -> 2.5993861e+08 | K26: =SUM(K9:K25) -> 31365431 | M26: =SUM(M9:M25) -> 778920.69 | N26: =SUM(N9:N25) -> 0 | O26: =SUM(O9:O25) -> 778920.69 | Q26: =SUM(Q9:Q25) -> 1.1601761e+08 | R26: =SUM(R9:R25) -> 97364760 | S26: =SUM(S9:S25) -> 18652847 | U26: =SUM(U9:U25) -> 1.175122e+08 | V26: =SUM(V9:V25) -> 97364760 | W26: =SUM(W9:W25) -> 20147436 | Y26: =SUM(Y9:Y25) -> -1494589.5 | Z26: =SUM(Z9:Z25) -> 0 | AA26: =SUM(AA9:AA25) -> -1494589.5 | AC26: =O26-AA26 -> 2273510.2
AC27: =O27-AA27 -> 0
A28: Rocklin Closed Jobs | AC28: =O28-AA28 -> 0
A29: =Bonus!A29 -> 51.1133 | B29: =Bonus!B29 -> CA Water Service Co. - S. San Francisco St 1-A Pump Replacement | C29: =Bonus!G29 -> 1 | D29: =GAAP!G29 -> 1 | E29: =Bonus!I29 -> 372738 | F29: =Bonus!F29 -> 331855.28 | G29: =E29-F29 -> 40882.72 | I29: =GAAP!I29 -> 372738 | J29: =GAAP!F29 -> 331855.28 | K29: =I29-J29 -> 40882.72 | M29: =E29-I29 -> 0 | N29: =F29-J29 -> 0 | O29: =G29-K29 -> 0 | Q29: =R29+S29 -> 52253.009 | R29: =Bonus!Q29 -> 28729.87 | S29: =Bonus!S29 -> 23523.139 | U29: =V29+W29 -> 52253.009 | V29: =GAAP!Q29 -> 28729.87 | W29: =GAAP!S29 -> 23523.139 | Y29: =Q29-U29 -> 0 | Z29: =R29-V29 -> 0 | AA29: =S29-W29 -> 0 | AC29: =O29-AA29 -> 0
A30: =Bonus!A30 -> 51.1136 | B30: =Bonus!B30 -> Union Sanitary Dist - USD Plant Misc. Improvements | C30: =Bonus!G30 -> 1 | D30: =GAAP!G30 -> 1 | E30: =Bonus!I30 -> 5483550 | F30: =Bonus!F30 -> 4531817.9 | G30: =E30-F30 -> 951732.14 | I30: =GAAP!I30 -> 5483550 | J30: =GAAP!F30 -> 4531817.9 | K30: =I30-J30 -> 951732.14 | M30: =E30-I30 -> 0 | N30: =F30-J30 -> 0 | O30: =G30-K30 -> 0 | Q30: =R30+S30 -> 495311.37 | R30: =Bonus!Q30 -> 302485.02 | S30: =Bonus!S30 -> 192826.35 | U30: =V30+W30 -> 495311.37 | V30: =GAAP!Q30 -> 302485.02 | W30: =GAAP!S30 -> 192826.35 | Y30: =Q30-U30 -> 0 | Z30: =R30-V30 -> 0 | AA30: =S30-W30 -> 0 | AC30: =O30-AA30 -> 0
A31: =Bonus!A31 -> 51.1138 | B31: =Bonus!B31 -> CA Water Service Co. - Bear Gulch Pump Station 21 | C31: =Bonus!G31 -> 1 | D31: =GAAP!G31 -> 1 | E31: =Bonus!I31 -> 1120182.1 | F31: =Bonus!F31 -> 1167704.1 | G31: =E31-F31 -> -47522.08 | I31: =GAAP!I31 -> 1120182.1 | J31: =GAAP!F31 -> 1167704.1 | K31: =I31-J31 -> -47522.08 | M31: =E31-I31 -> 0 | N31: =F31-J31 -> 0 | O31: =G31-K31 -> 0 | Q31: =R31+S31 -> 255501.92 | R31: =Bonus!Q31 -> 380802.1 | S31: =Bonus!S31 -> -125300.18 | U31: =V31+W31 -> 255501.92 | V31: =GAAP!Q31 -> 380802.1 | W31: =GAAP!S31 -> -125300.18 | Y31: =Q31-U31 -> 0 | Z31: =R31-V31 -> 0 | AA31: =S31-W31 -> 0 | AC31: =O31-AA31 -> 0
A32: =Bonus!A32 -> 51.1139 | B32: =Bonus!B32 -> CA Water Service Co. - Bear Gulch Pump Station 14/29 | C32: =Bonus!G32 -> 1 | D32: =GAAP!G32 -> 1 | E32: =Bonus!I32 -> 61902 | F32: =Bonus!F32 -> 56994.44 | G32: =E32-F32 -> 4907.56 | I32: =GAAP!I32 -> 61902 | J32: =GAAP!F32 -> 56994.44 | K32: =I32-J32 -> 4907.56 | M32: =E32-I32 -> 0 | N32: =F32-J32 -> 0 | O32: =G32-K32 -> 0 | Q32: =R32+S32 -> 481.20101 | R32: =Bonus!Q32 -> 0 | S32: =Bonus!S32 -> 481.20101 | U32: =V32+W32 -> 481.20101 | V32: =GAAP!Q32 -> 0 | W32: =GAAP!S32 -> 481.20101 | Y32: =Q32-U32 -> 0 | Z32: =R32-V32 -> 0 | AA32: =S32-W32 -> 0 | AC32: =O32-AA32 -> 0
A33: =Bonus!A33 -> 51.1141 | B33: =Bonus!B33 -> City of Colfax - WWTP Algae Reduction Project | C33: =Bonus!G33 -> 1 | D33: =GAAP!G33 -> 1 | E33: =Bonus!I33 -> 3967189.8 | F33: =Bonus!F33 -> 3835094.7 | G33: =E33-F33 -> 132095.06 | I33: =GAAP!I33 -> 3967189.8 | J33: =GAAP!F33 -> 3835094.7 | K33: =I33-J33 -> 132095.06 | M33: =E33-I33 -> 0 | N33: =F33-J33 -> 0 | O33: =G33-K33 -> 0 | Q33: =R33+S33 -> 777363.73 | R33: =Bonus!Q33 -> 725188.97 | S33: =Bonus!S33 -> 52174.761 | U33: =V33+W33 -> 777363.73 | V33: =GAAP!Q33 -> 725188.97 | W33: =GAAP!S33 -> 52174.761 | Y33: =Q33-U33 -> 0 | Z33: =R33-V33 -> 0 | AA33: =S33-W33 -> 0 | AC33: =O33-AA33 -> 0
A34: =Bonus!A34 -> 51.1143 | B34: =Bonus!B34 -> Olivehurst Plumas Lake Manganese Filter Expansion | C34: =Bonus!G34 -> 1 | D34: =GAAP!G34 -> 1 | E34: =Bonus!I34 -> 1991231.4 | F34: =Bonus!F34 -> 1758132.6 | G34: =E34-F34 -> 233098.8 | I34: =GAAP!I34 -> 1991231.4 | J34: =GAAP!F34 -> 1758132.6 | K34: =I34-J34 -> 233098.8 | M34: =E34-I34 -> 0 | N34: =F34-J34 -> 0 | O34: =G34-K34 -> 0 | Q34: =R34+S34 -> 34528.637 | R34: =Bonus!Q34 -> 27441.6 | S34: =Bonus!S34 -> 7087.0371 | U34: =V34+W34 -> 34528.637 | V34: =GAAP!Q34 -> 27441.6 | W34: =GAAP!S34 -> 7087.0371 | Y34: =Q34-U34 -> 0 | Z34: =R34-V34 -> 0 | AA34: =S34-W34 -> 0 | AC34: =O34-AA34 -> 0
A35: =Bonus!A35 -> 51.1147 | B35: =Bonus!B35 -> City of Lodi-Public Works Dept. - Aeration Diffusers Replacement Project | C35: =Bonus!G35 -> 1 | D35: =GAAP!G35 -> 1 | E35: =Bonus!I35 -> 2742860.1 | F35: =Bonus!F35 -> 2548724.9 | G35: =E35-F35 -> 194135.16 | I35: =GAAP!I35 -> 2742860.1 | J35: =GAAP!F35 -> 2548724.9 | K35: =I35-J35 -> 194135.16 | M35: =E35-I35 -> 0 | N35: =F35-J35 -> 0 | O35: =G35-K35 -> 0 | Q35: =R35+S35 -> 864663.22 | R35: =Bonus!Q35 -> 798812.6 | S35: =Bonus!S35 -> 65850.625 | U35: =V35+W35 -> 864663.22 | V35: =GAAP!Q35 -> 798812.6 | W35: =GAAP!S35 -> 65850.625 | Y35: =Q35-U35 -> 0 | Z35: =R35-V35 -> 0 | AA35: =S35-W35 -> 0 | AC35: =O35-AA35 -> 0
A36: =Bonus!A36 -> 51.115 | B36: =Bonus!B36 -> Sacramento Co. Dept. of Water Resources - D49 Metro Air Park Storm Drain Pump Station Phase 2 | C36: =Bonus!G36 -> 1 | D36: =GAAP!G36 -> 1 | E36: =Bonus!I36 -> 2486231.6 | F36: =Bonus!F36 -> 2239435.1 | G36: =E36-F36 -> 246796.44 | I36: =GAAP!I36 -> 2486231.6 | J36: =GAAP!F36 -> 2239435.1 | K36: =I36-J36 -> 246796.44 | M36: =E36-I36 -> 0 | N36: =F36-J36 -> 0 | O36: =G36-K36 -> 0 | Q36: =R36+S36 -> 248682.95 | R36: =Bonus!Q36 -> 168358.34 | S36: =Bonus!S36 -> 80324.611 | U36: =V36+W36 -> 248682.95 | V36: =GAAP!Q36 -> 168358.34 | W36: =GAAP!S36 -> 80324.611 | Y36: =Q36-U36 -> 0 | Z36: =R36-V36 -> 0 | AA36: =S36-W36 -> 0 | AC36: =O36-AA36 -> 0
A37: =Bonus!A37 -> 51.1156 | B37: =Bonus!B37 -> Rocklin Overhead 2025 | C37: =Bonus!G37 -> 1 | D37: =GAAP!G37 -> 1 | E37: =Bonus!I37 -> 0 | F37: =Bonus!F37 -> 1426058.7 | G37: =E37-F37 -> -1426058.7 | I37: =GAAP!I37 -> 0 | J37: =GAAP!F37 -> 1426058.7 | K37: =I37-J37 -> -1426058.7 | M37: =E37-I37 -> 0 | N37: =F37-J37 -> 0 | O37: =G37-K37 -> 0 | Q37: =R37+S37 -> 0 | R37: =Bonus!Q37 -> 1426058.7 | S37: =Bonus!S37 -> -1426058.7 | U37: =V37+W37 -> 0 | V37: =GAAP!Q37 -> 1426058.7 | W37: =GAAP!S37 -> -1426058.7 | Y37: =Q37-U37 -> 0 | Z37: =R37-V37 -> 0 | AA37: =S37-W37 -> 0 | AC37: =O37-AA37 -> 0
A38: =Bonus!A38 -> 51.1157 | B38: =Bonus!B38 -> Rocklin Estimating 2025 | C38: =Bonus!G38 -> 1 | D38: =GAAP!G38 -> 1 | E38: =Bonus!I38 -> 0 | F38: =Bonus!F38 -> 613546.52 | G38: =E38-F38 -> -613546.52 | I38: =GAAP!I38 -> 0 | J38: =GAAP!F38 -> 613546.52 | K38: =I38-J38 -> -613546.52 | M38: =E38-I38 -> 0 | N38: =F38-J38 -> 0 | O38: =G38-K38 -> 0 | Q38: =R38+S38 -> 0 | R38: =Bonus!Q38 -> 613546.52 | S38: =Bonus!S38 -> -613546.52 | U38: =V38+W38 -> 0 | V38: =GAAP!Q38 -> 613546.52 | W38: =GAAP!S38 -> -613546.52 | Y38: =Q38-U38 -> 0 | Z38: =R38-V38 -> 0 | AA38: =S38-W38 -> 0 | AC38: =O38-AA38 -> 0
AC39: =O39-AA39 -> 0
A40: Rocklin Closed Jobs Total | E40: =SUM(E29:E39) -> 18225885 | F40: =SUM(F29:F39) -> 18509364 | G40: =SUM(G29:G39) -> -283479.41 | I40: =SUM(I29:I39) -> 18225885 | J40: =SUM(J29:J39) -> 18509364 | K40: =SUM(K29:K39) -> -283479.41 | M40: =SUM(M29:M39) -> 0 | N40: =SUM(N29:N39) -> 0 | O40: =SUM(O29:O39) -> 0 | Q40: =SUM(Q29:Q39) -> 2728786 | R40: =SUM(R29:R39) -> 4471423.7 | S40: =SUM(S29:S39) -> -1742637.7 | U40: =SUM(U29:U39) -> 2728786 | V40: =SUM(V29:V39) -> 4471423.7 | W40: =SUM(W29:W39) -> -1742637.7 | Y40: =SUM(Y29:Y39) -> 0 | Z40: =SUM(Z29:Z39) -> 0 | AA40: =SUM(AA29:AA39) -> 0 | AC40: =O40-AA40 -> 0
AC41: =O41-AA41 -> 0
A42: Rocklin Total | E42: =E26+E40 -> 3.1030884e+08 | F42: =F26+F40 -> 2.7844797e+08 | G42: =G26+G40 -> 31860872 | I42: =I26+I40 -> 3.0952992e+08 | J42: =J26+J40 -> 2.7844797e+08 | K42: =K26+K40 -> 31081951 | M42: =M26+M40 -> 778920.69 | N42: =N26+N40 -> 0 | O42: =O26+O40 -> 778920.69 | Q42: =Q26+Q40 -> 1.1874639e+08 | R42: =R26+R40 -> 1.0183618e+08 | S42: =S26+S40 -> 16910209 | U42: =U26+U40 -> 1.2024098e+08 | V42: =V26+V40 -> 1.0183618e+08 | W42: =W26+W40 -> 18404798 | Y42: =Y26+Y40 -> -1494589.5 | Z42: =Z26+Z40 -> 0 | AA42: =AA26+AA40 -> -1494589.5 | AC42: =O42-AA42 -> 2273510.2
A44: Fresno Open Jobs
A45: =Bonus!A44 -> 52.8563 | B45: =Bonus!B44 -> City of Santa Cruz - Graham Hill WTP Facility Improvements - Phase 1 | C45: =Bonus!G44 -> 0.97534821 | D45: =GAAP!G44 -> 1 | E45: =Bonus!I44 -> 1152462.3 | F45: =Bonus!F44 -> 859077.05 | G45: =E45-F45 -> 293385.24 | I45: =GAAP!I44 -> 1134038.1 | J45: =GAAP!F44 -> 859077.05 | K45: =I45-J45 -> 274961.08 | M45: =E45-I45 -> 18424.16 | N45: =F45-J45 -> 0 | O45: =G45-K45 -> 18424.16 | Q45: =R45+S45 -> 167405.78 | R45: =Bonus!Q44 -> 138210.3 | S45: =Bonus!S44 -> 29195.48 | U45: =V45+W45 -> 218705.64 | V45: =GAAP!Q44 -> 138210.3 | W45: =GAAP!S44 -> 80495.34 | Y45: =Q45-U45 -> -51299.86 | Z45: =R45-V45 -> 0 | AA45: =S45-W45 -> -51299.86 | AC45: =O45-AA45 -> 69724.02
A46: =Bonus!A45 -> 52.8566 | B46: =Bonus!B45 -> City of Visalia - Water Reclamation Facility RPGS SCR System | C46: =Bonus!G45 -> 0.99458232 | D46: =GAAP!G45 -> 0.99458232 | E46: =Bonus!I45 -> 1252575 | F46: =Bonus!F45 -> 1023821.1 | G46: =E46-F46 -> 228753.93 | I46: =GAAP!I45 -> 1252575 | J46: =GAAP!F45 -> 1023821.1 | K46: =I46-J46 -> 228753.93 | M46: =E46-I46 -> 0 | N46: =F46-J46 -> 0 | O46: =G46-K46 -> 0 | Q46: =R46+S46 -> 33809.917 | R46: =Bonus!Q45 -> 29030.49 | S46: =Bonus!S45 -> 4779.4271 | U46: =V46+W46 -> 33809.917 | V46: =GAAP!Q45 -> 29030.49 | W46: =GAAP!S45 -> 4779.4271 | Y46: =Q46-U46 -> 0 | Z46: =R46-V46 -> 0 | AA46: =S46-W46 -> 0 | AC46: =O46-AA46 -> 0
A47: =Bonus!A46 -> 52.8586 | B47: =Bonus!B46 -> Tesoro Viejo MMWC- WTP/WWTP/RWSP Phase B Expansion - Phase 1 | C47: =Bonus!G46 -> 0.99100599 | D47: =GAAP!G46 -> 0.99100599 | E47: =Bonus!I46 -> 12497922 | F47: =Bonus!F46 -> 10565461 | G47: =E47-F47 -> 1932461.7 | I47: =GAAP!I46 -> 12497922 | J47: =GAAP!F46 -> 10565461 | K47: =I47-J47 -> 1932461.7 | M47: =E47-I47 -> 0 | N47: =F47-J47 -> 0 | O47: =G47-K47 -> 0 | Q47: =R47+S47 -> 506849.71 | R47: =Bonus!Q46 -> 332168.03 | S47: =Bonus!S46 -> 174681.68 | U47: =V47+W47 -> 506849.71 | V47: =GAAP!Q46 -> 332168.03 | W47: =GAAP!S46 -> 174681.68 | Y47: =Q47-U47 -> 0 | Z47: =R47-V47 -> 0 | AA47: =S47-W47 -> 0 | AC47: =O47-AA47 -> 0
A48: =Bonus!A47 -> 52.8634 | B48: =Bonus!B47 -> City of Huron - Water Treatment Plant Imp. Phase 2 | C48: =Bonus!G47 -> 0.88752212 | D48: =GAAP!G47 -> 0.88752212 | E48: =Bonus!I47 -> 12330099 | F48: =Bonus!F47 -> 11707058 | G48: =E48-F48 -> 623040.53 | I48: =GAAP!I47 -> 12330099 | J48: =GAAP!F47 -> 11707058 | K48: =I48-J48 -> 623040.53 | M48: =E48-I48 -> 0 | N48: =F48-J48 -> 0 | O48: =G48-K48 -> 0 | Q48: =R48+S48 -> 6838700.1 | R48: =Bonus!Q47 -> 6493631.6 | S48: =Bonus!S47 -> 345068.52 | U48: =V48+W48 -> 6838700.1 | V48: =GAAP!Q47 -> 6493631.6 | W48: =GAAP!S47 -> 345068.52 | Y48: =Q48-U48 -> 0 | Z48: =R48-V48 -> 0 | AA48: =S48-W48 -> 0 | AC48: =O48-AA48 -> 0
A49: =Bonus!A48 -> 52.8636 | B49: =Bonus!B48 -> Anaergia Technologies, LLC - Anaergia M1W Digester Mixing Project | C49: =Bonus!G48 -> 0.99995556 | D49: =GAAP!G48 -> 0.99584023 | E49: =Bonus!I48 -> 3642035.1 | F49: =Bonus!F48 -> 3367047.4 | G49: =E49-F49 -> 274987.78 | I49: =GAAP!I48 -> 3640903.4 | J49: =GAAP!F48 -> 3367047.4 | K49: =I49-J49 -> 273856.06 | M49: =E49-I49 -> 1131.7149 | N49: =F49-J49 -> 0 | O49: =G49-K49 -> 1131.7149 | Q49: =R49+S49 -> 1980915.9 | R49: =Bonus!Q48 -> 1910247.8 | S49: =Bonus!S48 -> 70668.068 | U49: =V49+W49 -> 1979784.2 | V49: =GAAP!Q48 -> 1910247.8 | W49: =GAAP!S48 -> 69536.353 | Y49: =Q49-U49 -> 1131.7149 | Z49: =R49-V49 -> 0 | AA49: =S49-W49 -> 1131.7149 | AC49: =O49-AA49 -> -1.7462298e-10
A50: =Bonus!A49 -> 52.8637 | B50: =Bonus!B49 -> Root Creek Water Dist. - Groundwater Blending & Arsenic | C50: =Bonus!G49 -> 0.99023836 | D50: =GAAP!G49 -> 0.99023836 | E50: =Bonus!I49 -> 26008192 | F50: =Bonus!F49 -> 24374299 | G50: =E50-F50 -> 1633893.3 | I50: =GAAP!I49 -> 26008192 | J50: =GAAP!F49 -> 24374299 | K50: =I50-J50 -> 1633893.3 | M50: =E50-I50 -> 0 | N50: =F50-J50 -> 0 | O50: =G50-K50 -> 0 | Q50: =R50+S50 -> 5357985.6 | R50: =Bonus!Q49 -> 4932484 | S50: =Bonus!S49 -> 425501.54 | U50: =V50+W50 -> 5357985.6 | V50: =GAAP!Q49 -> 4932484 | W50: =GAAP!S49 -> 425501.54 | Y50: =Q50-U50 -> 0 | Z50: =R50-V50 -> 0 | AA50: =S50-W50 -> 0 | AC50: =O50-AA50 -> 0
A51: =Bonus!A50 -> 52.864 | B51: =Bonus!B50 -> City of Dos Palos - WTP Replacement Project | C51: =Bonus!G50 -> 0.87452061 | D51: =GAAP!G50 -> 0.87452061 | E51: =Bonus!I50 -> 33797041 | F51: =Bonus!F50 -> 32158781 | G51: =E51-F51 -> 1638259.6 | I51: =GAAP!I50 -> 33797041 | J51: =GAAP!F50 -> 32158781 | K51: =I51-J51 -> 1638259.6 | M51: =E51-I51 -> 0 | N51: =F51-J51 -> 0 | O51: =G51-K51 -> 0 | Q51: =R51+S51 -> 20058621 | R51: =Bonus!Q50 -> 19124329 | S51: =Bonus!S50 -> 934292.73 | U51: =V51+W51 -> 20058621 | V51: =GAAP!Q50 -> 19124329 | W51: =GAAP!S50 -> 934292.73 | Y51: =Q51-U51 -> 0 | Z51: =R51-V51 -> 0 | AA51: =S51-W51 -> 0 | AC51: =O51-AA51 -> 0
A52: =Bonus!A51 -> 52.8668 | B52: =Bonus!B51 -> California Water Service Co. - Cal Water - Salinas Station 57 | C52: =Bonus!G51 -> 0.94884474 | D52: =GAAP!G51 -> 0.94884474 | E52: =Bonus!I51 -> 390782.65 | F52: =Bonus!F51 -> 357710.67 | G52: =E52-F52 -> 33071.983 | I52: =GAAP!I51 -> 390782.65 | J52: =GAAP!F51 -> 357710.67 | K52: =I52-J52 -> 33071.983 | M52: =E52-I52 -> 0 | N52: =F52-J52 -> 0 | O52: =G52-K52 -> 0 | Q52: =R52+S52 -> 341717.65 | R52: =Bonus!Q51 -> 308645.67 | S52: =Bonus!S51 -> 33071.983 | U52: =V52+W52 -> 336444.61 | V52: =GAAP!Q51 -> 308645.67 | W52: =GAAP!S51 -> 27798.937 | Y52: =Q52-U52 -> 5273.0464 | Z52: =R52-V52 -> 0 | AA52: =S52-W52 -> 5273.0464 | AC52: =O52-AA52 -> -5273.0464
A53: =Bonus!A52 -> 52.8678 | B53: =Bonus!B52 -> City of Chowcilla - Well 15 & Generator Improvement Projects | C53: =Bonus!G52 -> 0.7966881 | D53: =GAAP!G52 -> 0.7966881 | E53: =Bonus!I52 -> 988148.98 | F53: =Bonus!F52 -> 926007.31 | G53: =E53-F53 -> 62141.672 | I53: =GAAP!I52 -> 988148.98 | J53: =GAAP!F52 -> 926007.31 | K53: =I53-J53 -> 62141.672 | M53: =E53-I53 -> 0 | N53: =F53-J53 -> 0 | O53: =G53-K53 -> 0 | Q53: =R53+S53 -> 982585.35 | R53: =Bonus!Q52 -> 920443.68 | S53: =Bonus!S52 -> 62141.672 | U53: =V53+W53 -> 982585.35 | V53: =GAAP!Q52 -> 920443.68 | W53: =GAAP!S52 -> 62141.672 | Y53: =Q53-U53 -> 0 | Z53: =R53-V53 -> 0 | AA53: =S53-W53 -> 0 | AC53: =O53-AA53 -> 0
A54: =Bonus!A53 -> 52.8687 | B54: =Bonus!B53 -> California Water Service Co. - Salinas Station 205 | C54: =Bonus!G53 -> 0.93659097 | D54: =GAAP!G53 -> 0.93659097 | E54: =Bonus!I53 -> 822283.79 | F54: =Bonus!F53 -> 740629.43 | G54: =E54-F54 -> 81654.361 | I54: =GAAP!I53 -> 822283.79 | J54: =GAAP!F53 -> 740629.43 | K54: =I54-J54 -> 81654.361 | M54: =E54-I54 -> 0 | N54: =F54-J54 -> 0 | O54: =G54-K54 -> 0 | Q54: =R54+S54 -> 822283.79 | R54: =Bonus!Q53 -> 740629.43 | S54: =Bonus!S53 -> 81654.361 | U54: =V54+W54 -> 822283.79 | V54: =GAAP!Q53 -> 740629.43 | W54: =GAAP!S53 -> 81654.361 | Y54: =Q54-U54 -> 0 | Z54: =R54-V54 -> 0 | AA54: =S54-W54 -> 0 | AC54: =O54-AA54 -> 0
A55: =Bonus!A54 -> 52.8692 | B55: =Bonus!B54 -> New England Sheet Metal and Mechanical Co. - Clovis South T&M | C55: =Bonus!G54 -> 1 | D55: =GAAP!G54 -> 1 | E55: =Bonus!I54 -> 55135.37 | F55: =Bonus!F54 -> 49682.49 | G55: =E55-F55 -> 5452.88 | I55: =GAAP!I54 -> 55135.37 | J55: =GAAP!F54 -> 49682.49 | K55: =I55-J55 -> 5452.88 | M55: =E55-I55 -> 0 | N55: =F55-J55 -> 0 | O55: =G55-K55 -> 0 | Q55: =R55+S55 -> 55135.37 | R55: =Bonus!Q54 -> 49682.49 | S55: =Bonus!S54 -> 5452.88 | U55: =V55+W55 -> 55135.37 | V55: =GAAP!Q54 -> 49682.49 | W55: =GAAP!S54 -> 5452.88 | Y55: =Q55-U55 -> 0 | Z55: =R55-V55 -> 0 | AA55: =S55-W55 -> 0 | AC55: =O55-AA55 -> 0
A56: =Bonus!A55 -> 52.8697 | B56: =Bonus!B55 -> City of Tulare - Industrial WWTP Dewatering Improvements Pro | C56: =Bonus!G55 -> 0.58257127 | D56: =GAAP!G55 -> 0.58257127 | E56: =Bonus!I55 -> 808608.92 | F56: =Bonus!F55 -> 772187.73 | G56: =E56-F56 -> 36421.191 | I56: =GAAP!I55 -> 808608.92 | J56: =GAAP!F55 -> 772187.73 | K56: =I56-J56 -> 36421.191 | M56: =E56-I56 -> 0 | N56: =F56-J56 -> 0 | O56: =G56-K56 -> 0 | Q56: =R56+S56 -> 808608.92 | R56: =Bonus!Q55 -> 772187.73 | S56: =Bonus!S55 -> 36421.191 | U56: =V56+W56 -> 808608.92 | V56: =GAAP!Q55 -> 772187.73 | W56: =GAAP!S55 -> 36421.191 | Y56: =Q56-U56 -> 0 | Z56: =R56-V56 -> 0 | AA56: =S56-W56 -> 0 | AC56: =O56-AA56 -> 0
... A64: =Bonus!A63 -> 52.8714 | B64: =Bonus!B63 -> New England Sheet Metal and Mechanical Co. - VCH Digging Water Line T&M | C64: =Bonus!G63 -> 1 | D64: =GAAP!G63 -> 1 | E64: =Bonus!I63 -> 5084.94 | F64: =Bonus!F63 -> 4465.61 | G64: =E64-F64 -> 619.33 | I64: =GAAP!I63 -> 5084.94 | J64: =GAAP!F63 -> 4465.61 | K64: =I64-J64 -> 619.33 | M64: =E64-I64 -> 0 | N64: =F64-J64 -> 0 | O64: =G64-K64 -> 0 | Q64: =R64+S64 -> 5084.94 | R64: =Bonus!Q63 -> 4465.61 | S64: =Bonus!S63 -> 619.33 | U64: =V64+W64 -> 5084.94 | V64: =GAAP!Q63 -> 4465.61 | W64: =GAAP!S63 -> 619.33 | Y64: =Q64-U64 -> 0 | Z64: =R64-V64 -> 0 | AA64: =S64-W64 -> 0 | AC64: =O64-AA64 -> 0
R65: 0 | AC65: =O65-AA65 -> 0
A66: Fresno Open Jobs Total | E66: =SUM(E45:E65) -> 95993751 | F66: =SUM(F45:F65) -> 89053142 | G66: =SUM(G45:G65) -> 6940608.8 | I66: =SUM(I45:I65) -> 95974195 | J66: =SUM(J45:J65) -> 89053142 | K66: =SUM(K45:K65) -> 6921052.9 | M66: =SUM(M45:M65) -> 19555.875 | N66: =SUM(N45:N65) -> 0 | O66: =SUM(O45:O65) -> 19555.875 | Q66: =SUM(Q45:Q65) -> 40203083 | R66: =SUM(R45:R65) -> 37903069 | S66: =SUM(S45:S65) -> 2300014.2 | U66: =SUM(U45:U65) -> 40247979 | V66: =SUM(V45:V65) -> 37903069 | W66: =SUM(W45:W65) -> 2344909.3 | Y66: =SUM(Y45:Y65) -> -44895.099 | Z66: =SUM(Z45:Z65) -> 0 | AA66: =SUM(AA45:AA65) -> -44895.099 | AC66: =O66-AA66 -> 64450.974
AC67: =O67-AA67 -> 0
A68: Fresno Closed Jobs | AC68: =O68-AA68 -> 0
A69: =Bonus!A68 -> 52.8567 | B69: =Bonus!B68 -> City of Modesto - Grayson Well 69 | C69: =Bonus!G68 -> 1 | D69: =GAAP!G68 -> 1 | E69: =Bonus!I68 -> 3059859 | F69: =Bonus!F68 -> 3128023.9 | G69: =E69-F69 -> -68164.94 | I69: =GAAP!I68 -> 3059859 | J69: =GAAP!F68 -> 3128023.9 | K69: =I69-J69 -> -68164.94 | M69: =E69-I69 -> 0 | N69: =F69-J69 -> 0 | O69: =G69-K69 -> 0 | Q69: =R69+S69 -> 49233.73 | R69: =Bonus!Q68 -> 34398.67 | S69: =Bonus!S68 -> 14835.06 | U69: =V69+W69 -> 49233.73 | V69: =GAAP!Q68 -> 34398.67 | W69: =GAAP!S68 -> 14835.06 | Y69: =Q69-U69 -> 0 | Z69: =R69-V69 -> 0 | AA69: =S69-W69 -> 0 | AC69: =O69-AA69 -> 0
A70: =Bonus!A69 -> 52.8604 | B70: =Bonus!B69 -> City of Atwater - Project No. 20-2, Well 20-A TCP Mitigation | C70: =Bonus!G69 -> 1 | D70: =GAAP!G69 -> 1 | E70: =Bonus!I69 -> 5095691 | F70: =Bonus!F69 -> 4572503.2 | G70: =E70-F70 -> 523187.74 | I70: =GAAP!I69 -> 5095691 | J70: =GAAP!F69 -> 4572503.2 | K70: =I70-J70 -> 523187.74 | M70: =E70-I70 -> 0 | N70: =F70-J70 -> 0 | O70: =G70-K70 -> 0 | Q70: =R70+S70 -> 1102038.3 | R70: =Bonus!Q69 -> 908839.74 | S70: =Bonus!S69 -> 193198.61 | U70: =V70+W70 -> 1102038.3 | V70: =GAAP!Q69 -> 908839.74 | W70: =GAAP!S69 -> 193198.61 | Y70: =Q70-U70 -> 0 | Z70: =R70-V70 -> 0 | AA70: =S70-W70 -> 0 | AC70: =O70-AA70 -> 0
A71: =Bonus!A70 -> 52.8628 | B71: =Bonus!B70 -> City of Tulare - Well 4-3 Equipping & I Drive Pipeline Proj. | C71: =Bonus!G70 -> 1 | D71: =GAAP!G70 -> 1 | E71: =Bonus!I70 -> 5213345.5 | F71: =Bonus!F70 -> 4745798.5 | G71: =E71-F71 -> 467546.97 | I71: =GAAP!I70 -> 5213345.5 | J71: =GAAP!F70 -> 4745798.5 | K71: =I71-J71 -> 467546.97 | M71: =E71-I71 -> 0 | N71: =F71-J71 -> 0 | O71: =G71-K71 -> 0 | Q71: =R71+S71 -> 1174192.8 | R71: =Bonus!Q70 -> 903870.54 | S71: =Bonus!S70 -> 270322.22 | U71: =V71+W71 -> 1174192.8 | V71: =GAAP!Q70 -> 903870.54 | W71: =GAAP!S70 -> 270322.22 | Y71: =Q71-U71 -> 0 | Z71: =R71-V71 -> 0 | AA71: =S71-W71 -> 0 | AC71: =O71-AA71 -> 0
A72: =Bonus!A71 -> 52.8631 | B72: =Bonus!B71 -> Gunner Ranch, Inc. - Well 1 Equipping and Site Improvements | C72: =Bonus!G71 -> 1 | D72: =GAAP!G71 -> 1 | E72: =Bonus!I71 -> 2560650.1 | F72: =Bonus!F71 -> 2448658.3 | G72: =E72-F72 -> 111991.88 | I72: =GAAP!I71 -> 2560650.1 | J72: =GAAP!F71 -> 2448658.3 | K72: =I72-J72 -> 111991.88 | M72: =E72-I72 -> 0 | N72: =F72-J72 -> 0 | O72: =G72-K72 -> 0 | Q72: =R72+S72 -> 237953.3 | R72: =Bonus!Q71 -> 198965.12 | S72: =Bonus!S71 -> 38988.179 | U72: =V72+W72 -> 237953.3 | V72: =GAAP!Q71 -> 198965.12 | W72: =GAAP!S71 -> 38988.179 | Y72: =Q72-U72 -> 0 | Z72: =R72-V72 -> 0 | AA72: =S72-W72 -> 0 | AC72: =O72-AA72 -> 0
A73: =Bonus!A72 -> 52.8652 | B73: =Bonus!B72 -> California Water Service Co. - Salinas 77 Booster Station | C73: =Bonus!G72 -> 1 | D73: =GAAP!G72 -> 1 | E73: =Bonus!I72 -> 1290184 | F73: =Bonus!F72 -> 1039376.1 | G73: =E73-F73 -> 250807.92 | I73: =GAAP!I72 -> 1290184 | J73: =GAAP!F72 -> 1039376.1 | K73: =I73-J73 -> 250807.92 | M73: =E73-I73 -> 0 | N73: =F73-J73 -> 0 | O73: =G73-K73 -> 0 | Q73: =R73+S73 -> 133540.67 | R73: =Bonus!Q72 -> 53431.59 | S73: =Bonus!S72 -> 80109.083 | U73: =V73+W73 -> 133540.67 | V73: =GAAP!Q72 -> 53431.59 | W73: =GAAP!S72 -> 80109.083 | Y73: =Q73-U73 -> 0 | Z73: =R73-V73 -> 0 | AA73: =S73-W73 -> 0 | AC73: =O73-AA73 -> 0
A74: =Bonus!A73 -> 52.8658 | B74: =Bonus!B73 -> California Water Service Co. - Visalia Station 98 Water Storage Tank & Booster Site | C74: =Bonus!G73 -> 1 | D74: =GAAP!G73 -> 1 | E74: =Bonus!I73 -> 1870915 | F74: =Bonus!F73 -> 1633530.2 | G74: =E74-F74 -> 237384.78 | I74: =GAAP!I73 -> 1870915 | J74: =GAAP!F73 -> 1633530.2 | K74: =I74-J74 -> 237384.78 | M74: =E74-I74 -> 0 | N74: =F74-J74 -> 0 | O74: =G74-K74 -> 0 | Q74: =R74+S74 -> 200545.22 | R74: =Bonus!Q73 -> 111911.44 | S74: =Bonus!S73 -> 88633.78 | U74: =V74+W74 -> 203409.61 | V74: =GAAP!Q73 -> 111911.44 | W74: =GAAP!S73 -> 91498.175 | Y74: =Q74-U74 -> -2864.3946 | Z74: =R74-V74 -> 0 | AA74: =S74-W74 -> -2864.3946 | AC74: =O74-AA74 -> 2864.3946
A75: =Bonus!A74 -> 52.8663 | B75: =Bonus!B74 -> Root Creek Water Dist. - Ag Well 277 Conversion Project | C75: =Bonus!G74 -> 1 | D75: =GAAP!G74 -> 1 | E75: =Bonus!I74 -> 1641800 | F75: =Bonus!F74 -> 1379688.3 | G75: =E75-F75 -> 262111.72 | I75: =GAAP!I74 -> 1641800 | J75: =GAAP!F74 -> 1379688.3 | K75: =I75-J75 -> 262111.72 | M75: =E75-I75 -> 0 | N75: =F75-J75 -> 0 | O75: =G75-K75 -> 0 | Q75: =R75+S75 -> 1192257.7 | R75: =Bonus!Q74 -> 972822.89 | S75: =Bonus!S74 -> 219434.77 | U75: =V75+W75 -> 1192257.7 | V75: =GAAP!Q74 -> 972822.89 | W75: =GAAP!S74 -> 219434.77 | Y75: =Q75-U75 -> 0 | Z75: =R75-V75 -> 0 | AA75: =S75-W75 -> 0 | AC75: =O75-AA75 -> 0
A76: =Bonus!A75 -> 52.8667 | B76: =Bonus!B75 -> California Water Service Co. - Cal Water Salinas Station 33 | C76: =Bonus!G75 -> 1 | D76: =GAAP!G75 -> 1 | E76: =Bonus!I75 -> 314085.77 | F76: =Bonus!F75 -> 290726.11 | G76: =E76-F76 -> 23359.66 | I76: =GAAP!I75 -> 314085.77 | J76: =GAAP!F75 -> 290726.11 | K76: =I76-J76 -> 23359.66 | M76: =E76-I76 -> 0 | N76: =F76-J76 -> 0 | O76: =G76-K76 -> 0 | Q76: =R76+S76 -> 1869.5547 | R76: =Bonus!Q75 -> 5378.76 | S76: =Bonus!S75 -> -3509.2053 | U76: =V76+W76 -> 1869.5547 | V76: =GAAP!Q75 -> 5378.76 | W76: =GAAP!S75 -> -3509.2053 | Y76: =Q76-U76 -> 0 | Z76: =R76-V76 -> 0 | AA76: =S76-W76 -> 0 | AC76: =O76-AA76 -> 0
A77: =Bonus!A76 -> 52.867 | B77: =Bonus!B76 -> California Water Service Co. - Cal Water - King City Station 10 | C77: =Bonus!G76 -> 1 | D77: =GAAP!G76 -> 1 | E77: =Bonus!I76 -> 274166.01 | F77: =Bonus!F76 -> 267282.05 | G77: =E77-F77 -> 6883.96 | I77: =GAAP!I76 -> 274166.01 | J77: =GAAP!F76 -> 267282.05 | K77: =I77-J77 -> 6883.96 | M77: =E77-I77 -> 0 | N77: =F77-J77 -> 0 | O77: =G77-K77 -> 0 | Q77: =R77+S77 -> 142646.06 | R77: =Bonus!Q76 -> 146166.54 | S77: =Bonus!S76 -> -3520.4756 | U77: =V77+W77 -> 142646.06 | V77: =GAAP!Q76 -> 146166.54 | W77: =GAAP!S76 -> -3520.4756 | Y77: =Q77-U77 -> 0 | Z77: =R77-V77 -> 0 | AA77: =S77-W77 -> 0 | AC77: =O77-AA77 -> 0
A78: =Bonus!A77 -> 52.8674 | B78: =Bonus!B77 -> City of Hanford - WWTP Standby Influent Pump Install | C78: =Bonus!G77 -> 1 | D78: =GAAP!G77 -> 1 | E78: =Bonus!I77 -> 279244 | F78: =Bonus!F77 -> 251088.2 | G78: =E78-F78 -> 28155.8 | I78: =GAAP!I77 -> 279244 | J78: =GAAP!F77 -> 251088.2 | K78: =I78-J78 -> 28155.8 | M78: =E78-I78 -> 0 | N78: =F78-J78 -> 0 | O78: =G78-K78 -> 0 | Q78: =R78+S78 -> 78969.796 | R78: =Bonus!Q77 -> 66348.58 | S78: =Bonus!S77 -> 12621.216 | U78: =V78+W78 -> 78969.796 | V78: =GAAP!Q77 -> 66348.58 | W78: =GAAP!S77 -> 12621.216 | Y78: =Q78-U78 -> 0 | Z78: =R78-V78 -> 0 | AA78: =S78-W78 -> 0 | AC78: =O78-AA78 -> 0
A79: =Bonus!A78 -> 52.8677 | B79: =Bonus!B78 -> Gunner Ranch, Inc. - CSA 22C Tank and PW2 Site Improvements | C79: =Bonus!G78 -> 1 | D79: =GAAP!G78 -> 1 | E79: =Bonus!I78 -> 796055.3 | F79: =Bonus!F78 -> 689831.96 | G79: =E79-F79 -> 106223.34 | I79: =GAAP!I78 -> 796055.3 | J79: =GAAP!F78 -> 689831.96 | K79: =I79-J79 -> 106223.34 | M79: =E79-I79 -> 0 | N79: =F79-J79 -> 0 | O79: =G79-K79 -> 0 | Q79: =R79+S79 -> 762769.27 | R79: =Bonus!Q78 -> 656545.93 | S79: =Bonus!S78 -> 106223.34 | U79: =V79+W79 -> 762769.27 | V79: =GAAP!Q78 -> 656545.93 | W79: =GAAP!S78 -> 106223.34 | Y79: =Q79-U79 -> 0 | Z79: =R79-V79 -> 0 | AA79: =S79-W79 -> 0 | AC79: =O79-AA79 -> 0
A80: =Bonus!A79 -> 52.868 | B80: =Bonus!B79 -> City of Orange Cove - Orange Cove West Clarifier T&M | C80: =Bonus!G79 -> 1 | D80: =GAAP!G79 -> 1 | E80: =Bonus!I79 -> 29838.25 | F80: =Bonus!F79 -> 26088.33 | G80: =E80-F80 -> 3749.92 | I80: =GAAP!I79 -> 29838.25 | J80: =GAAP!F79 -> 26088.33 | K80: =I80-J80 -> 3749.92 | M80: =E80-I80 -> 0 | N80: =F80-J80 -> 0 | O80: =G80-K80 -> 0 | Q80: =R80+S80 -> 23324.04 | R80: =Bonus!Q79 -> 19574.12 | S80: =Bonus!S79 -> 3749.92 | U80: =V80+W80 -> 23324.04 | V80: =GAAP!Q79 -> 19574.12 | W80: =GAAP!S79 -> 3749.92 | Y80: =Q80-U80 -> 0 | Z80: =R80-V80 -> 0 | AA80: =S80-W80 -> 0 | AC80: =O80-AA80 -> 0
... A102: =Bonus!A101 -> 52.8715 | B102: =Bonus!B101 -> New England Sheet Metal and Mechanical Co. - Vitro Glass Plant Concrete Pad T&M | C102: =Bonus!G101 -> 1 | D102: =GAAP!G101 -> 1 | E102: =Bonus!I101 -> 10001.43 | F102: =Bonus!F101 -> 8585.44 | G102: =E102-F102 -> 1415.99 | I102: =GAAP!I101 -> 10001.43 | J102: =GAAP!F101 -> 8585.44 | K102: =I102-J102 -> 1415.99 | M102: =E102-I102 -> 0 | N102: =F102-J102 -> 0 | O102: =G102-K102 -> 0 | Q102: =R102+S102 -> 10001.43 | R102: =Bonus!Q101 -> 8585.44 | S102: =Bonus!S101 -> 1415.99 | U102: =V102+W102 -> 10001.43 | V102: =GAAP!Q101 -> 8585.44 | W102: =GAAP!S101 -> 1415.99 | Y102: =Q102-U102 -> 0 | Z102: =R102-V102 -> 0 | AA102: =S102-W102 -> 0 | AC102: =O102-AA102 -> 0
AC103: =O103-AA103 -> 0
A104: Fresno Closed Jobs Total | E104: =SUM(E69:E103) -> 24381266 | F104: =SUM(F69:F103) -> 23380699 | G104: =SUM(G69:G103) -> 1000567.2 | I104: =SUM(I69:I103) -> 24381266 | J104: =SUM(J69:J103) -> 23380699 | K104: =SUM(K69:K103) -> 1000567.2 | M104: =SUM(M69:M103) -> 0 | N104: =SUM(N69:N103) -> 0 | O104: =SUM(O69:O103) -> 0 | Q104: =SUM(Q69:Q103) -> 7033109.7 | R104: =SUM(R69:R103) -> 6980067 | S104: =SUM(S69:S103) -> 53042.704 | U104: =SUM(U69:U103) -> 7035974.1 | V104: =SUM(V69:V103) -> 6980067 | W104: =SUM(W69:W103) -> 55907.098 | Y104: =SUM(Y69:Y103) -> -2864.3946 | Z104: =SUM(Z69:Z103) -> 0 | AA104: =SUM(AA69:AA103) -> -2864.3946 | AC104: =O104-AA104 -> 2864.3946
A106: Fresno Total | E106: =E66+E104 -> 1.2037502e+08 | F106: =F66+F104 -> 1.1243384e+08 | G106: =G66+G104 -> 7941176 | I106: =I66+I104 -> 1.2035546e+08 | J106: =J66+J104 -> 1.1243384e+08 | K106: =K66+K104 -> 7921620.1 | M106: =M66+M104 -> 19555.875 | N106: =N66+N104 -> 0 | O106: =O66+O104 -> 19555.875 | Q106: =Q66+Q104 -> 47236193 | R106: =R66+R104 -> 44883136 | S106: =S66+S104 -> 2353056.9 | U106: =U66+U104 -> 47283953 | V106: =V66+V104 -> 44883136 | W106: =W66+W104 -> 2400816.4 | Y106: =Y66+Y104 -> -47759.493 | Z106: =Z66+Z104 -> 0 | AA106: =AA66+AA104 -> -47759.493 | AC106: =O106-AA106 -> 67315.368
A108: East Bay Open Jobs
A109: =Bonus!A107 -> 53.2007 | B109: =Bonus!B107 -> Union Sanitary Dist. - Phase 1B Secondary Clarifiers | C109: =Bonus!G107 -> 0.0013887146 | D109: =GAAP!G107 -> 0.0013887146 | E109: =Bonus!I107 -> 404852.16 | F109: =Bonus!F107 -> 404852.16 | G109: =E109-F109 -> 0 | I109: =GAAP!I107 -> 404852.16 | J109: =GAAP!F107 -> 404852.16 | K109: =I109-J109 -> 0 | M109: =E109-I109 -> 0 | N109: =F109-J109 -> 0 | O109: =G109-K109 -> 0 | Q109: =R109+S109 -> 404852.16 | R109: =Bonus!Q107 -> 404852.16 | S109: =Bonus!S107 -> 0 | U109: =V109+W109 -> 404852.16 | V109: =GAAP!Q107 -> 404852.16 | W109: =GAAP!S107 -> 0 | Y109: =Q109-U109 -> 0 | Z109: =R109-V109 -> 0 | AA109: =S109-W109 -> 0 | AC109: =O109-AA109 -> 0
AC110: =O110-AA110 -> 0
A111: East Bay Open Jobs Total | E111: =SUM(E109:E110) -> 404852.16 | F111: =SUM(F109:F110) -> 404852.16 | G111: =SUM(G109:G110) -> 0 | I111: =SUM(I109:I110) -> 404852.16 | J111: =SUM(J109:J110) -> 404852.16 | K111: =SUM(K109:K110) -> 0 | M111: =SUM(M109:M110) -> 0 | N111: =SUM(N109:N110) -> 0 | O111: =SUM(O109:O110) -> 0 | Q111: =SUM(Q109:Q110) -> 404852.16 | R111: =SUM(R109:R110) -> 404852.16 | S111: =SUM(S109:S110) -> 0 | U111: =SUM(U109:U110) -> 404852.16 | V111: =SUM(V109:V110) -> 404852.16 | W111: =SUM(W109:W110) -> 0 | Y111: =SUM(Y109:Y110) -> 0 | Z111: =SUM(Z109:Z110) -> 0 | AA111: =SUM(AA109:AA110) -> 0 | AC111: =O111-AA111 -> 0
A113: East Bay Closed Jobs
A114: =Bonus!A112 -> 53.2004 | B114: =Bonus!B112 -> City of Millbrae - Millbrae Sludge Thickener & Digester No. 2 Rehab Project | C114: =Bonus!G112 -> 1 | D114: =GAAP!G112 -> 1 | E114: =Bonus!I112 -> 1173753.5 | F114: =Bonus!F112 -> 980791.05 | G114: =E114-F114 -> 192962.42 | I114: =GAAP!I112 -> 1173753.5 | J114: =GAAP!F112 -> 980791.05 | K114: =I114-J114 -> 192962.42 | M114: =E114-I114 -> 0 | N114: =F114-J114 -> 0 | O114: =G114-K114 -> 0 | Q114: =R114+S114 -> 1151825 | R114: =Bonus!Q112 -> 958862.57 | S114: =Bonus!S112 -> 192962.42 | U114: =V114+W114 -> 1151825 | V114: =GAAP!Q112 -> 958862.57 | W114: =GAAP!S112 -> 192962.42 | Y114: =Q114-U114 -> 0 | Z114: =R114-V114 -> 0 | AA114: =S114-W114 -> 0 | AC114: =O114-AA114 -> 0
A115: =Bonus!A113 -> 53.2005 | B115: =Bonus!B113 -> East Bay Overhead 2025 | C115: =Bonus!G113 -> 1 | D115: =GAAP!G113 -> 1 | E115: =Bonus!I113 -> 0 | F115: =Bonus!F113 -> 279281.96 | G115: =E115-F115 -> -279281.96 | I115: =GAAP!I113 -> 0 | J115: =GAAP!F113 -> 279281.96 | K115: =I115-J115 -> -279281.96 | M115: =E115-I115 -> 0 | N115: =F115-J115 -> 0 | O115: =G115-K115 -> 0 | Q115: =R115+S115 -> 0 | R115: =Bonus!Q113 -> 279281.96 | S115: =Bonus!S113 -> -279281.96 | U115: =V115+W115 -> 0 | V115: =GAAP!Q113 -> 279281.96 | W115: =GAAP!S113 -> -279281.96 | Y115: =Q115-U115 -> 0 | Z115: =R115-V115 -> 0 | AA115: =S115-W115 -> 0 | AC115: =O115-AA115 -> 0
A116: =Bonus!A114 -> 53.2006 | B116: =Bonus!B114 -> East Bay Estimating 2026 | C116: =Bonus!G114 -> 1 | D116: =GAAP!G114 -> 1 | E116: =Bonus!I114 -> 0 | F116: =Bonus!F114 -> 304986.32 | G116: =E116-F116 -> -304986.32 | I116: =GAAP!I114 -> 0 | J116: =GAAP!F114 -> 304986.32 | K116: =I116-J116 -> -304986.32 | M116: =E116-I116 -> 0 | N116: =F116-J116 -> 0 | O116: =G116-K116 -> 0 | Q116: =R116+S116 -> 0 | R116: =Bonus!Q114 -> 304986.32 | S116: =Bonus!S114 -> -304986.32 | U116: =V116+W116 -> 0 | V116: =GAAP!Q114 -> 304986.32 | W116: =GAAP!S114 -> -304986.32 | Y116: =Q116-U116 -> 0 | Z116: =R116-V116 -> 0 | AA116: =S116-W116 -> 0 | AC116: =O116-AA116 -> 0
AC117: =O117-AA117 -> 0
A118: East Bay Closed Jobs Total | E118: =SUM(E113:E117) -> 1173753.5 | F118: =SUM(F113:F117) -> 1565059.3 | G118: =SUM(G113:G117) -> -391305.86 | I118: =SUM(I113:I117) -> 1173753.5 | J118: =SUM(J113:J117) -> 1565059.3 | K118: =SUM(K113:K117) -> -391305.86 | M118: =SUM(M113:M117) -> 0 | N118: =SUM(N113:N117) -> 0 | O118: =SUM(O113:O117) -> 0 | Q118: =SUM(Q113:Q117) -> 1151825 | R118: =SUM(R113:R117) -> 1543130.9 | S118: =SUM(S113:S117) -> -391305.86 | U118: =SUM(U113:U117) -> 1151825 | V118: =SUM(V113:V117) -> 1543130.9 | W118: =SUM(W113:W117) -> -391305.86 | Y118: =SUM(Y113:Y117) -> 0 | Z118: =SUM(Z113:Z117) -> 0 | AA118: =SUM(AA113:AA117) -> 0 | AC118: =O118-AA118 -> 0
A120: East Bay Total | E120: =E111+E118 -> 1578605.6 | F120: =F111+F118 -> 1969911.5 | G120: =G111+G118 -> -391305.86 | I120: =I111+I118 -> 1578605.6 | J120: =J111+J118 -> 1969911.5 | K120: =K111+K118 -> -391305.86 | M120: =M111+M118 -> 0 | N120: =N111+N118 -> 0 | O120: =O111+O118 -> 0 | Q120: =Q111+Q118 -> 1556677.1 | R120: =R111+R118 -> 1947983 | S120: =S111+S118 -> -391305.86 | U120: =U111+U118 -> 1556677.1 | V120: =V111+V118 -> 1947983 | W120: =W111+W118 -> -391305.86 | Y120: =Y111+Y118 -> 0 | Z120: =Z111+Z118 -> 0 | AA120: =AA111+AA118 -> 0 | AC120: =O120-AA120 -> 0
A122: Bakersfield Open Jobs
A123: =Bonus!A120 -> 54.9033 | B123: =Bonus!B120 -> Semitropic WSD - Stored Water Recovery Unit Phase 2A, Amendment 8 | C123: =Bonus!G120 -> 1 | D123: =GAAP!G120 -> 1 | E123: =Bonus!I120 -> 118278.58 | F123: =Bonus!F120 -> 104550.27 | G123: =E123-F123 -> 13728.31 | I123: =GAAP!I120 -> 118278.58 | J123: =GAAP!F120 -> 104550.27 | K123: =I123-J123 -> 13728.31 | M123: =E123-I123 -> 0 | N123: =F123-J123 -> 0 | O123: =G123-K123 -> 0 | Q123: =R123+S123 -> 24368.78 | R123: =Bonus!Q120 -> 21607.34 | S123: =Bonus!S120 -> 2761.44 | U123: =V123+W123 -> 24368.78 | V123: =GAAP!Q120 -> 21607.34 | W123: =GAAP!S120 -> 2761.44 | Y123: =Q123-U123 -> 0 | Z123: =R123-V123 -> 0 | AA123: =S123-W123 -> 0 | AC123: =O123-AA123 -> 0
A124: =Bonus!A121 -> 54.9135 | B124: =Bonus!B121 -> Calif. Rail Bldrs LLC - North Kern WSD Canal 9-22 Relocation Project | C124: =Bonus!G121 -> 1 | D124: =GAAP!G121 -> 1 | E124: =Bonus!I121 -> 9470658.6 | F124: =Bonus!F121 -> 9050951.9 | G124: =E124-F124 -> 419706.76 | I124: =GAAP!I121 -> 9470658.6 | J124: =GAAP!F121 -> 9050951.9 | K124: =I124-J124 -> 419706.76 | M124: =E124-I124 -> 0 | N124: =F124-J124 -> 0 | O124: =G124-K124 -> 0 | Q124: =R124+S124 -> 1547627.9 | R124: =Bonus!Q121 -> 1679915.5 | S124: =Bonus!S121 -> -132287.61 | U124: =V124+W124 -> 2099622.3 | V124: =GAAP!Q121 -> 1679915.5 | W124: =GAAP!S121 -> 419706.76 | Y124: =Q124-U124 -> -551994.37 | Z124: =R124-V124 -> 0 | AA124: =S124-W124 -> -551994.37 | AC124: =O124-AA124 -> 551994.37
A125: =Bonus!A122 -> 54.9257 | B125: =Bonus!B122 -> City of Guadalupe - Highway 1 Lift Station | C125: =Bonus!G122 -> 0.53438694 | D125: =GAAP!G122 -> 0.53438694 | E125: =Bonus!I122 -> 786258.46 | F125: =Bonus!F122 -> 762211.05 | G125: =E125-F125 -> 24047.412 | I125: =GAAP!I122 -> 786258.46 | J125: =GAAP!F122 -> 762211.05 | K125: =I125-J125 -> 24047.412 | M125: =E125-I125 -> 0 | N125: =F125-J125 -> 0 | O125: =G125-K125 -> 0 | Q125: =R125+S125 -> 772222.63 | R125: =Bonus!Q122 -> 748175.22 | S125: =Bonus!S122 -> 24047.412 | U125: =V125+W125 -> 772222.63 | V125: =GAAP!Q122 -> 748175.22 | W125: =GAAP!S122 -> 24047.412 | Y125: =Q125-U125 -> 0 | Z125: =R125-V125 -> 0 | AA125: =S125-W125 -> 0 | AC125: =O125-AA125 -> 0
A126: =Bonus!A123 -> 54.9268 | B126: =Bonus!B123 -> Semitropic Water Storage Dist. - Amendment No. 23 Raw Water Processing Plant Pipeline Replacement | C126: =Bonus!G123 -> 0.95487095 | D126: =GAAP!G123 -> 0.95487095 | E126: =Bonus!I123 -> 909648.28 | F126: =Bonus!F123 -> 844648.28 | G126: =E126-F126 -> 65000 | I126: =GAAP!I123 -> 906714.89 | J126: =GAAP!F123 -> 844648.28 | K126: =I126-J126 -> 62066.612 | M126: =E126-I126 -> 2933.388 | N126: =F126-J126 -> 0 | O126: =G126-K126 -> 2933.388 | Q126: =R126+S126 -> 50581.443 | R126: =Bonus!Q123 -> 56594.51 | S126: =Bonus!S123 -> -6013.0668 | U126: =V126+W126 -> 47648.055 | V126: =GAAP!Q123 -> 56594.51 | W126: =GAAP!S123 -> -8946.4548 | Y126: =Q126-U126 -> 2933.388 | Z126: =R126-V126 -> 0 | AA126: =S126-W126 -> 2933.388 | AC126: =O126-AA126 -> -2.910383e-11
A127: =Bonus!A124 -> 54.9269 | B127: =Bonus!B124 -> Semitropic Water Storage Dist. - Design & Construction of the Central TCP Facility-Phase 1 | C127: =Bonus!G124 -> 0.92942108 | D127: =GAAP!G124 -> 1 | E127: =Bonus!I124 -> 584066.79 | F127: =Bonus!F124 -> 549817.74 | G127: =E127-F127 -> 34249.05 | I127: =GAAP!I124 -> 625819.17 | J127: =GAAP!F124 -> 549817.74 | K127: =I127-J127 -> 76001.43 | M127: =E127-I127 -> -41752.38 | N127: =F127-J127 -> 0 | O127: =G127-K127 -> -41752.38 | Q127: =R127+S127 -> 243796.33 | R127: =Bonus!Q124 -> 243796.33 | S127: =Bonus!S124 -> 0 | U127: =V127+W127 -> 285548.71 | V127: =GAAP!Q124 -> 243796.33 | W127: =GAAP!S124 -> 41752.38 | Y127: =Q127-U127 -> -41752.38 | Z127: =R127-V127 -> 0 | AA127: =S127-W127 -> -41752.38 | AC127: =O127-AA127 -> 0
A128: =Bonus!A125 -> 54.9285 | B128: =Bonus!B125 -> Semitropic Water Storage Dist. - Emergency Radial Arm Gate Removal and Replacement | C128: =Bonus!G125 -> 0.80858393 | D128: =GAAP!G125 -> 0.80858393 | E128: =Bonus!I125 -> 373583.56 | F128: =Bonus!F125 -> 312939.77 | G128: =E128-F128 -> 60643.795 | I128: =GAAP!I125 -> 373583.56 | J128: =GAAP!F125 -> 312939.77 | K128: =I128-J128 -> 60643.795 | M128: =E128-I128 -> 0 | N128: =F128-J128 -> 0 | O128: =G128-K128 -> 0 | Q128: =R128+S128 -> 151844.58 | R128: =Bonus!Q125 -> 126887.02 | S128: =Bonus!S125 -> 24957.557 | U128: =V128+W128 -> 151844.58 | V128: =GAAP!Q125 -> 126887.02 | W128: =GAAP!S125 -> 24957.557 | Y128: =Q128-U128 -> 0 | Z128: =R128-V128 -> 0 | AA128: =S128-W128 -> 0 | AC128: =O128-AA128 -> 0
A129: =Bonus!A126 -> 54.9313 | B129: =Bonus!B126 -> Granite Construction Co. - Granite Chumash Camp 4 Infrastructure Project | C129: =Bonus!G126 -> 0.93780908 | D129: =GAAP!G126 -> 0.93780908 | E129: =Bonus!I126 -> 7396392.4 | F129: =Bonus!F126 -> 6449205.2 | G129: =E129-F129 -> 947187.17 | I129: =GAAP!I126 -> 7396392.4 | J129: =GAAP!F126 -> 6449205.2 | K129: =I129-J129 -> 947187.17 | M129: =E129-I129 -> 0 | N129: =F129-J129 -> 0 | O129: =G129-K129 -> 0 | Q129: =R129+S129 -> 5277538.8 | R129: =Bonus!Q126 -> 4528066.1 | S129: =Bonus!S126 -> 749472.66 | U129: =V129+W129 -> 5277538.8 | V129: =GAAP!Q126 -> 4528066.1 | W129: =GAAP!S126 -> 749472.66 | Y129: =Q129-U129 -> 0 | Z129: =R129-V129 -> 0 | AA129: =S129-W129 -> 0 | AC129: =O129-AA129 -> 0
A130: =Bonus!A127 -> 54.933 | B130: =Bonus!B127 -> City of Bakersfield Public Works - Wastewater Treatment Plant No. 3 Septage Processing Unit Rep | C130: =Bonus!G127 -> 0.99538556 | D130: =GAAP!G127 -> 0.99538556 | E130: =Bonus!I127 -> 323400.77 | F130: =Bonus!F127 -> 306221.41 | G130: =E130-F130 -> 17179.359 | I130: =GAAP!I127 -> 323400.77 | J130: =GAAP!F127 -> 306221.41 | K130: =I130-J130 -> 17179.359 | M130: =E130-I130 -> 0 | N130: =F130-J130 -> 0 | O130: =G130-K130 -> 0 | Q130: =R130+S130 -> 131310.37 | R130: =Bonus!Q127 -> 124773.14 | S130: =Bonus!S127 -> 6537.2322 | U130: =V130+W130 -> 131310.37 | V130: =GAAP!Q127 -> 124773.14 | W130: =GAAP!S127 -> 6537.2322 | Y130: =Q130-U130 -> 0 | Z130: =R130-V130 -> 0 | AA130: =S130-W130 -> 0 | AC130: =O130-AA130 -> 0
A131: =Bonus!A128 -> 54.9336 | B131: =Bonus!B128 -> Palmdale Water Dist. - Pure Water AV - Demonstration Facility | C131: =Bonus!G128 -> 0.53030685 | D131: =GAAP!G128 -> 0.53030685 | E131: =Bonus!I128 -> 13359053 | F131: =Bonus!F128 -> 12340864 | G131: =E131-F131 -> 1018189.1 | I131: =GAAP!I128 -> 13359053 | J131: =GAAP!F128 -> 12340864 | K131: =I131-J131 -> 1018189.1 | M131: =E131-I131 -> 0 | N131: =F131-J131 -> 0 | O131: =G131-K131 -> 0 | Q131: =R131+S131 -> 11238996 | R131: =Bonus!Q128 -> 10220807 | S131: =Bonus!S128 -> 1018189.1 | U131: =V131+W131 -> 11238996 | V131: =GAAP!Q128 -> 10220807 | W131: =GAAP!S128 -> 1018189.1 | Y131: =Q131-U131 -> 0 | Z131: =R131-V131 -> 0 | AA131: =S131-W131 -> 0 | AC131: =O131-AA131 -> 0
A132: =Bonus!A129 -> 54.9337 | B132: =Bonus!B129 -> City of Bakersfield Public Works - WWTP 3 Digester Gas Booster Blower Replacement Project | C132: =Bonus!G129 -> 0.38254116 | D132: =GAAP!G129 -> 0.38254116 | E132: =Bonus!I129 -> 1570273.3 | F132: =Bonus!F129 -> 1509066.7 | G132: =E132-F132 -> 61206.586 | I132: =GAAP!I129 -> 1570273.3 | J132: =GAAP!F129 -> 1509066.7 | K132: =I132-J132 -> 61206.586 | M132: =E132-I132 -> 0 | N132: =F132-J132 -> 0 | O132: =G132-K132 -> 0 | Q132: =R132+S132 -> 1417261.6 | R132: =Bonus!Q129 -> 1356055 | S132: =Bonus!S129 -> 61206.586 | U132: =V132+W132 -> 1417261.6 | V132: =GAAP!Q129 -> 1356055 | W132: =GAAP!S129 -> 61206.586 | Y132: =Q132-U132 -> 0 | Z132: =R132-V132 -> 0 | AA132: =S132-W132 -> 0 | AC132: =O132-AA132 -> 0
A133: =Bonus!A130 -> 54.9343 | B133: =Bonus!B130 -> Tehachapi-Cummings County Water District - DB – Replace Diesel Engines PP2 and PP3 | C133: =Bonus!G130 -> 0.57100364 | D133: =GAAP!G130 -> 0.57100364 | E133: =Bonus!I130 -> 3929247.4 | F133: =Bonus!F130 -> 3415344.1 | G133: =E133-F133 -> 513903.28 | I133: =GAAP!I130 -> 3929247.4 | J133: =GAAP!F130 -> 3415344.1 | K133: =I133-J133 -> 513903.28 | M133: =E133-I133 -> 0 | N133: =F133-J133 -> 0 | O133: =G133-K133 -> 0 | Q133: =R133+S133 -> 3329055.6 | R133: =Bonus!Q130 -> 2815152.3 | S133: =Bonus!S130 -> 513903.28 | U133: =V133+W133 -> 3329055.6 | V133: =GAAP!Q130 -> 2815152.3 | W133: =GAAP!S130 -> 513903.28 | Y133: =Q133-U133 -> 0 | Z133: =R133-V133 -> 0 | AA133: =S133-W133 -> 0 | AC133: =O133-AA133 -> 0
A134: =Bonus!A131 -> 54.9356 | B134: =Bonus!B131 -> North of River Sanitary Dist. No. 1 - WWTP Digester Gas Scrubber Vessel and Effluent Storage Pond | C134: =Bonus!G131 -> 0.84939808 | D134: =GAAP!G131 -> 0.84939808 | E134: =Bonus!I131 -> 1102799 | F134: =Bonus!F131 -> 775780.75 | G134: =E134-F134 -> 327018.26 | I134: =GAAP!I131 -> 1102799 | J134: =GAAP!F131 -> 775780.75 | K134: =I134-J134 -> 327018.26 | M134: =E134-I134 -> 0 | N134: =F134-J134 -> 0 | O134: =G134-K134 -> 0 | Q134: =R134+S134 -> 1039914.3 | R134: =Bonus!Q131 -> 712895.99 | S134: =Bonus!S131 -> 327018.26 | U134: =V134+W134 -> 1039914.3 | V134: =GAAP!Q131 -> 712895.99 | W134: =GAAP!S131 -> 327018.26 | Y134: =Q134-U134 -> 0 | Z134: =R134-V134 -> 0 | AA134: =S134-W134 -> 0 | AC134: =O134-AA134 -> 0
... A155: =Bonus!A152 -> 54.9421 | B155: =Bonus!B152 -> Nipomo Community Service Dist. - Tefft Emergency Pipe Repair | C155: =Bonus!G152 -> 1 | D155: =GAAP!G152 -> 1 | E155: =Bonus!I152 -> 3703.18 | F155: =Bonus!F152 -> 3703.18 | G155: =E155-F155 -> 0 | I155: =GAAP!I152 -> 3703.18 | J155: =GAAP!F152 -> 3703.18 | K155: =I155-J155 -> 0 | M155: =E155-I155 -> 0 | N155: =F155-J155 -> 0 | O155: =G155-K155 -> 0 | Q155: =R155+S155 -> 3703.18 | R155: =Bonus!Q152 -> 3703.18 | S155: =Bonus!S152 -> 0 | U155: =V155+W155 -> 3703.18 | V155: =GAAP!Q152 -> 3703.18 | W155: =GAAP!S152 -> 0 | Y155: =Q155-U155 -> 0 | Z155: =R155-V155 -> 0 | AA155: =S155-W155 -> 0 | AC155: =O155-AA155 -> 0
AA156: =S156-W156 -> 0 | AC156: =O156-AA156 -> 0
A157: Bakersfield Open Jobs Total | E157: =SUM(E123:E156) -> 50974822 | F157: =SUM(F123:F156) -> 46923257 | G157: =SUM(G123:G156) -> 4051564.8 | I157: =SUM(I123:I156) -> 51246145 | J157: =SUM(J123:J156) -> 46923257 | K157: =SUM(K123:K156) -> 4322887.2 | M157: =SUM(M123:M156) -> -271322.41 | N157: =SUM(N123:N156) -> 0 | O157: =SUM(O123:O156) -> -271322.41 | Q157: =SUM(Q123:Q156) -> 36268924 | R157: =SUM(R123:R156) -> 33129626 | S157: =SUM(S123:S156) -> 3139298.5 | U157: =SUM(U123:U156) -> 37092241 | V157: =SUM(V123:V156) -> 33129626 | W157: =SUM(W123:W156) -> 3962615.3 | Y157: =SUM(Y123:Y156) -> -823316.77 | Z157: =SUM(Z123:Z156) -> 0 | AA157: =SUM(AA123:AA156) -> -823316.77 | AC157: =O157-AA157 -> 551994.37
A159: Bakersfield Closed Jobs
...

Sheet Job Status
A1: W. M. Lyles Co. | Q1: A | R1: Opened in PY, Closed in CY
A2: Job Status Analysis | Q2: B | R2: Opened in PY, Still Open:
A3: For the Month Ended December 31, 2025 | I3: =Backlog!A3 -> 46022 | Q3: C | R3: Open in CY, Closed in CY:
Q4: D | R4: Opened in CY, Still Open:
C5: Billed | D5: Remaining | E5: Total | F5: Cost | G5: Estimate | I5: Projected | L5: Prior | M5: Net | Q5: O | R5: Overhead Jobs
C6: To | D6: To | E6: Contract | F6: Incurred | G6: Cost To | H6: Total Estimated | I6: Final | J6: Percent | K6: Job to Date | L6: Amount | M6: Change | Q6: U | R6: Under $250,000
A7: Job No. | B7: Project Name | C7: Date | D7: Bill | E7: Amount | F7: To Date | G7: Complete | H7: Cost | I7: Profit/(Loss) | J7: Complete | K7: Profit | L7: Claimed | Q7: W | R7: W Jobs
A8: Jobs with Contract Amounts greater than $250,000 | Q8: Print this worksheet in B&W!
A10: Opened in PY, Closed in CY: | N10: Opened | O10: Closed | P10: Size | Q10: Section
A11: =+GAAP!A29 -> 51.1133 | B11: =+GAAP!B29 -> CA Water Service Co. - S. San Francisco St 1-A Pump Replacement | C11: =+GAAP!J29 -> 372738 | D11: =+E11-C11 -> 0 | E11: =+GAAP!C29 -> 372738 | F11: =+GAAP!F29 -> 331855.28 | G11: =+H11-F11 -> 0 | H11: =+E11-I11 -> 331855.28 | I11: =+GAAP!E29 -> 40882.72 | J11: =+GAAP!G29 -> 1 | K11: =+GAAP!H29 -> 40882.72 | L11: =+GAAP!P29 -> 17359.581 | M11: =+K11-L11 -> 23523.139 | N11: =GAAP!T29 -> 2023 | O11: =GAAP!U29 -> 2025 | P11: =+GAAP!V29 -> .
A12: =+GAAP!A30 -> 51.1136 | B12: =+GAAP!B30 -> Union Sanitary Dist - USD Plant Misc. Improvements | C12: =+GAAP!J30 -> 5483550 | D12: =+E12-C12 -> 0 | E12: =+GAAP!C30 -> 5483550 | F12: =+GAAP!F30 -> 4531817.9 | G12: =+H12-F12 -> 0 | H12: =+E12-I12 -> 4531817.9 | I12: =+GAAP!E30 -> 951732.14 | J12: =+GAAP!G30 -> 1 | K12: =+GAAP!H30 -> 951732.14 | L12: =+GAAP!P30 -> 758905.79 | M12: =+K12-L12 -> 192826.35 | N12: =GAAP!T30 -> 2023 | O12: =GAAP!U30 -> 2025 | P12: =+GAAP!V30 -> .
A13: =+GAAP!A31 -> 51.1138 | B13: =+GAAP!B31 -> CA Water Service Co. - Bear Gulch Pump Station 21 | C13: =+GAAP!J31 -> 1120182.1 | D13: =+E13-C13 -> 0 | E13: =+GAAP!C31 -> 1120182.1 | F13: =+GAAP!F31 -> 1167704.1 | G13: =+H13-F13 -> 0 | H13: =+E13-I13 -> 1167704.1 | I13: =+GAAP!E31 -> -47522.08 | J13: =+GAAP!G31 -> 1 | K13: =+GAAP!H31 -> -47522.08 | L13: =+GAAP!P31 -> 77778.099 | M13: =+K13-L13 -> -125300.18 | N13: =GAAP!T31 -> 2023 | O13: =GAAP!U31 -> 2025 | P13: =+GAAP!V31 -> .
A14: =+GAAP!A33 -> 51.1141 | B14: =+GAAP!B33 -> City of Colfax - WWTP Algae Reduction Project | C14: =+GAAP!J33 -> 3967189.8 | D14: =+E14-C14 -> 0 | E14: =+GAAP!C33 -> 3967189.8 | F14: =+GAAP!F33 -> 3835094.7 | G14: =+H14-F14 -> 0 | H14: =+E14-I14 -> 3835094.7 | I14: =+GAAP!E33 -> 132095.06 | J14: =+GAAP!G33 -> 1 | K14: =+GAAP!H33 -> 132095.06 | L14: =+GAAP!P33 -> 79920.299 | M14: =+K14-L14 -> 52174.761 | N14: =GAAP!T33 -> 2023 | O14: =GAAP!U33 -> 2025 | P14: =+GAAP!V33 -> .
A15: =+GAAP!A34 -> 51.1143 | B15: =+GAAP!B34 -> Olivehurst Plumas Lake Manganese Filter Expansion | C15: =+GAAP!J34 -> 1991231.4 | D15: =+E15-C15 -> 0 | E15: =+GAAP!C34 -> 1991231.4 | F15: =+GAAP!F34 -> 1758132.6 | G15: =+H15-F15 -> 0 | H15: =+E15-I15 -> 1758132.6 | I15: =+GAAP!E34 -> 233098.8 | J15: =+GAAP!G34 -> 1 | K15: =+GAAP!H34 -> 233098.8 | L15: =+GAAP!P34 -> 226011.76 | M15: =+K15-L15 -> 7087.0371 | N15: =GAAP!T34 -> 2023 | O15: =GAAP!U34 -> 2025 | P15: =+GAAP!V34 -> .
A16: =+GAAP!A35 -> 51.1147 | B16: =+GAAP!B35 -> City of Lodi-Public Works Dept. - Aeration Diffusers Replacement Project | C16: =+GAAP!J35 -> 2742860.1 | D16: =+E16-C16 -> 0 | E16: =+GAAP!C35 -> 2742860.1 | F16: =+GAAP!F35 -> 2548724.9 | G16: =+H16-F16 -> 0 | H16: =+E16-I16 -> 2548724.9 | I16: =+GAAP!E35 -> 194135.16 | J16: =+GAAP!G35 -> 1 | K16: =+GAAP!H35 -> 194135.16 | L16: =+GAAP!P35 -> 128284.54 | M16: =+K16-L16 -> 65850.625 | N16: =GAAP!T35 -> 2023 | O16: =GAAP!U35 -> 2025 | P16: =+GAAP!V35 -> .
A17: =+GAAP!A36 -> 51.115 | B17: =+GAAP!B36 -> Sacramento Co. Dept. of Water Resources - D49 Metro Air Park Storm Drain Pump Station Phase 2 | C17: =+GAAP!J36 -> 2486231.6 | D17: =+E17-C17 -> 0 | E17: =+GAAP!C36 -> 2486231.6 | F17: =+GAAP!F36 -> 2239435.1 | G17: =+H17-F17 -> 0 | H17: =+E17-I17 -> 2239435.1 | I17: =+GAAP!E36 -> 246796.44 | J17: =+GAAP!G36 -> 1 | K17: =+GAAP!H36 -> 246796.44 | L17: =+GAAP!P36 -> 166471.83 | M17: =+K17-L17 -> 80324.611 | N17: =GAAP!T36 -> 2024 | O17: =GAAP!U36 -> 2025 | P17: =+GAAP!V36 -> .
A18: =+GAAP!A68 -> 52.8567 | B18: =+GAAP!B68 -> City of Modesto - Grayson Well 69 | C18: =+GAAP!J68 -> 3059859 | D18: =+E18-C18 -> 0 | E18: =+GAAP!C68 -> 3059859 | F18: =+GAAP!F68 -> 3128023.9 | G18: =+H18-F18 -> 0 | H18: =+E18-I18 -> 3128023.9 | I18: =+GAAP!E68 -> -68164.94 | J18: =+GAAP!G68 -> 1 | K18: =+GAAP!H68 -> -68164.94 | L18: =+GAAP!P68 -> -83000 | M18: =+K18-L18 -> 14835.06 | N18: =GAAP!T68 -> 2021 | O18: =GAAP!U68 -> 2025 | P18: =+GAAP!V68 -> .
A19: =+GAAP!A69 -> 52.8604 | B19: =+GAAP!B69 -> City of Atwater - Project No. 20-2, Well 20-A TCP Mitigation | C19: =+GAAP!J69 -> 5095691 | D19: =+E19-C19 -> 0 | E19: =+GAAP!C69 -> 5095691 | F19: =+GAAP!F69 -> 4572503.2 | G19: =+H19-F19 -> 0 | H19: =+E19-I19 -> 4572503.2 | I19: =+GAAP!E69 -> 523187.74 | J19: =+GAAP!G69 -> 1 | K19: =+GAAP!H69 -> 523187.74 | L19: =+GAAP!P69 -> 329989.13 | M19: =+K19-L19 -> 193198.61 | N19: =GAAP!T69 -> 2022 | O19: =GAAP!U69 -> 2025 | P19: =+GAAP!V69 -> .
A20: =+GAAP!A70 -> 52.8628 | B20: =+GAAP!B70 -> City of Tulare - Well 4-3 Equipping & I Drive Pipeline Proj. | C20: =+GAAP!J70 -> 5213345.5 | D20: =+E20-C20 -> 0 | E20: =+GAAP!C70 -> 5213345.5 | F20: =+GAAP!F70 -> 4745798.5 | G20: =+H20-F20 -> 0 | H20: =+E20-I20 -> 4745798.5 | I20: =+GAAP!E70 -> 467546.97 | J20: =+GAAP!G70 -> 1 | K20: =+GAAP!H70 -> 467546.97 | L20: =+GAAP!P70 -> 197224.75 | M20: =+K20-L20 -> 270322.22 | N20: =GAAP!T70 -> 2023 | O20: =GAAP!U70 -> 2025 | P20: =+GAAP!V70 -> .
A21: =+GAAP!A71 -> 52.8631 | B21: =+GAAP!B71 -> Gunner Ranch, Inc. - Well 1 Equipping and Site Improvements | C21: =+GAAP!J71 -> 2560650.1 | D21: =+E21-C21 -> 0 | E21: =+GAAP!C71 -> 2560650.1 | F21: =+GAAP!F71 -> 2448658.3 | G21: =+H21-F21 -> 0 | H21: =+E21-I21 -> 2448658.3 | I21: =+GAAP!E71 -> 111991.88 | J21: =+GAAP!G71 -> 1 | K21: =+GAAP!H71 -> 111991.88 | L21: =+GAAP!P71 -> 73003.701 | M21: =+K21-L21 -> 38988.179 | N21: =GAAP!T71 -> 2023 | O21: =GAAP!U71 -> 2025 | P21: =+GAAP!V71 -> .
A22: =+GAAP!A72 -> 52.8652 | B22: =+GAAP!B72 -> California Water Service Co. - Salinas 77 Booster Station | C22: =+GAAP!J72 -> 1290184 | D22: =+E22-C22 -> 0 | E22: =+GAAP!C72 -> 1290184 | F22: =+GAAP!F72 -> 1039376.1 | G22: =+H22-F22 -> 0 | H22: =+E22-I22 -> 1039376.1 | I22: =+GAAP!E72 -> 250807.92 | J22: =+GAAP!G72 -> 1 | K22: =+GAAP!H72 -> 250807.92 | L22: =+GAAP!P72 -> 170698.84 | M22: =+K22-L22 -> 80109.083 | N22: =GAAP!T72 -> 2024 | O22: =GAAP!U72 -> 2025 | P22: =+GAAP!V72 -> .
A23: =+GAAP!A73 -> 52.8658 | B23: =+GAAP!B73 -> California Water Service Co. - Visalia Station 98 Water Storage Tank & Booster Site | C23: =+GAAP!J73 -> 1870915 | D23: =+E23-C23 -> 0 | E23: =+GAAP!C73 -> 1870915 | F23: =+GAAP!F73 -> 1633530.2 | G23: =+H23-F23 -> 0 | H23: =+E23-I23 -> 1633530.2 | I23: =+GAAP!E73 -> 237384.78 | J23: =+GAAP!G73 -> 1 | K23: =+GAAP!H73 -> 237384.78 | L23: =+GAAP!P73 -> 145886.61 | M23: =+K23-L23 -> 91498.175 | N23: =GAAP!T73 -> 2023 | O23: =GAAP!U73 -> 2025 | P23: =+GAAP!V73 -> .
A24: =+GAAP!A74 -> 52.8663 | B24: =+GAAP!B74 -> Root Creek Water Dist. - Ag Well 277 Conversion Project | C24: =+GAAP!J74 -> 1641800 | D24: =+E24-C24 -> 0 | E24: =+GAAP!C74 -> 1641800 | F24: =+GAAP!F74 -> 1379688.3 | G24: =+H24-F24 -> 0 | H24: =+E24-I24 -> 1379688.3 | I24: =+GAAP!E74 -> 262111.72 | J24: =+GAAP!G74 -> 1 | K24: =+GAAP!H74 -> 262111.72 | L24: =+GAAP!P74 -> 42676.951 | M24: =+K24-L24 -> 219434.77 | N24: =GAAP!T74 -> 2024 | O24: =GAAP!U74 -> 2025 | P24: =+GAAP!V74 -> .
A25: =+GAAP!A75 -> 52.8667 | B25: =+GAAP!B75 -> California Water Service Co. - Cal Water Salinas Station 33 | C25: =+GAAP!J75 -> 314085.77 | D25: =+E25-C25 -> 0 | E25: =+GAAP!C75 -> 314085.77 | F25: =+GAAP!F75 -> 290726.11 | G25: =+H25-F25 -> 0 | H25: =+E25-I25 -> 290726.11 | I25: =+GAAP!E75 -> 23359.66 | J25: =+GAAP!G75 -> 1 | K25: =+GAAP!H75 -> 23359.66 | L25: =+GAAP!P75 -> 26868.865 | M25: =+K25-L25 -> -3509.2053 | N25: =GAAP!T75 -> 2024 | O25: =GAAP!U75 -> 2025 | P25: =+GAAP!V75 -> .
A26: =+GAAP!A76 -> 52.867 | B26: =+GAAP!B76 -> California Water Service Co. - Cal Water - King City Station 10 | C26: =+GAAP!J76 -> 274166.01 | D26: =+E26-C26 -> 0 | E26: =+GAAP!C76 -> 274166.01 | F26: =+GAAP!F76 -> 267282.05 | G26: =+H26-F26 -> 0 | H26: =+E26-I26 -> 267282.05 | I26: =+GAAP!E76 -> 6883.96 | J26: =+GAAP!G76 -> 1 | K26: =+GAAP!H76 -> 6883.96 | L26: =+GAAP!P76 -> 10404.436 | M26: =+K26-L26 -> -3520.4756 | N26: =GAAP!T76 -> 2024 | O26: =GAAP!U76 -> 2025 | P26: =+GAAP!V76 -> .
A27: =+GAAP!A77 -> 52.8674 | B27: =+GAAP!B77 -> City of Hanford - WWTP Standby Influent Pump Install | C27: =+GAAP!J77 -> 279244 | D27: =+E27-C27 -> 0 | E27: =+GAAP!C77 -> 279244 | F27: =+GAAP!F77 -> 251088.2 | G27: =+H27-F27 -> 0 | H27: =+E27-I27 -> 251088.2 | I27: =+GAAP!E77 -> 28155.8 | J27: =+GAAP!G77 -> 1 | K27: =+GAAP!H77 -> 28155.8 | L27: =+GAAP!P77 -> 15534.584 | M27: =+K27-L27 -> 12621.216 | N27: =GAAP!T77 -> 2024 | O27: =GAAP!U77 -> 2025 | P27: =+GAAP!V77 -> .
A28: =+GAAP!A78 -> 52.8677 | B28: =+GAAP!B78 -> Gunner Ranch, Inc. - CSA 22C Tank and PW2 Site Improvements | C28: =+GAAP!J78 -> 796055.3 | D28: =+E28-C28 -> 0 | E28: =+GAAP!C78 -> 796055.3 | F28: =+GAAP!F78 -> 689831.96 | G28: =+H28-F28 -> 0 | H28: =+E28-I28 -> 689831.96 | I28: =+GAAP!E78 -> 106223.34 | J28: =+GAAP!G78 -> 1 | K28: =+GAAP!H78 -> 106223.34 | L28: =+GAAP!P78 -> 0 | M28: =+K28-L28 -> 106223.34 | N28: =GAAP!T78 -> 2024 | O28: =GAAP!U78 -> 2025 | P28: =+GAAP!V78 -> .
A29: =+GAAP!A112 -> 53.2004 | B29: =+GAAP!B112 -> City of Millbrae - Millbrae Sludge Thickener & Digester No. 2 Rehab Project | C29: =+GAAP!J112 -> 1173753.5 | D29: =+E29-C29 -> 0 | E29: =+GAAP!C112 -> 1173753.5 | F29: =+GAAP!F112 -> 980791.05 | G29: =+H29-F29 -> 0 | H29: =+E29-I29 -> 980791.05 | I29: =+GAAP!E112 -> 192962.42 | J29: =+GAAP!G112 -> 1 | K29: =+GAAP!H112 -> 192962.42 | L29: =+GAAP!P112 -> 0 | M29: =+K29-L29 -> 192962.42 | N29: =GAAP!T112 -> 2024 | O29: =GAAP!U112 -> 2025 | P29: =+GAAP!V112 -> .
A30: =+GAAP!A157 -> 54.9099 | B30: =+GAAP!B157 -> Laguna County Sanitation Dist. - Phase 1 Plant Upgrade | C30: =+GAAP!J157 -> 55712110 | D30: =+E30-C30 -> 0 | E30: =+GAAP!C157 -> 55712110 | F30: =+GAAP!F157 -> 45328893 | G30: =+H30-F30 -> 0 | H30: =+E30-I30 -> 45328893 | I30: =+GAAP!E157 -> 10383217 | J30: =+GAAP!G157 -> 1 | K30: =+GAAP!H157 -> 10383217 | L30: =+GAAP!P157 -> 10372752 | M30: =+K30-L30 -> 10465.739 | N30: =GAAP!T157 -> 2020 | O30: =GAAP!U157 -> 2025 | P30: =+GAAP!V157 -> .
A31: =+GAAP!A158 -> 54.9172 | B31: =+GAAP!B158 -> Calif. Rail Bldrs LLC - SWSD Distribution System Conflict | C31: =+GAAP!J158 -> 24160002 | D31: =+E31-C31 -> 0 | E31: =+GAAP!C158 -> 24160002 | F31: =+GAAP!F158 -> 21018432 | G31: =+H31-F31 -> 0 | H31: =+E31-I31 -> 21018432 | I31: =+GAAP!E158 -> 3141570.2 | J31: =+GAAP!G158 -> 1 | K31: =+GAAP!H158 -> 3141570.2 | L31: =+GAAP!P158 -> 3107901.8 | M31: =+K31-L31 -> 33668.4 | N31: =GAAP!T158 -> 2021 | O31: =GAAP!U158 -> 2025 | P31: =+GAAP!V158 -> .
A32: =+GAAP!A159 -> 54.9216 | B32: =+GAAP!B159 -> CA Dept. of Corr. - Water Treatment Improvements | C32: =+GAAP!J159 -> 2472164 | D32: =+E32-C32 -> 0 | E32: =+GAAP!C159 -> 2472164 | F32: =+GAAP!F159 -> 2286264.4 | G32: =+H32-F32 -> 0 | H32: =+E32-I32 -> 2286264.4 | I32: =+GAAP!E159 -> 185899.62 | J32: =+GAAP!G159 -> 1 | K32: =+GAAP!H159 -> 185899.62 | L32: =+GAAP!P159 -> 140849.75 | M32: =+K32-L32 -> 45049.866 | N32: =GAAP!T159 -> 2022 | O32: =GAAP!U159 -> 2025 | P32: =+GAAP!V159 -> .
A33: =+GAAP!A160 -> 54.9246 | B33: =+GAAP!B160 -> Kern County Water Agency - Well 38 & 39 Well Equiping Project | C33: =+GAAP!J160 -> 1777852 | D33: =+E33-C33 -> 0 | E33: =+GAAP!C160 -> 1777852 | F33: =+GAAP!F160 -> 1708475.3 | G33: =+H33-F33 -> 0 | H33: =+E33-I33 -> 1708475.3 | I33: =+GAAP!E160 -> 69376.68 | J33: =+GAAP!G160 -> 1 | K33: =+GAAP!H160 -> 69376.68 | L33: =+GAAP!P160 -> 69196.454 | M33: =+K33-L33 -> 180.22572 | N33: =GAAP!T160 -> 2022 | O33: =GAAP!U160 -> 2025 | P33: =+GAAP!V160 -> .
A34: =+GAAP!A162 -> 54.9279 | B34: =+GAAP!B162 -> City of Bakersfield Public Works - Sewer Lift Station Rehabilitation | C34: =+GAAP!J162 -> 3216240 | D34: =+E34-C34 -> 0 | E34: =+GAAP!C162 -> 3216240 | F34: =+GAAP!F162 -> 3153237.4 | G34: =+H34-F34 -> 0 | H34: =+E34-I34 -> 3153237.4 | I34: =+GAAP!E162 -> 63002.61 | J34: =+GAAP!G162 -> 1 | K34: =+GAAP!H162 -> 63002.61 | L34: =+GAAP!P162 -> -15000 | M34: =+K34-L34 -> 78002.61 | N34: =GAAP!T162 -> 2023 | O34: =GAAP!U162 -> 2025 | P34: =+GAAP!V162 -> .
A35: =+GAAP!A165 -> 54.9309 | B35: =+GAAP!B165 -> Teviston Community Services Dist. - Teviston Drought Resilience Water System Impr | C35: =+GAAP!J165 -> 3968668.9 | D35: =+E35-C35 -> 0 | E35: =+GAAP!C165 -> 3968668.9 | F35: =+GAAP!F165 -> 3790858.3 | G35: =+H35-F35 -> 0 | H35: =+E35-I35 -> 3790858.3 | I35: =+GAAP!E165 -> 177810.56 | J35: =+GAAP!G165 -> 1 | K35: =+GAAP!H165 -> 177810.56 | L35: =+GAAP!P165 -> 62853.416 | M35: =+K35-L35 -> 114957.14 | N35: =GAAP!T165 -> 2024 | O35: =GAAP!U165 -> 2025 | P35: =+GAAP!V165 -> .
A36: =+GAAP!A168 -> 54.9333 | B36: =+GAAP!B168 -> Semitropic Water Storage Dist. - SWSD 2 Hydro Turbine Repair Project | C36: =+GAAP!J168 -> 427464.77 | D36: =+E36-C36 -> 0 | E36: =+GAAP!C168 -> 427464.77 | F36: =+GAAP!F168 -> 371915.26 | G36: =+H36-F36 -> 0 | H36: =+E36-I36 -> 371915.26 | I36: =+GAAP!E168 -> 55549.51 | J36: =+GAAP!G168 -> 1 | K36: =+GAAP!H168 -> 55549.51 | L36: =+GAAP!P168 -> 14888.68 | M36: =+K36-L36 -> 40660.83 | N36: =GAAP!T168 -> 2024 | O36: =GAAP!U168 -> 2025 | P36: =+GAAP!V168 -> .
A37: =+GAAP!A170 -> 54.9341 | B37: =+GAAP!B170 -> Nipomo Community Service Dist. - Water Project Interconnection Improvements | C37: =+GAAP!J170 -> 1251279 | D37: =+E37-C37 -> 0 | E37: =+GAAP!C170 -> 1251279 | F37: =+GAAP!F170 -> 1063532.4 | G37: =+H37-F37 -> 0 | H37: =+E37-I37 -> 1063532.4 | I37: =+GAAP!E170 -> 187746.6 | J37: =+GAAP!G170 -> 1 | K37: =+GAAP!H170 -> 187746.6 | L37: =+GAAP!P170 -> 9297.3859 | M37: =+K37-L37 -> 178449.21 | N37: =GAAP!T170 -> 2024 | O37: =GAAP!U170 -> 2025 | P37: =+GAAP!V170 -> .
A38: =+GAAP!A173 -> 54.9349 | B38: =+GAAP!B173 -> North of River Sanitary Dist. No. 1 - Sanitary Sewer Rehabilitation Package A | C38: =+GAAP!J173 -> 290129 | D38: =+E38-C38 -> 0 | E38: =+GAAP!C173 -> 290129 | F38: =+GAAP!F173 -> 197889.31 | G38: =+H38-F38 -> 0 | H38: =+E38-I38 -> 197889.31 | I38: =+GAAP!E173 -> 92239.69 | J38: =+GAAP!G173 -> 1 | K38: =+GAAP!H173 -> 92239.69 | L38: =+GAAP!P173 -> 4519.6837 | M38: =+K38-L38 -> 87720.006 | N38: =GAAP!T173 -> 2024 | O38: =GAAP!U173 -> 2025 | P38: =+GAAP!V173 -> .
A39: =+GAAP!A180 -> 54.9358 | B39: =+GAAP!B180 -> Arvin Edison Water Storage Dist. - Frick Unit - Phase I Turnout | C39: =+GAAP!J180 -> 1147640 | D39: =+E39-C39 -> 0 | E39: =+GAAP!C180 -> 1147640 | F39: =+GAAP!F180 -> 1125399.8 | G39: =+H39-F39 -> 0 | H39: =+E39-I39 -> 1125399.8 | I39: =+GAAP!E180 -> 22240.17 | J39: =+GAAP!G180 -> 1 | K39: =+GAAP!H180 -> 22240.17 | L39: =+GAAP!P180 -> 15917.551 | M39: =+K39-L39 -> 6322.6193 | N39: =GAAP!T180 -> 2024 | O39: =GAAP!U180 -> 2025 | P39: =+GAAP!V180 -> .
A40: =+GAAP!A183 -> 54.9362 | B40: =+GAAP!B183 -> Cawelo Water Dist. - Remove and Replace 24” and 18” Well Line | C40: =+GAAP!J183 -> 425035.04 | D40: =+E40-C40 -> 0 | E40: =+GAAP!C183 -> 425035.04 | F40: =+GAAP!F183 -> 375601.24 | G40: =+H40-F40 -> 0 | H40: =+E40-I40 -> 375601.24 | I40: =+GAAP!E183 -> 49433.8 | J40: =+GAAP!G183 -> 1 | K40: =+GAAP!H183 -> 49433.8 | L40: =+GAAP!P183 -> 0 | M40: =+K40-L40 -> 49433.8 | N40: =GAAP!T183 -> 2024 | O40: =GAAP!U183 -> 2025 | P40: =+GAAP!V183 -> .
A41: =+GAAP!A240 -> 55.123 | B41: =+GAAP!B240 -> Anaergia Technologies - VVWRA - DAF 3 Replacement | C41: =+GAAP!J240 -> 2273682.7 | D41: =+E41-C41 -> 0 | E41: =+GAAP!C240 -> 2273682.7 | F41: =+GAAP!F240 -> 1665145.3 | G41: =+H41-F41 -> 0 | H41: =+E41-I41 -> 1665145.3 | I41: =+GAAP!E240 -> 608537.39 | J41: =+GAAP!G240 -> 1 | K41: =+GAAP!H240 -> 608537.39 | L41: =+GAAP!P240 -> 480252.03 | M41: =+K41-L41 -> 128285.36 | N41: =GAAP!T240 -> 2023 | O41: =GAAP!U240 -> 2025 | P41: =+GAAP!V240 -> .
A42: =+GAAP!A241 -> 55.1231 | B42: =+GAAP!B241 -> City of Corona - WRF 1 Aeration System Improvements | C42: =+GAAP!J241 -> 4046200 | D42: =+E42-C42 -> 0 | E42: =+GAAP!C241 -> 4046200 | F42: =+GAAP!F241 -> 3321856.4 | G42: =+H42-F42 -> 0 | H42: =+E42-I42 -> 3321856.4 | I42: =+GAAP!E241 -> 724343.64 | J42: =+GAAP!G241 -> 1 | K42: =+GAAP!H241 -> 724343.64 | L42: =+GAAP!P241 -> 627907.4 | M42: =+K42-L42 -> 96436.245 | N42: =GAAP!T241 -> 2023 | O42: =GAAP!U241 -> 2025 | P42: =+GAAP!V241 -> .
A43: =+GAAP!A321 -> 56.1003 | B43: =+GAAP!B321 -> Con J. Franke Electric, Inc. - Well 22 GAC Water Treatment | C43: =+GAAP!J321 -> 332901 | D43: =+E43-C43 -> 0 | E43: =+GAAP!C321 -> 332901 | F43: =+GAAP!F321 -> 223395.74 | G43: =+H43-F43 -> 0 | H43: =+E43-I43 -> 223395.74 | I43: =+GAAP!E321 -> 109505.26 | J43: =+GAAP!G321 -> 1 | K43: =+GAAP!H321 -> 109505.26 | L43: =+GAAP!P321 -> 64460.986 | M43: =+K43-L43 -> 45044.274 | N43: =GAAP!T321 -> 2023 | O43: =GAAP!U321 -> 2025 | P43: =+GAAP!V321 -> .
A44: =+GAAP!A330 -> 56.103 | B44: =+GAAP!B330 -> AIC - Core Electrical Services, Inc. - Corte Madera, Town of - Paradise PS RehabiProject | C44: =+GAAP!J330 -> 689578.64 | D44: =+E44-C44 -> 0 | E44: =+GAAP!C330 -> 689578.64 | F44: =+GAAP!F330 -> 689578.64 | G44: =+H44-F44 -> 0 | H44: =+E44-I44 -> 689578.64 | I44: =+GAAP!E330 -> 0 | J44: =+GAAP!G330 -> 1 | K44: =+GAAP!H330 -> 0 | L44: =+GAAP!P330 -> 18034.019 | M44: =+K44-L44 -> -18034.019 | N44: =GAAP!T330 -> 2024 | O44: =GAAP!U330 -> 2025 | P44: =+GAAP!V330 -> .
A45: =+GAAP!A339 -> 56.1062 | B45: =+GAAP!B339 -> AIC - SCADA System Upgrade - City of Brentwood | C45: =+GAAP!J339 -> 409988.07 | D45: =+E45-C45 -> 0 | E45: =+GAAP!C339 -> 409988.07 | F45: =+GAAP!F339 -> 409988.07 | G45: =+H45-F45 -> 0 | H45: =+E45-I45 -> 409988.07 | I45: =+GAAP!E339 -> 0 | J45: =+GAAP!G339 -> 1 | K45: =+GAAP!H339 -> 0 | L45: =+GAAP!P339 -> 0 | M45: =+K45-L45 -> 0 | N45: =GAAP!T339 -> 2024 | O45: =GAAP!U339 -> 2025 | P45: =+GAAP!V339 -> .
A46: =+GAAP!A340 -> 56.1064 | B46: =+GAAP!B340 -> South Orange County Water Agency - CTP & JBL SCADA Upgrade | C46: =+GAAP!J340 -> 435153 | D46: =+E46-C46 -> 0 | E46: =+GAAP!C340 -> 435153 | F46: =+GAAP!F340 -> 202266.4 | G46: =+H46-F46 -> 0 | H46: =+E46-I46 -> 202266.4 | I46: =+GAAP!E340 -> 232886.6 | J46: =+GAAP!G340 -> 1 | K46: =+GAAP!H340 -> 232886.6 | L46: =+GAAP!P340 -> 69496.49 | M46: =+K46-L46 -> 163390.11 | N46: =GAAP!T340 -> 2024 | O46: =GAAP!U340 -> 2025 | P46: =+GAAP!V340 -> .
A48: Opened in PY, Still Open:
A49: =+GAAP!A9 -> 51.1108 | B49: =+GAAP!B9 -> City of Stockton - RWCF Phase 2A/2B | C49: =+GAAP!J9 -> 94045648 | D49: =+E49-C49 -> 0 | E49: =+GAAP!C9 -> 94045648 | F49: =+GAAP!F9 -> 89805618 | G49: =+H49-F49 -> 0 | H49: =+E49-I49 -> 89805618 | I49: =+GAAP!E9 -> 4240030.1 | J49: =+GAAP!G9 -> 1 | K49: =+GAAP!H9 -> 4240030.1 | L49: =+GAAP!P9 -> 4035762.6 | M49: =+K49-L49 -> 204267.49 | N49: =GAAP!T9 -> 2019 | O49: =+GAAP!U9 -> 0 | P49: =+GAAP!V9 -> .
A50: =+GAAP!A10 -> 51.1129 | B50: =+GAAP!B10 -> Union Sanit. Dist - Enhanced Trtmnt & Site Upgrd Ph. 1A Aeration Basin | C50: =+GAAP!J10 -> 96918207 | D50: =+E50-C50 -> 29565374 | E50: =+GAAP!C10 -> 1.2648358e+08 | F50: =+GAAP!F10 -> 87315159 | G50: =+H50-F50 -> 27918422 | H50: =+E50-I50 -> 1.1523358e+08 | I50: =+GAAP!E10 -> 11250000 | J50: =+GAAP!G10 -> 0.75772321 | K50: =+GAAP!H10 -> 8524386.2 | L50: =+GAAP!P10 -> 6957477.4 | M50: =+K50-L50 -> 1566908.8 | N50: =GAAP!T10 -> 2022 | O50: =+GAAP!U10 -> 0 | P50: =+GAAP!V10 -> .
A51: =+GAAP!A11 -> 51.1137 | B51: =+GAAP!B11 -> CA Water Service Co. - Bear Gulch Pump Station 18 | C51: =+GAAP!J11 -> 1121900 | D51: =+E51-C51 -> 190251.45 | E51: =+GAAP!C11 -> 1312151.5 | F51: =+GAAP!F11 -> 1042229.3 | G51: =+H51-F51 -> 156282.17 | H51: =+E51-I51 -> 1198511.5 | I51: =+GAAP!E11 -> 113640 | J51: =+GAAP!G11 -> 0.86960311 | K51: =+GAAP!H11 -> 98821.697 | L51: =+GAAP!P11 -> 27243.589 | M51: =+K51-L51 -> 71578.108 | N51: =GAAP!T11 -> 2023 | O51: =+GAAP!U11 -> 0 | P51: =+GAAP!V11 -> .
A52: =+GAAP!A12 -> 51.1144 | B52: =+GAAP!B12 -> Silicon Valley Clean Water - FEP Improvements Project | C52: =+GAAP!J12 -> 9667725.8 | D52: =+E52-C52 -> 5301840.2 | E52: =+GAAP!C12 -> 14969566 | F52: =+GAAP!F12 -> 8406760.8 | G52: =+H52-F52 -> 5432856.2 | H52: =+E52-I52 -> 13839617 | I52: =+GAAP!E12 -> 1129949 | J52: =+GAAP!G12 -> 0.60744172 | K52: =+GAAP!H12 -> 686378.17 | L52: =+GAAP!P12 -> 90331.451 | M52: =+K52-L52 -> 596046.72 | N52: =GAAP!T12 -> 2023 | O52: =+GAAP!U12 -> 0 | P52: =+GAAP!V12 -> .
A53: =+GAAP!A13 -> 51.1146 | B53: =+GAAP!B13 -> National Carbon Technologies, LLC - Aymium Williams Production Facility | C53: =+GAAP!J13 -> 60980234 | D53: =+E53-C53 -> 0 | E53: =+GAAP!C13 -> 60980234 | F53: =+GAAP!F13 -> 40950686 | G53: =+H53-F53 -> 3246167.5 | H53: =+E53-I53 -> 44196854 | I53: =+GAAP!E13 -> 16783380 | J53: =+GAAP!G13 -> 0.92655207 | K53: =+GAAP!H13 -> 15550675 | L53: =+GAAP!P13 -> 0 | M53: =+K53-L53 -> 15550675 | N53: =GAAP!T13 -> 2023 | O53: =+GAAP!U13 -> 0 | P53: =+GAAP!V13 -> .
A54: =+GAAP!A14 -> 51.1151 | B54: =+GAAP!B14 -> Sonoma Valley County Sanitation Dist. - Sonoma Valley Influent Effluent Upgrade | C54: =+GAAP!J14 -> 5009265.2 | D54: =+E54-C54 -> 5648934.8 | E54: =+GAAP!C14 -> 10658200 | F54: =+GAAP!F14 -> 4923435.2 | G54: =+H54-F54 -> 5155916.8 | H54: =+E54-I54 -> 10079352 | I54: =+GAAP!E14 -> 578848 | J54: =+GAAP!G14 -> 0.48846743 | K54: =+GAAP!H14 -> 282748.4 | L54: =+GAAP!P14 -> 0 | M54: =+K54-L54 -> 282748.4 | N54: =GAAP!T14 -> 2024 | O54: =+GAAP!U14 -> 0 | P54: =+GAAP!V14 -> .
A55: =+GAAP!A15 -> 51.1152 | B55: =+GAAP!B15 -> Mozingo Construction Inc - ElD Sly Park Intertie Project | C55: =+GAAP!J15 -> 15610649 | D55: =+E55-C55 -> 4363840.3 | E55: =+GAAP!C15 -> 19974489 | F55: =+GAAP!F15 -> 13474809 | G55: =+H55-F55 -> 5154139.8 | H55: =+E55-I55 -> 18628948 | I55: =+GAAP!E15 -> 1345541 | J55: =+GAAP!G15 -> 0.72332631 | K55: =+GAAP!H15 -> 973265.21 | L55: =+GAAP!P15 -> 0 | M55: =+K55-L55 -> 973265.21 | N55: =GAAP!T15 -> 2024 | O55: =+GAAP!U15 -> 0 | P55: =+GAAP!V15 -> .
A56: =+GAAP!A16 -> 51.1153 | B56: =+GAAP!B16 -> Linda County Water Dist. - Aeration Blower Replacement | C56: =+GAAP!J16 -> 549548.83 | D56: =+E56-C56 -> 13275.85 | E56: =+GAAP!C16 -> 562824.68 | F56: =+GAAP!F16 -> 334550.81 | G56: =+H56-F56 -> 119969.87 | H56: =+E56-I56 -> 454520.68 | I56: =+GAAP!E16 -> 108304 | J56: =+GAAP!G16 -> 0.7360519 | K56: =+GAAP!H16 -> 79717.365 | L56: =+GAAP!P16 -> 12859.389 | M56: =+K56-L56 -> 66857.976 | N56: =GAAP!T16 -> 2024 | O56: =+GAAP!U16 -> 0 | P56: =+GAAP!V16 -> .
A57: =+GAAP!A17 -> 51.1154 | B57: =+GAAP!B17 -> Keyes Community Services Dist. - TCP Treatment Impvmts Wells 7,8,9,10 | C57: =+GAAP!J17 -> 13340008 | D57: =+E57-C57 -> 23827 | E57: =+GAAP!C17 -> 13363835 | F57: =+GAAP!F17 -> 11872343 | G57: =+H57-F57 -> 616492.4 | H57: =+E57-I57 -> 12488835 | I57: =+GAAP!E17 -> 875000 | J57: =+GAAP!G17 -> 0.95063652 | K57: =+GAAP!H17 -> 831806.95 | L57: =+GAAP!P17 -> 94320.423 | M57: =+K57-L57 -> 737486.53 | N57: =GAAP!T17 -> 2024 | O57: =+GAAP!U17 -> 0 | P57: =+GAAP!V17 -> .
A58: =+GAAP!A44 -> 52.8563 | B58: =+GAAP!B44 -> City of Santa Cruz - Graham Hill WTP Facility Improvements - Phase 1 | C58: =+GAAP!J44 -> 1134038.1 | D58: =+E58-C58 -> 0 | E58: =+GAAP!C44 -> 1134038.1 | F58: =+GAAP!F44 -> 859077.05 | G58: =+H58-F58 -> 0 | H58: =+E58-I58 -> 859077.05 | I58: =+GAAP!E44 -> 274961.08 | J58: =+GAAP!G44 -> 1 | K58: =+GAAP!H44 -> 274961.08 | L58: =+GAAP!P44 -> 194465.74 | M58: =+K58-L58 -> 80495.34 | N58: =GAAP!T44 -> 2021 | O58: =+GAAP!U44 -> 0 | P58: =+GAAP!V44 -> .
A59: =+GAAP!A45 -> 52.8566 | B59: =+GAAP!B45 -> City of Visalia - Water Reclamation Facility RPGS SCR System | C59: =+GAAP!J45 -> 1242053 | D59: =+E59-C59 -> 17345 | E59: =+GAAP!C45 -> 1259398 | F59: =+GAAP!F45 -> 1023821.1 | G59: =+H59-F59 -> 5576.95 | H59: =+E59-I59 -> 1029398 | I59: =+GAAP!E45 -> 230000 | J59: =+GAAP!G45 -> 0.99458232 | K59: =+GAAP!H45 -> 228753.93 | L59: =+GAAP!P45 -> 223974.51 | M59: =+K59-L59 -> 4779.4271 | N59: =GAAP!T45 -> 2021 | O59: =+GAAP!U45 -> 0 | P59: =+GAAP!V45 -> .
A60: =+GAAP!A46 -> 52.8586 | B60: =+GAAP!B46 -> Tesoro Viejo MMWC- WTP/WWTP/RWSP Phase B Expansion - Phase 1 | C60: =+GAAP!J46 -> 12611349 | D60: =+E60-C60 -> 0 | E60: =+GAAP!C46 -> 12611349 | F60: =+GAAP!F46 -> 10565461 | G60: =+H60-F60 -> 95888.26 | H60: =+E60-I60 -> 10661349 | I60: =+GAAP!E46 -> 1950000 | J60: =+GAAP!G46 -> 0.99100599 | K60: =+GAAP!H46 -> 1932461.7 | L60: =+GAAP!P46 -> 1757780 | M60: =+K60-L60 -> 174681.68 | N60: =GAAP!T46 -> 2022 | O60: =+GAAP!U46 -> 0 | P60: =+GAAP!V46 -> .
A61: =+GAAP!A47 -> 52.8634 | B61: =+GAAP!B47 -> City of Huron - Water Treatment Plant Imp. Phase 2 | C61: =+GAAP!J47 -> 12576768 | D61: =+E61-C61 -> 1315954.7 | E61: =+GAAP!C47 -> 13892723 | F61: =+GAAP!F47 -> 11707058 | G61: =+H61-F61 -> 1483664.5 | H61: =+E61-I61 -> 13190723 | I61: =+GAAP!E47 -> 702000 | J61: =+GAAP!G47 -> 0.88752212 | K61: =+GAAP!H47 -> 623040.53 | L61: =+GAAP!P47 -> 277972.01 | M61: =+K61-L61 -> 345068.52 | N61: =GAAP!T47 -> 2023 | O61: =+GAAP!U47 -> 0 | P61: =+GAAP!V47 -> .
A62: =+GAAP!A48 -> 52.8636 | B62: =+GAAP!B48 -> Anaergia Technologies, LLC - Anaergia M1W Digester Mixing Project | C62: =+GAAP!J48 -> 3065635.6 | D62: =+E62-C62 -> 590476.4 | E62: =+GAAP!C48 -> 3656112 | F62: =+GAAP!F48 -> 3367047.4 | G62: =+H62-F62 -> 14064.64 | H62: =+E62-I62 -> 3381112 | I62: =+GAAP!E48 -> 275000 | J62: =+GAAP!G48 -> 0.99584023 | K62: =+GAAP!H48 -> 273856.06 | L62: =+GAAP!P48 -> 204319.71 | M62: =+K62-L62 -> 69536.353 | N62: =GAAP!T48 -> 2023 | O62: =+GAAP!U48 -> 0 | P62: =+GAAP!V48 -> .
A63: =+GAAP!A49 -> 52.8637 | B63: =+GAAP!B49 -> Root Creek Water Dist. - Groundwater Blending & Arsenic | C63: =+GAAP!J49 -> 26148625 | D63: =+E63-C63 -> 115952.65 | E63: =+GAAP!C49 -> 26264578 | F63: =+GAAP!F49 -> 24374299 | G63: =+H63-F63 -> 240278.62 | H63: =+E63-I63 -> 24614578 | I63: =+GAAP!E49 -> 1650000 | J63: =+GAAP!G49 -> 0.99023836 | K63: =+GAAP!H49 -> 1633893.3 | L63: =+GAAP!P49 -> 1208391.8 | M63: =+K63-L63 -> 425501.54 | N63: =GAAP!T49 -> 2023 | O63: =+GAAP!U49 -> 0 | P63: =+GAAP!V49 -> .
A64: =+GAAP!A50 -> 52.864 | B64: =+GAAP!B50 -> City of Dos Palos - WTP Replacement Project | C64: =+GAAP!J50 -> 34176042 | D64: =+E64-C64 -> 4470321.3 | E64: =+GAAP!C50 -> 38646363 | F64: =+GAAP!F50 -> 32158781 | G64: =+H64-F64 -> 4614258.7 | H64: =+E64-I64 -> 36773040 | I64: =+GAAP!E50 -> 1873323 | J64: =+GAAP!G50 -> 0.87452061 | K64: =+GAAP!H50 -> 1638259.6 | L64: =+GAAP!P50 -> 703966.84 | M64: =+K64-L64 -> 934292.73 | N64: =GAAP!T50 -> 2023 | O64: =+GAAP!U50 -> 0 | P64: =+GAAP!V50 -> .
A65: =+GAAP!A51 -> 52.8668 | B65: =+GAAP!B51 -> California Water Service Co. - Cal Water - Salinas Station 57 | C65: =+GAAP!J51 -> 349622.76 | D65: =+E65-C65 -> 62228.24 | E65: =+GAAP!C51 -> 411851 | F65: =+GAAP!F51 -> 357710.67 | G65: =+H65-F65 -> 19285.33 | H65: =+E65-I65 -> 376996 | I65: =+GAAP!E51 -> 34855 | J65: =+GAAP!G51 -> 0.94884474 | K65: =+GAAP!H51 -> 33071.983 | L65: =+GAAP!P51 -> 5273.0464 | M65: =+K65-L65 -> 27798.937 | N65: =GAAP!T51 -> 2024 | O65: =+GAAP!U51 -> 0 | P65: =+GAAP!V51 -> .
A66: =+GAAP!A52 -> 52.8678 | B66: =+GAAP!B52 -> City of Chowcilla - Well 15 & Generator Improvement Projects | C66: =+GAAP!J52 -> 1142122 | D66: =+E66-C66 -> 98199 | E66: =+GAAP!C52 -> 1240321 | F66: =+GAAP!F52 -> 926007.31 | G66: =+H66-F66 -> 236313.69 | H66: =+E66-I66 -> 1162321 | I66: =+GAAP!E52 -> 78000 | J66: =+GAAP!G52 -> 0.7966881 | K66: =+GAAP!H52 -> 62141.672 | L66: =+GAAP!P52 -> 0 | M66: =+K66-L66 -> 62141.672 | N66: =GAAP!T52 -> 2024 | O66: =+GAAP!U52 -> 0 | P66: =+GAAP!V52 -> .
A67: =+GAAP!A121 -> 54.9135 | B67: =+GAAP!B121 -> Calif. Rail Bldrs LLC - North Kern WSD Canal 9-22 Relocation Project | C67: =+GAAP!J121 -> 9470658.6 | D67: =+E67-C67 -> 0 | E67: =+GAAP!C121 -> 9470658.6 | F67: =+GAAP!F121 -> 9050951.9 | G67: =+H67-F67 -> 0 | H67: =+E67-I67 -> 9050951.9 | I67: =+GAAP!E121 -> 419706.76 | J67: =+GAAP!G121 -> 1 | K67: =+GAAP!H121 -> 419706.76 | L67: =+GAAP!P121 -> 0 | M67: =+K67-L67 -> 419706.76 | N67: =GAAP!T121 -> 2021 | O67: =+GAAP!U121 -> 0 | P67: =+GAAP!V121 -> .
A68: =+GAAP!A122 -> 54.9257 | B68: =+GAAP!B122 -> City of Guadalupe - Highway 1 Lift Station | C68: =+GAAP!J122 -> 890983 | D68: =+E68-C68 -> 580345 | E68: =+GAAP!C122 -> 1471328 | F68: =+GAAP!F122 -> 762211.05 | G68: =+H68-F68 -> 664116.95 | H68: =+E68-I68 -> 1426328 | I68: =+GAAP!E122 -> 45000 | J68: =+GAAP!G122 -> 0.53438694 | K68: =+GAAP!H122 -> 24047.412 | L68: =+GAAP!P122 -> 0 | M68: =+K68-L68 -> 24047.412 | N68: =GAAP!T122 -> 2023 | O68: =+GAAP!U122 -> 0 | P68: =+GAAP!V122 -> .
A69: =+GAAP!A123 -> 54.9268 | B69: =+GAAP!B123 -> Semitropic Water Storage Dist. - Amendment No. 23 Raw Water Processing Plant Pipeline Replacement | C69: =+GAAP!J123 -> 907298 | D69: =+E69-C69 -> 42269.99 | E69: =+GAAP!C123 -> 949567.99 | F69: =+GAAP!F123 -> 844648.28 | G69: =+H69-F69 -> 39919.71 | H69: =+E69-I69 -> 884567.99 | I69: =+GAAP!E123 -> 65000 | J69: =+GAAP!G123 -> 0.95487095 | K69: =+GAAP!H123 -> 62066.612 | L69: =+GAAP!P123 -> 71013.067 | M69: =+K69-L69 -> -8946.4548 | N69: =GAAP!T123 -> 2023 | O69: =+GAAP!U123 -> 0 | P69: =+GAAP!V123 -> .
A70: =+GAAP!A124 -> 54.9269 | B70: =+GAAP!B124 -> Semitropic Water Storage Dist. - Design & Construction of the Central TCP Facility-Phase 1 | C70: =+GAAP!J124 -> 625819.17 | D70: =+E70-C70 -> 0 | E70: =+GAAP!C124 -> 625819.17 | F70: =+GAAP!F124 -> 549817.74 | G70: =+H70-F70 -> 0 | H70: =+E70-I70 -> 549817.74 | I70: =+GAAP!E124 -> 76001.43 | J70: =+GAAP!G124 -> 1 | K70: =+GAAP!H124 -> 76001.43 | L70: =+GAAP!P124 -> 34249.05 | M70: =+K70-L70 -> 41752.38 | N70: =GAAP!T124 -> 2023 | O70: =+GAAP!U124 -> 0 | P70: =+GAAP!V124 -> .
A71: =+GAAP!A125 -> 54.9285 | B71: =+GAAP!B125 -> Semitropic Water Storage Dist. - Emergency Radial Arm Gate Removal and Replacement | C71: =+GAAP!J125 -> 427226 | D71: =+E71-C71 -> 34796 | E71: =+GAAP!C125 -> 462022 | F71: =+GAAP!F125 -> 312939.77 | G71: =+H71-F71 -> 74082.23 | H71: =+E71-I71 -> 387022 | I71: =+GAAP!E125 -> 75000 | J71: =+GAAP!G125 -> 0.80858393 | K71: =+GAAP!H125 -> 60643.795 | L71: =+GAAP!P125 -> 35686.238 | M71: =+K71-L71 -> 24957.557 | N71: =GAAP!T125 -> 2023 | O71: =+GAAP!U125 -> 0 | P71: =+GAAP!V125 -> .
A72: =+GAAP!A126 -> 54.9313 | B72: =+GAAP!B126 -> Granite Construction Co. - Granite Chumash Camp 4 Infrastructure Project | C72: =+GAAP!J126 -> 7886885 | D72: =+E72-C72 -> 0.04 | E72: =+GAAP!C126 -> 7886885 | F72: =+GAAP!F126 -> 6449205.2 | G72: =+H72-F72 -> 427679.82 | H72: =+E72-I72 -> 6876885 | I72: =+GAAP!E126 -> 1010000 | J72: =+GAAP!G126 -> 0.93780908 | K72: =+GAAP!H126 -> 947187.17 | L72: =+GAAP!P126 -> 197714.51 | M72: =+K72-L72 -> 749472.66 | N72: =GAAP!T126 -> 2024 | O72: =+GAAP!U126 -> 0 | P72: =+GAAP!V126 -> .
A73: =+GAAP!A127 -> 54.933 | B73: =+GAAP!B127 -> City of Bakersfield Public Works - Wastewater Treatment Plant No. 3 Septage Processing Unit Rep | C73: =+GAAP!J127 -> 324900 | D73: =+E73-C73 -> 0 | E73: =+GAAP!C127 -> 324900 | F73: =+GAAP!F127 -> 306221.41 | G73: =+H73-F73 -> 1419.59 | H73: =+E73-I73 -> 307641 | I73: =+GAAP!E127 -> 17259 | J73: =+GAAP!G127 -> 0.99538556 | K73: =+GAAP!H127 -> 17179.359 | L73: =+GAAP!P127 -> 10642.127 | M73: =+K73-L73 -> 6537.2322 | N73: =GAAP!T127 -> 2024 | O73: =+GAAP!U127 -> 0 | P73: =+GAAP!V127 -> .
A74: =+GAAP!A128 -> 54.9336 | B74: =+GAAP!B128 -> Palmdale Water Dist. - Pure Water AV - Demonstration Facility | C74: =+GAAP!J128 -> 14176593 | D74: =+E74-C74 -> 11014584 | E74: =+GAAP!C128 -> 25191177 | F74: =+GAAP!F128 -> 12340864 | G74: =+H74-F74 -> 10930312 | H74: =+E74-I74 -> 23271177 | I74: =+GAAP!E128 -> 1920000 | J74: =+GAAP!G128 -> 0.53030685 | K74: =+GAAP!H128 -> 1018189.1 | L74: =+GAAP!P128 -> 0 | M74: =+K74-L74 -> 1018189.1 | N74: =GAAP!T128 -> 2024 | O74: =+GAAP!U128 -> 0 | P74: =+GAAP!V128 -> .
A75: =+GAAP!A129 -> 54.9337 | B75: =+GAAP!B129 -> City of Bakersfield Public Works - WWTP 3 Digester Gas Booster Blower Replacement Project | C75: =+GAAP!J129 -> 520441.66 | D75: =+E75-C75 -> 3584406.3 | E75: =+GAAP!C129 -> 4104848 | F75: =+GAAP!F129 -> 1509066.7 | G75: =+H75-F75 -> 2435781.3 | H75: =+E75-I75 -> 3944848 | I75: =+GAAP!E129 -> 160000 | J75: =+GAAP!G129 -> 0.38254116 | K75: =+GAAP!H129 -> 61206.586 | L75: =+GAAP!P129 -> 0 | M75: =+K75-L75 -> 61206.586 | N75: =GAAP!T129 -> 2024 | O75: =+GAAP!U129 -> 0 | P75: =+GAAP!V129 -> .
A76: =+GAAP!A130 -> 54.9343 | B76: =+GAAP!B130 -> Tehachapi-Cummings County Water District - DB – Replace Diesel Engines PP2 and PP3 | C76: =+GAAP!J130 -> 3954560 | D76: =+E76-C76 -> 2926740 | E76: =+GAAP!C130 -> 6881300 | F76: =+GAAP!F130 -> 3415344.1 | G76: =+H76-F76 -> 2565955.9 | H76: =+E76-I76 -> 5981300 | I76: =+GAAP!E130 -> 900000 | J76: =+GAAP!G130 -> 0.57100364 | K76: =+GAAP!H130 -> 513903.28 | L76: =+GAAP!P130 -> 0 | M76: =+K76-L76 -> 513903.28 | N76: =GAAP!T130 -> 2024 | O76: =+GAAP!U130 -> 0 | P76: =+GAAP!V130 -> .
A77: =+GAAP!A131 -> 54.9356 | B77: =+GAAP!B131 -> North of River Sanitary Dist. No. 1 - WWTP Digester Gas Scrubber Vessel and Effluent Storage Pond | C77: =+GAAP!J131 -> 685017 | D77: =+E77-C77 -> 613313 | E77: =+GAAP!C131 -> 1298330 | F77: =+GAAP!F131 -> 775780.75 | G77: =+H77-F77 -> 137549.25 | H77: =+E77-I77 -> 913330 | I77: =+GAAP!E131 -> 385000 | J77: =+GAAP!G131 -> 0.84939808 | K77: =+GAAP!H131 -> 327018.26 | L77: =+GAAP!P131 -> 0 | M77: =+K77-L77 -> 327018.26 | N77: =GAAP!T131 -> 2024 | O77: =+GAAP!U131 -> 0 | P77: =+GAAP!V131 -> .
A78: =+GAAP!A132 -> 54.9366 | B78: =+GAAP!B132 -> City of Pismo Beach Community Development Dept. - WWTP Clarifier Equipment Replacement | C78: =+GAAP!J132 -> 1160831 | D78: =+E78-C78 -> 69300 | E78: =+GAAP!C132 -> 1230131 | F78: =+GAAP!F132 -> 923220.5 | G78: =+H78-F78 -> 156910.5 | H78: =+E78-I78 -> 1080131 | I78: =+GAAP!E132 -> 150000 | J78: =+GAAP!G132 -> 0.85473012 | K78: =+GAAP!H132 -> 128209.52 | L78: =+GAAP!P132 -> 0 | M78: =+K78-L78 -> 128209.52 | N78: =GAAP!T132 -> 2024 | O78: =+GAAP!U132 -> 0 | P78: =+GAAP!V132 -> .
A79: =+GAAP!A133 -> 54.9369 | B79: =+GAAP!B133 -> California Water Service Co. - PFAS Treatment Program Project | C79: =+GAAP!J133 -> 2927423 | D79: =+E79-C79 -> 25623202 | E79: =+GAAP!C133 -> 28550625 | F79: =+GAAP!F133 -> 2787466.7 | G79: =+H79-F79 -> 23392315 | H79: =+E79-I79 -> 26179782 | I79: =+GAAP!E133 -> 2370843 | J79: =+GAAP!G133 -> 0.10647402 | K79: =+GAAP!H133 -> 252433.19 | L79: =+GAAP!P133 -> 0 | M79: =+K79-L79 -> 252433.19 | N79: =GAAP!T133 -> 2024 | O79: =+GAAP!U133 -> 0 | P79: =+GAAP!V133 -> .
A80: =+GAAP!A223 -> 55.109 | B80: =+GAAP!B223 -> LA Dept of Water and Power - Silverlake | C80: =+GAAP!J223 -> 5235272.4 | D80: =+E80-C80 -> 0 | E80: =+GAAP!C223 -> 5235272.4 | F80: =+GAAP!F223 -> 3834064 | G80: =+H80-F80 -> 0 | H80: =+E80-I80 -> 3834064 | I80: =+GAAP!E223 -> 1401208.3 | J80: =+GAAP!G223 -> 1 | K80: =+GAAP!H223 -> 1401208.3 | L80: =+GAAP!P223 -> 1356365.1 | M80: =+K80-L80 -> 44843.22 | N80: =GAAP!T223 -> 2012 | O80: =+GAAP!U223 -> 0 | P80: =+GAAP!V223 -> .
A81: =+GAAP!A224 -> 55.1191 | B81: =+GAAP!B224 -> Inland Empire Utilities - IEUA RP-5 Liquids Exp. & Solids Treat. Facility | C81: =+GAAP!J224 -> 2.9663498e+08 | D81: =+E81-C81 -> 44808149 | E81: =+GAAP!C224 -> 3.4144313e+08 | F81: =+GAAP!F224 -> 2.9917962e+08 | G81: =+H81-F81 -> 38553011 | H81: =+E81-I81 -> 3.3773264e+08 | I81: =+GAAP!E224 -> 3710498 | J81: =+GAAP!G224 -> 0.88584754 | K81: =+GAAP!H224 -> 3286935.5 | L81: =+GAAP!P224 -> 6702671.5 | M81: =+K81-L81 -> -3415736 | N81: =GAAP!T224 -> 2020 | O81: =+GAAP!U224 -> 0 | P81: =+GAAP!V224 -> .
A82: =+GAAP!A225 -> 55.1192 | B82: =+GAAP!B225 -> Inland Empire Utilities - IEUA RP-1 Flare Improvements | C82: =+GAAP!J225 -> 6645760.5 | D82: =+E82-C82 -> 6043.02 | E82: =+GAAP!C225 -> 6651803.5 | F82: =+GAAP!F225 -> 6393992.7 | G82: =+H82-F82 -> 7810.84 | H82: =+E82-I82 -> 6401803.5 | I82: =+GAAP!E225 -> 250000 | J82: =+GAAP!G225 -> 0.9987799 | K82: =+GAAP!H225 -> 249694.98 | L82: =+GAAP!P225 -> 334963.84 | M82: =+K82-L82 -> -85268.865 | N82: =GAAP!T225 -> 2020 | O82: =+GAAP!U225 -> 0 | P82: =+GAAP!V225 -> .
A83: =+GAAP!A226 -> 55.12 | B83: =+GAAP!B226 -> East County Advanced Water Purification Project - Package 1 | C83: =+GAAP!J226 -> 197175877 | D83: =+E83-C83 -> 0 | E83: =+GAAP!C226 -> 197175877 | F83: =+GAAP!F226 -> 1.8997114e+08 | G83: =+H83-F83 -> 0 | H83: =+E83-I83 -> 1.8997114e+08 | I83: =+GAAP!E226 -> 7204739.5 | J83: =+GAAP!G226 -> 1 | K83: =+GAAP!H226 -> 7204739.5 | L83: =+GAAP!P226 -> 4174832.9 | M83: =+K83-L83 -> 3029906.6 | N83: =GAAP!T226 -> 2020 | O83: =+GAAP!U226 -> 0 | P83: =+GAAP!V226 -> .
A84: =+GAAP!A227 -> 55.1202 | B84: =+GAAP!B227 -> LA County Sanitation District - Oxygen Generation Project | C84: =+GAAP!J227 -> 10912273 | D84: =+E84-C84 -> 5483779 | E84: =+GAAP!C227 -> 16396052 | F84: =+GAAP!F227 -> 9590124.3 | G84: =+H84-F84 -> 5630518.2 | H84: =+E84-I84 -> 15220643 | I84: =+GAAP!E227 -> 1175409 | J84: =+GAAP!G227 -> 0.63007355 | K84: =+GAAP!H227 -> 740594.12 | L84: =+GAAP!P227 -> 647450.71 | M84: =+K84-L84 -> 93143.419 | N84: =GAAP!T227 -> 2020 | O84: =+GAAP!U227 -> 0 | P84: =+GAAP!V227 -> .
A85: =+GAAP!A228 -> 55.1204 | B85: =+GAAP!B228 -> East County Advanced Water Purification Project - Package 3 | C85: =+GAAP!J228 -> 57142227 | D85: =+E85-C85 -> 0 | E85: =+GAAP!C228 -> 57142227 | F85: =+GAAP!F228 -> 55213329 | G85: =+H85-F85 -> 0 | H85: =+E85-I85 -> 55213329 | I85: =+GAAP!E228 -> 1928897.8 | J85: =+GAAP!G228 -> 1 | K85: =+GAAP!H228 -> 1928897.8 | L85: =+GAAP!P228 -> 1627042.8 | M85: =+K85-L85 -> 301855.01 | N85: =GAAP!T228 -> 2020 | O85: =+GAAP!U228 -> 0 | P85: =+GAAP!V228 -> .
A86: =+GAAP!A229 -> 55.1227 | B86: =+GAAP!B229 -> Eastern Municipal Water District - MVRWRF Plant 2B Equipping and Flow Diversion Project | C86: =+GAAP!J229 -> 41483406 | D86: =+E86-C86 -> 20800 | E86: =+GAAP!C229 -> 41504206 | F86: =+GAAP!F229 -> 36953023 | G86: =+H86-F86 -> 201183.43 | H86: =+E86-I86 -> 37154206 | I86: =+GAAP!E229 -> 4350000 | J86: =+GAAP!G229 -> 0.99458518 | K86: =+GAAP!H229 -> 4326445.5 | L86: =+GAAP!P229 -> 3409470.3 | M86: =+K86-L86 -> 916975.18 | N86: =GAAP!T229 -> 2022 | O86: =+GAAP!U229 -> 0 | P86: =+GAAP!V229 -> .
A87: =+GAAP!A230 -> 55.1233 | B87: =+GAAP!B230 -> Veolia Water West Operating Services, Inc. - Rialto Solids Handling Design-Build Project (Design Phase) | C87: =+GAAP!J230 -> 123617 | D87: =+E87-C87 -> 2460.16 | E87: =+GAAP!C230 -> 126077.16 | F87: =+GAAP!F230 -> 126077.16 | G87: =+H87-F87 -> 0 | H87: =+E87-I87 -> 126077.16 | I87: =+GAAP!E230 -> 0 | J87: =+GAAP!G230 -> 1 | K87: =+GAAP!H230 -> 0 | L87: =+GAAP!P230 -> 8428.84 | M87: =+K87-L87 -> -8428.84 | N87: =GAAP!T230 -> 2024 | O87: =+GAAP!U230 -> 0 | P87: =+GAAP!V230 -> .
A88: =+GAAP!A231 -> 55.1248 | B88: =+GAAP!B231 -> Anaergia Technologies LLC - City of Riverside - Digester 5 Rehabilitation | C88: =+GAAP!J231 -> 4861991.8 | D88: =+E88-C88 -> 897310 | E88: =+GAAP!C231 -> 5759301.8 | F88: =+GAAP!F231 -> 3621770.2 | G88: =+H88-F88 -> 1312531.6 | H88: =+E88-I88 -> 4934301.8 | I88: =+GAAP!E231 -> 825000 | J88: =+GAAP!G231 -> 0.73399852 | K88: =+GAAP!H231 -> 605548.78 | L88: =+GAAP!P231 -> 0 | M88: =+K88-L88 -> 605548.78 | N88: =GAAP!T231 -> 2024 | O88: =+GAAP!U231 -> 0 | P88: =+GAAP!V231 -> .
A89: =+GAAP!A232 -> 55.1249 | B89: =+GAAP!B232 -> Inland Empire Utilities - IEUA - RP-1 Solids Thickening Project - EN22044 | C89: =+GAAP!J232 -> 15047043 | D89: =+E89-C89 -> 1.3247807e+08 | E89: =+GAAP!C232 -> 147525113 | F89: =+GAAP!F232 -> 15046314 | G89: =+H89-F89 -> 1.2465759e+08 | H89: =+E89-I89 -> 139703905 | I89: =+GAAP!E232 -> 7821208 | J89: =+GAAP!G232 -> 0.10770145 | K89: =+GAAP!H232 -> 842355.48 | L89: =+GAAP!P232 -> 0 | M89: =+K89-L89 -> 842355.48 | N89: =GAAP!T232 -> 2024 | O89: =+GAAP!U232 -> 0 | P89: =+GAAP!V232 -> .
A90: =+GAAP!A252 -> 57.0003 | B90: =+GAAP!B252 -> Moulton Niguel Water Dist. - Advanced Water Treatment Facility Salinity Management System - Ph 1 | C90: =+GAAP!J252 -> 6863233.2 | D90: =+E90-C90 -> 31302186 | E90: =+GAAP!C252 -> 38165420 | F90: =+GAAP!F252 -> 6316909.1 | G90: =+H90-F90 -> 29441424 | H90: =+E90-I90 -> 35758334 | I90: =+GAAP!E252 -> 2407086 | J90: =+GAAP!G252 -> 0.17665558 | K90: =+GAAP!H252 -> 425225.17 | L90: =+GAAP!P252 -> 96385.412 | M90: =+K90-L90 -> 328839.76 | N90: =GAAP!T252 -> 2024 | O90: =+GAAP!U252 -> 0 | P90: =+GAAP!V252 -> .
A91: =+GAAP!A253 -> 57.0004 | B91: =+GAAP!B253 -> Santa Margarita Water Dist. - Oso Creek Water Reclamation Plant Optimization Project | C91: =+GAAP!J253 -> 900072.76 | D91: =+E91-C91 -> 39206152 | E91: =+GAAP!C253 -> 40106225 | F91: =+GAAP!F253 -> 750298.86 | G91: =+H91-F91 -> 37146069 | H91: =+E91-I91 -> 37896368 | I91: =+GAAP!E253 -> 2209857 | J91: =+GAAP!G253 -> 0.019798701 | K91: =+GAAP!H253 -> 0 | L91: =+GAAP!P253 -> 0 | M91: =+K91-L91 -> 0 | N91: =GAAP!T253 -> 2024 | O91: =+GAAP!U253 -> 0 | P91: =+GAAP!V253 -> .
A92: =+GAAP!A267 -> 58.0003 | B92: =+GAAP!B267 -> Los Angeles County Sanitation Dist. - Los Coyotes WRP Process Air Compressor Replacement | C92: =+GAAP!J267 -> 11889202 | D92: =+E92-C92 -> 10635987 | E92: =+GAAP!C267 -> 22525189 | F92: =+GAAP!F267 -> 11034782 | G92: =+H92-F92 -> 10182392 | H92: =+E92-I92 -> 21217174 | I92: =+GAAP!E267 -> 1308015 | J92: =+GAAP!G267 -> 0.52008726 | K92: =+GAAP!H267 -> 680281.93 | L92: =+GAAP!P267 -> 151508.81 | M92: =+K92-L92 -> 528773.12 | N92: =GAAP!T267 -> 2024 | O92: =+GAAP!U267 -> 0 | P92: =+GAAP!V267 -> .
A93: =+GAAP!A283 -> 56.1004 | B93: =+GAAP!B283 -> San Joaquin Electric - Liberty Ranch Sewer Pump Station | C93: =+GAAP!J283 -> 371550 | D93: =+E93-C93 -> 1875 | E93: =+GAAP!C283 -> 373425 | F93: =+GAAP!F283 -> 236373.73 | G93: =+H93-F93 -> 33466.27 | H93: =+E93-I93 -> 269840 | I93: =+GAAP!E283 -> 103585 | J93: =+GAAP!G283 -> 0.87597736 | K93: =+GAAP!H283 -> 90738.115 | L93: =+GAAP!P283 -> 51359.963 | M93: =+K93-L93 -> 39378.152 | N93: =GAAP!T283 -> 2024 | O93: =+GAAP!U283 -> 0 | P93: =+GAAP!V283 -> .
A94: =+GAAP!A290 -> 56.1036 | B94: =+GAAP!B290 -> Darrel Varni Electric, Inc. - GSW, San Benito Co. Sewer Pump Station No. 2 | C94: =+GAAP!J290 -> 48000 | D94: =+E94-C94 -> 228000 | E94: =+GAAP!C290 -> 276000 | F94: =+GAAP!F290 -> 107051.95 | G94: =+H94-F94 -> 101972.05 | H94: =+E94-I94 -> 209024 | I94: =+GAAP!E290 -> 66976 | J94: =+GAAP!G290 -> 0.51215148 | K94: =+GAAP!H290 -> 34301.857 | L94: =+GAAP!P290 -> 17815.649 | M94: =+K94-L94 -> 16486.208 | N94: =GAAP!T290 -> 2024 | O94: =+GAAP!U290 -> 0 | P94: =+GAAP!V290 -> .
A95: =+GAAP!A293 -> 56.1039 | B95: =+GAAP!B293 -> Sac Valley Electrica Inc - Placer County - Creekview Ranch Sewer Lift Station | C95: =+GAAP!J293 -> 330000 | D95: =+E95-C95 -> 45000 | E95: =+GAAP!C293 -> 375000 | F95: =+GAAP!F293 -> 324049.23 | G95: =+H95-F95 -> 8234.77 | H95: =+E95-I95 -> 332284 | I95: =+GAAP!E293 -> 42716 | J95: =+GAAP!G293 -> 0.97521768 | K95: =+GAAP!H293 -> 41657.398 | L95: =+GAAP!P293 -> 4521.8913 | M95: =+K95-L95 -> 37135.507 | N95: =GAAP!T293 -> 2024 | O95: =+GAAP!U293 -> 0 | P95: =+GAAP!V293 -> .
A96: =+GAAP!A294 -> 56.1042 | B96: =+GAAP!B294 -> Trabuco Canyon Water Dist. - SCADA Integration Services | C96: =+GAAP!J294 -> 217715 | D96: =+E96-C96 -> 59850 | E96: =+GAAP!C294 -> 277565 | F96: =+GAAP!F294 -> 172683.27 | G96: =+H96-F96 -> 45604.73 | H96: =+E96-I96 -> 218288 | I96: =+GAAP!E294 -> 59277 | J96: =+GAAP!G294 -> 0.79108 | K96: =+GAAP!H294 -> 46892.849 | L96: =+GAAP!P294 -> 34822.218 | M96: =+K96-L96 -> 12070.631 | N96: =GAAP!T294 -> 2024 | O96: =+GAAP!U294 -> 0 | P96: =+GAAP!V294 -> .
A97: =+GAAP!A295 -> 56.1043 | B97: =+GAAP!B295 -> SD Electirc, Inc - Morgan Hill, City of - Sanitary Sewer Lift Station K & F Reh | C97: =+GAAP!J295 -> 0 | D97: =+E97-C97 -> 336610 | E97: =+GAAP!C295 -> 336610 | F97: =+GAAP!F295 -> 214994.3 | G97: =+H97-F97 -> 96396.7 | H97: =+E97-I97 -> 311391 | I97: =+GAAP!E295 -> 25219 | J97: =+GAAP!G295 -> 0.69043196 | K97: =+GAAP!H295 -> 17412.004 | L97: =+GAAP!P295 -> 4449.6548 | M97: =+K97-L97 -> 12962.349 | N97: =GAAP!T295 -> 2024 | O97: =+GAAP!U295 -> 0 | P97: =+GAAP!V295 -> .
A98: =+GAAP!A297 -> 56.1047 | B98: =+GAAP!B297 -> SD Electric, Inc - Lathrop, City of - Consolidated Treatment Facility Ph. 3 | C98: =+GAAP!J297 -> 1905218.2 | D98: =+E98-C98 -> 489539.75 | E98: =+GAAP!C297 -> 2394758 | F98: =+GAAP!F297 -> 1602869.6 | G98: =+H98-F98 -> 437685.37 | H98: =+E98-I98 -> 2040555 | I98: =+GAAP!E297 -> 354203 | J98: =+GAAP!G297 -> 0.7855067 | K98: =+GAAP!H297 -> 278228.83 | L98: =+GAAP!P297 -> 0 | M98: =+K98-L98 -> 278228.83 | N98: =GAAP!T297 -> 2024 | O98: =+GAAP!U297 -> 0 | P98: =+GAAP!V297 -> .
A99: =+GAAP!A299 -> 56.1049 | B99: =+GAAP!B299 -> East Orange County Water District - SCADA Field Site RTU Prog Ph.1 | C99: =+GAAP!J299 -> 291725 | D99: =+E99-C99 -> 17000 | E99: =+GAAP!C299 -> 308725 | F99: =+GAAP!F299 -> 214423.06 | G99: =+H99-F99 -> 34449.94 | H99: =+E99-I99 -> 248873 | I99: =+GAAP!E299 -> 59852 | J99: =+GAAP!G299 -> 0.86157623 | K99: =+GAAP!H299 -> 51567.06 | L99: =+GAAP!P299 -> 74409.071 | M99: =+K99-L99 -> -22842.011 | N99: =GAAP!T299 -> 2024 | O99: =+GAAP!U299 -> 0 | P99: =+GAAP!V299 -> .
A100: =+GAAP!A300 -> 56.105 | B100: =+GAAP!B300 -> Collins Electric - Watsonville, City of - WWTF Electrical System Hazard Mitigat | C100: =+GAAP!J300 -> 675979.5 | D100: =+E100-C100 -> 3116579.5 | E100: =+GAAP!C300 -> 3792559 | F100: =+GAAP!F300 -> 925847.53 | G100: =+H100-F100 -> 2439719.5 | H100: =+E100-I100 -> 3365567 | I100: =+GAAP!E300 -> 426992 | J100: =+GAAP!G300 -> 0.27509407 | K100: =+GAAP!H300 -> 117462.97 | L100: =+GAAP!P300 -> 0 | M100: =+K100-L100 -> 117462.97 | N100: =GAAP!T300 -> 2024 | O100: =+GAAP!U300 -> 0 | P100: =+GAAP!V300 -> .
A101: =+GAAP!A302 -> 56.1059 | B101: =+GAAP!B302 -> Fusion Electric, Inc - San Francisco Utilities Commission (SFPUC) - Moccasin Compou | C101: =+GAAP!J302 -> 0 | D101: =+E101-C101 -> 399389 | E101: =+GAAP!C302 -> 399389 | F101: =+GAAP!F302 -> 235841.92 | G101: =+H101-F101 -> 93364.08 | H101: =+E101-I101 -> 329206 | I101: =+GAAP!E302 -> 70183 | J101: =+GAAP!G302 -> 0.71639618 | K101: =+GAAP!H302 -> 50278.833 | L101: =+GAAP!P302 -> 0 | M101: =+K101-L101 -> 50278.833 | N101: =GAAP!T302 -> 2024 | O101: =+GAAP!U302 -> 0 | P101: =+GAAP!V302 -> .
A102: =+GAAP!A303 -> 56.106 | B102: =+GAAP!B303 -> Fusion Electric, Inc - Stockton, City of - N4 Pump Station Improvement Plans of Mar | C102: =+GAAP!J303 -> 0 | D102: =+E102-C102 -> 404663 | E102: =+GAAP!C303 -> 404663 | F102: =+GAAP!F303 -> 145563.36 | G102: =+H102-F102 -> 176927.64 | H102: =+E102-I102 -> 322491 | I102: =+GAAP!E303 -> 82172 | J102: =+GAAP!G303 -> 0.45137185 | K102: =+GAAP!H303 -> 37090.128 | L102: =+GAAP!P303 -> 10941.562 | M102: =+K102-L102 -> 26148.566 | N102: =GAAP!T303 -> 2024 | O102: =+GAAP!U303 -> 0 | P102: =+GAAP!V303 -> .
...

Sheet GAAP WIP
A1: W.M. Lyles Co.
A2: WORK IN PROCESS-GAAP BASIS
A3: =+GAAP!A4 -> For the Month Period Ended 12/31/2025
C4: AMOUNT | D4: REMAINING | E4: TOTAL | F4: COSTS | G4: ESTIMATED | H4: TOTAL | I4: TOTAL | J4: % OF | L4: OVER
C5: BILLED | D5: TO BE | E5: ESTIMATED | F5: INCURED | G5: COSTS TO | H5: ESTIMATED | I5: ESTIMATED | J5: COMPLETION | K5: PROFIT / | L5: (UNDER)
A6: JOB | C6: TO DATE | D6: BILLED | E6: CONTRACT | F6: TO DATE | G6: COMPLETE | H6: COSTS | I6: PROFIT | J6: COST/COST | K6: LOSS | L6: BILLIING
A7: =+GAAP!A9 -> 51.1108 | B7: =IF(GAAP!$G9<2,+GAAP!B9," " ) -> City of Stockton - RWCF Phase 2A/2B | C7: =IF(GAAP!$G9<2,+GAAP!J9," " ) -> 94045648 | D7: =IF(GAAP!$G9<2,+GAAP!M9," " ) -> 0 | E7: =IF(GAAP!$G9<2,+GAAP!C9," " ) -> 94045648 | F7: =IF(GAAP!$G9<2,+GAAP!F9," " ) -> 89805618 | G7: =IF(GAAP!$G9<2,+GAAP!L9," " ) -> 0 | H7: =IF(GAAP!$G9<2,+GAAP!D9," " ) -> 89805618 | I7: =IF(GAAP!$G9<2,+GAAP!E9," " ) -> 4240030.1 | J7: =IF(GAAP!$G9<2,+GAAP!G9," " ) -> 1 | K7: =IF(GAAP!$G9<2,+GAAP!H9," " ) -> 4240030.1 | L7: =+GAAP!K9 -> 0 | S7: =K7-'Bonus WIP'!K8 -> -80728.85 | T7: =L7-'Bonus WIP'!L8 -> 80728.85
A8: =+GAAP!A10 -> 51.1129 | B8: =IF(GAAP!$G10<2,+GAAP!B10," " ) -> Union Sanit. Dist - Enhanced Trtmnt & Site Upgrd Ph. 1A Aeration Basin | C8: =IF(GAAP!$G10<2,+GAAP!J10," " ) -> 96918207 | D8: =IF(GAAP!$G10<2,+GAAP!M10," " ) -> 29565374 | E8: =IF(GAAP!$G10<2,+GAAP!C10," " ) -> 1.2648358e+08 | F8: =IF(GAAP!$G10<2,+GAAP!F10," " ) -> 87315159 | G8: =IF(GAAP!$G10<2,+GAAP!L10," " ) -> 27918422 | H8: =IF(GAAP!$G10<2,+GAAP!D10," " ) -> 1.1523358e+08 | I8: =IF(GAAP!$G10<2,+GAAP!E10," " ) -> 11250000 | J8: =IF(GAAP!$G10<2,+GAAP!G10," " ) -> 0.75772321 | K8: =IF(GAAP!$G10<2,+GAAP!H10," " ) -> 8524386.2 | L8: =+GAAP!K10 -> 1078661.5 | S8: =K8-'Bonus WIP'!K9 -> -534407 | T8: =L8-'Bonus WIP'!L9 -> 534407
A9: =+GAAP!A11 -> 51.1137 | B9: =IF(GAAP!$G11<2,+GAAP!B11," " ) -> CA Water Service Co. - Bear Gulch Pump Station 18 | C9: =IF(GAAP!$G11<2,+GAAP!J11," " ) -> 1121900 | D9: =IF(GAAP!$G11<2,+GAAP!M11," " ) -> 190251.45 | E9: =IF(GAAP!$G11<2,+GAAP!C11," " ) -> 1312151.5 | F9: =IF(GAAP!$G11<2,+GAAP!F11," " ) -> 1042229.3 | G9: =IF(GAAP!$G11<2,+GAAP!L11," " ) -> 156282.17 | H9: =IF(GAAP!$G11<2,+GAAP!D11," " ) -> 1198511.5 | I9: =IF(GAAP!$G11<2,+GAAP!E11," " ) -> 113640 | J9: =IF(GAAP!$G11<2,+GAAP!G11," " ) -> 0.86960311 | K9: =IF(GAAP!$G11<2,+GAAP!H11," " ) -> 98821.697 | L9: =+GAAP!K11 -> -19150.977 | S9: =K9-'Bonus WIP'!K10 -> 0 | T9: =L9-'Bonus WIP'!L10 -> 0
A10: =+GAAP!A12 -> 51.1144 | B10: =IF(GAAP!$G12<2,+GAAP!B12," " ) -> Silicon Valley Clean Water - FEP Improvements Project | C10: =IF(GAAP!$G12<2,+GAAP!J12," " ) -> 9667725.8 | D10: =IF(GAAP!$G12<2,+GAAP!M12," " ) -> 5301840.2 | E10: =IF(GAAP!$G12<2,+GAAP!C12," " ) -> 14969566 | F10: =IF(GAAP!$G12<2,+GAAP!F12," " ) -> 8406760.8 | G10: =IF(GAAP!$G12<2,+GAAP!L12," " ) -> 5432856.2 | H10: =IF(GAAP!$G12<2,+GAAP!D12," " ) -> 13839617 | I10: =IF(GAAP!$G12<2,+GAAP!E12," " ) -> 1129949 | J10: =IF(GAAP!$G12<2,+GAAP!G12," " ) -> 0.60744172 | K10: =IF(GAAP!$G12<2,+GAAP!H12," " ) -> 686378.17 | L10: =+GAAP!K12 -> 574586.8 | S10: =K10-'Bonus WIP'!K11 -> 0 | T10: =L10-'Bonus WIP'!L11 -> 0
A11: =+GAAP!A13 -> 51.1146 | B11: =IF(GAAP!$G13<2,+GAAP!B13," " ) -> National Carbon Technologies, LLC - Aymium Williams Production Facility | C11: =IF(GAAP!$G13<2,+GAAP!J13," " ) -> 60980234 | D11: =IF(GAAP!$G13<2,+GAAP!M13," " ) -> 0 | E11: =IF(GAAP!$G13<2,+GAAP!C13," " ) -> 60980234 | F11: =IF(GAAP!$G13<2,+GAAP!F13," " ) -> 40950686 | G11: =IF(GAAP!$G13<2,+GAAP!L13," " ) -> 3246167.5 | H11: =IF(GAAP!$G13<2,+GAAP!D13," " ) -> 44196854 | I11: =IF(GAAP!$G13<2,+GAAP!E13," " ) -> 16783380 | J11: =IF(GAAP!$G13<2,+GAAP!G13," " ) -> 0.92655207 | K11: =IF(GAAP!$G13<2,+GAAP!H13," " ) -> 15550675 | L11: =+GAAP!K13 -> 4478872.1 | S11: =K11-'Bonus WIP'!K12 -> -173716.62 | T11: =L11-'Bonus WIP'!L12 -> 173716.62
A12: =+GAAP!A14 -> 51.1151 | B12: =IF(GAAP!$G14<2,+GAAP!B14," " ) -> Sonoma Valley County Sanitation Dist. - Sonoma Valley Influent Effluent Upgrade | C12: =IF(GAAP!$G14<2,+GAAP!J14," " ) -> 5009265.2 | D12: =IF(GAAP!$G14<2,+GAAP!M14," " ) -> 5648934.8 | E12: =IF(GAAP!$G14<2,+GAAP!C14," " ) -> 10658200 | F12: =IF(GAAP!$G14<2,+GAAP!F14," " ) -> 4923435.2 | G12: =IF(GAAP!$G14<2,+GAAP!L14," " ) -> 5155916.8 | H12: =IF(GAAP!$G14<2,+GAAP!D14," " ) -> 10079352 | I12: =IF(GAAP!$G14<2,+GAAP!E14," " ) -> 578848 | J12: =IF(GAAP!$G14<2,+GAAP!G14," " ) -> 0.48846743 | K12: =IF(GAAP!$G14<2,+GAAP!H14," " ) -> 282748.4 | L12: =+GAAP!K14 -> -196918.37 | S12: =K12-'Bonus WIP'!K13 -> 0 | T12: =L12-'Bonus WIP'!L13 -> 0
A13: =+GAAP!A15 -> 51.1152 | B13: =IF(GAAP!$G15<2,+GAAP!B15," " ) -> Mozingo Construction Inc - ElD Sly Park Intertie Project | C13: =IF(GAAP!$G15<2,+GAAP!J15," " ) -> 15610649 | D13: =IF(GAAP!$G15<2,+GAAP!M15," " ) -> 4363840.3 | E13: =IF(GAAP!$G15<2,+GAAP!C15," " ) -> 19974489 | F13: =IF(GAAP!$G15<2,+GAAP!F15," " ) -> 13474809 | G13: =IF(GAAP!$G15<2,+GAAP!L15," " ) -> 5154139.8 | H13: =IF(GAAP!$G15<2,+GAAP!D15," " ) -> 18628948 | I13: =IF(GAAP!$G15<2,+GAAP!E15," " ) -> 1345541 | J13: =IF(GAAP!$G15<2,+GAAP!G15," " ) -> 0.72332631 | K13: =IF(GAAP!$G15<2,+GAAP!H15," " ) -> 973265.21 | L13: =+GAAP!K15 -> 1162575.3 | S13: =K13-'Bonus WIP'!K14 -> 0 | T13: =L13-'Bonus WIP'!L14 -> 0
A14: =+GAAP!A16 -> 51.1153 | B14: =IF(GAAP!$G16<2,+GAAP!B16," " ) -> Linda County Water Dist. - Aeration Blower Replacement | C14: =IF(GAAP!$G16<2,+GAAP!J16," " ) -> 549548.83 | D14: =IF(GAAP!$G16<2,+GAAP!M16," " ) -> 13275.85 | E14: =IF(GAAP!$G16<2,+GAAP!C16," " ) -> 562824.68 | F14: =IF(GAAP!$G16<2,+GAAP!F16," " ) -> 334550.81 | G14: =IF(GAAP!$G16<2,+GAAP!L16," " ) -> 119969.87 | H14: =IF(GAAP!$G16<2,+GAAP!D16," " ) -> 454520.68 | I14: =IF(GAAP!$G16<2,+GAAP!E16," " ) -> 108304 | J14: =IF(GAAP!$G16<2,+GAAP!G16," " ) -> 0.7360519 | K14: =IF(GAAP!$G16<2,+GAAP!H16," " ) -> 79717.365 | L14: =+GAAP!K16 -> 135280.66 | S14: =K14-'Bonus WIP'!K15 -> 0 | T14: =L14-'Bonus WIP'!L15 -> 0
A15: =+GAAP!A17 -> 51.1154 | B15: =IF(GAAP!$G17<2,+GAAP!B17," " ) -> Keyes Community Services Dist. - TCP Treatment Impvmts Wells 7,8,9,10 | C15: =IF(GAAP!$G17<2,+GAAP!J17," " ) -> 13340008 | D15: =IF(GAAP!$G17<2,+GAAP!M17," " ) -> 23827 | E15: =IF(GAAP!$G17<2,+GAAP!C17," " ) -> 13363835 | F15: =IF(GAAP!$G17<2,+GAAP!F17," " ) -> 11872343 | G15: =IF(GAAP!$G17<2,+GAAP!L17," " ) -> 616492.4 | H15: =IF(GAAP!$G17<2,+GAAP!D17," " ) -> 12488835 | I15: =IF(GAAP!$G17<2,+GAAP!E17," " ) -> 875000 | J15: =IF(GAAP!$G17<2,+GAAP!G17," " ) -> 0.95063652 | K15: =IF(GAAP!$G17<2,+GAAP!H17," " ) -> 831806.95 | L15: =+GAAP!K17 -> 635858.45 | S15: =K15-'Bonus WIP'!K16 -> 0 | T15: =L15-'Bonus WIP'!L16 -> 0
A16: =+GAAP!A18 -> 51.1158 | B16: =IF(GAAP!$G18<2,+GAAP!B18," " ) -> Schneider Electric - City of Ceres WWTP Phase 1- Schneider Electric | C16: =IF(GAAP!$G18<2,+GAAP!J18," " ) -> 32282 | D16: =IF(GAAP!$G18<2,+GAAP!M18," " ) -> 72164 | E16: =IF(GAAP!$G18<2,+GAAP!C18," " ) -> 104446 | F16: =IF(GAAP!$G18<2,+GAAP!F18," " ) -> 56960.69 | G16: =IF(GAAP!$G18<2,+GAAP!L18," " ) -> 47485.31 | H16: =IF(GAAP!$G18<2,+GAAP!D18," " ) -> 104446 | I16: =IF(GAAP!$G18<2,+GAAP!E18," " ) -> 0 | J16: =IF(GAAP!$G18<2,+GAAP!G18," " ) -> 0.54536019 | K16: =IF(GAAP!$G18<2,+GAAP!H18," " ) -> 0 | L16: =+GAAP!K18 -> -24678.69 | S16: =K16-'Bonus WIP'!K17 -> 0 | T16: =L16-'Bonus WIP'!L17 -> 0
A17: =+GAAP!A19 -> 51.1159 | B17: =IF(GAAP!$G19<2,+GAAP!B19," " ) -> El Dorado Irrigation Dist. - EID Reservoir A WTP Backwash-to-waste Valve Repalcement | C17: =IF(GAAP!$G19<2,+GAAP!J19," " ) -> 732995 | D17: =IF(GAAP!$G19<2,+GAAP!M19," " ) -> 466005 | E17: =IF(GAAP!$G19<2,+GAAP!C19," " ) -> 1199000 | F17: =IF(GAAP!$G19<2,+GAAP!F19," " ) -> 790051.12 | G17: =IF(GAAP!$G19<2,+GAAP!L19," " ) -> 289188.88 | H17: =IF(GAAP!$G19<2,+GAAP!D19," " ) -> 1079240 | I17: =IF(GAAP!$G19<2,+GAAP!E19," " ) -> 119760 | J17: =IF(GAAP!$G19<2,+GAAP!G19," " ) -> 0.73204396 | K17: =IF(GAAP!$G19<2,+GAAP!H19," " ) -> 87669.584 | L17: =+GAAP!K19 -> -144725.7 | S17: =K17-'Bonus WIP'!K18 -> 0 | T17: =L17-'Bonus WIP'!L18 -> 0
A18: =+GAAP!A20 -> 51.116 | B18: =IF(GAAP!$G20<2,+GAAP!B20," " ) -> City of Galt Public Works - Industrial WWTP Expansion | C18: =IF(GAAP!$G20<2,+GAAP!J20," " ) -> 223725 | D18: =IF(GAAP!$G20<2,+GAAP!M20," " ) -> 1533275 | E18: =IF(GAAP!$G20<2,+GAAP!C20," " ) -> 1757000 | F18: =IF(GAAP!$G20<2,+GAAP!F20," " ) -> 250518.05 | G18: =IF(GAAP!$G20<2,+GAAP!L20," " ) -> 1439481.9 | H18: =IF(GAAP!$G20<2,+GAAP!D20," " ) -> 1690000 | I18: =IF(GAAP!$G20<2,+GAAP!E20," " ) -> 67000 | J18: =IF(GAAP!$G20<2,+GAAP!G20," " ) -> 0.14823553 | K18: =IF(GAAP!$G20<2,+GAAP!H20," " ) -> 9931.7807 | L18: =+GAAP!K20 -> -36724.831 | S18: =K18-'Bonus WIP'!K19 -> 9931.7807 | T18: =L18-'Bonus WIP'!L19 -> -9931.7807
... A21: =+GAAP!A23 -> 51.1164 | B21: =IF(GAAP!$G23<2,+GAAP!B23," " ) -> CA Water Service Co. - Stockton Roofing | C21: =IF(GAAP!$G23<2,+GAAP!J23," " ) -> 0 | D21: =IF(GAAP!$G23<2,+GAAP!M23," " ) -> 387260 | E21: =IF(GAAP!$G23<2,+GAAP!C23," " ) -> 387260 | F21: =IF(GAAP!$G23<2,+GAAP!F23," " ) -> 4363.25 | G21: =IF(GAAP!$G23<2,+GAAP!L23," " ) -> 379023.75 | H21: =IF(GAAP!$G23<2,+GAAP!D23," " ) -> 383387 | I21: =IF(GAAP!$G23<2,+GAAP!E23," " ) -> 3873 | J21: =IF(GAAP!$G23<2,+GAAP!G23," " ) -> 0.011380798 | K21: =IF(GAAP!$G23<2,+GAAP!H23," " ) -> 0 | L21: =+GAAP!K23 -> -4363.25 | S21: =K21-'Bonus WIP'!K22 -> 0 | T21: =L21-'Bonus WIP'!L22 -> 0
A22: =+GAAP!A24 -> 51.1165 | B22: =IF(GAAP!$G24<2,+GAAP!B24," " ) -> City of Yuba City - WTP Aquifer Storage and Recovery Well No. 3 | C22: =IF(GAAP!$G24<2,+GAAP!J24," " ) -> 0 | D22: =IF(GAAP!$G24<2,+GAAP!M24," " ) -> 5304500 | E22: =IF(GAAP!$G24<2,+GAAP!C24," " ) -> 5304500 | F22: =IF(GAAP!$G24<2,+GAAP!F24," " ) -> 23330.33 | G22: =IF(GAAP!$G24<2,+GAAP!L24," " ) -> 4863112.7 | H22: =IF(GAAP!$G24<2,+GAAP!D24," " ) -> 4886443 | I22: =IF(GAAP!$G24<2,+GAAP!E24," " ) -> 418057 | J22: =IF(GAAP!$G24<2,+GAAP!G24," " ) -> 0.0047745016 | K22: =IF(GAAP!$G24<2,+GAAP!H24," " ) -> 0 | L22: =+GAAP!K24 -> -23330.33 | S22: =K22-'Bonus WIP'!#REF! -> #REF! | T22: =L22-'Bonus WIP'!#REF! -> #REF!
S23: =K23-'Bonus WIP'!K24 -> 0 | T23: =L23-'Bonus WIP'!L24 -> 0
A24: =+GAAP!A44 -> 52.8563 | B24: =IF(GAAP!$G44<2,+GAAP!B44," " ) -> City of Santa Cruz - Graham Hill WTP Facility Improvements - Phase 1 | C24: =IF(GAAP!$G44<2,+GAAP!J44," " ) -> 1134038.1 | D24: =IF(GAAP!$G44<2,+GAAP!M44," " ) -> 0 | E24: =IF(GAAP!$G44<2,+GAAP!C44," " ) -> 1134038.1 | F24: =IF(GAAP!$G44<2,+GAAP!F44," " ) -> 859077.05 | G24: =IF(GAAP!$G44<2,+GAAP!L44," " ) -> 0 | H24: =IF(GAAP!$G44<2,+GAAP!D44," " ) -> 859077.05 | I24: =IF(GAAP!$G44<2,+GAAP!E44," " ) -> 274961.08 | J24: =IF(GAAP!$G44<2,+GAAP!G44," " ) -> 1 | K24: =IF(GAAP!$G44<2,+GAAP!H44," " ) -> 274961.08 | L24: =+GAAP!K44 -> 0 | S24: =K24-'Bonus WIP'!K25 -> -18424.16 | T24: =L24-'Bonus WIP'!L25 -> 18424.16
A25: =+GAAP!A45 -> 52.8566 | B25: =IF(GAAP!$G45<2,+GAAP!B45," " ) -> City of Visalia - Water Reclamation Facility RPGS SCR System | C25: =IF(GAAP!$G45<2,+GAAP!J45," " ) -> 1242053 | D25: =IF(GAAP!$G45<2,+GAAP!M45," " ) -> 17345 | E25: =IF(GAAP!$G45<2,+GAAP!C45," " ) -> 1259398 | F25: =IF(GAAP!$G45<2,+GAAP!F45," " ) -> 1023821.1 | G25: =IF(GAAP!$G45<2,+GAAP!L45," " ) -> 5576.95 | H25: =IF(GAAP!$G45<2,+GAAP!D45," " ) -> 1029398 | I25: =IF(GAAP!$G45<2,+GAAP!E45," " ) -> 230000 | J25: =IF(GAAP!$G45<2,+GAAP!G45," " ) -> 0.99458232 | K25: =IF(GAAP!$G45<2,+GAAP!H45," " ) -> 228753.93 | L25: =+GAAP!K45 -> -10521.983 | S25: =K25-'Bonus WIP'!K26 -> 0 | T25: =L25-'Bonus WIP'!L26 -> 0
A26: =+GAAP!A46 -> 52.8586 | B26: =IF(GAAP!$G46<2,+GAAP!B46," " ) -> Tesoro Viejo MMWC- WTP/WWTP/RWSP Phase B Expansion - Phase 1 | C26: =IF(GAAP!$G46<2,+GAAP!J46," " ) -> 12611349 | D26: =IF(GAAP!$G46<2,+GAAP!M46," " ) -> 0 | E26: =IF(GAAP!$G46<2,+GAAP!C46," " ) -> 12611349 | F26: =IF(GAAP!$G46<2,+GAAP!F46," " ) -> 10565461 | G26: =IF(GAAP!$G46<2,+GAAP!L46," " ) -> 95888.26 | H26: =IF(GAAP!$G46<2,+GAAP!D46," " ) -> 10661349 | I26: =IF(GAAP!$G46<2,+GAAP!E46," " ) -> 1950000 | J26: =IF(GAAP!$G46<2,+GAAP!G46," " ) -> 0.99100599 | K26: =IF(GAAP!$G46<2,+GAAP!H46," " ) -> 1932461.7 | L26: =+GAAP!K46 -> 113426.58 | S26: =K26-'Bonus WIP'!K27 -> 0 | T26: =L26-'Bonus WIP'!L27 -> 0
A27: =+GAAP!A47 -> 52.8634 | B27: =IF(GAAP!$G47<2,+GAAP!B47," " ) -> City of Huron - Water Treatment Plant Imp. Phase 2 | C27: =IF(GAAP!$G47<2,+GAAP!J47," " ) -> 12576768 | D27: =IF(GAAP!$G47<2,+GAAP!M47," " ) -> 1315954.7 | E27: =IF(GAAP!$G47<2,+GAAP!C47," " ) -> 13892723 | F27: =IF(GAAP!$G47<2,+GAAP!F47," " ) -> 11707058 | G27: =IF(GAAP!$G47<2,+GAAP!L47," " ) -> 1483664.5 | H27: =IF(GAAP!$G47<2,+GAAP!D47," " ) -> 13190723 | I27: =IF(GAAP!$G47<2,+GAAP!E47," " ) -> 702000 | J27: =IF(GAAP!$G47<2,+GAAP!G47," " ) -> 0.88752212 | K27: =IF(GAAP!$G47<2,+GAAP!H47," " ) -> 623040.53 | L27: =+GAAP!K47 -> 246669.27 | S27: =K27-'Bonus WIP'!K28 -> 0 | T27: =L27-'Bonus WIP'!L28 -> 0
A28: =+GAAP!A48 -> 52.8636 | B28: =IF(GAAP!$G48<2,+GAAP!B48," " ) -> Anaergia Technologies, LLC - Anaergia M1W Digester Mixing Project | C28: =IF(GAAP!$G48<2,+GAAP!J48," " ) -> 3065635.6 | D28: =IF(GAAP!$G48<2,+GAAP!M48," " ) -> 590476.4 | E28: =IF(GAAP!$G48<2,+GAAP!C48," " ) -> 3656112 | F28: =IF(GAAP!$G48<2,+GAAP!F48," " ) -> 3367047.4 | G28: =IF(GAAP!$G48<2,+GAAP!L48," " ) -> 14064.64 | H28: =IF(GAAP!$G48<2,+GAAP!D48," " ) -> 3381112 | I28: =IF(GAAP!$G48<2,+GAAP!E48," " ) -> 275000 | J28: =IF(GAAP!$G48<2,+GAAP!G48," " ) -> 0.99584023 | K28: =IF(GAAP!$G48<2,+GAAP!H48," " ) -> 273856.06 | L28: =+GAAP!K48 -> -575267.82 | S28: =K28-'Bonus WIP'!K29 -> -1131.7149 | T28: =L28-'Bonus WIP'!L29 -> 1131.7149
A29: =+GAAP!A49 -> 52.8637 | B29: =IF(GAAP!$G49<2,+GAAP!B49," " ) -> Root Creek Water Dist. - Groundwater Blending & Arsenic | C29: =IF(GAAP!$G49<2,+GAAP!J49," " ) -> 26148625 | D29: =IF(GAAP!$G49<2,+GAAP!M49," " ) -> 115952.65 | E29: =IF(GAAP!$G49<2,+GAAP!C49," " ) -> 26264578 | F29: =IF(GAAP!$G49<2,+GAAP!F49," " ) -> 24374299 | G29: =IF(GAAP!$G49<2,+GAAP!L49," " ) -> 240278.62 | H29: =IF(GAAP!$G49<2,+GAAP!D49," " ) -> 24614578 | I29: =IF(GAAP!$G49<2,+GAAP!E49," " ) -> 1650000 | J29: =IF(GAAP!$G49<2,+GAAP!G49," " ) -> 0.99023836 | K29: =IF(GAAP!$G49<2,+GAAP!H49," " ) -> 1633893.3 | L29: =+GAAP!K49 -> 140432.67 | S29: =K29-'Bonus WIP'!K30 -> 0 | T29: =L29-'Bonus WIP'!L30 -> 0
A30: =+GAAP!A50 -> 52.864 | B30: =IF(GAAP!$G50<2,+GAAP!B50," " ) -> City of Dos Palos - WTP Replacement Project | C30: =IF(GAAP!$G50<2,+GAAP!J50," " ) -> 34176042 | D30: =IF(GAAP!$G50<2,+GAAP!M50," " ) -> 4470321.3 | E30: =IF(GAAP!$G50<2,+GAAP!C50," " ) -> 38646363 | F30: =IF(GAAP!$G50<2,+GAAP!F50," " ) -> 32158781 | G30: =IF(GAAP!$G50<2,+GAAP!L50," " ) -> 4614258.7 | H30: =IF(GAAP!$G50<2,+GAAP!D50," " ) -> 36773040 | I30: =IF(GAAP!$G50<2,+GAAP!E50," " ) -> 1873323 | J30: =IF(GAAP!$G50<2,+GAAP!G50," " ) -> 0.87452061 | K30: =IF(GAAP!$G50<2,+GAAP!H50," " ) -> 1638259.6 | L30: =+GAAP!K50 -> 379000.81 | S30: =K30-'Bonus WIP'!K31 -> 0 | T30: =L30-'Bonus WIP'!L31 -> 0
A31: =+GAAP!A51 -> 52.8668 | B31: =IF(GAAP!$G51<2,+GAAP!B51," " ) -> California Water Service Co. - Cal Water - Salinas Station 57 | C31: =IF(GAAP!$G51<2,+GAAP!J51," " ) -> 349622.76 | D31: =IF(GAAP!$G51<2,+GAAP!M51," " ) -> 62228.24 | E31: =IF(GAAP!$G51<2,+GAAP!C51," " ) -> 411851 | F31: =IF(GAAP!$G51<2,+GAAP!F51," " ) -> 357710.67 | G31: =IF(GAAP!$G51<2,+GAAP!L51," " ) -> 19285.33 | H31: =IF(GAAP!$G51<2,+GAAP!D51," " ) -> 376996 | I31: =IF(GAAP!$G51<2,+GAAP!E51," " ) -> 34855 | J31: =IF(GAAP!$G51<2,+GAAP!G51," " ) -> 0.94884474 | K31: =IF(GAAP!$G51<2,+GAAP!H51," " ) -> 33071.983 | L31: =+GAAP!K51 -> -41159.893 | S31: =K31-'Bonus WIP'!K32 -> 0 | T31: =L31-'Bonus WIP'!L32 -> 0
A32: =+GAAP!A52 -> 52.8678 | B32: =IF(GAAP!$G52<2,+GAAP!B52," " ) -> City of Chowcilla - Well 15 & Generator Improvement Projects | C32: =IF(GAAP!$G52<2,+GAAP!J52," " ) -> 1142122 | D32: =IF(GAAP!$G52<2,+GAAP!M52," " ) -> 98199 | E32: =IF(GAAP!$G52<2,+GAAP!C52," " ) -> 1240321 | F32: =IF(GAAP!$G52<2,+GAAP!F52," " ) -> 926007.31 | G32: =IF(GAAP!$G52<2,+GAAP!L52," " ) -> 236313.69 | H32: =IF(GAAP!$G52<2,+GAAP!D52," " ) -> 1162321 | I32: =IF(GAAP!$G52<2,+GAAP!E52," " ) -> 78000 | J32: =IF(GAAP!$G52<2,+GAAP!G52," " ) -> 0.7966881 | K32: =IF(GAAP!$G52<2,+GAAP!H52," " ) -> 62141.672 | L32: =+GAAP!K52 -> 153973.02 | S32: =K32-'Bonus WIP'!K33 -> 0 | T32: =L32-'Bonus WIP'!L33 -> 0
A33: =+GAAP!A53 -> 52.8687 | B33: =IF(GAAP!$G53<2,+GAAP!B53," " ) -> California Water Service Co. - Salinas Station 205 | C33: =IF(GAAP!$G53<2,+GAAP!J53," " ) -> 827811.95 | D33: =IF(GAAP!$G53<2,+GAAP!M53," " ) -> 50142.05 | E33: =IF(GAAP!$G53<2,+GAAP!C53," " ) -> 877954 | F33: =IF(GAAP!$G53<2,+GAAP!F53," " ) -> 740629.43 | G33: =IF(GAAP!$G53<2,+GAAP!L53," " ) -> 50142.05 | H33: =IF(GAAP!$G53<2,+GAAP!D53," " ) -> 790771.48 | I33: =IF(GAAP!$G53<2,+GAAP!E53," " ) -> 87182.52 | J33: =IF(GAAP!$G53<2,+GAAP!G53," " ) -> 0.93659097 | K33: =IF(GAAP!$G53<2,+GAAP!H53," " ) -> 81654.361 | L33: =+GAAP!K53 -> 5528.1588 | S33: =K33-'Bonus WIP'!K34 -> 0 | T33: =L33-'Bonus WIP'!L34 -> 0
A34: =+GAAP!A54 -> 52.8692 | B34: =IF(GAAP!$G54<2,+GAAP!B54," " ) -> New England Sheet Metal and Mechanical Co. - Clovis South T&M | C34: =IF(GAAP!$G54<2,+GAAP!J54," " ) -> 55135.37 | D34: =IF(GAAP!$G54<2,+GAAP!M54," " ) -> 0 | E34: =IF(GAAP!$G54<2,+GAAP!C54," " ) -> 55135.37 | F34: =IF(GAAP!$G54<2,+GAAP!F54," " ) -> 49682.49 | G34: =IF(GAAP!$G54<2,+GAAP!L54," " ) -> 0 | H34: =IF(GAAP!$G54<2,+GAAP!D54," " ) -> 49682.49 | I34: =IF(GAAP!$G54<2,+GAAP!E54," " ) -> 5452.88 | J34: =IF(GAAP!$G54<2,+GAAP!G54," " ) -> 1 | K34: =IF(GAAP!$G54<2,+GAAP!H54," " ) -> 5452.88 | L34: =+GAAP!K54 -> 0 | S34: =K34-'Bonus WIP'!K35 -> 0 | T34: =L34-'Bonus WIP'!L35 -> 0
A35: =+GAAP!A55 -> 52.8697 | B35: =IF(GAAP!$G55<2,+GAAP!B55," " ) -> City of Tulare - Industrial WWTP Dewatering Improvements Pro | C35: =IF(GAAP!$G55<2,+GAAP!J55," " ) -> 1069317 | D35: =IF(GAAP!$G55<2,+GAAP!M55," " ) -> 318683 | E35: =IF(GAAP!$G55<2,+GAAP!C55," " ) -> 1388000 | F35: =IF(GAAP!$G55<2,+GAAP!F55," " ) -> 772187.73 | G35: =IF(GAAP!$G55<2,+GAAP!L55," " ) -> 553294.27 | H35: =IF(GAAP!$G55<2,+GAAP!D55," " ) -> 1325482 | I35: =IF(GAAP!$G55<2,+GAAP!E55," " ) -> 62518 | J35: =IF(GAAP!$G55<2,+GAAP!G55," " ) -> 0.58257127 | K35: =IF(GAAP!$G55<2,+GAAP!H55," " ) -> 36421.191 | L35: =+GAAP!K55 -> 260708.08 | P35: 2025 book to tax diff | S35: =K35-'Bonus WIP'!K36 -> 0 | T35: =L35-'Bonus WIP'!L36 -> 0
A36: =+GAAP!A56 -> 52.8698 | B36: =IF(GAAP!$G56<2,+GAAP!B56," " ) -> California Water Service Co. - Tesoro Viejo RWSP Liner Repair | C36: =IF(GAAP!$G56<2,+GAAP!J56," " ) -> 0 | D36: =IF(GAAP!$G56<2,+GAAP!M56," " ) -> 22713 | E36: =IF(GAAP!$G56<2,+GAAP!C56," " ) -> 22713 | F36: =IF(GAAP!$G56<2,+GAAP!F56," " ) -> 15264 | G36: =IF(GAAP!$G56<2,+GAAP!L56," " ) -> 864 | H36: =IF(GAAP!$G56<2,+GAAP!D56," " ) -> 16128 | I36: =IF(GAAP!$G56<2,+GAAP!E56," " ) -> 6585 | J36: =IF(GAAP!$G56<2,+GAAP!G56," " ) -> 0.94642857 | K36: =IF(GAAP!$G56<2,+GAAP!H56," " ) -> 6232.2321 | L36: =+GAAP!K56 -> -21496.232 | N36: sum of | O36: (1) | P36: =O106+O62+O111+O115 -> 5553.6984 | S36: =K36-'Bonus WIP'!K37 -> 0 | T36: =L36-'Bonus WIP'!L37 -> 0
A37: =+GAAP!A57 -> 52.8704 | B37: =IF(GAAP!$G57<2,+GAAP!B57," " ) -> City of Visalia - Solids Handling Improvements Project | C37: =IF(GAAP!$G57<2,+GAAP!J57," " ) -> 1037950 | D37: =IF(GAAP!$G57<2,+GAAP!M57," " ) -> 12706050 | E37: =IF(GAAP!$G57<2,+GAAP!C57," " ) -> 13744000 | F37: =IF(GAAP!$G57<2,+GAAP!F57," " ) -> 820988.3 | G37: =IF(GAAP!$G57<2,+GAAP!L57," " ) -> 12670139 | H37: =IF(GAAP!$G57<2,+GAAP!D57," " ) -> 13491127 | I37: =IF(GAAP!$G57<2,+GAAP!E57," " ) -> 252873 | J37: =IF(GAAP!$G57<2,+GAAP!G57," " ) -> 0.060853945 | K37: =IF(GAAP!$G57<2,+GAAP!H57," " ) -> 0 | L37: =+GAAP!K57 -> 216961.7 | S37: =K37-'Bonus WIP'!#REF! -> #REF! | T37: =L37-'Bonus WIP'!#REF! -> #REF!
A38: =+GAAP!A58 -> 52.8705 | B38: =IF(GAAP!$G58<2,+GAAP!B58," " ) -> California Water Service Co. - Visalia Station 200 - New Storage Tank & Booster | C38: =IF(GAAP!$G58<2,+GAAP!J58," " ) -> 261232 | D38: =IF(GAAP!$G58<2,+GAAP!M58," " ) -> 513768 | E38: =IF(GAAP!$G58<2,+GAAP!C58," " ) -> 775000 | F38: =IF(GAAP!$G58<2,+GAAP!F58," " ) -> 285425.72 | G38: =IF(GAAP!$G58<2,+GAAP!L58," " ) -> 433834.28 | H38: =IF(GAAP!$G58<2,+GAAP!D58," " ) -> 719260 | I38: =IF(GAAP!$G58<2,+GAAP!E58," " ) -> 55740 | J38: =IF(GAAP!$G58<2,+GAAP!G58," " ) -> 0.39683247 | K38: =IF(GAAP!$G58<2,+GAAP!H58," " ) -> 22119.442 | L38: =+GAAP!K58 -> -46313.162 | S38: =K38-'Bonus WIP'!K38 -> 22119.442 | T38: =L38-'Bonus WIP'!L38 -> -263274.86
A39: =+GAAP!A59 -> 52.8707 | B39: =IF(GAAP!$G59<2,+GAAP!B59," " ) -> County of Fresno - Westside Water Tank and Pump Station | C39: =IF(GAAP!$G59<2,+GAAP!J59," " ) -> 913135 | D39: =IF(GAAP!$G59<2,+GAAP!M59," " ) -> 2780065 | E39: =IF(GAAP!$G59<2,+GAAP!C59," " ) -> 3693200 | F39: =IF(GAAP!$G59<2,+GAAP!F59," " ) -> 1012057.1 | G39: =IF(GAAP!$G59<2,+GAAP!L59," " ) -> 2449519.9 | H39: =IF(GAAP!$G59<2,+GAAP!D59," " ) -> 3461577 | I39: =IF(GAAP!$G59<2,+GAAP!E59," " ) -> 231623 | J39: =IF(GAAP!$G59<2,+GAAP!G59," " ) -> 0.29236881 | K39: =IF(GAAP!$G59<2,+GAAP!H59," " ) -> 67719.34 | L39: =+GAAP!K59 -> -166641.48 | S39: =K39-'Bonus WIP'!K39 -> 45599.899 | T39: =L39-'Bonus WIP'!L39 -> -120328.32
A40: =+GAAP!A60 -> 52.8708 | B40: =IF(GAAP!$G60<2,+GAAP!B60," " ) -> County of Fresno - CSA 44A Wastewater Improvements | C40: =IF(GAAP!$G60<2,+GAAP!J60," " ) -> 0 | D40: =IF(GAAP!$G60<2,+GAAP!M60," " ) -> 363833 | E40: =IF(GAAP!$G60<2,+GAAP!C60," " ) -> 363833 | F40: =IF(GAAP!$G60<2,+GAAP!F60," " ) -> 7682.19 | G40: =IF(GAAP!$G60<2,+GAAP!L60," " ) -> 326074.81 | H40: =IF(GAAP!$G60<2,+GAAP!D60," " ) -> 333757 | I40: =IF(GAAP!$G60<2,+GAAP!E60," " ) -> 30076 | J40: =IF(GAAP!$G60<2,+GAAP!G60," " ) -> 0.023017315 | K40: =IF(GAAP!$G60<2,+GAAP!H60," " ) -> 0 | L40: =+GAAP!K60 -> -7682.19 | S40: =K40-'Bonus WIP'!K40 -> -67719.34 | T40: =L40-'Bonus WIP'!L40 -> 158959.29
A41: =+GAAP!A61 -> 52.8711 | B41: =IF(GAAP!$G61<2,+GAAP!B61," " ) -> California Water Service Co. - Tesoro Viejo ARV Replacement | C41: =IF(GAAP!$G61<2,+GAAP!J61," " ) -> 0 | D41: =IF(GAAP!$G61<2,+GAAP!M61," " ) -> 6860 | E41: =IF(GAAP!$G61<2,+GAAP!C61," " ) -> 6860 | F41: =IF(GAAP!$G61<2,+GAAP!F61," " ) -> 4568.81 | G41: =IF(GAAP!$G61<2,+GAAP!L61," " ) -> 1746.19 | H41: =IF(GAAP!$G61<2,+GAAP!D61," " ) -> 6315 | I41: =IF(GAAP!$G61<2,+GAAP!E61," " ) -> 545 | J41: =IF(GAAP!$G61<2,+GAAP!G61," " ) -> 0.72348535 | K41: =IF(GAAP!$G61<2,+GAAP!H61," " ) -> 394.29952 | L41: =+GAAP!K61 -> -4963.1095 | S41: =K41-'Bonus WIP'!K41 -> 394.29952 | T41: =L41-'Bonus WIP'!L41 -> 2719.0805
A42: =+GAAP!A62 -> 52.8713 | B42: =IF(GAAP!$G62<2,+GAAP!B62," " ) -> City of Visalia - Remove & Replace Chain and Flight Mechanic | C42: =IF(GAAP!$G62<2,+GAAP!J62," " ) -> 0 | D42: =IF(GAAP!$G62<2,+GAAP!M62," " ) -> 218842 | E42: =IF(GAAP!$G62<2,+GAAP!C62," " ) -> 218842 | F42: =IF(GAAP!$G62<2,+GAAP!F62," " ) -> 927.5 | G42: =IF(GAAP!$G62<2,+GAAP!L62," " ) -> 189511.5 | H42: =IF(GAAP!$G62<2,+GAAP!D62," " ) -> 190439 | I42: =IF(GAAP!$G62<2,+GAAP!E62," " ) -> 28403 | J42: =IF(GAAP!$G62<2,+GAAP!G62," " ) -> 0.0048703259 | K42: =IF(GAAP!$G62<2,+GAAP!H62," " ) -> 0 | L42: =+GAAP!K62 -> -927.5 | N42: 100% of loss is recognized for books, not for tax. | S42: =K42-'Bonus WIP'!K42 -> -394.29952 | T42: =L42-'Bonus WIP'!L42 -> 4035.6095
A43: =+GAAP!A63 -> 52.8714 | B43: =IF(GAAP!$G63<2,+GAAP!B63," " ) -> New England Sheet Metal and Mechanical Co. - VCH Digging Water Line T&M | C43: =IF(GAAP!$G63<2,+GAAP!J63," " ) -> 5084.94 | D43: =IF(GAAP!$G63<2,+GAAP!M63," " ) -> 0 | E43: =IF(GAAP!$G63<2,+GAAP!C63," " ) -> 5084.94 | F43: =IF(GAAP!$G63<2,+GAAP!F63," " ) -> 4465.61 | G43: =IF(GAAP!$G63<2,+GAAP!L63," " ) -> 0 | H43: =IF(GAAP!$G63<2,+GAAP!D63," " ) -> 4465.61 | I43: =IF(GAAP!$G63<2,+GAAP!E63," " ) -> 619.33 | J43: =IF(GAAP!$G63<2,+GAAP!G63," " ) -> 1 | K43: =IF(GAAP!$G63<2,+GAAP!H63," " ) -> 619.33 | L43: =+GAAP!K63 -> 0 | N43: For tax, need to make an adjustment by taking | S43: =K43-'Bonus WIP'!K43 -> 619.33 | T43: =L43-'Bonus WIP'!L43 -> 927.5
N44: actual %age complete and tax difference as income. | S44: =K44-'Bonus WIP'!K45 -> 0 | T44: =L44-'Bonus WIP'!L45 -> 0
A45: =+GAAP!A107 -> 53.2007 | B45: =IF(GAAP!$G107<2,+GAAP!B107," " ) -> Union Sanitary Dist. - Phase 1B Secondary Clarifiers | C45: =IF(GAAP!$G107<2,+GAAP!J107," " ) -> 0 | D45: =IF(GAAP!$G107<2,+GAAP!M107," " ) -> 324530134 | E45: =IF(GAAP!$G107<2,+GAAP!C107," " ) -> 324530134 | F45: =IF(GAAP!$G107<2,+GAAP!F107," " ) -> 404852.16 | G45: =IF(GAAP!$G107<2,+GAAP!L107," " ) -> 2.9112528e+08 | H45: =IF(GAAP!$G107<2,+GAAP!D107," " ) -> 291530134 | I45: =IF(GAAP!$G107<2,+GAAP!E107," " ) -> 33000000 | J45: =IF(GAAP!$G107<2,+GAAP!G107," " ) -> 0.0013887146 | K45: =IF(GAAP!$G107<2,+GAAP!H107," " ) -> 0 | L45: =+GAAP!K107 -> -404852.16 | S45: =#REF!-'Bonus WIP'!#REF! -> #REF! | T45: =#REF!-'Bonus WIP'!#REF! -> #REF!
A47: =+GAAP!A120 -> 54.9033 | B47: =IF(GAAP!$G120<2,+GAAP!B120," " ) -> Semitropic WSD - Stored Water Recovery Unit Phase 2A, Amendment 8 | C47: =IF(GAAP!$G120<2,+GAAP!J120," " ) -> 118278.58 | D47: =IF(GAAP!$G120<2,+GAAP!M120," " ) -> 0 | E47: =IF(GAAP!$G120<2,+GAAP!C120," " ) -> 118278.58 | F47: =IF(GAAP!$G120<2,+GAAP!F120," " ) -> 104550.27 | G47: =IF(GAAP!$G120<2,+GAAP!L120," " ) -> 0 | H47: =IF(GAAP!$G120<2,+GAAP!D120," " ) -> 104550.27 | I47: =IF(GAAP!$G120<2,+GAAP!E120," " ) -> 13728.31 | J47: =IF(GAAP!$G120<2,+GAAP!G120," " ) -> 1 | K47: =IF(GAAP!$G120<2,+GAAP!H120," " ) -> 13728.31 | L47: =+GAAP!K120 -> 0 | S47: =K47-'Bonus WIP'!K48 -> 0 | T47: =L47-'Bonus WIP'!L48 -> 0
A48: =+GAAP!A121 -> 54.9135 | B48: =IF(GAAP!$G121<2,+GAAP!B121," " ) -> Calif. Rail Bldrs LLC - North Kern WSD Canal 9-22 Relocation Project | C48: =IF(GAAP!$G121<2,+GAAP!J121," " ) -> 9470658.6 | D48: =IF(GAAP!$G121<2,+GAAP!M121," " ) -> 0 | E48: =IF(GAAP!$G121<2,+GAAP!C121," " ) -> 9470658.6 | F48: =IF(GAAP!$G121<2,+GAAP!F121," " ) -> 9050951.9 | G48: =IF(GAAP!$G121<2,+GAAP!L121," " ) -> 0 | H48: =IF(GAAP!$G121<2,+GAAP!D121," " ) -> 9050951.9 | I48: =IF(GAAP!$G121<2,+GAAP!E121," " ) -> 419706.76 | J48: =IF(GAAP!$G121<2,+GAAP!G121," " ) -> 1 | K48: =IF(GAAP!$G121<2,+GAAP!H121," " ) -> 419706.76 | L48: =+GAAP!K121 -> 0 | S48: =K48-'Bonus WIP'!K49 -> 0 | T48: =L48-'Bonus WIP'!L49 -> 0
A49: =+GAAP!A122 -> 54.9257 | B49: =IF(GAAP!$G122<2,+GAAP!B122," " ) -> City of Guadalupe - Highway 1 Lift Station | C49: =IF(GAAP!$G122<2,+GAAP!J122," " ) -> 890983 | D49: =IF(GAAP!$G122<2,+GAAP!M122," " ) -> 580345 | E49: =IF(GAAP!$G122<2,+GAAP!C122," " ) -> 1471328 | F49: =IF(GAAP!$G122<2,+GAAP!F122," " ) -> 762211.05 | G49: =IF(GAAP!$G122<2,+GAAP!L122," " ) -> 664116.95 | H49: =IF(GAAP!$G122<2,+GAAP!D122," " ) -> 1426328 | I49: =IF(GAAP!$G122<2,+GAAP!E122," " ) -> 45000 | J49: =IF(GAAP!$G122<2,+GAAP!G122," " ) -> 0.53438694 | K49: =IF(GAAP!$G122<2,+GAAP!H122," " ) -> 24047.412 | L49: =+GAAP!K122 -> 104724.54 | S49: =K49-'Bonus WIP'!K50 -> 0 | T49: =L49-'Bonus WIP'!L50 -> 0
A50: =+GAAP!A123 -> 54.9268 | B50: =IF(GAAP!$G123<2,+GAAP!B123," " ) -> Semitropic Water Storage Dist. - Amendment No. 23 Raw Water Processing Plant Pipeline Replacement | C50: =IF(GAAP!$G123<2,+GAAP!J123," " ) -> 907298 | D50: =IF(GAAP!$G123<2,+GAAP!M123," " ) -> 42269.99 | E50: =IF(GAAP!$G123<2,+GAAP!C123," " ) -> 949567.99 | F50: =IF(GAAP!$G123<2,+GAAP!F123," " ) -> 844648.28 | G50: =IF(GAAP!$G123<2,+GAAP!L123," " ) -> 39919.71 | H50: =IF(GAAP!$G123<2,+GAAP!D123," " ) -> 884567.99 | I50: =IF(GAAP!$G123<2,+GAAP!E123," " ) -> 65000 | J50: =IF(GAAP!$G123<2,+GAAP!G123," " ) -> 0.95487095 | K50: =IF(GAAP!$G123<2,+GAAP!H123," " ) -> 62066.612 | L50: =+GAAP!K123 -> 583.10803 | S50: =K50-'Bonus WIP'!K51 -> -2933.388 | T50: =L50-'Bonus WIP'!L51 -> 2933.388
A51: =+GAAP!A124 -> 54.9269 | B51: =IF(GAAP!$G124<2,+GAAP!B124," " ) -> Semitropic Water Storage Dist. - Design & Construction of the Central TCP Facility-Phase 1 | C51: =IF(GAAP!$G124<2,+GAAP!J124," " ) -> 625819.17 | D51: =IF(GAAP!$G124<2,+GAAP!M124," " ) -> 0 | E51: =IF(GAAP!$G124<2,+GAAP!C124," " ) -> 625819.17 | F51: =IF(GAAP!$G124<2,+GAAP!F124," " ) -> 549817.74 | G51: =IF(GAAP!$G124<2,+GAAP!L124," " ) -> 0 | H51: =IF(GAAP!$G124<2,+GAAP!D124," " ) -> 549817.74 | I51: =IF(GAAP!$G124<2,+GAAP!E124," " ) -> 76001.43 | J51: =IF(GAAP!$G124<2,+GAAP!G124," " ) -> 1 | K51: =IF(GAAP!$G124<2,+GAAP!H124," " ) -> 76001.43 | L51: =+GAAP!K124 -> 0 | S51: =K51-'Bonus WIP'!K52 -> 41752.38 | T51: =L51-'Bonus WIP'!L52 -> -41752.38
A52: =+GAAP!A125 -> 54.9285 | B52: =IF(GAAP!$G125<2,+GAAP!B125," " ) -> Semitropic Water Storage Dist. - Emergency Radial Arm Gate Removal and Replacement | C52: =IF(GAAP!$G125<2,+GAAP!J125," " ) -> 427226 | D52: =IF(GAAP!$G125<2,+GAAP!M125," " ) -> 34796 | E52: =IF(GAAP!$G125<2,+GAAP!C125," " ) -> 462022 | F52: =IF(GAAP!$G125<2,+GAAP!F125," " ) -> 312939.77 | G52: =IF(GAAP!$G125<2,+GAAP!L125," " ) -> 74082.23 | H52: =IF(GAAP!$G125<2,+GAAP!D125," " ) -> 387022 | I52: =IF(GAAP!$G125<2,+GAAP!E125," " ) -> 75000 | J52: =IF(GAAP!$G125<2,+GAAP!G125," " ) -> 0.80858393 | K52: =IF(GAAP!$G125<2,+GAAP!H125," " ) -> 60643.795 | L52: =+GAAP!K125 -> 53642.435 | S52: =K52-'Bonus WIP'!K53 -> 0 | T52: =L52-'Bonus WIP'!L53 -> 0
A53: =+GAAP!A126 -> 54.9313 | B53: =IF(GAAP!$G126<2,+GAAP!B126," " ) -> Granite Construction Co. - Granite Chumash Camp 4 Infrastructure Project | C53: =IF(GAAP!$G126<2,+GAAP!J126," " ) -> 7886885 | D53: =IF(GAAP!$G126<2,+GAAP!M126," " ) -> 0.04 | E53: =IF(GAAP!$G126<2,+GAAP!C126," " ) -> 7886885 | F53: =IF(GAAP!$G126<2,+GAAP!F126," " ) -> 6449205.2 | G53: =IF(GAAP!$G126<2,+GAAP!L126," " ) -> 427679.82 | H53: =IF(GAAP!$G126<2,+GAAP!D126," " ) -> 6876885 | I53: =IF(GAAP!$G126<2,+GAAP!E126," " ) -> 1010000 | J53: =IF(GAAP!$G126<2,+GAAP!G126," " ) -> 0.93780908 | K53: =IF(GAAP!$G126<2,+GAAP!H126," " ) -> 947187.17 | L53: =+GAAP!K126 -> 490492.61 | S53: =K53-'Bonus WIP'!K54 -> 0 | T53: =L53-'Bonus WIP'!L54 -> 0
A54: =+GAAP!A127 -> 54.933 | B54: =IF(GAAP!$G127<2,+GAAP!B127," " ) -> City of Bakersfield Public Works - Wastewater Treatment Plant No. 3 Septage Processing Unit Rep | C54: =IF(GAAP!$G127<2,+GAAP!J127," " ) -> 324900 | D54: =IF(GAAP!$G127<2,+GAAP!M127," " ) -> 0 | E54: =IF(GAAP!$G127<2,+GAAP!C127," " ) -> 324900 | F54: =IF(GAAP!$G127<2,+GAAP!F127," " ) -> 306221.41 | G54: =IF(GAAP!$G127<2,+GAAP!L127," " ) -> 1419.59 | H54: =IF(GAAP!$G127<2,+GAAP!D127," " ) -> 307641 | I54: =IF(GAAP!$G127<2,+GAAP!E127," " ) -> 17259 | J54: =IF(GAAP!$G127<2,+GAAP!G127," " ) -> 0.99538556 | K54: =IF(GAAP!$G127<2,+GAAP!H127," " ) -> 17179.359 | L54: =+GAAP!K127 -> 1499.2306 | S54: =K54-'Bonus WIP'!K55 -> 0 | T54: =L54-'Bonus WIP'!L55 -> 0
A55: =+GAAP!A128 -> 54.9336 | B55: =IF(GAAP!$G128<2,+GAAP!B128," " ) -> Palmdale Water Dist. - Pure Water AV - Demonstration Facility | C55: =IF(GAAP!$G128<2,+GAAP!J128," " ) -> 14176593 | D55: =IF(GAAP!$G128<2,+GAAP!M128," " ) -> 11014584 | E55: =IF(GAAP!$G128<2,+GAAP!C128," " ) -> 25191177 | F55: =IF(GAAP!$G128<2,+GAAP!F128," " ) -> 12340864 | G55: =IF(GAAP!$G128<2,+GAAP!L128," " ) -> 10930312 | H55: =IF(GAAP!$G128<2,+GAAP!D128," " ) -> 23271177 | I55: =IF(GAAP!$G128<2,+GAAP!E128," " ) -> 1920000 | J55: =IF(GAAP!$G128<2,+GAAP!G128," " ) -> 0.53030685 | K55: =IF(GAAP!$G128<2,+GAAP!H128," " ) -> 1018189.1 | L55: =+GAAP!K128 -> 817539.5 | S55: =K55-'Bonus WIP'!K56 -> 0 | T55: =L55-'Bonus WIP'!L56 -> 0
A56: =+GAAP!A129 -> 54.9337 | B56: =IF(GAAP!$G129<2,+GAAP!B129," " ) -> City of Bakersfield Public Works - WWTP 3 Digester Gas Booster Blower Replacement Project | C56: =IF(GAAP!$G129<2,+GAAP!J129," " ) -> 520441.66 | D56: =IF(GAAP!$G129<2,+GAAP!M129," " ) -> 3584406.3 | E56: =IF(GAAP!$G129<2,+GAAP!C129," " ) -> 4104848 | F56: =IF(GAAP!$G129<2,+GAAP!F129," " ) -> 1509066.7 | G56: =IF(GAAP!$G129<2,+GAAP!L129," " ) -> 2435781.3 | H56: =IF(GAAP!$G129<2,+GAAP!D129," " ) -> 3944848 | I56: =IF(GAAP!$G129<2,+GAAP!E129," " ) -> 160000 | J56: =IF(GAAP!$G129<2,+GAAP!G129," " ) -> 0.38254116 | K56: =IF(GAAP!$G129<2,+GAAP!H129," " ) -> 61206.586 | L56: =+GAAP!K129 -> -1049831.7 | S56: =K56-'Bonus WIP'!K57 -> 0 | T56: =L56-'Bonus WIP'!L57 -> 0
A57: =+GAAP!A130 -> 54.9343 | B57: =IF(GAAP!$G130<2,+GAAP!B130," " ) -> Tehachapi-Cummings County Water District - DB – Replace Diesel Engines PP2 and PP3 | C57: =IF(GAAP!$G130<2,+GAAP!J130," " ) -> 3954560 | D57: =IF(GAAP!$G130<2,+GAAP!M130," " ) -> 2926740 | E57: =IF(GAAP!$G130<2,+GAAP!C130," " ) -> 6881300 | F57: =IF(GAAP!$G130<2,+GAAP!F130," " ) -> 3415344.1 | G57: =IF(GAAP!$G130<2,+GAAP!L130," " ) -> 2565955.9 | H57: =IF(GAAP!$G130<2,+GAAP!D130," " ) -> 5981300 | I57: =IF(GAAP!$G130<2,+GAAP!E130," " ) -> 900000 | J57: =IF(GAAP!$G130<2,+GAAP!G130," " ) -> 0.57100364 | K57: =IF(GAAP!$G130<2,+GAAP!H130," " ) -> 513903.28 | L57: =+GAAP!K130 -> 25312.643 | S57: =K57-'Bonus WIP'!K58 -> 0 | T57: =L57-'Bonus WIP'!L58 -> 0
A58: =+GAAP!A131 -> 54.9356 | B58: =IF(GAAP!$G131<2,+GAAP!B131," " ) -> North of River Sanitary Dist. No. 1 - WWTP Digester Gas Scrubber Vessel and Effluent Storage Pond | C58: =IF(GAAP!$G131<2,+GAAP!J131," " ) -> 685017 | D58: =IF(GAAP!$G131<2,+GAAP!M131," " ) -> 613313 | E58: =IF(GAAP!$G131<2,+GAAP!C131," " ) -> 1298330 | F58: =IF(GAAP!$G131<2,+GAAP!F131," " ) -> 775780.75 | G58: =IF(GAAP!$G131<2,+GAAP!L131," " ) -> 137549.25 | H58: =IF(GAAP!$G131<2,+GAAP!D131," " ) -> 913330 | I58: =IF(GAAP!$G131<2,+GAAP!E131," " ) -> 385000 | J58: =IF(GAAP!$G131<2,+GAAP!G131," " ) -> 0.84939808 | K58: =IF(GAAP!$G131<2,+GAAP!H131," " ) -> 327018.26 | L58: =+GAAP!K131 -> -417782.01 | S58: =K58-'Bonus WIP'!K59 -> 0 | T58: =L58-'Bonus WIP'!L59 -> 0
... A61: =+GAAP!A134 -> 54.9373 | B61: =IF(GAAP!$G134<2,+GAAP!B134," " ) -> City of Guadalupe - Guadalupe Pioneer Lift Station Replacement | C61: =IF(GAAP!$G134<2,+GAAP!J134," " ) -> 0 | D61: =IF(GAAP!$G134<2,+GAAP!M134," " ) -> 1524766 | E61: =IF(GAAP!$G134<2,+GAAP!C134," " ) -> 1524766 | F61: =IF(GAAP!$G134<2,+GAAP!F134," " ) -> 50303.97 | G61: =IF(GAAP!$G134<2,+GAAP!L134," " ) -> 1343022 | H61: =IF(GAAP!$G134<2,+GAAP!D134," " ) -> 1393326 | I61: =IF(GAAP!$G134<2,+GAAP!E134," " ) -> 131440 | J61: =IF(GAAP!$G134<2,+GAAP!G134," " ) -> 0.036103518 | K61: =IF(GAAP!$G134<2,+GAAP!H134," " ) -> 0 | L61: =+GAAP!K134 -> -50303.97 | S61: =K61-'Bonus WIP'!K62 -> 0 | T61: =L61-'Bonus WIP'!L62 -> 0
A62: =+GAAP!A135 -> 54.9389 | B62: =IF(GAAP!$G135<2,+GAAP!B135," " ) -> City of Atascadero - Atascadero Lift Stations 4 & 11 Rehab Project | C62: =IF(GAAP!$G135<2,+GAAP!J135," " ) -> 291620 | D62: =IF(GAAP!$G135<2,+GAAP!M135," " ) -> 8160 | E62: =IF(GAAP!$G135<2,+GAAP!C135," " ) -> 299780 | F62: =IF(GAAP!$G135<2,+GAAP!F135," " ) -> 311891.85 | G62: =IF(GAAP!$G135<2,+GAAP!L135," " ) -> 2888.15 | H62: =IF(GAAP!$G135<2,+GAAP!D135," " ) -> 314780 | I62: =IF(GAAP!$G135<2,+GAAP!E135," " ) -> -15000 | J62: =IF(GAAP!$G135<2,+GAAP!G135," " ) -> 0.99082486 | K62: =IF(GAAP!$G135<2,+GAAP!H135," " ) -> -15000 | L62: =+GAAP!K135 -> -5271.85 | N62: =I62*J62 -> -14862.373 | O62: =N62-K62 -> 137.62707 | P62: (1) | S62: =K62-'Bonus WIP'!K63 -> 0 | T62: =L62-'Bonus WIP'!L63 -> 0
A63: =+GAAP!A136 -> 54.9391 | B63: =IF(GAAP!$G136<2,+GAAP!B136," " ) -> Arvin Edison Water Storage Dist. - HQ Concrete R&R | C63: =IF(GAAP!$G136<2,+GAAP!J136," " ) -> 532604.57 | D63: =IF(GAAP!$G136<2,+GAAP!M136," " ) -> 0 | E63: =IF(GAAP!$G136<2,+GAAP!C136," " ) -> 532604.57 | F63: =IF(GAAP!$G136<2,+GAAP!F136," " ) -> 512057.34 | G63: =IF(GAAP!$G136<2,+GAAP!L136," " ) -> 0 | H63: =IF(GAAP!$G136<2,+GAAP!D136," " ) -> 512057.34 | I63: =IF(GAAP!$G136<2,+GAAP!E136," " ) -> 20547.23 | J63: =IF(GAAP!$G136<2,+GAAP!G136," " ) -> 1 | K63: =IF(GAAP!$G136<2,+GAAP!H136," " ) -> 20547.23 | L63: =+GAAP!K136 -> 0 | S63: =K63-'Bonus WIP'!K64 -> 0 | T63: =L63-'Bonus WIP'!L64 -> 0
A64: =+GAAP!A137 -> 54.9395 | B64: =IF(GAAP!$G137<2,+GAAP!B137," " ) -> Semitropic Water Storage Dist. - Pond Poso Pumping Plant Siphon Pipe Replacement Project | C64: =IF(GAAP!$G137<2,+GAAP!J137," " ) -> 1374448.2 | D64: =IF(GAAP!$G137<2,+GAAP!M137," " ) -> 421204.49 | E64: =IF(GAAP!$G137<2,+GAAP!C137," " ) -> 1795652.7 | F64: =IF(GAAP!$G137<2,+GAAP!F137," " ) -> 1349601.9 | G64: =IF(GAAP!$G137<2,+GAAP!L137," " ) -> 344050.74 | H64: =IF(GAAP!$G137<2,+GAAP!D137," " ) -> 1693652.7 | I64: =IF(GAAP!$G137<2,+GAAP!E137," " ) -> 102000 | J64: =IF(GAAP!$G137<2,+GAAP!G137," " ) -> 0.79685874 | K64: =IF(GAAP!$G137<2,+GAAP!H137," " ) -> 81279.591 | L64: =+GAAP!K137 -> -56433.341 | S64: =K64-'Bonus WIP'!K65 -> 0 | T64: =L64-'Bonus WIP'!L65 -> 0
A65: =+GAAP!A138 -> 54.9396 | B65: =IF(GAAP!$G138<2,+GAAP!B138," " ) -> Mojave Groundwater Storage LLC - Mojave Water Bank Northern Pipeline Facilities Construction | C65: =IF(GAAP!$G138<2,+GAAP!J138," " ) -> 0 | D65: =IF(GAAP!$G138<2,+GAAP!M138," " ) -> 157746.09 | E65: =IF(GAAP!$G138<2,+GAAP!C138," " ) -> 157746.09 | F65: =IF(GAAP!$G138<2,+GAAP!F138," " ) -> 157746.09 | G65: =IF(GAAP!$G138<2,+GAAP!L138," " ) -> 0 | H65: =IF(GAAP!$G138<2,+GAAP!D138," " ) -> 157746.09 | I65: =IF(GAAP!$G138<2,+GAAP!E138," " ) -> 0 | J65: =IF(GAAP!$G138<2,+GAAP!G138," " ) -> 1 | K65: =IF(GAAP!$G138<2,+GAAP!H138," " ) -> 0 | L65: =+GAAP!K138 -> -157746.09 | S65: =K65-'Bonus WIP'!K66 -> 0 | T65: =L65-'Bonus WIP'!L66 -> 0
A66: =+GAAP!A139 -> 54.9397 | B66: =IF(GAAP!$G139<2,+GAAP!B139," " ) -> Cawelo Water Dist. - Friant-Kern Canal Pump Station | C66: =IF(GAAP!$G139<2,+GAAP!J139," " ) -> 1033150.2 | D66: =IF(GAAP!$G139<2,+GAAP!M139," " ) -> 2657494.8 | E66: =IF(GAAP!$G139<2,+GAAP!C139," " ) -> 3690645 | F66: =IF(GAAP!$G139<2,+GAAP!F139," " ) -> 1035065.4 | G66: =IF(GAAP!$G139<2,+GAAP!L139," " ) -> 2355579.6 | H66: =IF(GAAP!$G139<2,+GAAP!D139," " ) -> 3390645 | I66: =IF(GAAP!$G139<2,+GAAP!E139," " ) -> 300000 | J66: =IF(GAAP!$G139<2,+GAAP!G139," " ) -> 0.30527095 | K66: =IF(GAAP!$G139<2,+GAAP!H139," " ) -> 91581.284 | L66: =+GAAP!K139 -> -93496.484 | S66: =K66-'Bonus WIP'!K67 -> 0 | T66: =L66-'Bonus WIP'!L67 -> 0
A67: =+GAAP!A140 -> 54.9403 | B67: =IF(GAAP!$G140<2,+GAAP!B140," " ) -> Lost Hills Utility Dist. - WTP Improvements | C67: =IF(GAAP!$G140<2,+GAAP!J140," " ) -> 140100 | D67: =IF(GAAP!$G140<2,+GAAP!M140," " ) -> 241500 | E67: =IF(GAAP!$G140<2,+GAAP!C140," " ) -> 381600 | F67: =IF(GAAP!$G140<2,+GAAP!F140," " ) -> 129004.89 | G67: =IF(GAAP!$G140<2,+GAAP!L140," " ) -> 209096.11 | H67: =IF(GAAP!$G140<2,+GAAP!D140," " ) -> 338101 | I67: =IF(GAAP!$G140<2,+GAAP!E140," " ) -> 43499 | J67: =IF(GAAP!$G140<2,+GAAP!G140," " ) -> 0.38155726 | K67: =IF(GAAP!$G140<2,+GAAP!H140," " ) -> 16597.359 | L67: =+GAAP!K140 -> -5502.2491 | S67: =K67-'Bonus WIP'!K68 -> 0 | T67: =L67-'Bonus WIP'!L68 -> 0
A68: =+GAAP!A141 -> 54.9404 | B68: =IF(GAAP!$G141<2,+GAAP!B141," " ) -> Cawelo Water Dist. - Reuse of Produced Water | C68: =IF(GAAP!$G141<2,+GAAP!J141," " ) -> 1746890 | D68: =IF(GAAP!$G141<2,+GAAP!M141," " ) -> 1973110 | E68: =IF(GAAP!$G141<2,+GAAP!C141," " ) -> 3720000 | F68: =IF(GAAP!$G141<2,+GAAP!F141," " ) -> 1939024.6 | G68: =IF(GAAP!$G141<2,+GAAP!L141," " ) -> 1646367.4 | H68: =IF(GAAP!$G141<2,+GAAP!D141," " ) -> 3585392 | I68: =IF(GAAP!$G141<2,+GAAP!E141," " ) -> 134608 | J68: =IF(GAAP!$G141<2,+GAAP!G141," " ) -> 0.54081245 | K68: =IF(GAAP!$G141<2,+GAAP!H141," " ) -> 72797.682 | L68: =+GAAP!K141 -> -264932.31 | S68: =K68-'Bonus WIP'!K69 -> 0 | T68: =L68-'Bonus WIP'!L69 -> 0
A69: =+GAAP!A142 -> 54.9405 | B69: =IF(GAAP!$G142<2,+GAAP!B142," " ) -> Semitropic Water Storage Dist. - Pump Platform Replacement Project | C69: =IF(GAAP!$G142<2,+GAAP!J142," " ) -> 746125 | D69: =IF(GAAP!$G142<2,+GAAP!M142," " ) -> 195875 | E69: =IF(GAAP!$G142<2,+GAAP!C142," " ) -> 942000 | F69: =IF(GAAP!$G142<2,+GAAP!F142," " ) -> 577796.16 | G69: =IF(GAAP!$G142<2,+GAAP!L142," " ) -> 234203.84 | H69: =IF(GAAP!$G142<2,+GAAP!D142," " ) -> 812000 | I69: =IF(GAAP!$G142<2,+GAAP!E142," " ) -> 130000 | J69: =IF(GAAP!$G142<2,+GAAP!G142," " ) -> 0.71157163 | K69: =IF(GAAP!$G142<2,+GAAP!H142," " ) -> 92504.311 | L69: =+GAAP!K142 -> 75824.529 | S69: =K69-'Bonus WIP'!K70 -> 0 | T69: =L69-'Bonus WIP'!L70 -> 0
A70: =+GAAP!A143 -> 54.9406 | B70: =IF(GAAP!$G143<2,+GAAP!B143," " ) -> California Water Service Co. - Emergency PACL leak repair | C70: =IF(GAAP!$G143<2,+GAAP!J143," " ) -> 0 | D70: =IF(GAAP!$G143<2,+GAAP!M143," " ) -> 1120.65 | E70: =IF(GAAP!$G143<2,+GAAP!C143," " ) -> 1120.65 | F70: =IF(GAAP!$G143<2,+GAAP!F143," " ) -> 1120.65 | G70: =IF(GAAP!$G143<2,+GAAP!L143," " ) -> 0 | H70: =IF(GAAP!$G143<2,+GAAP!D143," " ) -> 1120.65 | I70: =IF(GAAP!$G143<2,+GAAP!E143," " ) -> 0 | J70: =IF(GAAP!$G143<2,+GAAP!G143," " ) -> 1 | K70: =IF(GAAP!$G143<2,+GAAP!H143," " ) -> 0 | L70: =+GAAP!K143 -> -1120.65 | S70: =K70-'Bonus WIP'!K71 -> 0 | T70: =L70-'Bonus WIP'!L71 -> 0
A71: =+GAAP!A144 -> 54.9408 | B71: =IF(GAAP!$G144<2,+GAAP!B144," " ) -> Nipomo Community Service Dist. - Frontage Road Sewer Trunk Line | C71: =IF(GAAP!$G144<2,+GAAP!J144," " ) -> 0 | D71: =IF(GAAP!$G144<2,+GAAP!M144," " ) -> 3777777 | E71: =IF(GAAP!$G144<2,+GAAP!C144," " ) -> 3777777 | F71: =IF(GAAP!$G144<2,+GAAP!F144," " ) -> 41652.43 | G71: =IF(GAAP!$G144<2,+GAAP!L144," " ) -> 3495532.6 | H71: =IF(GAAP!$G144<2,+GAAP!D144," " ) -> 3537185 | I71: =IF(GAAP!$G144<2,+GAAP!E144," " ) -> 240592 | J71: =IF(GAAP!$G144<2,+GAAP!G144," " ) -> 0.011775587 | K71: =IF(GAAP!$G144<2,+GAAP!H144," " ) -> 0 | L71: =+GAAP!K144 -> -41652.43 | S71: =K71-'Bonus WIP'!K72 -> 0 | T71: =L71-'Bonus WIP'!L72 -> 0
A72: =+GAAP!A145 -> 54.9411 | B72: =IF(GAAP!$G145<2,+GAAP!B145," " ) -> Moorefield Construction Inc. - Hard Rock Tejon AEWSD Line Relocation | C72: =IF(GAAP!$G145<2,+GAAP!J145," " ) -> 103000 | D72: =IF(GAAP!$G145<2,+GAAP!M145," " ) -> 300 | E72: =IF(GAAP!$G145<2,+GAAP!C145," " ) -> 103300 | F72: =IF(GAAP!$G145<2,+GAAP!F145," " ) -> 71370.85 | G72: =IF(GAAP!$G145<2,+GAAP!L145," " ) -> 6929.15 | H72: =IF(GAAP!$G145<2,+GAAP!D145," " ) -> 78300 | I72: =IF(GAAP!$G145<2,+GAAP!E145," " ) -> 25000 | J72: =IF(GAAP!$G145<2,+GAAP!G145," " ) -> 0.91150511 | K72: =IF(GAAP!$G145<2,+GAAP!H145," " ) -> 22787.628 | L72: =+GAAP!K145 -> 8841.5223 | S72: =K72-'Bonus WIP'!K73 -> 0 | T72: =L72-'Bonus WIP'!L73 -> 0
A73: =+GAAP!A146 -> 54.9412 | B73: =IF(GAAP!$G146<2,+GAAP!B146," " ) -> Arvin Edison Water Storage Dist. - Sycamore Well 39 Earthwork | C73: =IF(GAAP!$G146<2,+GAAP!J146," " ) -> 116752.04 | D73: =IF(GAAP!$G146<2,+GAAP!M146," " ) -> 0 | E73: =IF(GAAP!$G146<2,+GAAP!C146," " ) -> 116752.04 | F73: =IF(GAAP!$G146<2,+GAAP!F146," " ) -> 115708.88 | G73: =IF(GAAP!$G146<2,+GAAP!L146," " ) -> 0 | H73: =IF(GAAP!$G146<2,+GAAP!D146," " ) -> 115708.88 | I73: =IF(GAAP!$G146<2,+GAAP!E146," " ) -> 1043.16 | J73: =IF(GAAP!$G146<2,+GAAP!G146," " ) -> 1 | K73: =IF(GAAP!$G146<2,+GAAP!H146," " ) -> 1043.16 | L73: =+GAAP!K146 -> 0 | S73: =K73-'Bonus WIP'!K74 -> 0 | T73: =L73-'Bonus WIP'!L74 -> 0
A74: =+GAAP!A147 -> 54.9413 | B74: =IF(GAAP!$G147<2,+GAAP!B147," " ) -> Arvin Edison Water Storage Dist. - Tejon Well 102 Earthwork | C74: =IF(GAAP!$G147<2,+GAAP!J147," " ) -> 149366.83 | D74: =IF(GAAP!$G147<2,+GAAP!M147," " ) -> 0 | E74: =IF(GAAP!$G147<2,+GAAP!C147," " ) -> 149366.83 | F74: =IF(GAAP!$G147<2,+GAAP!F147," " ) -> 132138.74 | G74: =IF(GAAP!$G147<2,+GAAP!L147," " ) -> 0 | H74: =IF(GAAP!$G147<2,+GAAP!D147," " ) -> 132138.74 | I74: =IF(GAAP!$G147<2,+GAAP!E147," " ) -> 17228.09 | J74: =IF(GAAP!$G147<2,+GAAP!G147," " ) -> 1 | K74: =IF(GAAP!$G147<2,+GAAP!H147," " ) -> 17228.09 | L74: =+GAAP!K147 -> 0 | S74: =K74-'Bonus WIP'!K75 -> 0 | T74: =L74-'Bonus WIP'!L75 -> 0
... A79: =+GAAP!A152 -> 54.9421 | B79: =IF(GAAP!$G152<2,+GAAP!B152," " ) -> Nipomo Community Service Dist. - Tefft Emergency Pipe Repair | C79: =IF(GAAP!$G152<2,+GAAP!J152," " ) -> 0 | D79: =IF(GAAP!$G152<2,+GAAP!M152," " ) -> 3703.18 | E79: =IF(GAAP!$G152<2,+GAAP!C152," " ) -> 3703.18 | F79: =IF(GAAP!$G152<2,+GAAP!F152," " ) -> 3703.18 | G79: =IF(GAAP!$G152<2,+GAAP!L152," " ) -> 0 | H79: =IF(GAAP!$G152<2,+GAAP!D152," " ) -> 3703.18 | I79: =IF(GAAP!$G152<2,+GAAP!E152," " ) -> 0 | J79: =IF(GAAP!$G152<2,+GAAP!G152," " ) -> 1 | K79: =IF(GAAP!$G152<2,+GAAP!H152," " ) -> 0 | L79: =+GAAP!K152 -> -3703.18 | S79: =K79-'Bonus WIP'!K80 -> 0 | T79: =L79-'Bonus WIP'!L80 -> 0
S80: =K80-'Bonus WIP'!K81 -> 0 | T80: =L80-'Bonus WIP'!L81 -> 0
A81: =+GAAP!A223 -> 55.109 | B81: =IF(GAAP!$G223<2,+GAAP!B223," " ) -> LA Dept of Water and Power - Silverlake | C81: =IF(GAAP!$G223<2,+GAAP!J223," " ) -> 5235272.4 | D81: =IF(GAAP!$G223<2,+GAAP!M223," " ) -> 0 | E81: =IF(GAAP!$G223<2,+GAAP!C223," " ) -> 5235272.4 | F81: =IF(GAAP!$G223<2,+GAAP!F223," " ) -> 3834064 | G81: =IF(GAAP!$G223<2,+GAAP!L223," " ) -> 0 | H81: =IF(GAAP!$G223<2,+GAAP!D223," " ) -> 3834064 | I81: =IF(GAAP!$G223<2,+GAAP!E223," " ) -> 1401208.3 | J81: =IF(GAAP!$G223<2,+GAAP!G223," " ) -> 1 | K81: =IF(GAAP!$G223<2,+GAAP!H223," " ) -> 1401208.3 | L81: =+GAAP!K223 -> 0 | S81: =K81-'Bonus WIP'!K82 -> -73431.709 | T81: =L81-'Bonus WIP'!L82 -> 73431.709
A82: =+GAAP!A224 -> 55.1191 | B82: =IF(GAAP!$G224<2,+GAAP!B224," " ) -> Inland Empire Utilities - IEUA RP-5 Liquids Exp. & Solids Treat. Facility | C82: =IF(GAAP!$G224<2,+GAAP!J224," " ) -> 2.9663498e+08 | D82: =IF(GAAP!$G224<2,+GAAP!M224," " ) -> 44808149 | E82: =IF(GAAP!$G224<2,+GAAP!C224," " ) -> 3.4144313e+08 | F82: =IF(GAAP!$G224<2,+GAAP!F224," " ) -> 2.9917962e+08 | G82: =IF(GAAP!$G224<2,+GAAP!L224," " ) -> 38553011 | H82: =IF(GAAP!$G224<2,+GAAP!D224," " ) -> 3.3773264e+08 | I82: =IF(GAAP!$G224<2,+GAAP!E224," " ) -> 3710498 | J82: =IF(GAAP!$G224<2,+GAAP!G224," " ) -> 0.88584754 | K82: =IF(GAAP!$G224<2,+GAAP!H224," " ) -> 3286935.5 | L82: =+GAAP!K224 -> -5831575.9 | S82: =K82-'Bonus WIP'!K83 -> -423562.47 | T82: =L82-'Bonus WIP'!L83 -> 423562.47
A83: =+GAAP!A225 -> 55.1192 | B83: =IF(GAAP!$G225<2,+GAAP!B225," " ) -> Inland Empire Utilities - IEUA RP-1 Flare Improvements | C83: =IF(GAAP!$G225<2,+GAAP!J225," " ) -> 6645760.5 | D83: =IF(GAAP!$G225<2,+GAAP!M225," " ) -> 6043.02 | E83: =IF(GAAP!$G225<2,+GAAP!C225," " ) -> 6651803.5 | F83: =IF(GAAP!$G225<2,+GAAP!F225," " ) -> 6393992.7 | G83: =IF(GAAP!$G225<2,+GAAP!L225," " ) -> 7810.84 | H83: =IF(GAAP!$G225<2,+GAAP!D225," " ) -> 6401803.5 | I83: =IF(GAAP!$G225<2,+GAAP!E225," " ) -> 250000 | J83: =IF(GAAP!$G225<2,+GAAP!G225," " ) -> 0.9987799 | K83: =IF(GAAP!$G225<2,+GAAP!H225," " ) -> 249694.98 | L83: =+GAAP!K225 -> 2072.845 | S83: =K83-'Bonus WIP'!K84 -> -305.02498 | T83: =L83-'Bonus WIP'!L84 -> 305.02498
A84: =+GAAP!A226 -> 55.12 | B84: =IF(GAAP!$G226<2,+GAAP!B226," " ) -> East County Advanced Water Purification Project - Package 1 | C84: =IF(GAAP!$G226<2,+GAAP!J226," " ) -> 197175877 | D84: =IF(GAAP!$G226<2,+GAAP!M226," " ) -> 0 | E84: =IF(GAAP!$G226<2,+GAAP!C226," " ) -> 197175877 | F84: =IF(GAAP!$G226<2,+GAAP!F226," " ) -> 1.8997114e+08 | G84: =IF(GAAP!$G226<2,+GAAP!L226," " ) -> 0 | H84: =IF(GAAP!$G226<2,+GAAP!D226," " ) -> 1.8997114e+08 | I84: =IF(GAAP!$G226<2,+GAAP!E226," " ) -> 7204739.5 | J84: =IF(GAAP!$G226<2,+GAAP!G226," " ) -> 1 | K84: =IF(GAAP!$G226<2,+GAAP!H226," " ) -> 7204739.5 | L84: =+GAAP!K226 -> 0 | S84: =K84-'Bonus WIP'!K85 -> -575254.77 | T84: =L84-'Bonus WIP'!L85 -> 575254.77
A85: =+GAAP!A227 -> 55.1202 | B85: =IF(GAAP!$G227<2,+GAAP!B227," " ) -> LA County Sanitation District - Oxygen Generation Project | C85: =IF(GAAP!$G227<2,+GAAP!J227," " ) -> 10912273 | D85: =IF(GAAP!$G227<2,+GAAP!M227," " ) -> 5483779 | E85: =IF(GAAP!$G227<2,+GAAP!C227," " ) -> 16396052 | F85: =IF(GAAP!$G227<2,+GAAP!F227," " ) -> 9590124.3 | G85: =IF(GAAP!$G227<2,+GAAP!L227," " ) -> 5630518.2 | H85: =IF(GAAP!$G227<2,+GAAP!D227," " ) -> 15220643 | I85: =IF(GAAP!$G227<2,+GAAP!E227," " ) -> 1175409 | J85: =IF(GAAP!$G227<2,+GAAP!G227," " ) -> 0.63007355 | K85: =IF(GAAP!$G227<2,+GAAP!H227," " ) -> 740594.12 | L85: =+GAAP!K227 -> 581554.11 | S85: =K85-'Bonus WIP'!K86 -> 0 | T85: =L85-'Bonus WIP'!L86 -> 0
A86: =+GAAP!A228 -> 55.1204 | B86: =IF(GAAP!$G228<2,+GAAP!B228," " ) -> East County Advanced Water Purification Project - Package 3 | C86: =IF(GAAP!$G228<2,+GAAP!J228," " ) -> 57142227 | D86: =IF(GAAP!$G228<2,+GAAP!M228," " ) -> 0 | E86: =IF(GAAP!$G228<2,+GAAP!C228," " ) -> 57142227 | F86: =IF(GAAP!$G228<2,+GAAP!F228," " ) -> 55213329 | G86: =IF(GAAP!$G228<2,+GAAP!L228," " ) -> 0 | H86: =IF(GAAP!$G228<2,+GAAP!D228," " ) -> 55213329 | I86: =IF(GAAP!$G228<2,+GAAP!E228," " ) -> 1928897.8 | J86: =IF(GAAP!$G228<2,+GAAP!G228," " ) -> 1 | K86: =IF(GAAP!$G228<2,+GAAP!H228," " ) -> 1928897.8 | L86: =+GAAP!K228 -> 0 | S86: =K86-'Bonus WIP'!K87 -> -433141.22 | T86: =L86-'Bonus WIP'!L87 -> 433141.22
A87: =+GAAP!A229 -> 55.1227 | B87: =IF(GAAP!$G229<2,+GAAP!B229," " ) -> Eastern Municipal Water District - MVRWRF Plant 2B Equipping and Flow Diversion Project | C87: =IF(GAAP!$G229<2,+GAAP!J229," " ) -> 41483406 | D87: =IF(GAAP!$G229<2,+GAAP!M229," " ) -> 20800 | E87: =IF(GAAP!$G229<2,+GAAP!C229," " ) -> 41504206 | F87: =IF(GAAP!$G229<2,+GAAP!F229," " ) -> 36953023 | G87: =IF(GAAP!$G229<2,+GAAP!L229," " ) -> 201183.43 | H87: =IF(GAAP!$G229<2,+GAAP!D229," " ) -> 37154206 | I87: =IF(GAAP!$G229<2,+GAAP!E229," " ) -> 4350000 | J87: =IF(GAAP!$G229<2,+GAAP!G229," " ) -> 0.99458518 | K87: =IF(GAAP!$G229<2,+GAAP!H229," " ) -> 4326445.5 | L87: =+GAAP!K229 -> 203937.91 | S87: =K87-'Bonus WIP'!K88 -> 0 | T87: =L87-'Bonus WIP'!L88 -> 0
A88: =+GAAP!A230 -> 55.1233 | B88: =IF(GAAP!$G230<2,+GAAP!B230," " ) -> Veolia Water West Operating Services, Inc. - Rialto Solids Handling Design-Build Project (Design Phase) | C88: =IF(GAAP!$G230<2,+GAAP!J230," " ) -> 123617 | D88: =IF(GAAP!$G230<2,+GAAP!M230," " ) -> 2460.16 | E88: =IF(GAAP!$G230<2,+GAAP!C230," " ) -> 126077.16 | F88: =IF(GAAP!$G230<2,+GAAP!F230," " ) -> 126077.16 | G88: =IF(GAAP!$G230<2,+GAAP!L230," " ) -> 0 | H88: =IF(GAAP!$G230<2,+GAAP!D230," " ) -> 126077.16 | I88: =IF(GAAP!$G230<2,+GAAP!E230," " ) -> 0 | J88: =IF(GAAP!$G230<2,+GAAP!G230," " ) -> 1 | K88: =IF(GAAP!$G230<2,+GAAP!H230," " ) -> 0 | L88: =+GAAP!K230 -> -2460.16 | S88: =K88-'Bonus WIP'!K89 -> -8429 | T88: =L88-'Bonus WIP'!L89 -> 8429
A89: =+GAAP!A231 -> 55.1248 | B89: =IF(GAAP!$G231<2,+GAAP!B231," " ) -> Anaergia Technologies LLC - City of Riverside - Digester 5 Rehabilitation | C89: =IF(GAAP!$G231<2,+GAAP!J231," " ) -> 4861991.8 | D89: =IF(GAAP!$G231<2,+GAAP!M231," " ) -> 897310 | E89: =IF(GAAP!$G231<2,+GAAP!C231," " ) -> 5759301.8 | F89: =IF(GAAP!$G231<2,+GAAP!F231," " ) -> 3621770.2 | G89: =IF(GAAP!$G231<2,+GAAP!L231," " ) -> 1312531.6 | H89: =IF(GAAP!$G231<2,+GAAP!D231," " ) -> 4934301.8 | I89: =IF(GAAP!$G231<2,+GAAP!E231," " ) -> 825000 | J89: =IF(GAAP!$G231<2,+GAAP!G231," " ) -> 0.73399852 | K89: =IF(GAAP!$G231<2,+GAAP!H231," " ) -> 605548.78 | L89: =+GAAP!K231 -> 634672.81 | S89: =K89-'Bonus WIP'!K90 -> 0 | T89: =L89-'Bonus WIP'!L90 -> 0
A90: =+GAAP!A232 -> 55.1249 | B90: =IF(GAAP!$G232<2,+GAAP!B232," " ) -> Inland Empire Utilities - IEUA - RP-1 Solids Thickening Project - EN22044 | C90: =IF(GAAP!$G232<2,+GAAP!J232," " ) -> 15047043 | D90: =IF(GAAP!$G232<2,+GAAP!M232," " ) -> 1.3247807e+08 | E90: =IF(GAAP!$G232<2,+GAAP!C232," " ) -> 147525113 | F90: =IF(GAAP!$G232<2,+GAAP!F232," " ) -> 15046314 | G90: =IF(GAAP!$G232<2,+GAAP!L232," " ) -> 1.2465759e+08 | H90: =IF(GAAP!$G232<2,+GAAP!D232," " ) -> 139703905 | I90: =IF(GAAP!$G232<2,+GAAP!E232," " ) -> 7821208 | J90: =IF(GAAP!$G232<2,+GAAP!G232," " ) -> 0.10770145 | K90: =IF(GAAP!$G232<2,+GAAP!H232," " ) -> 842355.48 | L90: =+GAAP!K232 -> -841626.41 | S90: =K90-'Bonus WIP'!K91 -> 842355.48 | T90: =L90-'Bonus WIP'!L91 -> -842355.48
A91: =+GAAP!A233 -> 55.1254 | B91: =IF(GAAP!$G233<2,+GAAP!B233," " ) -> JV w/City of Banning - Wastewater Treatment Plant Recycled Water | C91: =IF(GAAP!$G233<2,+GAAP!J233," " ) -> 158952.89 | D91: =IF(GAAP!$G233<2,+GAAP!M233," " ) -> 0 | E91: =IF(GAAP!$G233<2,+GAAP!C233," " ) -> 158952.89 | F91: =IF(GAAP!$G233<2,+GAAP!F233," " ) -> 156561.66 | G91: =IF(GAAP!$G233<2,+GAAP!L233," " ) -> 0 | H91: =IF(GAAP!$G233<2,+GAAP!D233," " ) -> 156561.66 | I91: =IF(GAAP!$G233<2,+GAAP!E233," " ) -> 2391.23 | J91: =IF(GAAP!$G233<2,+GAAP!G233," " ) -> 1 | K91: =IF(GAAP!$G233<2,+GAAP!H233," " ) -> 2391.23 | L91: =+GAAP!K233 -> 0
A92: =+GAAP!A234 -> 55.1255 | B92: =IF(GAAP!$G234<2,+GAAP!B234," " ) -> City of Riverside - RWQCP Emergency Repair | C92: =IF(GAAP!$G234<2,+GAAP!J234," " ) -> 0 | D92: =IF(GAAP!$G234<2,+GAAP!M234," " ) -> 14160.81 | E92: =IF(GAAP!$G234<2,+GAAP!C234," " ) -> 14160.81 | F92: =IF(GAAP!$G234<2,+GAAP!F234," " ) -> 14160.81 | G92: =IF(GAAP!$G234<2,+GAAP!L234," " ) -> 0 | H92: =IF(GAAP!$G234<2,+GAAP!D234," " ) -> 14160.81 | I92: =IF(GAAP!$G234<2,+GAAP!E234," " ) -> 0 | J92: =IF(GAAP!$G234<2,+GAAP!G234," " ) -> 1 | K92: =IF(GAAP!$G234<2,+GAAP!H234," " ) -> 0 | L92: =+GAAP!K234 -> -14160.81
A93: =+GAAP!A235 -> 55.1256 | B93: =IF(GAAP!$G235<2,+GAAP!B235," " ) -> Anaergia Technologies LLC - City of Riverside - OPS | C93: =IF(GAAP!$G235<2,+GAAP!J235," " ) -> 101150 | D93: =IF(GAAP!$G235<2,+GAAP!M235," " ) -> 2786950 | E93: =IF(GAAP!$G235<2,+GAAP!C235," " ) -> 2888100 | F93: =IF(GAAP!$G235<2,+GAAP!F235," " ) -> 94989.88 | G93: =IF(GAAP!$G235<2,+GAAP!L235," " ) -> 2618110.1 | H93: =IF(GAAP!$G235<2,+GAAP!D235," " ) -> 2713100 | I93: =IF(GAAP!$G235<2,+GAAP!E235," " ) -> 175000 | J93: =IF(GAAP!$G235<2,+GAAP!G235," " ) -> 0.035011566 | K93: =IF(GAAP!$G235<2,+GAAP!H235," " ) -> 0 | L93: =+GAAP!K235 -> 6160.12 | S93: =K93-'Bonus WIP'!#REF! -> #REF! | T93: =L93-'Bonus WIP'!#REF! -> #REF!
S94: =K94-'Bonus WIP'!K95 -> 0 | T94: =L94-'Bonus WIP'!L95 -> 0
A95: =+GAAP!A252 -> 57.0003 | B95: =IF(GAAP!$G252<2,+GAAP!B252," " ) -> Moulton Niguel Water Dist. - Advanced Water Treatment Facility Salinity Management System - Ph 1 | C95: =IF(GAAP!$G252<2,+GAAP!J252," " ) -> 6863233.2 | D95: =IF(GAAP!$G252<2,+GAAP!M252," " ) -> 31302186 | E95: =IF(GAAP!$G252<2,+GAAP!C252," " ) -> 38165420 | F95: =IF(GAAP!$G252<2,+GAAP!F252," " ) -> 6316909.1 | G95: =IF(GAAP!$G252<2,+GAAP!L252," " ) -> 29441424 | H95: =IF(GAAP!$G252<2,+GAAP!D252," " ) -> 35758334 | I95: =IF(GAAP!$G252<2,+GAAP!E252," " ) -> 2407086 | J95: =IF(GAAP!$G252<2,+GAAP!G252," " ) -> 0.17665558 | K95: =IF(GAAP!$G252<2,+GAAP!H252," " ) -> 425225.17 | L95: =+GAAP!K252 -> 121098.95 | S95: =K95-'Bonus WIP'!K96 -> 301303 | T95: =L95-'Bonus WIP'!L96 -> -301303
A96: =+GAAP!A253 -> 57.0004 | B96: =IF(GAAP!$G253<2,+GAAP!B253," " ) -> Santa Margarita Water Dist. - Oso Creek Water Reclamation Plant Optimization Project | C96: =IF(GAAP!$G253<2,+GAAP!J253," " ) -> 900072.76 | D96: =IF(GAAP!$G253<2,+GAAP!M253," " ) -> 39206152 | E96: =IF(GAAP!$G253<2,+GAAP!C253," " ) -> 40106225 | F96: =IF(GAAP!$G253<2,+GAAP!F253," " ) -> 750298.86 | G96: =IF(GAAP!$G253<2,+GAAP!L253," " ) -> 37146069 | H96: =IF(GAAP!$G253<2,+GAAP!D253," " ) -> 37896368 | I96: =IF(GAAP!$G253<2,+GAAP!E253," " ) -> 2209857 | J96: =IF(GAAP!$G253<2,+GAAP!G253," " ) -> 0.019798701 | K96: =IF(GAAP!$G253<2,+GAAP!H253," " ) -> 0 | L96: =+GAAP!K253 -> 149773.9 | S96: =K96-'Bonus WIP'!K97 -> 0 | T96: =L96-'Bonus WIP'!L97 -> 0
A97: =+GAAP!A254 -> 57.0007 | B97: =IF(GAAP!$G254<2,+GAAP!B254," " ) -> Anaergia Technologies, LLC - East County Package 5 - Phase 1B | C97: =IF(GAAP!$G254<2,+GAAP!J254," " ) -> 153858.36 | D97: =IF(GAAP!$G254<2,+GAAP!M254," " ) -> 42390.04 | E97: =IF(GAAP!$G254<2,+GAAP!C254," " ) -> 196248.4 | F97: =IF(GAAP!$G254<2,+GAAP!F254," " ) -> 196248.4 | G97: =IF(GAAP!$G254<2,+GAAP!L254," " ) -> 0 | H97: =IF(GAAP!$G254<2,+GAAP!D254," " ) -> 196248.4 | I97: =IF(GAAP!$G254<2,+GAAP!E254," " ) -> 0 | J97: =IF(GAAP!$G254<2,+GAAP!G254," " ) -> 1 | K97: =IF(GAAP!$G254<2,+GAAP!H254," " ) -> 0 | L97: =+GAAP!K254 -> -42390.04
A98: =+GAAP!A255 -> 57.0008 | B98: =IF(GAAP!$G255<2,+GAAP!B255," " ) -> Imperial Irrigation Dist. - El Centro Generating Station WWTP | C98: =IF(GAAP!$G255<2,+GAAP!J255," " ) -> 266758 | D98: =IF(GAAP!$G255<2,+GAAP!M255," " ) -> 2609289 | E98: =IF(GAAP!$G255<2,+GAAP!C255," " ) -> 2876047 | F98: =IF(GAAP!$G255<2,+GAAP!F255," " ) -> 262382.86 | G98: =IF(GAAP!$G255<2,+GAAP!L255," " ) -> 2481599.1 | H98: =IF(GAAP!$G255<2,+GAAP!D255," " ) -> 2743982 | I98: =IF(GAAP!$G255<2,+GAAP!E255," " ) -> 132065 | J98: =IF(GAAP!$G255<2,+GAAP!G255," " ) -> 0.095621203 | K98: =IF(GAAP!$G255<2,+GAAP!H255," " ) -> 0 | L98: =+GAAP!K255 -> 4375.14
S99: =K99-'Bonus WIP'!K100 -> 0 | T99: =L99-'Bonus WIP'!L100 -> 0
A100: =+GAAP!A267 -> 58.0003 | B100: =IF(GAAP!$G267<2,+GAAP!B267," " ) -> Los Angeles County Sanitation Dist. - Los Coyotes WRP Process Air Compressor Replacement | C100: =IF(GAAP!$G267<2,+GAAP!J267," " ) -> 11889202 | D100: =IF(GAAP!$G267<2,+GAAP!M267," " ) -> 10635987 | E100: =IF(GAAP!$G267<2,+GAAP!C267," " ) -> 22525189 | F100: =IF(GAAP!$G267<2,+GAAP!F267," " ) -> 11034782 | G100: =IF(GAAP!$G267<2,+GAAP!L267," " ) -> 10182392 | H100: =IF(GAAP!$G267<2,+GAAP!D267," " ) -> 21217174 | I100: =IF(GAAP!$G267<2,+GAAP!E267," " ) -> 1308015 | J100: =IF(GAAP!$G267<2,+GAAP!G267," " ) -> 0.52008726 | K100: =IF(GAAP!$G267<2,+GAAP!H267," " ) -> 680281.93 | L100: =+GAAP!K267 -> 174138.04 | S100: =K100-'Bonus WIP'!K101 -> 0 | T100: =L100-'Bonus WIP'!L101 -> 0
S101: =K101-'Bonus WIP'!K102 -> 0 | T101: =L101-'Bonus WIP'!L102 -> 0
A102: =+GAAP!A283 -> 56.1004 | B102: =IF(GAAP!$G283<2,+GAAP!B283," " ) -> San Joaquin Electric - Liberty Ranch Sewer Pump Station | C102: =IF(GAAP!$G283<2,+GAAP!J283," " ) -> 371550 | D102: =IF(GAAP!$G283<2,+GAAP!M283," " ) -> 1875 | E102: =IF(GAAP!$G283<2,+GAAP!C283," " ) -> 373425 | F102: =IF(GAAP!$G283<2,+GAAP!F283," " ) -> 236373.73 | G102: =IF(GAAP!$G283<2,+GAAP!L283," " ) -> 33466.27 | H102: =IF(GAAP!$G283<2,+GAAP!D283," " ) -> 269840 | I102: =IF(GAAP!$G283<2,+GAAP!E283," " ) -> 103585 | J102: =IF(GAAP!$G283<2,+GAAP!G283," " ) -> 0.87597736 | K102: =IF(GAAP!$G283<2,+GAAP!H283," " ) -> 90738.115 | L102: =+GAAP!K283 -> 44438.155 | S102: =K102-'Bonus WIP'!K103 -> 0 | T102: =L102-'Bonus WIP'!L103 -> 0
A103: =+GAAP!A284 -> 56.1005 | B103: =IF(GAAP!$G284<2,+GAAP!B284," " ) -> SD Electric, Inc. - Stormwater Evacuation Lines & Outfall Manifold | C103: =IF(GAAP!$G284<2,+GAAP!J284," " ) -> 135000 | D103: =IF(GAAP!$G284<2,+GAAP!M284," " ) -> 0 | E103: =IF(GAAP!$G284<2,+GAAP!C284," " ) -> 135000 | F103: =IF(GAAP!$G284<2,+GAAP!F284," " ) -> 51037.42 | G103: =IF(GAAP!$G284<2,+GAAP!L284," " ) -> 16987.58 | H103: =IF(GAAP!$G284<2,+GAAP!D284," " ) -> 68025 | I103: =IF(GAAP!$G284<2,+GAAP!E284," " ) -> 66975 | J103: =IF(GAAP!$G284<2,+GAAP!G284," " ) -> 0.75027446 | K103: =IF(GAAP!$G284<2,+GAAP!H284," " ) -> 50249.632 | L103: =+GAAP!K284 -> 33712.948 | S103: =K103-'Bonus WIP'!K104 -> 0 | T103: =L103-'Bonus WIP'!L104 -> 0
A104: =+GAAP!A285 -> 56.101 | B104: =IF(GAAP!$G285<2,+GAAP!B285," " ) -> Placer County Water Agency -PCWA Time & Material Contract | C104: =IF(GAAP!$G285<2,+GAAP!J285," " ) -> 49250 | D104: =IF(GAAP!$G285<2,+GAAP!M285," " ) -> 0 | E104: =IF(GAAP!$G285<2,+GAAP!C285," " ) -> 49250 | F104: =IF(GAAP!$G285<2,+GAAP!F285," " ) -> 36461.94 | G104: =IF(GAAP!$G285<2,+GAAP!L285," " ) -> 0 | H104: =IF(GAAP!$G285<2,+GAAP!D285," " ) -> 36461.94 | I104: =IF(GAAP!$G285<2,+GAAP!E285," " ) -> 12788.06 | J104: =IF(GAAP!$G285<2,+GAAP!G285," " ) -> 1 | K104: =IF(GAAP!$G285<2,+GAAP!H285," " ) -> 12788.06 | L104: =+GAAP!K285 -> 0 | S104: =K104-'Bonus WIP'!K105 -> 0 | T104: =L104-'Bonus WIP'!L105 -> 0
A105: =+GAAP!A286 -> 56.1015 | B105: =IF(GAAP!$G286<2,+GAAP!B286," " ) -> Mike Brown Electric Co. - Riverside Ponds & Headworks Mitigation – City of Calistoga | C105: =IF(GAAP!$G286<2,+GAAP!J286," " ) -> 160000 | D105: =IF(GAAP!$G286<2,+GAAP!M286," " ) -> 0 | E105: =IF(GAAP!$G286<2,+GAAP!C286," " ) -> 160000 | F105: =IF(GAAP!$G286<2,+GAAP!F286," " ) -> 142358.95 | G105: =IF(GAAP!$G286<2,+GAAP!L286," " ) -> 0 | H105: =IF(GAAP!$G286<2,+GAAP!D286," " ) -> 142358.95 | I105: =IF(GAAP!$G286<2,+GAAP!E286," " ) -> 17641.05 | J105: =IF(GAAP!$G286<2,+GAAP!G286," " ) -> 1 | K105: =IF(GAAP!$G286<2,+GAAP!H286," " ) -> 17641.05 | L105: =+GAAP!K286 -> 0 | S105: =K105-'Bonus WIP'!K106 -> -881.28194 | T105: =L105-'Bonus WIP'!L106 -> 881.28194
A106: =+GAAP!A287 -> 56.1017 | B106: =IF(GAAP!$G287<2,+GAAP!B287," " ) -> Bay Tech Engineering - SDDS Gate Valves Replacement – SF International Airport | C106: =IF(GAAP!$G287<2,+GAAP!J287," " ) -> 99118 | D106: =IF(GAAP!$G287<2,+GAAP!M287," " ) -> 3750 | E106: =IF(GAAP!$G287<2,+GAAP!C287," " ) -> 102868 | F106: =IF(GAAP!$G287<2,+GAAP!F287," " ) -> 95450.46 | G106: =IF(GAAP!$G287<2,+GAAP!L287," " ) -> 19444.54 | H106: =IF(GAAP!$G287<2,+GAAP!D287," " ) -> 114895 | I106: =IF(GAAP!$G287<2,+GAAP!E287," " ) -> -12027 | J106: =IF(GAAP!$G287<2,+GAAP!G287," " ) -> 0.83076252 | K106: =IF(GAAP!$G287<2,+GAAP!H287," " ) -> -12027 | L106: =+GAAP!K287 -> 15694.54 | N106: =I106*J106 -> -9991.5809 | O106: =N106-K106 -> 2035.4191 | P106: (1) | S106: =K106-'Bonus WIP'!K107 -> 0 | T106: =L106-'Bonus WIP'!L107 -> 0
A107: =+GAAP!A288 -> 56.1018 | B107: =IF(GAAP!$G288<2,+GAAP!B288," " ) -> CM Controls - Salinas AG Industrial Phase 1 – City of Salinas | C107: =IF(GAAP!$G288<2,+GAAP!J288," " ) -> 50000 | D107: =IF(GAAP!$G288<2,+GAAP!M288," " ) -> 103913 | E107: =IF(GAAP!$G288<2,+GAAP!C288," " ) -> 153913 | F107: =IF(GAAP!$G288<2,+GAAP!F288," " ) -> 41991.15 | G107: =IF(GAAP!$G288<2,+GAAP!L288," " ) -> 29053.85 | H107: =IF(GAAP!$G288<2,+GAAP!D288," " ) -> 71045 | I107: =IF(GAAP!$G288<2,+GAAP!E288," " ) -> 82868 | J107: =IF(GAAP!$G288<2,+GAAP!G288," " ) -> 0.59105004 | K107: =IF(GAAP!$G288<2,+GAAP!H288," " ) -> 48979.135 | L107: =+GAAP!K288 -> -40970.285 | S107: =K107-'Bonus WIP'!K108 -> 0 | T107: =L107-'Bonus WIP'!L108 -> 0
A108: =+GAAP!A289 -> 56.1032 | B108: =IF(GAAP!$G289<2,+GAAP!B289," " ) -> Newtron - Watsonville, City of - Zone 2 Water Res & AirportBPS Mods | C108: =IF(GAAP!$G289<2,+GAAP!J289," " ) -> 0 | D108: =IF(GAAP!$G289<2,+GAAP!M289," " ) -> 85000 | E108: =IF(GAAP!$G289<2,+GAAP!C289," " ) -> 85000 | F108: =IF(GAAP!$G289<2,+GAAP!F289," " ) -> 35024.34 | G108: =IF(GAAP!$G289<2,+GAAP!L289," " ) -> 47950.66 | H108: =IF(GAAP!$G289<2,+GAAP!D289," " ) -> 82975 | I108: =IF(GAAP!$G289<2,+GAAP!E289," " ) -> 2025 | J108: =IF(GAAP!$G289<2,+GAAP!G289," " ) -> 0.42210714 | K108: =IF(GAAP!$G289<2,+GAAP!H289," " ) -> 854.76696 | L108: =+GAAP!K289 -> -35879.107 | S108: =K108-'Bonus WIP'!K109 -> 0 | T108: =L108-'Bonus WIP'!L109 -> 0
A109: =+GAAP!A290 -> 56.1036 | B109: =IF(GAAP!$G290<2,+GAAP!B290," " ) -> Darrel Varni Electric, Inc. - GSW, San Benito Co. Sewer Pump Station No. 2 | C109: =IF(GAAP!$G290<2,+GAAP!J290," " ) -> 48000 | D109: =IF(GAAP!$G290<2,+GAAP!M290," " ) -> 228000 | E109: =IF(GAAP!$G290<2,+GAAP!C290," " ) -> 276000 | F109: =IF(GAAP!$G290<2,+GAAP!F290," " ) -> 107051.95 | G109: =IF(GAAP!$G290<2,+GAAP!L290," " ) -> 101972.05 | H109: =IF(GAAP!$G290<2,+GAAP!D290," " ) -> 209024 | I109: =IF(GAAP!$G290<2,+GAAP!E290," " ) -> 66976 | J109: =IF(GAAP!$G290<2,+GAAP!G290," " ) -> 0.51215148 | K109: =IF(GAAP!$G290<2,+GAAP!H290," " ) -> 34301.857 | L109: =+GAAP!K290 -> -93353.807 | S109: =K109-'Bonus WIP'!K110 -> 0 | T109: =L109-'Bonus WIP'!L110 -> 0
...

Sheet GAAP
A1: W.M. Lyles Co.
A2: PROFIT AND LOSS BY JOB (GAAP Basis)
A3: FISCAL YEAR ENDING 12/31/25 | T3: Prior year info hidden in Columns N, O & P
A4: For the Month Period Ended 12/31/2025 | T4: Note: Any job over 95% complete, review Cost to Complete and the cost incurred after 9/30, if costs are substantially more then CTC, profits may need to be reviewed/changed (unless there is CCO work)
C6: CONTRACT | D6: EST. TOTAL | E6: EXPECTED | F6: JOB TO DATE | G6: COST / | H6: JOB TO DATE | I6: JOB TO DATE | L6: EST. COST TO | M6: CONTRACT | N6: PY JTD COSTS | O6: PY JTD BILLINGS | P6: PY JTD PROFIT | T6: Fiscal Y/E | U6: Fiscal Y/E
A7: JOB | B7: DESCRIPTION | C7: AMOUNT | D7: COSTS | E7: PROFIT | F7: JOB COSTS | G7: COST | H7: PROFIT/LOSS | I7: EARNED REV. | J7: JTD BILLED | K7: CURRENT WIP | L7: COMPLETE | M7: BALANCE | N7: 45657 | O7: =+N7 -> 45657 | P7: =+N7 -> 45657 | Q7: YTD COSTS | R7: YTD BILLINGS | S7: YTD PROFIT | T7: Job Opens | U7: Job Closes
A8: =+Bonus!A8 -> Rocklin Area - Open Jobs
A9: =Bonus!A9 -> 51.1108 | B9: =Bonus!B9 -> City of Stockton - RWCF Phase 2A/2B | C9: =J9 -> 94045648 | D9: =F9 -> 89805618 | E9: =C9-D9 -> 4240030.1 | F9: =Bonus!F9 -> 89805618 | G9: =IF(D9<>0,+F9/D9,0) -> 1 | H9: =IF(E9<=0,E9,IF(G9<0.1,0,IF(G9<=1,G9*E9,E9))) -> 4240030.1 | I9: =+F9+H9 -> 94045648 | J9: =Bonus!J9 -> 94045648 | K9: =J9-I9 -> 0 | L9: =+D9-F9 -> 0 | M9: =+C9-J9 -> 0 | N9: =Bonus!N9 -> 88519195 | O9: =Bonus!O9 -> 92554958 | P9: =Bonus!W9 -> 4035762.6 | Q9: =F9-N9 -> 1286422.8 | R9: =+J9-O9 -> 1490690.3 | S9: =H9-P9 -> 204267.49 | T9: =Bonus!T9 -> 2019 | U9: =Bonus!U9 -> 0 | V9: =+Bonus!V9 -> .
A10: =Bonus!A10 -> 51.1129 | B10: =Bonus!B10 -> Union Sanit. Dist - Enhanced Trtmnt & Site Upgrd Ph. 1A Aeration Basin | C10: =Bonus!C10 -> 1.2648358e+08 | D10: =Bonus!D10 -> 1.1523358e+08 | E10: =Bonus!E10 -> 11250000 | F10: =Bonus!F10 -> 87315159 | G10: =IF(D10<>0,+F10/D10,0) -> 0.75772321 | H10: =IF(E10<=0,E10,IF(G10<0.1,0,IF(G10<=1,G10*E10,E10))) -> 8524386.2 | I10: =+F10+H10 -> 95839545 | J10: =Bonus!J10 -> 96918207 | K10: =J10-I10 -> 1078661.5 | L10: =+D10-F10 -> 27918422 | M10: =+C10-J10 -> 29565374 | N10: =Bonus!N10 -> 63757071 | O10: =Bonus!O10 -> 66921921 | P10: =Bonus!W10 -> 6957477.4 | Q10: =F10-N10 -> 23558089 | R10: =+J10-O10 -> 29996286 | S10: =H10-P10 -> 1566908.8 | T10: =Bonus!T10 -> 2022 | U10: =Bonus!U10 -> 0 | V10: =+Bonus!V10 -> .
A11: =Bonus!A11 -> 51.1137 | B11: =Bonus!B11 -> CA Water Service Co. - Bear Gulch Pump Station 18 | C11: =Bonus!C11 -> 1312151.5 | D11: =Bonus!D11 -> 1198511.5 | E11: =Bonus!E11 -> 113640 | F11: =Bonus!F11 -> 1042229.3 | G11: =IF(D11<>0,+F11/D11,0) -> 0.86960311 | H11: =IF(E11<=0,E11,IF(G11<0.1,0,IF(G11<=1,G11*E11,E11))) -> 98821.697 | I11: =+F11+H11 -> 1141051 | J11: =Bonus!J11 -> 1121900 | K11: =J11-I11 -> -19150.977 | L11: =+D11-F11 -> 156282.17 | M11: =+C11-J11 -> 190251.45 | N11: =Bonus!N11 -> 271684.42 | O11: =Bonus!O11 -> 78558 | P11: =Bonus!W11 -> 27243.589 | Q11: =F11-N11 -> 770544.87 | R11: =+J11-O11 -> 1043342 | S11: =H11-P11 -> 71578.108 | T11: =Bonus!T11 -> 2023 | U11: =Bonus!U11 -> 0 | V11: =+Bonus!V11 -> .
A12: =Bonus!A12 -> 51.1144 | B12: =Bonus!B12 -> Silicon Valley Clean Water - FEP Improvements Project | C12: =Bonus!C12 -> 14969566 | D12: =Bonus!D12 -> 13839617 | E12: =Bonus!E12 -> 1129949 | F12: =Bonus!F12 -> 8406760.8 | G12: =IF(D12<>0,+F12/D12,0) -> 0.60744172 | H12: =IF(E12<=0,E12,IF(G12<0.1,0,IF(G12<=1,G12*E12,E12))) -> 686378.17 | I12: =+F12+H12 -> 9093139 | J12: =Bonus!J12 -> 9667725.8 | K12: =J12-I12 -> 574586.8 | L12: =+D12-F12 -> 5432856.2 | M12: =+C12-J12 -> 5301840.2 | N12: =Bonus!N12 -> 1353379.4 | O12: =Bonus!O12 -> 1514359.6 | P12: =Bonus!W12 -> 90331.451 | Q12: =F12-N12 -> 7053381.4 | R12: =+J12-O12 -> 8153366.2 | S12: =H12-P12 -> 596046.72 | T12: =Bonus!T12 -> 2023 | U12: =Bonus!U12 -> 0 | V12: =+Bonus!V12 -> .
A13: =Bonus!A13 -> 51.1146 | B13: =Bonus!B13 -> National Carbon Technologies, LLC - Aymium Williams Production Facility | C13: =Bonus!C13 -> 60980234 | D13: =Bonus!D13 -> 44196854 | E13: =Bonus!E13 -> 16783380 | F13: =Bonus!F13 -> 40950686 | G13: =IF(D13<>0,+F13/D13,0) -> 0.92655207 | H13: =IF(E13<=0,E13,IF(G13<0.1,0,IF(G13<=1,G13*E13,E13))) -> 15550675 | I13: =+F13+H13 -> 56501362 | J13: =Bonus!J13 -> 60980234 | K13: =J13-I13 -> 4478872.1 | L13: =+D13-F13 -> 3246167.5 | M13: =+C13-J13 -> 0 | N13: =Bonus!N13 -> 4561081.2 | O13: =Bonus!O13 -> 9363858.4 | P13: =Bonus!W13 -> 0 | Q13: =F13-N13 -> 36389605 | R13: =+J13-O13 -> 51616376 | S13: =H13-P13 -> 15550675 | T13: =Bonus!T13 -> 2023 | U13: =Bonus!U13 -> 0 | V13: =+Bonus!V13 -> .
A14: =Bonus!A14 -> 51.1151 | B14: =Bonus!B14 -> Sonoma Valley County Sanitation Dist. - Sonoma Valley Influent Effluent Upgrade | C14: =Bonus!C14 -> 10658200 | D14: =Bonus!D14 -> 10079352 | E14: =Bonus!E14 -> 578848 | F14: =Bonus!F14 -> 4923435.2 | G14: =IF(D14<>0,+F14/D14,0) -> 0.48846743 | H14: =IF(E14<=0,E14,IF(G14<0.1,0,IF(G14<=1,G14*E14,E14))) -> 282748.4 | I14: =+F14+H14 -> 5206183.6 | J14: =Bonus!J14 -> 5009265.2 | K14: =J14-I14 -> -196918.37 | L14: =+D14-F14 -> 5155916.8 | M14: =+C14-J14 -> 5648934.8 | N14: =Bonus!N14 -> 187144.08 | O14: =Bonus!O14 -> 0 | P14: =Bonus!W14 -> 0 | Q14: =F14-N14 -> 4736291.1 | R14: =+J14-O14 -> 5009265.2 | S14: =H14-P14 -> 282748.4 | T14: =Bonus!T14 -> 2024 | U14: =Bonus!U14 -> 0 | V14: =+Bonus!V14 -> .
A15: =Bonus!A15 -> 51.1152 | B15: =Bonus!B15 -> Mozingo Construction Inc - ElD Sly Park Intertie Project | C15: =Bonus!C15 -> 19974489 | D15: =Bonus!D15 -> 18628948 | E15: =Bonus!E15 -> 1345541 | F15: =Bonus!F15 -> 13474809 | G15: =IF(D15<>0,+F15/D15,0) -> 0.72332631 | H15: =IF(E15<=0,E15,IF(G15<0.1,0,IF(G15<=1,G15*E15,E15))) -> 973265.21 | I15: =+F15+H15 -> 14448074 | J15: =Bonus!J15 -> 15610649 | K15: =J15-I15 -> 1162575.3 | L15: =+D15-F15 -> 5154139.8 | M15: =+C15-J15 -> 4363840.3 | N15: =Bonus!N15 -> 1446770.9 | O15: =Bonus!O15 -> 2807450 | P15: =Bonus!W15 -> 0 | Q15: =F15-N15 -> 12028038 | R15: =+J15-O15 -> 12803199 | S15: =H15-P15 -> 973265.21 | T15: =Bonus!T15 -> 2024 | U15: =Bonus!U15 -> 0 | V15: =+Bonus!V15 -> .
A16: =Bonus!A16 -> 51.1153 | B16: =Bonus!B16 -> Linda County Water Dist. - Aeration Blower Replacement | C16: =Bonus!C16 -> 562824.68 | D16: =Bonus!D16 -> 454520.68 | E16: =Bonus!E16 -> 108304 | F16: =Bonus!F16 -> 334550.81 | G16: =IF(D16<>0,+F16/D16,0) -> 0.7360519 | H16: =IF(E16<=0,E16,IF(G16<0.1,0,IF(G16<=1,G16*E16,E16))) -> 79717.365 | I16: =+F16+H16 -> 414268.17 | J16: =Bonus!J16 -> 549548.83 | K16: =J16-I16 -> 135280.66 | L16: =+D16-F16 -> 119969.87 | M16: =+C16-J16 -> 13275.85 | N16: =Bonus!N16 -> 98963.36 | O16: =Bonus!O16 -> 116846.83 | P16: =Bonus!W16 -> 12859.389 | Q16: =F16-N16 -> 235587.45 | R16: =+J16-O16 -> 432702 | S16: =H16-P16 -> 66857.976 | T16: =Bonus!T16 -> 2024 | U16: =Bonus!U16 -> 0 | V16: =+Bonus!V16 -> .
A17: =Bonus!A17 -> 51.1154 | B17: =Bonus!B17 -> Keyes Community Services Dist. - TCP Treatment Impvmts Wells 7,8,9,10 | C17: =Bonus!C17 -> 13363835 | D17: =Bonus!D17 -> 12488835 | E17: =Bonus!E17 -> 875000 | F17: =Bonus!F17 -> 11872343 | G17: =IF(D17<>0,+F17/D17,0) -> 0.95063652 | H17: =IF(E17<=0,E17,IF(G17<0.1,0,IF(G17<=1,G17*E17,E17))) -> 831806.95 | I17: =+F17+H17 -> 12704150 | J17: =Bonus!J17 -> 13340008 | K17: =J17-I17 -> 635858.45 | L17: =+D17-F17 -> 616492.4 | M17: =+C17-J17 -> 23827 | N17: =Bonus!N17 -> 2378559.2 | O17: =Bonus!O17 -> 3186935 | P17: =Bonus!W17 -> 94320.423 | Q17: =F17-N17 -> 9493783.4 | R17: =+J17-O17 -> 10153073 | S17: =H17-P17 -> 737486.53 | T17: =Bonus!T17 -> 2024 | U17: =Bonus!U17 -> 0 | V17: =+Bonus!V17 -> .
A18: =Bonus!A18 -> 51.1158 | B18: =Bonus!B18 -> Schneider Electric - City of Ceres WWTP Phase 1- Schneider Electric | C18: =Bonus!C18 -> 104446 | D18: =Bonus!D18 -> 104446 | E18: =Bonus!E18 -> 0 | F18: =Bonus!F18 -> 56960.69 | G18: =IF(D18<>0,+F18/D18,0) -> 0.54536019 | H18: =IF(E18<=0,E18,IF(G18<0.1,0,IF(G18<=1,G18*E18,E18))) -> 0 | I18: =+F18+H18 -> 56960.69 | J18: =Bonus!J18 -> 32282 | K18: =J18-I18 -> -24678.69 | L18: =+D18-F18 -> 47485.31 | M18: =+C18-J18 -> 72164 | N18: =Bonus!N18 -> 0 | O18: =Bonus!O18 -> 0 | P18: =Bonus!W18 -> 0 | Q18: =F18-N18 -> 56960.69 | R18: =+J18-O18 -> 32282 | S18: =H18-P18 -> 0 | T18: =Bonus!T18 -> 2025 | U18: =Bonus!U18 -> 0 | V18: =+Bonus!V18 -> < 250k
A19: =Bonus!A19 -> 51.1159 | B19: =Bonus!B19 -> El Dorado Irrigation Dist. - EID Reservoir A WTP Backwash-to-waste Valve Repalcement | C19: =Bonus!C19 -> 1199000 | D19: =Bonus!D19 -> 1079240 | E19: =Bonus!E19 -> 119760 | F19: =Bonus!F19 -> 790051.12 | G19: =IF(D19<>0,+F19/D19,0) -> 0.73204396 | H19: =IF(E19<=0,E19,IF(G19<0.1,0,IF(G19<=1,G19*E19,E19))) -> 87669.584 | I19: =+F19+H19 -> 877720.7 | J19: =Bonus!J19 -> 732995 | K19: =J19-I19 -> -144725.7 | L19: =+D19-F19 -> 289188.88 | M19: =+C19-J19 -> 466005 | N19: =Bonus!N19 -> 0 | O19: =Bonus!O19 -> 0 | P19: =Bonus!W19 -> 0 | Q19: =F19-N19 -> 790051.12 | R19: =+J19-O19 -> 732995 | S19: =H19-P19 -> 87669.584 | T19: =Bonus!T19 -> 2025 | U19: =Bonus!U19 -> 0 | V19: =+Bonus!V19 -> .
A20: =Bonus!A20 -> 51.116 | B20: =Bonus!B20 -> City of Galt Public Works - Industrial WWTP Expansion | C20: =Bonus!C20 -> 1757000 | D20: =Bonus!D20 -> 1690000 | E20: =Bonus!E20 -> 67000 | F20: =Bonus!F20 -> 250518.05 | G20: =IF(D20<>0,+F20/D20,0) -> 0.14823553 | H20: =IF(E20<=0,E20,IF(G20<0.1,0,IF(G20<=1,G20*E20,E20))) -> 9931.7807 | I20: =+F20+H20 -> 260449.83 | J20: =Bonus!J20 -> 223725 | K20: =J20-I20 -> -36724.831 | L20: =+D20-F20 -> 1439481.9 | M20: =+C20-J20 -> 1533275 | N20: =Bonus!N20 -> 0 | O20: =Bonus!O20 -> 0 | P20: =Bonus!W20 -> 0 | Q20: =F20-N20 -> 250518.05 | R20: =+J20-O20 -> 223725 | S20: =H20-P20 -> 9931.7807 | T20: =Bonus!T20 -> 2025 | U20: =Bonus!U20 -> 0 | V20: =+Bonus!V20 -> .
A21: =Bonus!A21 -> 51.1161 | B21: =Bonus!B21 -> Sacramento Area Sewer Dist. - SASD Influent Pump Nos. 2 and 5 Installation Project | C21: =Bonus!C21 -> 10848599 | D21: =Bonus!D21 -> 10261252 | E21: =Bonus!E21 -> 587347 | F21: =Bonus!F21 -> 601852.17 | G21: =IF(D21<>0,+F21/D21,0) -> 0.058652896 | H21: =IF(E21<=0,E21,IF(G21<0.1,0,IF(G21<=1,G21*E21,E21))) -> 0 | I21: =+F21+H21 -> 601852.17 | J21: =Bonus!J21 -> 745707.2 | K21: =J21-I21 -> 143855.03 | L21: =+D21-F21 -> 9659400.3 | M21: =+C21-J21 -> 10102892 | N21: =Bonus!N21 -> 0 | O21: =Bonus!O21 -> 0 | P21: =Bonus!W21 -> 0 | Q21: =F21-N21 -> 601852.17 | R21: =+J21-O21 -> 745707.2 | S21: =H21-P21 -> 0 | T21: =Bonus!T21 -> 2025 | U21: =Bonus!U21 -> 0 | V21: =+Bonus!V21 -> .
... A24: =Bonus!A24 -> 51.1165 | B24: =Bonus!B24 -> City of Yuba City - WTP Aquifer Storage and Recovery Well No. 3 | C24: =Bonus!C24 -> 5304500 | D24: =Bonus!D24 -> 4886443 | E24: =Bonus!E24 -> 418057 | F24: =Bonus!F24 -> 23330.33 | G24: =IF(D24<>0,+F24/D24,0) -> 0.0047745016 | H24: =IF(E24<=0,E24,IF(G24<0.1,0,IF(G24<=1,G24*E24,E24))) -> 0 | I24: =+F24+H24 -> 23330.33 | J24: =Bonus!J24 -> 0 | K24: =J24-I24 -> -23330.33 | L24: =+D24-F24 -> 4863112.7 | M24: =+C24-J24 -> 5304500 | N24: =Bonus!N24 -> 0 | O24: =Bonus!O24 -> 0 | P24: =Bonus!W24 -> 0 | Q24: =F24-N24 -> 23330.33 | R24: =+J24-O24 -> 0 | S24: =H24-P24 -> 0 | T24: =Bonus!T24 -> 2025 | U24: =Bonus!U24 -> 0 | V24: =+Bonus!V24 -> .
A26: =+Bonus!A26 -> Rocklin Area - Open Job Totals | C26: =SUM(C$9:C$25) -> 3.6798108e+08 | D26: =SUM(D$9:D$25) -> 3.3017587e+08 | E26: =SUM(E$9:E$25) -> 37805216 | F26: =SUM(F$9:F$25) -> 2.5993861e+08 | H26: =SUM(H$9:H$25) -> 31365431 | I26: =SUM(I$9:I$25) -> 2.9130404e+08 | J26: =SUM(J$9:J$25) -> 2.9897789e+08 | K26: =SUM(K$9:K$25) -> 7673856.3 | L26: =SUM(L$9:L$25) -> 70237261 | M26: =SUM(M$9:M$25) -> 69003190 | N26: =SUM(N$9:N$25) -> 1.6257385e+08 | O26: =SUM(O$9:O$25) -> 1.7654489e+08 | ... S26: =SUM(S$9:S$25) -> 20147436
A28: =+Bonus!A28 -> Rocklin Area - Closed Jobs
A29: =Bonus!A29 -> 51.1133 | B29: =Bonus!B29 -> CA Water Service Co. - S. San Francisco St 1-A Pump Replacement | C29: =Bonus!C29 -> 372738 | D29: =Bonus!D29 -> 331855.28 | E29: =Bonus!E29 -> 40882.72 | F29: =Bonus!F29 -> 331855.28 | G29: =IF(D29<>0,+F29/D29,0) -> 1 | H29: =IF(E29<=0,E29,IF(G29<0.1,0,IF(G29<=1,G29*E29,E29))) -> 40882.72 | I29: =+F29+H29 -> 372738 | J29: =Bonus!J29 -> 372738 | K29: =J29-I29 -> 0 | L29: =+D29-F29 -> 0 | M29: =+C29-J29 -> 0 | N29: =Bonus!N29 -> 303125.41 | O29: =Bonus!O29 -> 326664 | P29: =Bonus!W29 -> 17359.581 | Q29: =F29-N29 -> 28729.87 | R29: =+J29-O29 -> 46074 | S29: =H29-P29 -> 23523.139 | T29: =Bonus!T29 -> 2023 | U29: =Bonus!U29 -> 2025 | V29: =+Bonus!V29 -> .
A30: =Bonus!A30 -> 51.1136 | B30: =Bonus!B30 -> Union Sanitary Dist - USD Plant Misc. Improvements | C30: =Bonus!C30 -> 5483550 | D30: =Bonus!D30 -> 4531817.9 | E30: =Bonus!E30 -> 951732.14 | F30: =Bonus!F30 -> 4531817.9 | G30: =IF(D30<>0,+F30/D30,0) -> 1 | H30: =IF(E30<=0,E30,IF(G30<0.1,0,IF(G30<=1,G30*E30,E30))) -> 951732.14 | I30: =+F30+H30 -> 5483550 | J30: =Bonus!J30 -> 5483550 | K30: =J30-I30 -> 0 | L30: =+D30-F30 -> 0 | M30: =+C30-J30 -> 0 | N30: =Bonus!N30 -> 4229332.8 | O30: =Bonus!O30 -> 5133927.2 | P30: =Bonus!W30 -> 758905.79 | Q30: =F30-N30 -> 302485.02 | R30: =+J30-O30 -> 349622.8 | S30: =H30-P30 -> 192826.35 | T30: =Bonus!T30 -> 2023 | U30: =Bonus!U30 -> 2025 | V30: =+Bonus!V30 -> .
A31: =Bonus!A31 -> 51.1138 | B31: =Bonus!B31 -> CA Water Service Co. - Bear Gulch Pump Station 21 | C31: =Bonus!C31 -> 1120182.1 | D31: =Bonus!D31 -> 1167704.1 | E31: =Bonus!E31 -> -47522.08 | F31: =Bonus!F31 -> 1167704.1 | G31: =IF(D31<>0,+F31/D31,0) -> 1 | H31: =IF(E31<=0,E31,IF(G31<0.1,0,IF(G31<=1,G31*E31,E31))) -> -47522.08 | I31: =+F31+H31 -> 1120182.1 | J31: =Bonus!J31 -> 1120182.1 | K31: =J31-I31 -> 0 | L31: =+D31-F31 -> 0 | M31: =+C31-J31 -> 0 | N31: =Bonus!N31 -> 786902.05 | O31: =Bonus!O31 -> 831943.71 | P31: =Bonus!W31 -> 77778.099 | Q31: =F31-N31 -> 380802.1 | R31: =+J31-O31 -> 288238.36 | S31: =H31-P31 -> -125300.18 | T31: =Bonus!T31 -> 2023 | U31: =Bonus!U31 -> 2025 | V31: =+Bonus!V31 -> .
A32: =Bonus!A32 -> 51.1139 | B32: =Bonus!B32 -> CA Water Service Co. - Bear Gulch Pump Station 14/29 | C32: =Bonus!C32 -> 61902 | D32: =Bonus!D32 -> 56994.44 | E32: =Bonus!E32 -> 4907.56 | F32: =Bonus!F32 -> 56994.44 | G32: =IF(D32<>0,+F32/D32,0) -> 1 | H32: =IF(E32<=0,E32,IF(G32<0.1,0,IF(G32<=1,G32*E32,E32))) -> 4907.56 | I32: =+F32+H32 -> 61902 | J32: =Bonus!J32 -> 61902 | K32: =J32-I32 -> 0 | L32: =+D32-F32 -> 0 | M32: =+C32-J32 -> 0 | N32: =Bonus!N32 -> 56994.44 | O32: =Bonus!O32 -> 61902 | P32: =Bonus!W32 -> 4426.359 | Q32: =F32-N32 -> 0 | R32: =+J32-O32 -> 0 | S32: =H32-P32 -> 481.20101 | T32: =Bonus!T32 -> 2023 | U32: =Bonus!U32 -> 2025 | V32: =+Bonus!V32 -> < 250k
A33: =Bonus!A33 -> 51.1141 | B33: =Bonus!B33 -> City of Colfax - WWTP Algae Reduction Project | C33: =Bonus!C33 -> 3967189.8 | D33: =Bonus!D33 -> 3835094.7 | E33: =Bonus!E33 -> 132095.06 | F33: =Bonus!F33 -> 3835094.7 | G33: =IF(D33<>0,+F33/D33,0) -> 1 | H33: =IF(E33<=0,E33,IF(G33<0.1,0,IF(G33<=1,G33*E33,E33))) -> 132095.06 | I33: =+F33+H33 -> 3967189.8 | J33: =Bonus!J33 -> 3967189.8 | K33: =J33-I33 -> 0 | L33: =+D33-F33 -> 0 | M33: =+C33-J33 -> 0 | N33: =Bonus!N33 -> 3109905.8 | O33: =Bonus!O33 -> 3392862.8 | P33: =Bonus!W33 -> 79920.299 | Q33: =F33-N33 -> 725188.97 | R33: =+J33-O33 -> 574326.99 | S33: =H33-P33 -> 52174.761 | T33: =Bonus!T33 -> 2023 | U33: =Bonus!U33 -> 2025 | V33: =+Bonus!V33 -> .
A34: =Bonus!A34 -> 51.1143 | B34: =Bonus!B34 -> Olivehurst Plumas Lake Manganese Filter Expansion | C34: =Bonus!C34 -> 1991231.4 | D34: =Bonus!D34 -> 1758132.6 | E34: =Bonus!E34 -> 233098.8 | F34: =Bonus!F34 -> 1758132.6 | G34: =IF(D34<>0,+F34/D34,0) -> 1 | H34: =IF(E34<=0,E34,IF(G34<0.1,0,IF(G34<=1,G34*E34,E34))) -> 233098.8 | I34: =+F34+H34 -> 1991231.4 | J34: =Bonus!J34 -> 1991231.4 | K34: =J34-I34 -> 0 | L34: =+D34-F34 -> 0 | M34: =+C34-J34 -> 0 | N34: =Bonus!N34 -> 1730691 | O34: =Bonus!O34 -> 1955683.4 | P34: =Bonus!W34 -> 226011.76 | Q34: =F34-N34 -> 27441.6 | R34: =+J34-O34 -> 35548 | S34: =H34-P34 -> 7087.0371 | T34: =Bonus!T34 -> 2023 | U34: =Bonus!U34 -> 2025 | V34: =+Bonus!V34 -> .
A35: =Bonus!A35 -> 51.1147 | B35: =Bonus!B35 -> City of Lodi-Public Works Dept. - Aeration Diffusers Replacement Project | C35: =Bonus!C35 -> 2742860.1 | D35: =Bonus!D35 -> 2548724.9 | E35: =Bonus!E35 -> 194135.16 | F35: =Bonus!F35 -> 2548724.9 | G35: =IF(D35<>0,+F35/D35,0) -> 1 | H35: =IF(E35<=0,E35,IF(G35<0.1,0,IF(G35<=1,G35*E35,E35))) -> 194135.16 | I35: =+F35+H35 -> 2742860.1 | J35: =Bonus!J35 -> 2742860.1 | K35: =J35-I35 -> 0 | L35: =+D35-F35 -> 0 | M35: =+C35-J35 -> 0 | N35: =Bonus!N35 -> 1749912.3 | O35: =Bonus!O35 -> 1894059.7 | P35: =Bonus!W35 -> 128284.54 | Q35: =F35-N35 -> 798812.6 | R35: =+J35-O35 -> 848800.39 | S35: =H35-P35 -> 65850.625 | T35: =Bonus!T35 -> 2023 | U35: =Bonus!U35 -> 2025 | V35: =+Bonus!V35 -> .
A36: =Bonus!A36 -> 51.115 | B36: =Bonus!B36 -> Sacramento Co. Dept. of Water Resources - D49 Metro Air Park Storm Drain Pump Station Phase 2 | C36: =Bonus!C36 -> 2486231.6 | D36: =Bonus!D36 -> 2239435.1 | E36: =Bonus!E36 -> 246796.44 | F36: =Bonus!F36 -> 2239435.1 | G36: =IF(D36<>0,+F36/D36,0) -> 1 | H36: =IF(E36<=0,E36,IF(G36<0.1,0,IF(G36<=1,G36*E36,E36))) -> 246796.44 | I36: =+F36+H36 -> 2486231.6 | J36: =Bonus!J36 -> 2486231.6 | K36: =J36-I36 -> 0 | L36: =+D36-F36 -> 0 | M36: =+C36-J36 -> 0 | N36: =Bonus!N36 -> 2071076.8 | O36: =Bonus!O36 -> 2378955.8 | P36: =Bonus!W36 -> 166471.83 | Q36: =F36-N36 -> 168358.34 | R36: =+J36-O36 -> 107275.82 | S36: =H36-P36 -> 80324.611 | T36: =Bonus!T36 -> 2024 | U36: =Bonus!U36 -> 2025 | V36: =+Bonus!V36 -> .
A37: =Bonus!A37 -> 51.1156 | B37: =Bonus!B37 -> Rocklin Overhead 2025 | C37: =Bonus!C37 -> 0 | D37: =Bonus!D37 -> 1426058.7 | E37: =Bonus!E37 -> -1426058.7 | F37: =Bonus!F37 -> 1426058.7 | G37: =IF(D37<>0,+F37/D37,0) -> 1 | H37: =IF(E37<=0,E37,IF(G37<0.1,0,IF(G37<=1,G37*E37,E37))) -> -1426058.7 | I37: =+F37+H37 -> 0 | J37: =Bonus!J37 -> 0 | K37: =J37-I37 -> 0 | L37: =+D37-F37 -> 0 | M37: =+C37-J37 -> 0 | N37: =Bonus!N37 -> 0 | O37: =Bonus!O37 -> 0 | P37: =Bonus!W37 -> 0 | Q37: =F37-N37 -> 1426058.7 | R37: =+J37-O37 -> 0 | S37: =H37-P37 -> -1426058.7 | T37: =Bonus!T37 -> 2025 | U37: =Bonus!U37 -> 2025 | V37: =+Bonus!V37 -> OH
A38: =Bonus!A38 -> 51.1157 | B38: =Bonus!B38 -> Rocklin Estimating 2025 | C38: =Bonus!C38 -> 0 | D38: =Bonus!D38 -> 613546.52 | E38: =Bonus!E38 -> -613546.52 | F38: =Bonus!F38 -> 613546.52 | G38: =IF(D38<>0,+F38/D38,0) -> 1 | H38: =IF(E38<=0,E38,IF(G38<0.1,0,IF(G38<=1,G38*E38,E38))) -> -613546.52 | I38: =+F38+H38 -> 0 | J38: =Bonus!J38 -> 0 | K38: =J38-I38 -> 0 | L38: =+D38-F38 -> 0 | M38: =+C38-J38 -> 0 | N38: =Bonus!N38 -> 0 | O38: =Bonus!O38 -> 0 | P38: =Bonus!W38 -> 0 | Q38: =F38-N38 -> 613546.52 | R38: =+J38-O38 -> 0 | S38: =H38-P38 -> -613546.52 | T38: =Bonus!T38 -> 2025 | U38: =Bonus!U38 -> 2025 | V38: =+Bonus!V38 -> OH
A40: =+Bonus!A40 -> Rocklin Area - Closed Totals | C40: =SUM(C29:C39) -> 18225885 | D40: =SUM(D29:D39) -> 18509364 | E40: =SUM(E29:E39) -> -283479.41 | F40: =SUM(F29:F39) -> 18509364 | H40: =SUM(H29:H39) -> -283479.41 | I40: =SUM(I29:I39) -> 18225885 | J40: =SUM(J29:J39) -> 18225885 | K40: =SUM(K29:K39) -> 0 | L40: =SUM(L29:L39) -> 0 | M40: =SUM(M29:M39) -> 0 | N40: =SUM(N29:N39) -> 14037941 | O40: =SUM(O29:O39) -> 15975999 | ... S40: =SUM(S29:S39) -> -1742637.7
A41: =+Bonus!A41 -> Rocklin Area - Grand Totals | C41: =+C40+C26 -> 3.8620697e+08 | D41: =+D40+D26 -> 3.4868523e+08 | E41: =+E40+E26 -> 37521737 | F41: =+F40+F26 -> 2.7844797e+08 | H41: =+H40+H26 -> 31081951 | I41: =+I40+I26 -> 3.0952992e+08 | J41: =+J40+J26 -> 3.1720378e+08 | K41: =+K40+K26 -> 7673856.3 | L41: =+L40+L26 -> 70237261 | M41: =+M40+M26 -> 69003190 | N41: =+N40+N26 -> 1.7661179e+08 | O41: =+O40+O26 -> 1.9252089e+08 | ... S41: =+S40+S26 -> 18404798
A43: =+Bonus!A43 -> Fresno Area - Open Jobs
A44: =+Bonus!A44 -> 52.8563 | B44: =+Bonus!B44 -> City of Santa Cruz - Graham Hill WTP Facility Improvements - Phase 1 | C44: =J44 -> 1134038.1 | D44: =F44 -> 859077.05 | E44: =C44-D44 -> 274961.08 | F44: =+Bonus!F44 -> 859077.05 | G44: =IF(D44<>0,+F44/D44,0) -> 1 | H44: =IF(E44<=0,E44,IF(G44<0.1,0,IF(G44<=1,G44*E44,E44))) -> 274961.08 | I44: =+F44+H44 -> 1134038.1 | J44: =+Bonus!J44 -> 1134038.1 | K44: =J44-I44 -> 0 | L44: =+D44-F44 -> 0 | M44: =+C44-J44 -> 0 | N44: =Bonus!N44 -> 720866.75 | O44: =Bonus!O44 -> 915332.49 | P44: =Bonus!W44 -> 194465.74 | Q44: =F44-N44 -> 138210.3 | R44: =+J44-O44 -> 218705.64 | S44: =H44-P44 -> 80495.34 | T44: =+Bonus!T44 -> 2021 | U44: =+Bonus!U44 -> 0 | V44: =+Bonus!V44 -> .
A45: =+Bonus!A45 -> 52.8566 | B45: =+Bonus!B45 -> City of Visalia - Water Reclamation Facility RPGS SCR System | C45: =Bonus!C45 -> 1259398 | D45: =Bonus!D45 -> 1029398 | E45: =Bonus!E45 -> 230000 | F45: =+Bonus!F45 -> 1023821.1 | G45: =IF(D45<>0,+F45/D45,0) -> 0.99458232 | H45: =IF(E45<=0,E45,IF(G45<0.1,0,IF(G45<=1,G45*E45,E45))) -> 228753.93 | I45: =+F45+H45 -> 1252575 | J45: =+Bonus!J45 -> 1242053 | K45: =J45-I45 -> -10521.983 | L45: =+D45-F45 -> 5576.95 | M45: =+C45-J45 -> 17345 | N45: =Bonus!N45 -> 994790.56 | O45: =Bonus!O45 -> 1242053 | P45: =Bonus!W45 -> 223974.51 | Q45: =F45-N45 -> 29030.49 | R45: =+J45-O45 -> 0 | S45: =H45-P45 -> 4779.4271 | T45: =+Bonus!T45 -> 2021 | U45: =+Bonus!U45 -> 0 | V45: =+Bonus!V45 -> .
A46: =+Bonus!A46 -> 52.8586 | B46: =+Bonus!B46 -> Tesoro Viejo MMWC- WTP/WWTP/RWSP Phase B Expansion - Phase 1 | C46: =Bonus!C46 -> 12611349 | D46: =Bonus!D46 -> 10661349 | E46: =Bonus!E46 -> 1950000 | F46: =+Bonus!F46 -> 10565461 | G46: =IF(D46<>0,+F46/D46,0) -> 0.99100599 | H46: =IF(E46<=0,E46,IF(G46<0.1,0,IF(G46<=1,G46*E46,E46))) -> 1932461.7 | I46: =+F46+H46 -> 12497922 | J46: =+Bonus!J46 -> 12611349 | K46: =J46-I46 -> 113426.58 | L46: =+D46-F46 -> 95888.26 | M46: =+C46-J46 -> 0 | N46: =Bonus!N46 -> 10233293 | O46: =Bonus!O46 -> 12384954 | P46: =Bonus!W46 -> 1757780 | Q46: =F46-N46 -> 332168.03 | R46: =+J46-O46 -> 226395 | S46: =H46-P46 -> 174681.68 | T46: =+Bonus!T46 -> 2022 | U46: =+Bonus!U46 -> 0 | V46: =+Bonus!V46 -> .
A47: =+Bonus!A47 -> 52.8634 | B47: =+Bonus!B47 -> City of Huron - Water Treatment Plant Imp. Phase 2 | C47: =Bonus!C47 -> 13892723 | D47: =Bonus!D47 -> 13190723 | E47: =Bonus!E47 -> 702000 | F47: =+Bonus!F47 -> 11707058 | G47: =IF(D47<>0,+F47/D47,0) -> 0.88752212 | H47: =IF(E47<=0,E47,IF(G47<0.1,0,IF(G47<=1,G47*E47,E47))) -> 623040.53 | I47: =+F47+H47 -> 12330099 | J47: =+Bonus!J47 -> 12576768 | K47: =J47-I47 -> 246669.27 | L47: =+D47-F47 -> 1483664.5 | M47: =+C47-J47 -> 1315954.7 | N47: =Bonus!N47 -> 5213426.6 | O47: =Bonus!O47 -> 5564075.4 | P47: =Bonus!W47 -> 277972.01 | Q47: =F47-N47 -> 6493631.6 | R47: =+J47-O47 -> 7012692.7 | S47: =H47-P47 -> 345068.52 | T47: =+Bonus!T47 -> 2023 | U47: =+Bonus!U47 -> 0 | V47: =+Bonus!V47 -> .
A48: =+Bonus!A48 -> 52.8636 | B48: =+Bonus!B48 -> Anaergia Technologies, LLC - Anaergia M1W Digester Mixing Project | C48: 3656112 | D48: =C48-E48 -> 3381112 | E48: =Bonus!E48 -> 275000 | F48: =+Bonus!F48 -> 3367047.4 | G48: =IF(D48<>0,+F48/D48,0) -> 0.99584023 | H48: =IF(E48<=0,E48,IF(G48<0.1,0,IF(G48<=1,G48*E48,E48))) -> 273856.06 | I48: =+F48+H48 -> 3640903.4 | J48: =+Bonus!J48 -> 3065635.6 | K48: =J48-I48 -> -575267.82 | L48: =+D48-F48 -> 14064.64 | M48: =+C48-J48 -> 590476.4 | N48: =Bonus!N48 -> 1456799.5 | O48: =Bonus!O48 -> 1731771.2 | P48: =Bonus!W48 -> 204319.71 | Q48: =F48-N48 -> 1910247.8 | R48: =+J48-O48 -> 1333864.4 | S48: =H48-P48 -> 69536.353 | T48: =+Bonus!T48 -> 2023 | U48: =+Bonus!U48 -> 0 | V48: =+Bonus!V48 -> .
A49: =+Bonus!A49 -> 52.8637 | B49: =+Bonus!B49 -> Root Creek Water Dist. - Groundwater Blending & Arsenic | C49: =Bonus!C49 -> 26264578 | D49: =Bonus!D49 -> 24614578 | E49: =Bonus!E49 -> 1650000 | F49: =+Bonus!F49 -> 24374299 | G49: =IF(D49<>0,+F49/D49,0) -> 0.99023836 | H49: =IF(E49<=0,E49,IF(G49<0.1,0,IF(G49<=1,G49*E49,E49))) -> 1633893.3 | I49: =+F49+H49 -> 26008192 | J49: =+Bonus!J49 -> 26148625 | K49: =J49-I49 -> 140432.67 | L49: =+D49-F49 -> 240278.62 | M49: =+C49-J49 -> 115952.65 | N49: =Bonus!N49 -> 19441815 | O49: =Bonus!O49 -> 20860138 | P49: =Bonus!W49 -> 1208391.8 | Q49: =F49-N49 -> 4932484 | R49: =+J49-O49 -> 5288487 | S49: =H49-P49 -> 425501.54 | T49: =+Bonus!T49 -> 2023 | U49: =+Bonus!U49 -> 0 | V49: =+Bonus!V49 -> .
A50: =+Bonus!A50 -> 52.864 | B50: =+Bonus!B50 -> City of Dos Palos - WTP Replacement Project | C50: =Bonus!C50 -> 38646363 | D50: =Bonus!D50 -> 36773040 | E50: =Bonus!E50 -> 1873323 | F50: =+Bonus!F50 -> 32158781 | G50: =IF(D50<>0,+F50/D50,0) -> 0.87452061 | H50: =IF(E50<=0,E50,IF(G50<0.1,0,IF(G50<=1,G50*E50,E50))) -> 1638259.6 | I50: =+F50+H50 -> 33797041 | J50: =+Bonus!J50 -> 34176042 | K50: =J50-I50 -> 379000.81 | L50: =+D50-F50 -> 4614258.7 | M50: =+C50-J50 -> 4470321.3 | N50: =Bonus!N50 -> 13034453 | O50: =Bonus!O50 -> 13664734 | P50: =Bonus!W50 -> 703966.84 | Q50: =F50-N50 -> 19124329 | R50: =+J50-O50 -> 20511308 | S50: =H50-P50 -> 934292.73 | T50: =+Bonus!T50 -> 2023 | U50: =+Bonus!U50 -> 0 | V50: =+Bonus!V50 -> .
